Workbook

Sheet kshotoku1631
A1: Ⅲ．雇用者報酬
A2: Compensation of Employees | S2: (単位:10億円、%)
A3: 名 目 | K3: 実 質(2005暦年連鎖価格)
A4: AT CURRENT PRICES | K4: Chained (2005) yen
C5: 四半期・原系列 | E5: 四半期・季節調整系列 | G5: 年度 、 暦年 | M5: 四半期・原系列 | O5: 四半期・季節調整系列 | Q5: 年度 、 暦年
C6: Original series | E6: Seasonally adjusted series | G6: Fiscal year , Calendar year | M6: Original series | O6: Seasonally adjusted series | Q6: Fiscal year , Calendar year
C7: 実数 | D7: (**) | E7: 実数 | F7: (***) | H7: 実数 | I7: (**) | M7: 実数 | N7: (**) | O7: 実数 | P7: (***) | R7: 実数 | S7: (**)
C8: billion yen | D8: (**) | E8: billion yen | F8: (***) | H8: billion yen | I8: (**) | M8: billion yen | N8: (**) | O8: billion yen | P8: (***) | R8: billion yen | S8: (**)
A9: 1980/ | B9: 1-3. | C9: 25552.1 | E9: 124110.7
B10: 4-6. | C10: 31503 | E10: 126919.2 | F10: 2.3
B11: 7-9. | C11: 32068.3 | E11: 131191 | F11: 3.4
B12: 10-12. | C12: 40327.3 | E12: 134097.1 | F12: 2.2
A13: 1981/ | B13: 1-3. | C13: 27951.7 | D13: 9.4 | E13: 135507.4 | F13: 1.1
B14: 4-6. | C14: 34652.4 | D14: 10 | E14: 138934.6 | F14: 2.5
B15: 7-9. | C15: 34272.8 | D15: 6.9 | E15: 140458.7 | F15: 1.1
B16: 10-12. | C16: 43335.4 | D16: 7.5 | E16: 144577.2 | F16: 2.9
A17: 1982/ | B17: 1-3. | C17: 29837.1 | D17: 6.7 | E17: 144263.5 | F17: -0.2
B18: 4-6. | C18: 36628.4 | D18: 5.7 | E18: 146887 | F18: 1.8
B19: 7-9. | C19: 36421.4 | D19: 6.3 | E19: 149120.3 | F19: 1.5
B20: 10-12. | C20: 45253 | D20: 4.4 | E20: 151218.7 | F20: 1.4
A21: 1983/ | B21: 1-3. | C21: 31930.2 | D21: 7 | E21: 153874.8 | F21: 1.8
B22: 4-6. | C22: 38500.2 | D22: 5.1 | E22: 154328.2 | F22: 0.3
B23: 7-9. | C23: 38256.5 | D23: 5 | E23: 156784.3 | F23: 1.6
B24: 10-12. | C24: 47107.2 | D24: 4.1 | E24: 157849.2 | F24: 0.7
A25: 1984/ | B25: 1-3. | C25: 33437.4 | D25: 4.7 | E25: 160673.2 | F25: 1.8
B26: 4-6. | C26: 40757.7 | D26: 5.9 | E26: 163500.9 | F26: 1.8
B27: 7-9. | C27: 40117.1 | D27: 4.9 | E27: 164339.9 | F27: 0.5
B28: 10-12. | C28: 50005.6 | D28: 6.2 | E28: 167802.4 | F28: 2.1
A29: 1985/ | B29: 1-3. | C29: 35136.8 | D29: 5.1 | E29: 168533.3 | F29: 0.4
B30: 4-6. | C30: 42509.9 | D30: 4.3 | E30: 170237.7 | F30: 1
B31: 7-9. | C31: 42163.1 | D31: 5.1 | E31: 172902.1 | F31: 1.6
B32: 10-12. | C32: 52046.2 | D32: 4.1 | E32: 175093.4 | F32: 1.3
A33: 1986/ | B33: 1-3. | C33: 37257.8 | D33: 6 | E33: 178303.6 | F33: 1.8
B34: 4-6. | C34: 44327.2 | D34: 4.3 | E34: 177664 | F34: -0.4
B35: 7-9. | C35: 43898.5 | D35: 4.1 | E35: 179952.6 | F35: 1.3
B36: 10-12. | C36: 53702.7 | D36: 3.2 | E36: 180927 | F36: 0.5
A37: 1987/ | B37: 1-3. | C37: 38261 | D37: 2.7 | E37: 183103.8 | F37: 1.2
B38: 4-6. | C38: 46264 | D38: 4.4 | E38: 184080.9 | F38: 0.5
B39: 7-9. | C39: 45092.4 | D39: 2.7 | E39: 185299 | F39: 0.7
B40: 10-12. | C40: 55752.8 | D40: 3.8 | E40: 187985.2 | F40: 1.4
A41: 1988/ | B41: 1-3. | C41: 39989.7 | D41: 4.5 | E41: 191666.7 | F41: 2
B42: 4-6. | C42: 48828.9 | D42: 5.5 | E42: 193624.8 | F42: 1
B43: 7-9. | C43: 48023.4 | D43: 6.5 | E43: 197704.2 | F43: 2.1
B44: 10-12. | C44: 59299.1 | D44: 6.4 | E44: 200041.3 | F44: 1.2
A45: 1989/ | B45: 1-3. | C45: 42335.2 | D45: 5.9 | E45: 203432.7 | F45: 1.7
B46: 4-6. | C46: 52669.9 | D46: 7.9 | E46: 208290.1 | F46: 2.4
B47: 7-9. | C47: 51249.7 | D47: 6.7 | E47: 211249.9 | F47: 1.4
B48: 10-12. | C48: 63913.2 | D48: 7.8 | E48: 215330.3 | F48: 1.9
A49: 1990/ | B49: 1-3. | C49: 45476.4 | D49: 7.4 | E49: 219012.7 | F49: 1.7
B50: 4-6. | C50: 56899.6 | D50: 8 | E50: 224933.6 | F50: 2.7
B51: 7-9. | C51: 55172 | D51: 7.7 | E51: 227502.4 | F51: 1.1
B52: 10-12. | C52: 69760.6 | D52: 9.1 | E52: 235145.5 | F52: 3.4
A53: 1991/ | B53: 1-3. | C53: 49429.3 | D53: 8.7 | E53: 238143.3 | F53: 1.3
B54: 4-6. | C54: 61734.2 | D54: 8.5 | E54: 243509.9 | F54: 2.3
B55: 7-9. | C55: 60006.6 | D55: 8.8 | E55: 247221.6 | F55: 1.5
B56: 10-12. | C56: 74416 | D56: 6.7 | E56: 251312.5 | F56: 1.7
A57: 1992/ | B57: 1-3. | C57: 52154.2 | D57: 5.5 | E57: 251073.3 | F57: -0.1
B58: 4-6. | C58: 63659.8 | D58: 3.1 | E58: 252095.5 | F58: 0.4
B59: 7-9. | C59: 61973.8 | D59: 3.3 | E59: 254381.7 | F59: 0.9
B60: 10-12. | C60: 75775 | D60: 1.8 | E60: 256377.9 | F60: 0.8
A61: 1993/ | B61: 1-3. | C61: 53435.8 | D61: 2.5 | E61: 256453.9 | F61: 0
B62: 4-6. | C62: 65104.9 | D62: 2.3 | E62: 257154.2 | F62: 0.3
B63: 7-9. | C63: 63828.7 | D63: 3 | E63: 262230.5 | F63: 2
B64: 10-12. | C64: 76711.8 | D64: 1.2 | E64: 261141.6 | F64: -0.4
A65: 1994/ | B65: 1-3. | C65: 55078.5 | D65: 3.1 | E65: 263099.2 | F65: 0.7 | G65: 1980/4-3. | H65: 131850.4 | K65: 1994/ | L65: 1-3. | M65: 51443.8 | O65: 244235
B66: 4-6. | C66: 67987.9 | D66: 4.4 | E66: 267892.6 | F66: 1.8 | G66: 1981/4-3. | H66: 142097.7 | I66: 7.8 | L66: 4-6. | M66: 62756.6 | O66: 248142.6 | P66: 1.6
B67: 7-9. | C67: 63534.2 | D67: -0.5 | E67: 261520.8 | F67: -2.4 | G67: 1982/4-3. | H67: 150232.9 | I67: 5.7 | L67: 7-9. | M67: 59153.3 | O67: 242927 | P67: -2.1
B68: 10-12. | C68: 77695.3 | D68: 1.3 | E68: 265480.4 | F68: 1.5 | G68: 1983/4-3. | H68: 157301.3 | I68: 4.7 | L68: 10-12. | M68: 71845.5 | O68: 246645.7 | P68: 1.5
A69: 1995/ | B69: 1-3. | C69: 56349.6 | D69: 2.3 | E69: 267830.1 | F69: 0.9 | G69: 1984/4-3. | H69: 166017.3 | I69: 5.5 | K69: 1995/ | L69: 1-3. | M69: 52773.5 | N69: 2.6 | O69: 249325.7 | P69: 1.1
B70: 4-6. | C70: 68765.7 | D70: 1.1 | E70: 269078.4 | F70: 0.5 | G70: 1985/4-3. | H70: 173977 | I70: 4.8 | L70: 4-6. | M70: 64047.1 | N70: 2.1 | O70: 251575.8 | P70: 0.9
B71: 7-9. | C71: 65075.1 | D71: 2.4 | E71: 269182.6 | F71: 0 | G71: 1986/4-3. | H71: 180189.4 | I71: 3.6 | L71: 7-9. | M71: 61148.2 | N71: 3.4 | O71: 252339.6 | P71: 0.3
B72: 10-12. | C72: 78894 | D72: 1.5 | E72: 270794 | F72: 0.6 | G72: 1987/4-3. | H72: 187098.9 | I72: 3.8 | L72: 10-12. | M72: 73714.2 | N72: 2.6 | O72: 254186 | P72: 0.7
A73: 1996/ | B73: 1-3. | C73: 57453.1 | D73: 2 | E73: 271396.2 | F73: 0.2 | G73: 1988/4-3. | H73: 198486.5 | I73: 6.1 | K73: 1996/ | L73: 1-3. | M73: 54382.6 | N73: 3 | O73: 255235.4 | P73: 0.4
B74: 4-6. | C74: 69556 | D74: 1.1 | E74: 272157.9 | F74: 0.3 | G74: 1989/4-3. | H74: 213309.1 | I74: 7.5 | L74: 4-6. | M74: 65068.4 | N74: 1.6 | O74: 255586.8 | P74: 0.1
B75: 7-9. | C75: 65641.5 | D75: 0.9 | E75: 272230.2 | F75: 0 | G75: 1990/4-3. | H75: 231261.5 | I75: 8.4 | L75: 7-9. | M75: 61885.6 | N75: 1.2 | O75: 256060.6 | P75: 0.2
B76: 10-12. | C76: 79900.5 | D76: 1.3 | E76: 274427.9 | F76: 0.8 | G76: 1991/4-3. | H76: 248310.9 | I76: 7.4 | L76: 10-12. | M76: 74776.1 | N76: 1.4 | O76: 258142.3 | P76: 0.8
A77: 1997/ | B77: 1-3. | C77: 59031.3 | D77: 2.7 | E77: 277248.5 | F77: 1 | G77: 1992/4-3. | H77: 254844.4 | I77: 2.6 | K77: 1997/ | L77: 1-3. | M77: 55890 | N77: 2.8 | O77: 260704.1 | P77: 1
B78: 4-6. | C78: 71348.7 | D78: 2.6 | E78: 278635.8 | F78: 0.5 | G78: 1993/4-3. | H78: 260724 | I78: 2.3 | L78: 4-6. | M78: 65801.7 | N78: 1.1 | O78: 258040.8 | P78: -1
B79: 7-9. | C79: 67299 | D79: 2.5 | E79: 279984.5 | F79: 0.5 | G79: 1994/4-3. | H79: 265567 | I79: 1.9 | L79: 7-9. | M79: 62520.3 | N79: 1 | O79: 259362.3 | P79: 0.5 | Q79: 1994/4-3. | R79: 246528.9
B80: 10-12. | C80: 80686 | D80: 1 | E80: 277860.8 | F80: -0.8 | G80: 1995/4-3. | H80: 270187.8 | I80: 1.7 | L80: 10-12. | M80: 74527.2 | N80: -0.3 | O80: 258122.1 | P80: -0.5 | Q80: 1995/4-3. | R80: 253292.1 | S80: 2.7
A81: 1998/ | B81: 1-3. | C81: 59662.6 | D81: 1.1 | E81: 278558.1 | F81: 0.3 | G81: 1996/4-3. | H81: 274129.2 | I81: 1.5 | K81: 1998/ | L81: 1-3. | M81: 55906.1 | N81: 0 | O81: 259202.9 | P81: 0.4 | Q81: 1996/4-3. | R81: 257620.2 | S81: 1.7
B82: 4-6. | C82: 70450.2 | D82: -1.3 | E82: 275401 | F82: -1.1 | G82: 1997/4-3. | H82: 278996.3 | I82: 1.8 | L82: 4-6. | M82: 65392.9 | N82: -0.6 | O82: 256692.6 | P82: -1 | Q82: 1997/4-3. | R82: 258755.3 | S82: 0.4
B83: 7-9. | C83: 65361.4 | D83: -2.9 | E83: 272322.3 | F83: -1.1 | G83: 1998/4-3. | H83: 272937.9 | I83: -2.2 | L83: 7-9. | M83: 61304.2 | N83: -1.9 | O83: 254681.3 | P83: -0.8 | Q83: 1998/4-3. | R83: 254677.2 | S83: -1.6
B84: 10-12. | C84: 78736.5 | D84: -2.4 | E84: 272043.1 | F84: -0.1 | G84: 1999/4-3. | H84: 268001.5 | I84: -1.8 | L84: 10-12. | M84: 72941.6 | N84: -2.1 | O84: 253509.6 | P84: -0.5 | Q84: 1999/4-3. | R84: 251785 | S84: -1.1
A85: 1999/ | B85: 1-3. | C85: 58389.7 | D85: -2.1 | E85: 271528.9 | F85: -0.2 | G85: 2000/4-3. | H85: 269158.9 | I85: 0.4 | K85: 1999/ | L85: 1-3. | M85: 55038.5 | N85: -1.6 | O85: 254143.3 | P85: 0.2 | Q85: 2000/4-3. | R85: 254982.1 | S85: 1.3
B86: 4-6. | C86: 68525.4 | D86: -2.7 | E86: 267772.1 | F86: -1.4 | G86: 2001/4-3. | H86: 265692.2 | I86: -1.3 | L86: 4-6. | M86: 64001.3 | N86: -2.1 | O86: 251175.7 | P86: -1.2 | Q86: 2001/4-3. | R86: 256069.7 | S86: 0.4
B87: 7-9. | C87: 64266.8 | D87: -1.7 | E87: 267925.8 | F87: 0.1 | G87: 2002/4-3. | H87: 258088.1 | I87: -2.9 | L87: 7-9. | M87: 60508.8 | N87: -1.3 | O87: 251453.9 | P87: 0.1 | Q87: 2002/4-3. | R87: 252397.4 | S87: -1.4
B88: 10-12. | C88: 77065.1 | D88: -2.1 | E88: 266863 | F88: -0.4 | G88: 2003/4-3. | H88: 252787.1 | I88: -2.1 | L88: 10-12. | M88: 72206.8 | N88: -1 | O88: 251467.3 | P88: 0 | Q88: 2003/4-3. | R88: 249964.8 | S88: -1
A89: 2000/ | B89: 1-3. | C89: 58144.2 | D89: -0.4 | E89: 269846.4 | F89: 1.1 | G89: 2004/4-3. | H89: 252159.4 | I89: -0.2 | K89: 2000/ | L89: 1-3. | M89: 55068.1 | N89: 0.1 | O89: 253929 | P89: 1 | Q89: 2004/4-3. | R89: 250901.4 | S89: 0.4
B90: 4-6. | C90: 68653 | D90: 0.2 | E90: 268286 | F90: -0.6 | G90: 2005/4-3. | H90: 254064 | I90: 0.8 | L90: 4-6. | M90: 64642.5 | N90: 1 | O90: 253604.3 | P90: -0.1 | Q90: 2005/4-3. | R90: 254057.4 | S90: 1.3
B91: 7-9. | C91: 64296.4 | D91: 0 | E91: 268303.9 | F91: 0 | G91: 2006/4-3. | H91: 255747.5 | I91: 0.7 | L91: 7-9. | M91: 61032.9 | N91: 0.9 | O91: 253940.1 | P91: 0.1 | Q91: 2006/4-3. | R91: 256896 | S91: 1.1
B92: 10-12. | C92: 77959.8 | D92: 1.2 | E92: 270071.4 | F92: 0.7 | G92: 2007/4-3. | H92: 255640.1 | I92: 0 | L92: 10-12. | M92: 73663 | N92: 2 | O92: 256559.8 | P92: 1 | Q92: 2007/4-3. | R92: 257233.9 | S92: 0.1
A93: 2001/ | B93: 1-3. | C93: 58249.8 | D93: 0.2 | E93: 270199.5 | F93: 0 | G93: 2008/4-3. | H93: 254279.5 | I93: -0.5 | K93: 2001/ | L93: 1-3. | M93: 55643.7 | N93: 1 | O93: 256301.8 | P93: -0.1 | Q93: 2008/4-3. | R93: 255453.4 | S93: -0.7
B94: 4-6. | C94: 68940.8 | D94: 0.4 | E94: 268972.9 | F94: -0.5 | G94: 2009/4-3. | H94: 242980.7 | I94: -4.4 | L94: 4-6. | M94: 65748.2 | N94: 1.7 | O94: 257545.3 | P94: 0.5 | Q94: 2009/4-3. | R94: 251154.8 | S94: -1.7
B95: 7-9. | C95: 63987.4 | D95: -0.5 | E95: 267275.4 | F95: -0.6 | G95: 2010/4-3. | H95: 243951.6 | I95: 0.4 | L95: 7-9. | M95: 61630.2 | N95: 1 | O95: 256899.9 | P95: -0.3 | Q95: 2010/4-3. | R95: 255969 | S95: 1.9
B96: 10-12. | C96: 75837.2 | D96: -2.7 | E96: 262589.3 | F96: -1.8 | G96: 2011/4-3. | H96: 245638.6 | I96: 0.7 | L96: 10-12. | M96: 73086.8 | N96: -0.8 | O96: 254351.6 | P96: -1 | Q96: 2011/4-3. | R96: 259456.9 | S96: 1.4
A97: 2002/ | B97: 1-3. | C97: 56926.8 | D97: -2.3 | E97: 264757 | F97: 0.8 | G97: 2012/4-3. | H97: 245924 | I97: 0.1 | K97: 2002/ | L97: 1-3. | M97: 55604.4 | N97: -0.1 | O97: 256929.6 | P97: 1 | Q97: 2012/4-3. | R97: 261489 | S97: 0.8
B98: 4-6. | C98: 66777.4 | D98: -3.1 | E98: 259163 | F98: -2.1 | G98: 2013/4-3. | H98: 247851.1 | I98: 0.8 | L98: 4-6. | M98: 64802.8 | N98: -1.4 | O98: 252366.7 | P98: -1.8 | Q98: 2013/4-3. | R98: 261844.3 | S98: 0.1
B99: 7-9. | C99: 61646.7 | D99: -3.7 | E99: 258526.3 | F99: -0.2 | G99: 2014/4-3. | H99: 252491.6 | I99: 1.9 | L99: 7-9. | M99: 60353.2 | N99: -2.1 | O99: 252669.1 | P99: 0.1 | Q99: 2014/4-3. | R99: 259130.2 | S99: -1
B100: 10-12. | C100: 74319.8 | D100: -2 | E100: 256471 | F100: -0.8 | G100: 2015/4-3. | H100: 256850.6 | I100: 1.7 | L100: 10-12. | M100: 72537.2 | N100: -0.8 | O100: 251480.3 | P100: -0.5 | Q100: 2015/4-3. | R100: 263747 | S100: 1.8
...

Sheet kgaku-mk1131
A1: 名目季節調整系列 | R1: (単位:10億円)
A2: Nominal (seasonally adjusted series) | R2: (billion yen)
B3: 家計最終消費支出（再掲） | M3: 財貨・サービス
C4: 居住者家計の海外での直接購入 | D4: （控除）非居住者家計の国内での直接購入 | E4: 国内家計最終消費支出 | L4: 純輸出（再掲） | M4: 輸出（再掲） | P4: 輸入（再掲）
F5: 耐久財 | G5: 半耐久財 | H5: 非耐久財 | I5: サービス | N5: 財貨 | O5: サービス（含む非居住者家計の国内での直接購入） | Q5: 財貨 | R5: サービス（含む居住者家計の海外での直接購入）
B6: Consumptionof households(id, at §Ｉ) | C6: Directpurchasesabroad byresidenthouseholds | D6: (Less) Directpurchases inthe domesticmarket bynon-residenthouseholds | E6: Domestic final consumption expenditure of households | F6: Durablegoods | G6: Semi-durablegoods | H6: Non-durablegoods | I6: Services | M6: Goods & Services
L7: Net Exports(id, at §Ｉ) | M7: Exports(id, at §Ｉ) | P7: Imports(id, at §Ｉ)
N8: Goods | O8: Services（including directpurchases in thedomestic marketby non-residenthouseholds) | Q8: Goods | R8: Services（including directpurchasesabroad byresidenthouseholds)
A9: 1980/ 1- 3. | B9: 126227.9 | C9: 617.1 | D9: 97.7 | E9: 125708.5 | F9: 8636.7 | G9: 16644.7 | H9: 45044.9 | I9: 55382.1 | L9: -3378.3 | M9: 32405.7 | N9: 28347.2 | O9: 4058.4 | P9: 35783.9 | Q9: 29652.4 | R9: 6131.5
A10: 4- 6. | B10: 128731.1 | C10: 625 | D10: 94.4 | E10: 128200.5 | F10: 8282.7 | G10: 17020.1 | H10: 46185.1 | I10: 56712.6 | L10: -4367.3 | M10: 32842.5 | N10: 28954.6 | O10: 3887.9 | P10: 37209.8 | Q10: 31238.9 | R10: 5970.9
A11: 7- 9. | B11: 131821.4 | C11: 624.8 | D11: 89.7 | E11: 131286.3 | F11: 8254.2 | G11: 17233.4 | H11: 47236.7 | I11: 58562 | L11: -1801.9 | M11: 31961.2 | N11: 28252.9 | O11: 3708.2 | P11: 33763.1 | Q11: 28167 | R11: 5596.1
A12: 10-12. | B12: 133934.7 | C12: 532.3 | D12: 93.1 | E12: 133495.5 | F12: 8329.1 | G12: 17748.9 | H12: 48217.9 | I12: 59199.6 | L12: 556.2 | M12: 34029.9 | N12: 30260.8 | O12: 3769.1 | P12: 33473.7 | Q12: 27660.5 | R12: 5813.2
A13: 1981/ 1- 3. | B13: 135583.3 | C13: 572.2 | D13: 95.6 | E13: 135106.6 | F13: 8243.4 | G13: 17163.6 | H13: 49269 | I13: 60430.6 | L13: 1194.6 | M13: 35309.6 | N13: 31386.9 | O13: 3922.7 | P13: 34115 | Q13: 28044.7 | R13: 6070.2
A14: 4- 6. | B14: 137352.8 | C14: 560.2 | D14: 97.1 | E14: 136889.7 | F14: 8711.4 | G14: 16940.8 | H14: 49679.2 | I14: 61558.4 | L14: 1281.3 | M14: 37673.8 | N14: 33369.9 | O14: 4303.9 | P14: 36392.5 | Q14: 29945.2 | R14: 6447.3
A15: 7- 9. | B15: 139438.9 | C15: 564.9 | D15: 120.4 | E15: 138994.4 | F15: 8999.9 | G15: 17159.2 | H15: 50352.8 | I15: 62482.5 | L15: 2879.2 | M15: 39338.2 | N15: 34896.8 | O15: 4441.4 | P15: 36458.9 | Q15: 29910.9 | R15: 6548
A16: 10-12. | B16: 141814 | C16: 556.6 | D16: 98.9 | E16: 141356.3 | F16: 8825.6 | G16: 17703.6 | H16: 51284.1 | I16: 63543.1 | L16: 2106.7 | M16: 38834.4 | N16: 34507.3 | O16: 4327 | P16: 36727.7 | Q16: 30152.6 | R16: 6575.1
A17: 1982/ 1- 3. | B17: 145022.4 | C17: 532 | D17: 109.1 | E17: 144599.5 | F17: 8996.3 | G17: 18460.6 | H17: 51693.6 | I17: 65448.9 | L17: 1863.7 | M17: 39909.6 | N17: 35318.2 | O17: 4591.4 | P17: 38045.9 | Q17: 31386.3 | R17: 6659.6
A18: 4- 6. | B18: 147947.7 | C18: 513.5 | D18: 125 | E18: 147559.1 | F18: 9359.2 | G18: 18574 | H18: 52642.3 | I18: 66983.5 | L18: 2014.4 | M18: 39106.5 | N18: 34628.2 | O18: 4478.3 | P18: 37092 | Q18: 30482.2 | R18: 6609.8
A19: 7- 9. | B19: 148700.2 | C19: 516.2 | D19: 121.3 | E19: 148305.3 | F19: 9177.8 | G19: 18850.5 | H19: 53156.4 | I19: 67120.7 | L19: 1920.6 | M19: 39212.3 | N19: 34696.7 | O19: 4515.6 | P19: 37291.7 | Q19: 30616.2 | R19: 6675.5
A20: 10-12. | B20: 153540.7 | C20: 539.5 | D20: 135.3 | E20: 153136.5 | F20: 10260.4 | G20: 18974.9 | H20: 53777 | I20: 70124.2 | L20: 1639.6 | M20: 38591.4 | N20: 34051.6 | O20: 4539.8 | P20: 36951.8 | Q20: 30213.8 | R20: 6738
... A135: 7- 9. | B135: 271665.8 | C135: 1932.8 | D135: 706.8 | E135: 270439.8 | F135: 21847.2 | G135: 19227.6 | H135: 72622.7 | I135: 156742.3 | L135: -4801.6 | M135: 72755.7 | N135: 64933.2 | O135: 7822.5 | P135: 77557.3 | Q135: 66414.1 | R135: 11143.2
A136: ＊年率で表示している。
A139: avg | B139: =+AVERAGE(B9:B135) -> 239166.08 | C139: =+AVERAGE(C9:C135) -> 2136.3819 | D139: =+AVERAGE(D9:D135) -> 399.30866 | E139: =+AVERAGE(E9:E135) -> 237429 | F139: =+AVERAGE(F9:F135) -> 20408.809 | G139: =+AVERAGE(G9:G135) -> 23519.694 | H139: =+AVERAGE(H9:H135) -> 68177.198 | I139: =+AVERAGE(I9:I135) -> 125323.29 | L139: =+AVERAGE(L9:L135) -> 6315.248

Sheet kgaku-jk1131
A1: 実質季節調整系列 | R1: (単位:2000暦年連鎖価格、10億円)
A2: Real (seasonally adjusted series) | R2: (Billions of chained (2000) yen)
B3: 家計最終消費支出（再掲） | M3: 財貨・サービス
C4: 居住者家計の海外での直接購入 | D4: （控除）非居住者家計の国内での直接購入 | E4: 国内家計最終消費支出 | L4: 純輸出（再掲） | M4: 輸出（再掲） | P4: 輸入（再掲）
F5: 耐久財 | G5: 半耐久財 | H5: 非耐久財 | I5: サービス | N5: 財貨 | O5: サービス（含む非居住者家計の国内での直接購入） | Q5: 財貨 | R5: サービス（含む居住者家計の海外での直接購入）
B6: Consumptionof households(id, at §Ｉ) | C6: Directpurchasesabroad byresidenthouseholds | D6: (Less) Directpurchases inthe domesticmarket bynon-residenthouseholds | E6: Domestic finalconsumptionexpenditure ofhouseholds | F6: Durablegoods | G6: Semi-durablegoods | H6: Non-durablegoods | I6: Services | M6: Goods & Services
L7: Net Exports(id, at §Ｉ) | M7: Exports(id, at §Ｉ) | P7: Imports(id, at §Ｉ)
N8: Goods | O8: Services（including directpurchases in thedomestic marketby non-residenthouseholds) | Q8: Goods | R8: Services（including directpurchasesabroad byresidenthouseholds)
A9: 1980/ 1- 3. | B9: 164321.7 | C9: 663.2 | D9: 130.9 | E9: 163400.1 | F9: 5146.7 | G9: 20835.2 | H9: 56436.4 | I9: 85122.8 | L9: 1300.1 | M9: 19818.1 | N9: 16541.6 | O9: 3718.4 | P9: 18518 | Q9: 13532.1 | R9: 4808.5
A10: 4- 6. | B10: 164003.9 | C10: 698 | D10: 123.4 | E10: 163036.3 | F10: 4937.9 | G10: 21100.4 | H10: 55984.2 | I10: 85458 | L10: 693.7 | M10: 20099.1 | N10: 16940.5 | O10: 3517 | P10: 19405.4 | Q10: 14366.5 | R10: 4724.6
A11: 7- 9. | B11: 165557.5 | C11: 733.5 | D11: 115.3 | E11: 164539.3 | F11: 4900.1 | G11: 21089 | H11: 56052.2 | I11: 87265.6 | L11: 1704.1 | M11: 19895.4 | N11: 16827.5 | O11: 3390.5 | P11: 18191.3 | Q11: 13387.8 | R11: 4563.9
A12: 10-12. | B12: 166481.3 | C12: 608 | D12: 119.9 | E12: 165606.8 | F12: 4923.5 | G12: 21398.6 | H12: 56729.3 | I12: 87251.9 | L12: 3168.6 | M12: 21244.1 | N12: 18073.3 | O12: 3458 | P12: 18075.5 | Q12: 13322.8 | R12: 4500.7
A13: 1981/ 1- 3. | B13: 166230.2 | C13: 629 | D13: 120.1 | E13: 165332.6 | F13: 4889.6 | G13: 20496.2 | H13: 56731.8 | I13: 88110.9 | L13: 3477.8 | M13: 21863.2 | N13: 18669.5 | O13: 3451.2 | P13: 18385.4 | Q13: 13403 | R13: 4828.5
A14: 4- 6. | B14: 167358.8 | C14: 575.3 | D14: 120.9 | E14: 166520.2 | F14: 5169.7 | G14: 20213.5 | H14: 56840.9 | I14: 89021.1 | L14: 3941.5 | M14: 22919.7 | N14: 19469 | O14: 3776.8 | P14: 18978.3 | Q14: 13731.1 | R14: 5160.2
A15: 7- 9. | B15: 168444.5 | C15: 547.4 | D15: 148.6 | E15: 167662.4 | F15: 5335.1 | G15: 20339.4 | H15: 57121.1 | I15: 89455.6 | L15: 4554 | M15: 23568.1 | N15: 20029.7 | O15: 3868.3 | P15: 19014.1 | Q15: 13585.9 | R15: 5459.3
A16: 10-12. | B16: 169824.3 | C16: 534.6 | D16: 122.4 | E16: 169029.1 | F16: 5233.1 | G16: 20831.4 | H16: 57826.5 | I16: 89855.3 | L16: 4123.6 | M16: 23478.1 | N16: 19973.6 | O16: 3822 | P16: 19354.6 | Q16: 13805.9 | R16: 5596.4
A17: 1982/ 1- 3. | B17: 172416.5 | C17: 475.9 | D17: 133 | E17: 171698.3 | F17: 5337.8 | G17: 21664 | H17: 57822.2 | I17: 91768.2 | L17: 3824.9 | M17: 23493.6 | N17: 19920.2 | O17: 3924.6 | P17: 19668.7 | Q17: 13986.8 | R17: 5775.2
A18: 4- 6. | B18: 175600 | C18: 445.4 | D18: 151.9 | E18: 174932.2 | F18: 5589 | G18: 21740.2 | H18: 59293.8 | I18: 93051.5 | L18: 4443.6 | M18: 23268.1 | N18: 19757.3 | O18: 3844.3 | P18: 18824.5 | Q18: 13368.1 | R18: 5560
A19: 7- 9. | B19: 175110.7 | C19: 426.4 | D19: 145.8 | E19: 174461.8 | F19: 5486.3 | G19: 21866.7 | H19: 59241.5 | I19: 92657.2 | L19: 4681.8 | M19: 23302.5 | N19: 19796.8 | O19: 3834.6 | P19: 18620.7 | Q19: 13081.3 | R19: 5752.3
A20: 10-12. | B20: 179828.1 | C20: 430.9 | D20: 163.6 | E20: 179185.2 | F20: 6159.5 | G20: 21859.3 | H20: 59757 | I20: 95997.1 | L20: 5034.7 | M20: 23157.6 | N20: 19659.4 | O20: 3832.2 | P20: 18122.9 | Q20: 12668 | R20: 5711.6
... A135: 7- 9. | B135: 302118.6 | C135: 1623.2 | D135: 737.2 | E135: 301039.1 | F135: 57368.3 | G135: 21414.8 | H135: 69777.4 | I135: 163276.7 | L135: 24646.5 | M135: 85965.7 | N135: 77299.2 | O135: 8759.2 | P135: 61319.2 | Q135: 52089.1 | R135: 9576.1
A136: ＊年率で表示している。
A139: avg | B139: =+AVERAGE(B9:B135) -> 252273.82 | C139: =+AVERAGE(C9:C135) -> 2041.1402 | D139: =+AVERAGE(D9:D135) -> 415.48583 | E139: =+AVERAGE(E9:E135) -> 250220.26 | F139: =+AVERAGE(F9:F135) -> 22165.157 | G139: =+AVERAGE(G9:G135) -> 24611.282 | H139: =+AVERAGE(H9:H135) -> 69798.688 | I139: =+AVERAGE(I9:I135) -> 135865.37 | L139: =+AVERAGE(L9:L135) -> 8983.3441

Sheet gaku-mk1131
A1: 名目季節調整系列 | P1: <参考> | Y1: (単位:10億円)
A2: Nominal Gross Domestic Product (seasonally adjusted series) | P2: <cf> | Y2: (billion yen)
B3: 国内総生産(支出側) | C3: 民間最終消費支出 | F3: 民間住宅 | G3: 民間企業設備 | H3: 民間在庫品増加 | I3: 政府最終消費支出 | J3: 公的固定資本形成 | K3: 公的在庫品増加 | L3: 財貨・サービス | P3: 海外からの所得 | S3: 国民総所得 | U3: 国内需要 | V3: 民間需要 | W3: 公的需要 | Y3: 総固定資本形成
D4: 家計最終消費支出 | L4: 純輸出 | M4: 輸出 | N4: 輸入 | P4: 純受取 | Q4: 受取 | R4: 支払
E5: 除く持ち家の帰属家賃
B6: GDP(expenditure approach) | C6: PrivateConsumption | D6: Consumption ofHouseholds | E6: Excludingimputed rent | F6: PrivateResidentialInvestment | G6: Private Non-Resi.Investment | H6: PrivateInventory | I6: GovernmentConsumption | J6: PublicInvestment | K6: PublicInventory | L6: Goods & Services | P6: Income from /to the rest of the world | S6: GNI | U6: Domestic Demand | V6: PrivateDemand | W6: PublicDemand | Y6: Gross fixed capitalformation
L7: Net Exports | M7: Exports | N7: Imports | P7: Net | Q7: Receipt | R7: Payment
A8: 1980/ 1- 3. | B8: 233029.6 | C8: 128052.3 | D8: 126227.9 | E8: 112301.7 | F8: 15583.7 | G8: 37613.5 | H8: 195.3 | I8: 32919.4 | J8: 22358 | K8: -314.4 | L8: -3378.3 | M8: 32405.7 | N8: 35783.9 | P8: -61 | Q8: 2738.4 | R8: 2799.5 | S8: 232968.6 | U8: 236407.9 | V8: 181444.8 | W8: 54963.1 | Y8: 75555.2
A9: 4- 6. | B9: 237769.2 | C9: 130597.2 | D9: 128731.1 | E9: 114369.3 | F9: 15962 | G9: 38771.5 | H9: 1210.8 | I9: 33600.2 | J9: 22235 | K9: -240.1 | L9: -4367.3 | M9: 32842.5 | N9: 37209.8 | P9: -150.3 | Q9: 2611 | R9: 2761.3 | S9: 237618.9 | U9: 242136.5 | V9: 186541.4 | W9: 55595.1 | Y9: 76968.5
A10: 7- 9. | B10: 245482.1 | C10: 133751.5 | D10: 131821.4 | E10: 117166.8 | F10: 15226.9 | G10: 39100.1 | H10: 2439.1 | I10: 34420.7 | J10: 22425 | K10: -79.3 | L10: -1801.9 | M10: 31961.2 | N10: 33763.1 | P10: -13.7 | Q10: 2557.4 | R10: 2571.2 | S10: 245468.3 | U10: 247284 | V10: 190517.6 | W10: 56766.4 | Y10: 76752
A11: 10-12. | B11: 253512.7 | C11: 135908.7 | D11: 133934.7 | E11: 118987.3 | F11: 14633.4 | G11: 39978.5 | H11: 2761 | I11: 36038.8 | J11: 23886.4 | K11: -250.2 | L11: 556.2 | M11: 34029.9 | N11: 33473.7 | P11: 43 | Q11: 2616.1 | R11: 2573.1 | S11: 253555.7 | U11: 252956.6 | V11: 193281.6 | W11: 59675 | Y11: 78498.3
A12: 1981/ 1- 3. | B12: 255922.4 | C12: 137581.4 | D12: 135583.3 | E12: 120303.3 | F12: 14649.3 | G12: 40811.6 | H12: 1676.9 | I12: 35605.1 | J12: 24660.5 | K12: -257 | L12: 1194.6 | M12: 35309.6 | N12: 34115 | P12: -520 | Q12: 2972.5 | R12: 3492.5 | S12: 255402.4 | U12: 254727.8 | V12: 194719.2 | W12: 60008.6 | Y12: 80121.4
A13: 4- 6. | B13: 260361.1 | C13: 139382.7 | D13: 137352.8 | E13: 121750.6 | F13: 14996.9 | G13: 40684.7 | H13: 4086.1 | I13: 36368.7 | J13: 23853.5 | K13: -292.7 | L13: 1281.3 | M13: 37673.8 | N13: 36392.5 | P13: -484 | Q13: 3432 | R13: 3916 | S13: 259877.1 | U13: 259079.8 | V13: 199150.4 | W13: 59929.5 | Y13: 79535.1
A14: 7- 9. | B14: 261195.9 | C14: 141508.4 | D14: 139438.9 | E14: 123528 | F14: 15093.6 | G14: 41092.9 | H14: -428.1 | I14: 36998 | J14: 24359.2 | K14: -307.3 | L14: 2879.2 | M14: 39338.2 | N14: 36458.9 | P14: -561.1 | Q14: 3876.3 | R14: 4437.4 | S14: 260634.8 | U14: 258316.6 | V14: 197266.7 | W14: 61049.9 | Y14: 80545.6
A15: 10-12. | B15: 265677.1 | C15: 143903.8 | D15: 141814 | E15: 125605.7 | F15: 14582.1 | G15: 41827.3 | H15: 891.2 | I15: 38339.7 | J15: 24092.2 | K15: -65.8 | L15: 2106.7 | M15: 38834.4 | N15: 36727.7 | P15: -199.9 | Q15: 4255.1 | R15: 4455 | S15: 265477.2 | U15: 263570.4 | V15: 201204.3 | W15: 62366.1 | Y15: 80501.6
A16: 1982/ 1- 3. | B16: 271140 | C16: 147113.1 | D16: 145022.4 | E16: 128519.3 | F16: 14461.4 | G16: 41721 | H16: 3617.9 | I16: 38694.3 | J16: 23907.4 | K16: -238.8 | L16: 1863.7 | M16: 39909.6 | N16: 38045.9 | P16: -125.4 | Q16: 4467.1 | R16: 4592.5 | S16: 271014.6 | U16: 269276.3 | V16: 206913.3 | W16: 62362.9 | Y16: 80089.9
A17: 4- 6. | B17: 272602.8 | C17: 150022.9 | D17: 147947.7 | E17: 131146.4 | F17: 14679.6 | G17: 42343.7 | H17: 661.6 | I17: 39111.4 | J17: 23934.8 | K17: -165.6 | L17: 2014.4 | M17: 39106.5 | N17: 37092 | P17: -180.1 | Q17: 4754.2 | R17: 4934.4 | S17: 272422.6 | U17: 270588.3 | V17: 207707.8 | W17: 62880.6 | Y17: 80958.1
A18: 7- 9. | B18: 274408.1 | C18: 150768.2 | D18: 148700.2 | E18: 131616.9 | F18: 15097.2 | G18: 42485.3 | H18: 1129.9 | I18: 39609.8 | J18: 23901.3 | K18: -504.3 | L18: 1920.6 | M18: 39212.3 | N18: 37291.7 | P18: 164.4 | Q18: 4825.8 | R18: 4661.4 | S18: 274572.5 | U18: 272487.4 | V18: 209480.7 | W18: 63006.8 | Y18: 81483.8
A19: 10-12. | B19: 277819.1 | C19: 155641.4 | D19: 153540.7 | E19: 136190.9 | F19: 15543.9 | G19: 41850.9 | H19: 459 | I19: 39257.6 | J19: 23848.7 | K19: -422 | L19: 1639.6 | M19: 38591.4 | N19: 36951.8 | P19: 605.2 | Q19: 4993 | R19: 4387.7 | S19: 278424.3 | U19: 276179.4 | V19: 213495.2 | W19: 62684.3 | Y19: 81243.4
... A134: 7- 9. | B134: 469552.2 | C134: 278005.8 | D134: 271665.8 | E134: 225085.6 | F134: 13967.6 | G134: 65575.3 | H134: -499 | I134: 98025 | J134: 19015.5 | K134: 263.6 | L134: -4801.6 | M134: 72755.7 | N134: 77557.3 | P134: 15002.9 | Q134: 20851.7 | R134: 5848.9 | S134: 484555.1 | U134: 474353.8 | V134: 357049.7 | W134: 117304.2 | Y134: 98558.4
A135: ＊年率で表示している。
A136: ＊総固定資本形成＝民間住宅＋民間企業設備＋公的固定資本形成
A139: avg | B139: =+AVERAGE(B9:B135) -> 438515.47 | C139: =+AVERAGE(C9:C135) -> 244662.99 | D139: =+AVERAGE(D9:D135) -> 240062.42 | E139: =+AVERAGE(E9:E135) -> 205665.78 | F139: =+AVERAGE(F9:F135) -> 19082.314 | G139: =+AVERAGE(G9:G135) -> 68070.467 | H139: =+AVERAGE(H9:H135) -> 957.63968 | I139: =+AVERAGE(I9:I135) -> 70746.279 | ... L139: =+AVERAGE(L9:L135) -> 6392.181 | W139: =+AVERAGE(W9:W135) -> 99349.878
C140: =+C139/$C$139 -> 1 | F140: =+F139/$C$139 -> 0.077994282 | I140: =+I139/$C$139 -> 0.28915807 | J140: =+J139/$C$139 -> 0.11643713 | K140: =+K139/$C$139 -> 0.00047306407 | W140: =+W139/$C$139 -> 0.40606827
G141: =+G139/$G$139 -> 1 | H141: =+H139/$G$139 -> 0.014068358 | L141: =+L139/$G$139 -> 0.093905348

Sheet gaku-jk1131
A1: 実質季節調整系列 | Q1: <参考> | AB1: (単位:2000暦年連鎖価格、10億円)
A2: Real Gross Domestic Product (seasonally adjusted series) | Q2: <cf> | AB2: (Billions of chained (2000) yen)
B3: 国内総生産(支出側) | C3: 民間最終消費支出 | F3: 民間住宅 | G3: 民間企業設備 | H3: 民間在庫品増加 | I3: 政府最終消費支出 | J3: 公的固定資本形成 | K3: 公的在庫品増加 | L3: 財貨・サービス | O3: 開差 | Q3: 交易利得 | R3: 国内総所得 | S3: 海外からの所得 | V3: 国民総所得 | X3: 国内需要 | Y3: 民間需要 | Z3: 公的需要 | AB3: 総固定資本形成
D4: 家計最終消費支出 | L4: 純輸出 | M4: 輸出 | N4: 輸入 | S4: 純受取 | T4: 受取 | U4: 支払
E5: 除く持ち家の帰属家賃
B6: GDP(expenditure approach) | C6: PrivateConsumption | D6: Consumption ofHouseholds | E6: Excludingimputed rent | F6: PrivateResidentialInvestment | G6: Private Non-Resi.Investment | H6: PrivateInventory | I6: GovernmentConsumption | J6: PublicInvestment | K6: PublicInventory | L6: Goods & Services | O6: Residual | Q6: Tradinggains/losses | R6: GDI | S6: Income from /to the rest of the world | V6: GNI | X6: DomesticDemand | Y6: PrivateDemand | Z6: PublicDemand | AB6: Gross fixed capitalformation
L7: Net Exports | M7: Exports | N7: Imports | S7: Net | T7: Receipt | U7: Payment
A8: 1980/ 1- 3. | B8: 280828.2 | C8: 166750.6 | D8: 164321.7 | E8: 139484.8 | F8: 19358.5 | G8: 34479.1 | H8: 568.9 | I8: 42623.1 | J8: 25651.5 | K8: -2196.8 | L8: 1300.1 | M8: 19818.1 | N8: 18518 | O8: -7706.8 | Q8: -3199.4 | R8: 277628.8 | S8: -70.3 | T8: 3305.6 | U8: 3375.9 | V8: 277558.5 | X8: 285025.8 | Y8: 218515 | Z8: 66976 | AB8: 77308.7
A9: 4- 6. | B9: 279347.8 | C9: 166430.2 | D9: 164003.9 | E9: 138851.7 | F9: 19104.4 | G9: 34907.1 | H9: 842.6 | I9: 42929.9 | J9: 24673.4 | K9: -1964.7 | L9: 693.7 | M9: 20099.1 | N9: 19405.4 | O9: -8268.9 | Q9: -3156.6 | R9: 276191.2 | S9: -180.1 | T9: 3075.8 | U9: 3255.9 | V9: 276011.1 | X9: 284979.4 | Y9: 219074.4 | Z9: 66353.8 | AB9: 76696.1
A10: 7- 9. | B10: 285605 | C10: 168019.5 | D10: 165557.5 | E10: 140164.1 | F10: 18488.6 | G10: 34904.7 | H10: 2277 | I10: 43416.2 | J10: 24607.9 | K10: -2228.9 | L10: 1704.1 | M10: 19895.4 | N10: 18191.3 | O10: -5584.2 | Q10: -2748.3 | R10: 282856.6 | S10: -16.7 | T10: 2980.4 | U10: 2997.2 | V10: 282839.9 | X10: 288941.4 | Y10: 222794.8 | Z10: 66583.3 | AB10: 76129.4
A11: 10-12. | B11: 291675.5 | C11: 168970.5 | D11: 166481.3 | E11: 140885.9 | F11: 18007.2 | G11: 35675.3 | H11: 2216.1 | I11: 44014.2 | J11: 26232.4 | K11: -2749.8 | L11: 3168.6 | M11: 21244.1 | N11: 18075.5 | O11: -3858.9 | Q11: -2844.7 | R11: 288830.9 | S11: 47.3 | T11: 3022.5 | U11: 2975.2 | V11: 288878.2 | X11: 292201.6 | Y11: 224088.3 | Z11: 68587.7 | AB11: 78053.1
A12: 1981/ 1- 3. | B12: 293463.7 | C12: 168737.9 | D12: 166230.2 | E12: 140489.3 | F12: 18094.2 | G12: 36179.8 | H12: 1737.1 | I12: 44521.7 | J12: 26990.6 | K12: -1982 | L12: 3477.8 | M12: 21863.2 | N12: 18385.4 | O12: -4293.4 | Q12: -2785.2 | R12: 290678.5 | S12: -596.7 | T12: 3419.6 | U12: 4016.3 | V12: 290081.8 | X12: 293504 | Y12: 223656.4 | Z12: 70362.7 | AB12: 79367.7
A13: 4- 6. | B13: 297055 | C13: 169896.1 | D13: 167358.8 | E13: 141412.8 | F13: 18419.6 | G13: 36176.5 | H13: 2574.6 | I13: 45458.2 | J13: 26030 | K13: -1992.9 | L13: 3941.5 | M13: 22919.7 | N13: 18978.3 | O13: -3448.6 | Q13: -3216.7 | R13: 293838.4 | S13: -556.3 | T13: 3932.8 | U13: 4489.2 | V13: 293282.1 | X13: 296411.2 | Y13: 226699.1 | Z13: 70210 | AB13: 78766.7
A14: 7- 9. | B14: 296394.3 | C14: 171014.6 | D14: 168444.5 | E14: 142302.8 | F14: 18538.7 | G14: 36687.1 | H14: 276.1 | I14: 45951.7 | J14: 26397.4 | K14: -1839.5 | L14: 4554 | M14: 23568.1 | N14: 19014.1 | O14: -5185.8 | Q14: -2936.5 | R14: 293457.8 | S14: -641.4 | T14: 4413.9 | U14: 5055.3 | V14: 292816.5 | X14: 294594 | Y14: 223953.4 | Z14: 71172.7 | AB14: 79763
A15: 10-12. | B15: 298557.8 | C15: 172400.5 | D15: 169824.3 | E15: 143470 | F15: 17726.3 | G15: 37260.6 | H15: 1027.5 | I15: 46590.1 | J15: 26008.6 | K15: -1596.2 | L15: 4123.6 | M15: 23478.1 | N15: 19354.6 | O15: -4983.1 | Q15: -2929.4 | R15: 295628.4 | S15: -228.5 | T15: 4806.8 | U15: 5035.3 | V15: 295399.9 | X15: 297693.3 | Y15: 226708.8 | Z15: 71512.2 | AB15: 79385
A16: 1982/ 1- 3. | B16: 303133.2 | C16: 174972.9 | D16: 172416.5 | E16: 145790 | F16: 17460.6 | G16: 36887.5 | H16: 2909.9 | I16: 47083.6 | J16: 25703.7 | K16: -1729.4 | L16: 3824.9 | M16: 23493.6 | N16: 19668.7 | O16: -3980.5 | Q16: -2793 | R16: 300340.1 | S16: -141 | T16: 5024.4 | U16: 5165.4 | V16: 300199.2 | X16: 302942.2 | Y16: 231864.8 | Z16: 71568.5 | AB16: 78479
A17: 4- 6. | B17: 305214.4 | C17: 178113.1 | D17: 175600 | E17: 148681.7 | F17: 17728.4 | G17: 37765.3 | H17: 672.2 | I17: 47373.9 | J17: 25769.3 | K17: -1532.8 | L17: 4443.6 | M17: 23268.1 | N17: 18824.5 | O17: -5118.7 | Q17: -3330.8 | R17: 301883.5 | S17: -202.9 | T17: 5338.3 | U17: 5541.1 | V17: 301680.6 | X17: 303624.4 | Y17: 232086.7 | Z17: 72042.8 | AB17: 79731.5
A18: 7- 9. | B18: 306548.2 | C18: 177590.4 | D18: 175110.7 | E18: 148063.1 | F18: 18133.2 | G18: 37735.6 | H18: 1180.2 | I18: 47864.3 | J18: 25581.6 | K18: -1915.7 | L18: 4681.8 | M18: 23302.5 | N18: 18620.7 | O18: -4303.1 | Q18: -3629.3 | R18: 302918.9 | S18: 180 | T18: 5379.1 | U18: 5199.1 | V18: 303099 | X18: 304449.2 | Y18: 232889 | Z18: 72059.7 | AB18: 79855.4
A19: 10-12. | B19: 310808 | C19: 182334 | D19: 179828.1 | E19: 152401.1 | F19: 18597.5 | G19: 37055.1 | H19: 802.1 | I19: 48340.5 | J19: 25442.4 | K19: -2211 | L19: 5034.7 | M19: 23157.6 | N19: 18122.9 | O19: -4587.4 | Q19: -4138.7 | R19: 306669.3 | S19: 674.7 | T19: 5572.6 | U19: 4897.9 | V19: 307344.1 | X19: 307907.1 | Y19: 236214.2 | Z19: 72170 | AB19: 79348.5
... A134: 7- 9. | B134: 542503.9 | C134: 308997.9 | D134: 302118.6 | E134: 250367.9 | F134: 13315.3 | G134: 73474.3 | H134: -287.7 | I134: 105080.7 | J134: 18443.1 | K134: 314.7 | L134: 24646.5 | M134: 85965.7 | N134: 61319.2 | O134: -1481 | Q134: -29351.4 | R134: 513152.5 | S134: 16348.9 | T134: 22705.1 | U134: 6356.2 | V134: 529501.4 | X134: 518013 | Y134: 394281.1 | Z134: 123569.6 | AB134: 104594.9
A135: ＊年率で表示している。
A136: ＊開差＝国内総生産(支出側)－国内総生産(支出側)の内訳項目計

Sheet kshotoku1722
A1: Ⅲ.雇用者報酬
A2: Compensation of Employees | S2: (単位:10億円、%)
A3: 名 目 | K3: 実 質(2011暦年連鎖価格)
A4: Nominal | K4: Real (Chained (2011) Yen)
C5: 四半期・原系列 | E5: 四半期・季節調整系列 | G5: 年度 、 暦年 | M5: 四半期・原系列 | O5: 四半期・季節調整系列 | Q5: 年度 、 暦年
C6: Original Series | E6: Seasonally Adjusted Series | G6: Fiscal Year , Calendar Year | M6: Original Series | O6: Seasonally Adjusted Series | Q6: Fiscal Year , Calendar Year
C7: 実数 | D7: (**) | E7: 実数 | F7: (***) | H7: 実数 | I7: (**) | M7: 実数 | N7: (**) | O7: 実数 | P7: (***) | R7: 実数 | S7: (**)
C8: Billion Yen | D8: (**) | E8: Billion Yen | F8: (***) | H8: Billion Yen | I8: (**) | M8: Billion Yen | N8: (**) | O8: Billion Yen | P8: (***) | R8: Billion Yen | S8: (**)
A9: 1994/ | B9: 1-3. | C9: 53407.2 | E9: 257247.3 | K9: 1994/ | L9: 1-3. | M9: 47687.9 | O9: 228441.1
B10: 4-6. | C10: 66121.2 | E10: 263611.9 | F10: 2.5 | L10: 4-6. | M10: 58404.7 | O10: 233595.2 | P10: 2.3
B11: 7-9. | C11: 63292.8 | E11: 259229.4 | F11: -1.7 | L11: 7-9. | M11: 56364.7 | O11: 230373.1 | P11: -1.4
B12: 10-12. | C12: 78268.5 | E12: 263214.7 | F12: 1.5 | L12: 10-12. | M12: 69264 | O12: 233918.5 | P12: 1.5
A13: 1995/ | B13: 1-3. | C13: 54613.6 | D13: 2.3 | E13: 262822.7 | F13: -0.1 | K13: 1995/ | L13: 1-3. | M13: 48929.7 | N13: 2.6 | O13: 234197.7 | P13: 0.1
B14: 4-6. | C14: 66251.3 | D14: 0.2 | E14: 264163.8 | F14: 0.5 | L14: 4-6. | M14: 59095.6 | N14: 1.2 | O14: 236474.2 | P14: 1
B15: 7-9. | C15: 64975.6 | D15: 2.7 | E15: 265998 | F15: 0.7 | L15: 7-9. | M15: 58397.6 | N15: 3.6 | O15: 238589 | P15: 0.9
B16: 10-12. | C16: 79668.1 | D16: 1.8 | E16: 268509.3 | F16: 0.9 | L16: 10-12. | M16: 71295 | N16: 2.9 | O16: 241245.8 | P16: 1.1
A17: 1996/ | B17: 1-3. | C17: 55704.7 | D17: 2 | E17: 267305.4 | F17: -0.4 | K17: 1996/ | L17: 1-3. | M17: 50398.9 | N17: 3 | O17: 240523 | P17: -0.3
B18: 4-6. | C18: 67411.9 | D18: 1.8 | E18: 268747.4 | F18: 0.5 | L18: 4-6. | M18: 60350.9 | N18: 2.1 | O18: 241383.4 | P18: 0.4
B19: 7-9. | C19: 66353.5 | D19: 2.1 | E19: 271624.3 | F19: 1.1 | L19: 7-9. | M19: 59818.7 | N19: 2.4 | O19: 244429.8 | P19: 1.3
B20: 10-12. | C20: 80720.9 | D20: 1.3 | E20: 272798.8 | F20: 0.4 | L20: 10-12. | M20: 72333.8 | N20: 1.5 | O20: 245517.7 | P20: 0.4
A21: 1997/ | B21: 1-3. | C21: 57974.1 | D21: 4.1 | E21: 277130.1 | F21: 1.6 | K21: 1997/ | L21: 1-3. | M21: 52494.4 | N21: 4.2 | O21: 249487 | P21: 1.6
B22: 4-6. | C22: 69814.1 | D22: 3.6 | E22: 278190.1 | F22: 0.4 | L22: 4-6. | M22: 61620.9 | N22: 2.1 | O22: 246372.8 | P22: -1.2
B23: 7-9. | C23: 68188.3 | D23: 2.8 | E23: 279329.9 | F23: 0.4 | L23: 7-9. | M23: 60560.9 | N23: 1.2 | O23: 247512.1 | P23: 0.5
B24: 10-12. | C24: 82266.2 | D24: 1.9 | E24: 278817.4 | F24: -0.2 | L24: 10-12. | M24: 72742.8 | N24: 0.6 | O24: 247765.1 | P24: 0.1
A25: 1998/ | B25: 1-3. | C25: 58280 | D25: 0.5 | E25: 277440.5 | F25: -0.5 | K25: 1998/ | L25: 1-3. | M25: 52199.3 | N25: -0.6 | O25: 247048.3 | P25: -0.3
B26: 4-6. | C26: 69257.1 | D26: -0.8 | E26: 275589.9 | F26: -0.7 | L26: 4-6. | M26: 61498.2 | N26: -0.2 | O26: 245553.1 | P26: -0.6
B27: 7-9. | C27: 66477 | D27: -2.5 | E27: 272725.1 | F27: -1 | L27: 7-9. | M27: 59576.6 | N27: -1.6 | O27: 243739.8 | P27: -0.7
B28: 10-12. | C28: 80064.6 | D28: -2.7 | E28: 272228.3 | F28: -0.2 | L28: 10-12. | M28: 70943.1 | N28: -2.5 | O28: 242559.1 | P28: -0.5
A29: 1999/ | B29: 1-3. | C29: 57090.2 | D29: -2 | E29: 270516.2 | F29: -0.6 | K29: 1999/ | L29: 1-3. | M29: 51425.6 | N29: -1.5 | O29: 242253.3 | P29: -0.1
B30: 4-6. | C30: 67592.5 | D30: -2.4 | E30: 268651 | F30: -0.7 | L30: 4-6. | M30: 60346.9 | N30: -1.9 | O30: 240690.3 | P30: -0.6
B31: 7-9. | C31: 65404.6 | D31: -1.6 | E31: 268720.7 | F31: 0 | L31: 7-9. | M31: 58830.5 | N31: -1.3 | O31: 240983.2 | P31: 0.1
B32: 10-12. | C32: 78719 | D32: -1.7 | E32: 268309.1 | F32: -0.2 | L32: 10-12. | M32: 70564.8 | N32: -0.5 | O32: 241792.9 | P32: 0.3
A33: 2000/ | B33: 1-3. | C33: 57022.8 | D33: -0.1 | E33: 269444 | F33: 0.4 | K33: 2000/ | L33: 1-3. | M33: 51798.6 | N33: 0.7 | O33: 243322.9 | P33: 0.6
B34: 4-6. | C34: 67761.1 | D34: 0.2 | E34: 268733.7 | F34: -0.3 | L34: 4-6. | M34: 61156.9 | N34: 1.3 | O34: 243389.5 | P34: 0
B35: 7-9. | C35: 65487.5 | D35: 0.1 | E35: 269580.7 | F35: 0.3 | L35: 7-9. | M35: 59633.1 | N35: 1.4 | O35: 244889.3 | P35: 0.6
B36: 10-12. | C36: 79207.6 | D36: 0.6 | E36: 270499.4 | F36: 0.3 | L36: 10-12. | M36: 71924.2 | N36: 1.9 | O36: 246823.8 | P36: 0.8
A37: 2001/ | B37: 1-3. | C37: 57880.1 | D37: 1.5 | E37: 272914.6 | F37: 0.9 | K37: 2001/ | L37: 1-3. | M37: 53071.3 | N37: 2.5 | O37: 248692.1 | P37: 0.8
B38: 4-6. | C38: 67971.5 | D38: 0.3 | E38: 268430.5 | F38: -1.6 | L38: 4-6. | M38: 62208.1 | N38: 1.7 | O38: 246527.6 | P38: -0.9
B39: 7-9. | C39: 64342.6 | D39: -1.7 | E39: 265650.7 | F39: -1 | L39: 7-9. | M39: 59468.3 | N39: -0.3 | O39: 245143.9 | P39: -0.6
B40: 10-12. | C40: 76048.4 | D40: -4 | E40: 260297.7 | F40: -2 | L40: 10-12. | M40: 70329.4 | N40: -2.2 | O40: 241786 | P40: -1.4
A41: 2002/ | B41: 1-3. | C41: 55900.1 | D41: -3.4 | E41: 263506 | F41: 1.2 | K41: 2002/ | L41: 1-3. | M41: 52382.3 | N41: -1.3 | O41: 245502.4 | P41: 1.5
B42: 4-6. | C42: 64977.6 | D42: -4.4 | E42: 255091.3 | F42: -3.2 | L42: 4-6. | M42: 60522 | N42: -2.7 | O42: 238347.6 | P42: -2.9
B43: 7-9. | C43: 62019 | D43: -3.6 | E43: 257191 | F43: 0.8 | L43: 7-9. | M43: 58249.8 | N43: -2 | O43: 241247.4 | P43: 1.2
B44: 10-12. | C44: 74220.2 | D44: -2.4 | E44: 254209.5 | F44: -1.2 | L44: 10-12. | M44: 69527.3 | N44: -1.1 | O44: 239082.3 | P44: -0.9
A45: 2003/ | B45: 1-3. | C45: 55191 | D45: -1.3 | E45: 260563.8 | F45: 2.5 | G45: 1994/4-3. | H45: 262296.2 | K45: 2003/ | L45: 1-3. | M45: 52346.3 | N45: -0.1 | O45: 245780.9 | P45: 2.8 | Q45: 1994/4-3. | R45: 232963.2
B46: 4-6. | C46: 65349.9 | D46: 0.6 | E46: 254980.5 | F46: -2.1 | G46: 1995/4-3. | H46: 266599.7 | I46: 1.6 | L46: 4-6. | M46: 61687.2 | N46: 1.9 | O46: 241370.7 | P46: -1.8 | Q46: 1995/4-3. | R46: 239187.2 | S46: 2.7
B47: 7-9. | C47: 60423.3 | D47: -2.6 | E47: 251865.1 | F47: -1.2 | G47: 1996/4-3. | H47: 272460.4 | I47: 2.2 | L47: 7-9. | M47: 57389.5 | N47: -1.5 | O47: 238960.3 | P47: -1 | Q47: 1996/4-3. | R47: 244997.8 | S47: 2.4
B48: 10-12. | C48: 73923.8 | D48: -0.4 | E48: 253052.8 | F48: 0.5 | G48: 1997/4-3. | H48: 278548.6 | I48: 2.2 | L48: 10-12. | M48: 70055.4 | N48: 0.8 | O48: 240780.1 | P48: 0.8 | Q48: 1997/4-3. | R48: 247123.8 | S48: 0.9
A49: 2004/ | B49: 1-3. | C49: 53430.1 | D49: -3.2 | E49: 253089.8 | F49: 0 | G49: 1998/4-3. | H49: 272888.9 | I49: -2 | K49: 2004/ | L49: 1-3. | M49: 51142.6 | N49: -2.3 | O49: 240980.1 | P49: 0.1 | Q49: 1998/4-3. | R49: 243443.6 | S49: -1.5
B50: 4-6. | C50: 65411.5 | D50: 0.1 | E50: 253941 | F50: 0.3 | G50: 1999/4-3. | H50: 268738.8 | I50: -1.5 | L50: 4-6. | M50: 62218.7 | N50: 0.9 | O50: 242133.9 | P50: 0.5 | Q50: 1999/4-3. | R50: 241540.8 | S50: -0.8
B51: 7-9. | C51: 60667.8 | D51: 0.4 | E51: 253967.7 | F51: 0 | G51: 2000/4-3. | H51: 270336.4 | I51: 0.6 | L51: 7-9. | M51: 58031 | N51: 1.1 | O51: 242787.1 | P51: 0.3 | Q51: 2000/4-3. | R51: 245785.4 | S51: 1.8
B52: 10-12. | C52: 74222.4 | D52: 0.4 | E52: 253800.5 | F52: -0.1 | G52: 2001/4-3. | H52: 264262.6 | I52: -2.2 | L52: 10-12. | M52: 70522.7 | N52: 0.7 | O52: 242147.1 | P52: -0.3 | Q52: 2001/4-3. | R52: 244388 | S52: -0.6
A53: 2005/ | B53: 1-3. | C53: 53650 | D53: 0.4 | E53: 254637.1 | F53: 0.3 | G53: 2002/4-3. | H53: 256407.8 | I53: -3 | K53: 2005/ | L53: 1-3. | M53: 51645.8 | N53: 1 | O53: 243768.7 | P53: 0.7 | Q53: 2002/4-3. | R53: 240645.5 | S53: -1.5
B54: 4-6. | C54: 66235.9 | D54: 1.3 | E54: 256151.9 | F54: 0.6 | G54: 2003/4-3. | H54: 253127.2 | I54: -1.3 | L54: 4-6. | M54: 63399.6 | N54: 1.9 | O54: 245724.7 | P54: 0.8 | Q54: 2003/4-3. | R54: 240274.7 | S54: -0.2
B55: 7-9. | C55: 61251 | D55: 1 | E55: 257419.6 | F55: 0.5 | G55: 2004/4-3. | H55: 253951.6 | I55: 0.3 | L55: 7-9. | M55: 58966 | N55: 1.6 | O55: 247773.6 | P55: 0.8 | Q55: 2004/4-3. | R55: 242418.2 | S55: 0.9
B56: 10-12. | C56: 76000.6 | D56: 2.4 | E56: 259537.4 | F56: 0.8 | G56: 2005/4-3. | H56: 257956.2 | I56: 1.6 | L56: 10-12. | M56: 72845.2 | N56: 3.3 | O56: 249782 | P56: 0.8 | Q56: 2005/4-3. | R56: 247831.1 | S56: 2.2
A57: 2006/ | B57: 1-3. | C57: 54468.7 | D57: 1.5 | E57: 258873.7 | F57: -0.3 | G57: 2006/4-3. | H57: 260787.4 | I57: 1.1 | K57: 2006/ | L57: 1-3. | M57: 52620.3 | N57: 1.9 | O57: 248575.3 | P57: -0.5 | Q57: 2006/4-3. | R57: 251164 | S57: 1.3
B58: 4-6. | C58: 67447.1 | D58: 1.8 | E58: 260121.9 | F58: 0.5 | G58: 2007/4-3. | H58: 262934.7 | I58: 0.8 | L58: 4-6. | M58: 64733 | N58: 2.1 | O58: 250212.8 | P58: 0.7 | Q58: 2007/4-3. | R58: 253563.6 | S58: 1
B59: 7-9. | C59: 61847.6 | D59: 1 | E59: 260646.5 | F59: 0.2 | G59: 2008/4-3. | H59: 262626.2 | I59: -0.1 | L59: 7-9. | M59: 59430.7 | N59: 0.8 | O59: 250541.1 | P59: 0.1 | Q59: 2008/4-3. | R59: 252171.8 | S59: -0.5
B60: 10-12. | C60: 76644.4 | D60: 0.8 | E60: 261787.8 | F60: 0.4 | G60: 2009/4-3. | H60: 251072.9 | I60: -4.4 | L60: 10-12. | M60: 73576.2 | N60: 1 | O60: 252333.4 | P60: 0.7 | Q60: 2009/4-3. | R60: 247348.8 | S60: -1.9
A61: 2007/ | B61: 1-3. | C61: 54848.3 | D61: 0.7 | E61: 260372.7 | F61: -0.5 | G61: 2010/4-3. | H61: 252199.9 | I61: 0.4 | K61: 2007/ | L61: 1-3. | M61: 53424.1 | N61: 1.5 | O61: 251948.9 | P61: -0.2 | Q61: 2010/4-3. | R61: 251533.5 | S61: 1.7
B62: 4-6. | C62: 68037.1 | D62: 0.9 | E62: 262097.2 | F62: 0.7 | G62: 2011/4-3. | H62: 253919.3 | I62: 0.7 | L62: 4-6. | M62: 65632.5 | N62: 1.4 | O62: 253507 | P62: 0.6 | Q62: 2011/4-3. | R62: 253805.8 | S62: 0.9
B63: 7-9. | C63: 62103.7 | D63: 0.4 | E63: 262017.4 | F63: 0 | G63: 2012/4-3. | H63: 253102.5 | I63: -0.3 | L63: 7-9. | M63: 60079.7 | N63: 1.1 | O63: 253625.9 | P63: 0 | Q63: 2012/4-3. | R63: 254515.1 | S63: 0.3
B64: 10-12. | C64: 76967.7 | D64: 0.4 | E64: 263416.1 | F64: 0.5 | G64: 2013/4-3. | H64: 254872.7 | I64: 0.7 | L64: 10-12. | M64: 73889.4 | N64: 0.4 | O64: 253811 | P64: 0.1 | Q64: 2013/4-3. | R64: 254438.2 | S64: 0
A65: 2008/ | B65: 1-3. | C65: 55826.1 | D65: 1.8 | E65: 264041.8 | F65: 0.2 | G65: 2014/4-3. | H65: 259505.2 | I65: 1.8 | K65: 2008/ | L65: 1-3. | M65: 53962.1 | N65: 1 | O65: 253436.1 | P65: -0.1 | Q65: 2014/4-3. | R65: 251265.4 | S65: -1.2
B66: 4-6. | C66: 68988.5 | D66: 1.4 | E66: 265849.3 | F66: 0.7 | G66: 2015/4-3. | H66: 263420.4 | I66: 1.5 | L66: 4-6. | M66: 65846.6 | N66: 0.3 | O66: 254559.1 | P66: 0.4 | Q66: 2015/4-3. | R66: 254610 | S66: 1.3
B67: 7-9. | C67: 62489.5 | D67: 0.6 | E67: 263436.1 | F67: -0.9 | G67: 2016/4-3. | H67: 268571.9 | I67: 2 | L67: 7-9. | M67: 59457.9 | N67: -1 | O67: 250949 | P67: -1.4 | Q67: 2016/4-3. | R67: 260139 | S67: 2.2
B68: 10-12. | C68: 76445.2 | D68: -0.7 | E68: 262663.4 | F68: -0.3 | L68: 10-12. | M68: 73314.1 | N68: -0.8 | O68: 252549.2 | P68: 0.6
A69: 2009/ | B69: 1-3. | C69: 54703.1 | D69: -2 | E69: 257256.4 | F69: -2.1 | K69: 2009/ | L69: 1-3. | M69: 53553.2 | N69: -0.8 | O69: 250191.2 | P69: -0.9
B70: 4-6. | C70: 64885.5 | D70: -5.9 | E70: 250393.2 | F70: -2.7 | L70: 4-6. | M70: 63174.3 | N70: -4.1 | O70: 244713.6 | P70: -2.2
B71: 7-9. | C71: 59554.5 | D71: -4.7 | E71: 250605 | F71: 0.1 | L71: 7-9. | M71: 58580.4 | N71: -1.5 | O71: 246772 | P71: 0.8
B72: 10-12. | C72: 72417.9 | D72: -5.3 | E72: 249941 | F72: -0.3 | L72: 10-12. | M72: 71567 | N72: -2.4 | O72: 247188.7 | P72: 0.2
A73: 2010/ | B73: 1-3. | C73: 54215 | D73: -0.9 | E73: 253648.1 | F73: 1.5 | G73: 1994/1-12. | H73: 261089.8 | K73: 2010/ | L73: 1-3. | M73: 54027.1 | N73: 0.9 | O73: 251270.4 | P73: 1.7 | Q73: 1994/1-12. | R73: 231721.4
B74: 4-6. | C74: 65328.7 | D74: 0.7 | E74: 252224.2 | F74: -0.6 | G74: 1995/1-12. | H74: 265508.6 | I74: 1.7 | L74: 4-6. | M74: 64496.9 | N74: 2.1 | O74: 250112.6 | P74: -0.5 | Q74: 1995/1-12. | R74: 237718 | S74: 2.6
B75: 7-9. | C75: 60008.7 | D75: 0.8 | E75: 252283 | F75: 0 | G75: 1996/1-12. | H75: 270191 | I75: 1.8 | L75: 7-9. | M75: 60040.5 | N75: 2.5 | O75: 252712.1 | P75: 1 | Q75: 1996/1-12. | R75: 242902.3 | S75: 2.2
B76: 10-12. | C76: 72574 | D76: 0.2 | E76: 251353.8 | F76: -0.4 | G76: 1997/1-12. | H76: 278242.6 | I76: 3 | L76: 10-12. | M76: 72538.2 | N76: 1.4 | O76: 251111.8 | P76: -0.6 | Q76: 1997/1-12. | R76: 247418.9 | S76: 1.9
A77: 2011/ | B77: 1-3. | C77: 54288.4 | D77: 0.1 | E77: 253107.7 | F77: 0.7 | G77: 1998/1-12. | H77: 274078.8 | I77: -1.5 | K77: 2011/ | L77: 1-3. | M77: 54457.9 | N77: 0.8 | O77: 252669.4 | P77: 0.6 | Q77: 1998/1-12. | R77: 244217.2 | S77: -1.3
B78: 4-6. | C78: 65581.5 | D78: 0.4 | E78: 253090.8 | F78: 0 | G78: 1999/1-12. | H78: 268806.2 | I78: -1.9 | L78: 4-6. | M78: 65326.9 | N78: 1.3 | O78: 253268.5 | P78: 0.2 | Q78: 1999/1-12. | R78: 241167.8 | S78: -1.2
B79: 7-9. | C79: 60087.1 | D79: 0.1 | E79: 252693.1 | F79: -0.2 | G79: 2000/1-12. | H79: 269479 | I79: 0.3 | L79: 7-9. | M79: 60184.4 | N79: 0.2 | O79: 253189.8 | P79: 0 | Q79: 2000/1-12. | R79: 244512.7 | S79: 1.4
B80: 10-12. | C80: 73492.4 | D80: 1.3 | E80: 254907.8 | F80: 0.9 | G80: 2001/1-12. | H80: 266242.7 | I80: -1.2 | L80: 10-12. | M80: 73429.5 | N80: 1.2 | O80: 254644 | P80: 0.6 | Q80: 2001/1-12. | R80: 245077 | S80: 0.2
A81: 2012/ | B81: 1-3. | C81: 54758.3 | D81: 0.9 | E81: 255069.4 | F81: 0.1 | G81: 2002/1-12. | H81: 257116.9 | I81: -3.4 | K81: 2012/ | L81: 1-3. | M81: 54865 | N81: 0.7 | O81: 254576 | P81: 0 | Q81: 2002/1-12. | R81: 240681.4 | S81: -1.8
B82: 4-6. | C82: 65694.3 | D82: 0.2 | E82: 253207.2 | F82: -0.7 | G82: 2003/1-12. | H82: 254888.1 | I82: -0.9 | L82: 4-6. | M82: 65574.4 | N82: 0.4 | O82: 253743.4 | P82: -0.3 | Q82: 2003/1-12. | R82: 241478.4 | S82: 0.3
B83: 7-9. | C83: 60197.2 | D83: 0.2 | E83: 253347.2 | F83: 0.1 | G83: 2004/1-12. | H83: 253731.7 | I83: -0.5 | L83: 7-9. | M83: 60796.6 | N83: 1 | O83: 255898.7 | P83: 0.8 | Q83: 2004/1-12. | R83: 241915 | S83: 0.2
B84: 10-12. | C84: 72754.1 | D84: -1 | E84: 252407.1 | F84: -0.4 | G84: 2005/1-12. | H84: 257137.5 | I84: 1.3 | L84: 10-12. | M84: 73133.4 | N84: -0.4 | O84: 253796.6 | P84: -0.8 | Q84: 2005/1-12. | R84: 246856.7 | S84: 2
A85: 2013/ | B85: 1-3. | C85: 54456.9 | D85: -0.6 | E85: 253782.3 | F85: 0.5 | G85: 2006/1-12. | H85: 260407.8 | I85: 1.3 | K85: 2013/ | L85: 1-3. | M85: 55010.7 | N85: 0.3 | O85: 255259.8 | P85: 0.6 | Q85: 2006/1-12. | R85: 250360.2 | S85: 1.4
B86: 4-6. | C86: 66301.3 | D86: 0.9 | E86: 255350.4 | F86: 0.6 | G86: 2007/1-12. | H86: 261956.9 | I86: 0.6 | L86: 4-6. | M86: 66457.4 | N86: 1.3 | O86: 256966.5 | P86: 0.7 | Q86: 2007/1-12. | R86: 253025.7 | S86: 1.1
B87: 7-9. | C87: 60236.9 | D87: 0.1 | E87: 253625.3 | F87: -0.7 | G87: 2008/1-12. | H87: 263749.3 | I87: 0.7 | L87: 7-9. | M87: 60337.5 | N87: -0.8 | O87: 254045.6 | P87: -1.1 | Q87: 2008/1-12. | R87: 252580.7 | S87: -0.2
B88: 10-12. | C88: 73540.2 | D88: 1.1 | E88: 255001.4 | F88: 0.5 | G88: 2009/1-12. | H88: 251560.9 | I88: -4.6 | L88: 10-12. | M88: 73071.9 | N88: -0.1 | O88: 253669.5 | P88: -0.1 | Q88: 2009/1-12. | R88: 246874.9 | S88: -2.3
A89: 2014/ | B89: 1-3. | C89: 54794.3 | D89: 0.6 | E89: 255544.8 | F89: 0.2 | G89: 2010/1-12. | H89: 252126.4 | I89: 0.2 | K89: 2014/ | L89: 1-3. | M89: 54571.4 | N89: -0.8 | O89: 253249.9 | P89: -0.2 | Q89: 2010/1-12. | R89: 251102.7 | S89: 1.7
B90: 4-6. | C90: 67199.4 | D90: 1.4 | E90: 258892.4 | F90: 1.3 | G90: 2011/1-12. | H90: 253449.5 | I90: 0.5 | L90: 4-6. | M90: 64860.4 | N90: -2.4 | O90: 250925 | P90: -0.9 | Q90: 2011/1-12. | R90: 253398.7 | S90: 0.9
B91: 7-9. | C91: 61632.7 | D91: 2.3 | E91: 259347.3 | F91: 0.2 | G91: 2012/1-12. | H91: 253403.9 | I91: 0 | L91: 7-9. | M91: 59672.5 | N91: -1.1 | O91: 250998.3 | P91: 0 | Q91: 2012/1-12. | R91: 254369.5 | S91: 0.4
B92: 10-12. | C92: 74920.5 | D92: 1.9 | E92: 259701.4 | F92: 0.1 | G92: 2013/1-12. | H92: 254535.3 | I92: 0.4 | L92: 10-12. | M92: 72360.3 | N92: -1 | O92: 251305 | P92: 0.1 | Q92: 2013/1-12. | R92: 254877.5 | S92: 0.2
A93: 2015/ | B93: 1-3. | C93: 55752.6 | D93: 1.7 | E93: 260063.5 | F93: 0.1 | G93: 2014/1-12. | H93: 258546.9 | I93: 1.6 | K93: 2015/ | L93: 1-3. | M93: 54372.1 | N93: -0.4 | O93: 252099 | P93: 0.3 | Q93: 2014/1-12. | R93: 251464.6 | S93: -1.3
B94: 4-6. | C94: 67530.9 | D94: 0.5 | E94: 260441.4 | F94: 0.1 | G94: 2015/1-12. | H94: 261947.6 | I94: 1.3 | L94: 4-6. | M94: 64959.5 | N94: 0.2 | O94: 251727.8 | P94: -0.1 | Q94: 2015/1-12. | R94: 253121.8 | S94: 0.7
B95: 7-9. | C95: 62481.7 | D95: 1.4 | E95: 262766.3 | F95: 0.9 | G95: 2016/1-12. | H95: 268018.1 | I95: 2.3 | L95: 7-9. | M95: 60391.4 | N95: 1.2 | O95: 253763.1 | P95: 0.8 | Q95: 2016/1-12. | R95: 259776.6 | S95: 2.6
B96: 10-12. | C96: 76182.3 | D96: 1.7 | E96: 263873.3 | F96: 0.4 | L96: 10-12. | M96: 73398.8 | N96: 1.4 | O96: 254804.2 | P96: 0.4
A97: 2016/ | B97: 1-3. | C97: 57225.5 | D97: 2.6 | E97: 267040.6 | F97: 1.2 | K97: 2016/ | L97: 1-3. | M97: 55860.3 | N97: 2.7 | O97: 259146.3 | P97: 1.7
B98: 4-6. | C98: 69049.1 | D98: 2.2 | E98: 266558.6 | F98: -0.2 | L98: 4-6. | M98: 66722 | N98: 2.7 | O98: 258837.2 | P98: -0.1
B99: 7-9. | C99: 63888.5 | D99: 2.3 | E99: 268621.2 | F99: 0.8 | L99: 7-9. | M99: 62146.7 | N99: 2.9 | O99: 260944 | P99: 0.8
B100: 10-12. | C100: 77855 | D100: 2.2 | E100: 269358.9 | F100: 0.3 | L100: 10-12. | M100: 75047.7 | N100: 2.2 | O100: 260196.9 | P100: -0.3
...

Sheet kgaku-mk1722
A1: 名目季節調整系列 | Y1: (単位:10億円)
A2: Nominal, Seasonally Adjusted Series | Y2: (Billion Yen)
B3: 家計最終消費支出（再掲） | K3: 形態別総固定資本形成 | P3: 総資本形成 | S3: 財貨・サービス
C4: 居住者家計の海外での直接購入 | D4: （控除）非居住者家計の国内での直接購入 | E4: 国内家計最終消費支出 | K4: 住宅 | L4: その他の建物・構築物 | M4: 輸送用機械 | N4: その他の機械設備等 | O4: 知的財産生産物 | Q4: うち在庫変動 | S4: 純輸出（再掲） | T4: 輸出（再掲） | W4: 輸入（再掲）
F5: 耐久財 | G5: 半耐久財 | H5: 非耐久財 | I5: サービス | U5: 財貨 | V5: サービス（含む非居住者家計の国内での直接購入） | X5: 財貨 | Y5: サービス（含む居住者家計の海外での直接購入）
B6: Consumptionof Households(id, at §Ｉ) | C6: DirectPurchasesAbroad byResidentHouseholds | D6: (Less) DirectPurchases inthe DomesticMarket byNon-ResidentHouseholds | E6: Domestic FinalConsumptionExpenditure ofHouseholds | F6: DurableGoods | G6: Semi-DurableGoods | H6: Non-DurableGoods | I6: Services | K6: Gross Fixed Capital Formation by Type | P6: Gross CapitalFormation | Q6: Of WhichChange inInventories | S6: Goods & Services
K7: ResidentialInvestment | L7: Other Buildingsand Structures | M7: TransportEquipment | N7: OtherMachinery andEquipment etc. | O7: IntellectualPropertyProducts | S7: Net Exports(id, at §Ｉ) | T7: Exports(id, at §Ｉ) | W7: Imports(id, at §Ｉ)
U8: Goods | V8: Services（Including DirectPurchases in theDomestic Marketby Non-ResidentHouseholds) | X8: Goods | Y8: Services（Including DirectPurchasesAbroad byResidentHouseholds)
A9: 1994/ 1- 3. | B9: 261777.1 | C9: 2600.1 | D9: 269.7 | E9: 259446.7 | F9: 21744.5 | G9: 22820.1 | H9: 74540.1 | I9: 140341.9 | K9: 26371.6 | L9: 58706.7 | M9: 7102.3 | N9: 37529.7 | O9: 18016.4 | P9: 150031 | Q9: 2735 | S9: 11000.2 | T9: 44990.7 | U9: 38972.8 | V9: 6017.9 | W9: 33990.4 | X9: 22993.1 | Y9: 10997.4
A10: 4- 6. | B10: 262262.7 | C10: 2650 | D10: 269.2 | E10: 259881.8 | F10: 22109.8 | G10: 23198.7 | H10: 74247.1 | I10: 140326.3 | K10: 27409 | L10: 58374.5 | M10: 6996.6 | N10: 38205.5 | O10: 17929.7 | P10: 146505.6 | Q10: -2238.3 | S10: 9964.8 | T10: 45487.7 | U10: 39475.8 | V10: 6011.8 | W10: 35522.9 | X10: 24178.5 | Y10: 11344.4
A11: 7- 9. | B11: 265821.2 | C11: 2531.7 | D11: 225.2 | E11: 263514.6 | F11: 23555.5 | G11: 22717.1 | H11: 74634.6 | I11: 142607.4 | K11: 29808.7 | L11: 55322.9 | M11: 7205.7 | N11: 38282.1 | O11: 18105.7 | P11: 149428.9 | Q11: 717.7 | S11: 8579.2 | T11: 45045.2 | U11: 39351.2 | V11: 5694.1 | W11: 36466.1 | X11: 25278 | Y11: 11188
A12: 10-12. | B12: 265264.9 | C12: 2442.2 | D12: 220.6 | E12: 263043.2 | F12: 23357.6 | G12: 22560.2 | H12: 74318.1 | I12: 142807.4 | K12: 28502.8 | L12: 54175.2 | M12: 7149 | N12: 39303.7 | O12: 18254.1 | P12: 146910.1 | Q12: -704.2 | S12: 8606.2 | T12: 45098.2 | U12: 39515.4 | V12: 5582.8 | W12: 36492 | X12: 25722 | Y12: 10769.9
A13: 1995/ 1- 3. | B13: 266488.5 | C13: 2496.9 | D13: 187.5 | E13: 264179.2 | F13: 24193 | G13: 22939.4 | H13: 74824.9 | I13: 142221.9 | K13: 27512.1 | L13: 54645.8 | M13: 7337.2 | N13: 39379.5 | O13: 17822.9 | P13: 148228.5 | Q13: 1725.6 | S13: 7756.7 | T13: 45059 | U13: 39581.8 | V13: 5477.2 | W13: 37302.3 | X13: 26005.1 | Y13: 11297.2
A14: 4- 6. | B14: 268686.8 | C14: 2546.7 | D14: 175.6 | E14: 266315.7 | F14: 25369.6 | G14: 23029.5 | H14: 75239.9 | I14: 142676.6 | K14: 26755 | L14: 54788.9 | M14: 7707.7 | N14: 42279.7 | O14: 18529.6 | P14: 151189.8 | Q14: 1374.6 | S14: 7394.1 | T14: 44066.3 | U14: 39035.1 | V14: 5031.2 | W14: 36672.2 | X14: 26116.1 | Y14: 10556.1
A15: 7- 9. | B15: 270195.9 | C15: 2896.2 | D15: 215.8 | E15: 267515.5 | F15: 24886.8 | G15: 23577.2 | H15: 75369.5 | I15: 143682 | K15: 26111.7 | L15: 58851.2 | M15: 7230 | N15: 42961 | O15: 18678.9 | P15: 156049.9 | Q15: 2266 | S15: 6271.9 | T15: 46797.9 | U15: 40726.5 | V15: 6071.4 | W15: 40526 | X15: 28598.5 | Y15: 11927.6
A16: 10-12. | B16: 271775.3 | C16: 3096.7 | D16: 244.3 | E16: 268922.8 | F16: 24521 | G16: 23602.2 | H16: 75459.5 | I16: 145340.1 | K16: 26617.6 | L16: 58360.7 | M16: 7044.5 | N16: 43891 | O16: 19135.3 | P16: 156852.2 | Q16: 1396 | S16: 4476.6 | T16: 47873.8 | U16: 41511.7 | V16: 6362.1 | W16: 43397.2 | X16: 30571.9 | Y16: 12825.3
A17: 1996/ 1- 3. | B17: 272896.5 | C17: 3225.2 | D17: 284.3 | E17: 269955.5 | F17: 24714.7 | G17: 22719.2 | H17: 74441.5 | I17: 148080.2 | K17: 27727 | L17: 59657.1 | M17: 6987.4 | N17: 44370.3 | O17: 19456.6 | P17: 159809.8 | Q17: 1920 | S17: 3814.5 | T17: 48791.1 | U17: 42164.9 | V17: 6626.2 | W17: 44976.6 | X17: 31726.6 | Y17: 13250
A18: 4- 6. | B18: 274902.2 | C18: 3150 | D18: 304.5 | E18: 272056.8 | F18: 24944.6 | G18: 22379.9 | H18: 75267.5 | I18: 149464.8 | K18: 29045.6 | L18: 58093.2 | M18: 7147.7 | N18: 46209 | O18: 19889.8 | P18: 164057.9 | Q18: 3522.1 | S18: 1330.9 | T18: 48905 | U18: 42186.2 | V18: 6718.8 | W18: 47574.1 | X18: 34225.2 | Y18: 13348.9
A19: 7- 9. | B19: 274573 | C19: 3205 | D19: 318.7 | E19: 271686.7 | F19: 25404.9 | G19: 22091.5 | H19: 73689.8 | I19: 150500.6 | K19: 30455.1 | L19: 55378.6 | M19: 7387 | N19: 47270.6 | O19: 20172.2 | P19: 162306.3 | Q19: 1572.2 | S19: 1629.7 | T19: 49604.3 | U19: 42701.6 | V19: 6902.7 | W19: 47974.6 | X19: 34374 | Y19: 13600.7
A20: 10-12. | B20: 277684.8 | C20: 3338.9 | D20: 336 | E20: 274682 | F20: 25921.8 | G20: 21911.5 | H20: 75307.2 | I20: 151541.5 | K20: 31456.3 | L20: 54149.8 | M20: 7478.1 | N20: 47378.3 | O20: 20695 | P20: 163447.8 | Q20: 2625.8 | S20: 2264.7 | T20: 51956.4 | U20: 44878.5 | V20: 7077.9 | W20: 49691.6 | X20: 35585.6 | Y20: 14106
... A102: 4- 6. | B102: 296926.3 | C102: 1843.6 | D102: 3345.7 | E102: 298428.4 | F102: 25879.4 | G102: 15350 | H102: 80016.9 | I102: 177182 | K102: 18186.8 | L102: 40388.1 | M102: 7939.7 | N102: 32047.8 | O102: 30419.5 | P102: 128037.5 | Q102: -1402.7 | S102: 3401.3 | T102: 93549.7 | U102: 74302.1 | V102: 19247.6 | W102: 90148.3 | X102: 70921.7 | Y102: 19226.6
A103: ＊年率で表示している。

Sheet kgaku-jk1722
A1: 実質季節調整系列 | Y1: (単位:2011暦年連鎖価格、10億円)
A2: Real, Seasonally Adjusted Series | Y2: (Billions of Chained (2011) Yen)
B3: 家計最終消費支出（再掲） | K3: 形態別総固定資本形成 | P3: 総資本形成 | S3: 財貨・サービス
C4: 居住者家計の海外での直接購入 | D4: （控除）非居住者家計の国内での直接購入 | E4: 国内家計最終消費支出 | K4: 住宅 | L4: その他の建物・構築物 | M4: 輸送用機械 | N4: その他の機械設備等 | O4: 知的財産生産物 | Q4: うち在庫変動 | S4: 純輸出（再掲） | T4: 輸出（再掲） | W4: 輸入（再掲）
F5: 耐久財 | G5: 半耐久財 | H5: 非耐久財 | I5: サービス | U5: 財貨 | V5: サービス（含む非居住者家計の国内での直接購入） | X5: 財貨 | Y5: サービス（含む居住者家計の海外での直接購入）
B6: Consumptionof Households(id, at §Ｉ) | C6: DirectPurchasesAbroad byResidentHouseholds | D6: (Less) DirectPurchases inthe DomesticMarket byNon-ResidentHouseholds | E6: Domestic FinalConsumptionExpenditure ofHouseholds | F6: DurableGoods | G6: Semi-DurableGoods | H6: Non-DurableGoods | I6: Services | K6: Gross Fixed Capital Formation by Type | P6: Gross CapitalFormation | Q6: Of WhichChange inInventories | S6: Goods & Services
K7: ResidentialInvestment | L7: Other Buildingsand Structures | M7: TransportEquipment | N7: OtherMachinery andEquipment etc. | O7: IntellectualPropertyProducts | S7: Net Exports(id, at §Ｉ) | T7: Exports(id, at §Ｉ) | W7: Imports(id, at §Ｉ)
U8: Goods | V8: Services（Including DirectPurchases in theDomestic Marketby Non-ResidentHouseholds) | X8: Goods | Y8: Services（Including DirectPurchasesAbroad byResidentHouseholds)
A9: 1994/ 1- 3. | B9: 239049.9 | C9: 3853 | D9: 262.3 | E9: 235760.5 | F9: 6929.5 | G9: 19971.3 | H9: 76350.5 | I9: 142657.8 | K9: 26362.9 | L9: 60026.4 | M9: 6435.2 | N9: 22809.6 | O9: 17577.4 | P9: 130161.1 | Q9: 3428.5 | S9: -9150.2 | T9: 33923.4 | U9: 28753.6 | V9: 5251.1 | W9: 43073.6 | X9: 29535.6 | Y9: 12516.7
A10: 4- 6. | B10: 238591.4 | C10: 3853.8 | D10: 262.7 | E10: 235304.2 | F10: 7161.8 | G10: 20331.6 | H10: 76353.1 | I10: 141019.3 | K10: 27367.9 | L10: 59537.3 | M10: 6395.4 | N10: 23434.1 | O10: 17619.2 | P10: 126100.9 | Q10: -2269 | S10: -9661 | T10: 34107.3 | U10: 28859.2 | V10: 5339.3 | W10: 43768.3 | X10: 30222.9 | Y10: 12530
A11: 7- 9. | B11: 242143.6 | C11: 3806.5 | D11: 219.9 | E11: 238827.4 | F11: 7708.3 | G11: 20005.7 | H11: 77081.4 | I11: 142900.3 | K11: 29786.3 | L11: 56200.8 | M11: 6609.2 | N11: 23597.7 | O11: 17889.3 | P11: 129241.3 | Q11: 587.6 | S11: -10343.7 | T11: 34735.6 | U11: 29671.3 | V11: 5102.9 | W11: 45079.3 | X11: 31434 | Y11: 12631.8
A12: 10-12. | B12: 241315.1 | C12: 3751.5 | D12: 214.1 | E12: 238031 | F12: 7721.8 | G12: 19895.8 | H12: 76756.7 | I12: 142419 | K12: 28547.9 | L12: 55338.2 | M12: 6564.2 | N12: 24401.7 | O12: 18035.2 | P12: 127504.5 | Q12: -766 | S12: -10601 | T12: 34897.7 | U12: 29911.5 | V12: 5004.7 | W12: 45498.7 | X12: 32369 | Y12: 12174.7
A13: 1995/ 1- 3. | B13: 242841.8 | C13: 3964.5 | D13: 182.3 | E13: 239391.1 | F13: 8125.1 | G13: 20319.1 | H13: 77663.8 | I13: 141312.3 | K13: 27563.5 | L13: 55808.4 | M13: 6745.6 | N13: 24538.4 | O13: 17621.2 | P13: 129635.8 | Q13: 2272.4 | S13: -11786.9 | T13: 35325.1 | U13: 30367.1 | V13: 4958.7 | W13: 47112 | X13: 33087.9 | Y13: 12989.9
A14: 4- 6. | B14: 245698.5 | C14: 4359 | D14: 171.6 | E14: 241984 | F14: 8661 | G14: 20391.5 | H14: 78316 | I14: 141811.8 | K14: 26951.1 | L14: 56026 | M14: 7117.7 | N14: 26756.1 | O14: 18374.3 | P14: 132292 | Q14: 1273.8 | S14: -12579.8 | T14: 35877 | U14: 30970.3 | V14: 4882.9 | W14: 48456.7 | X14: 34771.7 | Y14: 12699.5
A15: 7- 9. | B15: 247319.2 | C15: 4440.7 | D15: 211 | E15: 243584 | F15: 8591.9 | G15: 20887.4 | H15: 78867 | I15: 142692.1 | K15: 26277 | L15: 60088 | M15: 6667.9 | N15: 27211.4 | O15: 18489.2 | P15: 136746.9 | Q15: 2187.3 | S15: -14937.4 | T15: 36199.3 | U15: 30669.3 | V15: 5618.8 | W15: 51136.7 | X15: 36570.1 | Y15: 13513.5
A16: 10-12. | B16: 248939.2 | C16: 4454.2 | D16: 238.8 | E16: 245213.9 | F16: 8580.1 | G16: 20868.1 | H16: 79422.2 | I16: 144012.1 | K16: 26868.4 | L16: 59713.8 | M16: 6475.7 | N16: 28060 | O16: 18909.2 | P16: 137699.8 | Q16: 1316.3 | S16: -17456.1 | T16: 36105 | U16: 30415.1 | V16: 5815 | W16: 53561.1 | X16: 38368.1 | Y16: 14096.9
A17: 1996/ 1- 3. | B17: 250030.3 | C17: 4481.5 | D17: 277.9 | E17: 246320.2 | F17: 8770.1 | G17: 20073.7 | H17: 78494.1 | I17: 146437.4 | K17: 27917.2 | L17: 61001.1 | M17: 6414.1 | N17: 28665.5 | O17: 19241.3 | P17: 141195.5 | Q17: 2377 | S17: -17623 | T17: 36675.8 | U17: 30778.1 | V17: 6054.9 | W17: 54298.8 | X17: 38903 | Y17: 14285.5
A18: 4- 6. | B18: 251053.7 | C18: 4092 | D18: 297.8 | E18: 247584.4 | F18: 8997.2 | G18: 19844 | H18: 78918.1 | I18: 147016.9 | K18: 29236.1 | L18: 59426.6 | M18: 6564.9 | N18: 30282.8 | O18: 19675.7 | P18: 145024.4 | Q18: 3272.5 | S18: -19275.3 | T18: 36655.3 | U18: 30636.7 | V18: 6205.7 | W18: 55930.7 | X18: 40721.9 | Y18: 14135.9
A19: 7- 9. | B19: 250902.8 | C19: 4124.6 | D19: 311.5 | E19: 247429.2 | F19: 9279.7 | G19: 19641.7 | H19: 77358.7 | I19: 147748.4 | K19: 30436.9 | L19: 56200.3 | M19: 6768.3 | N19: 31299 | O19: 19883.7 | P19: 143502.2 | Q19: 1454.7 | S19: -18130.7 | T19: 37695.6 | U19: 31557.5 | V19: 6320.8 | W19: 55826.4 | X19: 40426.9 | Y19: 14304.8
A20: 10-12. | B20: 253565.5 | C20: 4132.7 | D20: 327.4 | E20: 250088.8 | F20: 9554.4 | G20: 19521.3 | H20: 78959.7 | I20: 148487.8 | K20: 31124 | L20: 54780.6 | M20: 6895.7 | N20: 31602.2 | O20: 20336.2 | P20: 144142.1 | Q20: 2528.1 | S20: -17098.8 | T20: 39316.9 | U20: 33020.1 | V20: 6464 | W20: 56415.7 | X20: 40778.1 | Y20: 14523.3
... A102: 4- 6. | B102: 293369.8 | C102: 1318.6 | D102: 3174.4 | E102: 295295.5 | F102: 27446.9 | G102: 14552.5 | H102: 75269.8 | I102: 178416.3 | K102: 17098.6 | L102: 38553.1 | M102: 7686.4 | N102: 32152.3 | O102: 29799.1 | P102: 124405.1 | Q102: -1247.6 | S102: -3185.1 | T102: 87955 | U102: 70317.7 | V102: 17555.7 | W102: 91140.1 | X102: 73356 | Y102: 17901.2
A103: ＊年率で表示している。

Sheet gaku-mk1722
A1: 名目季節調整系列 | P1: <参考> | AA1: (単位:10億円)
A2: Nominal, Seasonally Adjusted Series | P2: <cf> | AA2: (Billion Yen)
B3: 国内総生産(支出側) | C3: 民間最終消費支出 | F3: 民間住宅 | G3: 民間企業設備 | H3: 民間在庫変動 | I3: 政府最終消費支出 | J3: 公的固定資本形成 | K3: 公的在庫変動 | L3: 財貨・サービス | P3: 海外からの所得 | S3: 国民総所得 | U3: 国内需要 | V3: 民間需要 | W3: 公的需要 | Y3: 総固定資本形成 | AA3: 最終需要
D4: 家計最終消費支出 | L4: 純輸出 | M4: 輸出 | N4: 輸入 | P4: 純受取 | Q4: 受取 | R4: 支払
E5: 除く持ち家の帰属家賃
B6: GDP(Expenditure Approach) | C6: PrivateConsumption | D6: Consumption ofHouseholds | E6: ExcludingImputed Rent | F6: PrivateResidentialInvestment | G6: Private Non-Resi.Investment | H6: Changein PrivateInventories | I6: GovernmentConsumption | J6: PublicInvestment | K6: Changein PublicInventories | L6: Goods & Services | P6: Income from /to the Rest of the World | S6: GNI | U6: DomesticDemand | V6: PrivateDemand | W6: PublicDemand | Y6: Gross Fixed CapitalFormation | AA6: Final Sales of Domestic Product
L7: Net Exports | M7: Exports | N7: Imports | P7: Net | Q7: Receipt | R7: Payment
A8: 1994/ 1- 3. | B8: 500939.5 | C8: 266326.9 | D8: 261777.1 | E8: 227333.8 | F8: 24875.9 | G8: 76097.8 | H8: 3177.8 | I8: 73581.4 | J8: 46322.3 | K8: -442.8 | L8: 11000.2 | M8: 44990.7 | N8: 33990.4 | P8: 4435.1 | Q8: 15711.7 | R8: 11276.6 | S8: 505374.6 | U8: 489939.3 | V8: 370478.5 | W8: 119460.8 | Y8: 147296.1 | AA8: 498204.6
A9: 4- 6. | B9: 498477.8 | C9: 266882.3 | D9: 262262.7 | E9: 227447.4 | F9: 26083.5 | G9: 75329.9 | H9: -2760.5 | I9: 75125.1 | J9: 47330.5 | K9: 522.3 | L9: 9964.8 | M9: 45487.7 | N9: 35522.9 | P9: 4185.7 | Q9: 15667.5 | R9: 11481.8 | S9: 502663.4 | U9: 488513 | V9: 365535.1 | W9: 122977.9 | Y9: 148743.9 | AA9: 500716.1
A10: 7- 9. | B10: 504391.1 | C10: 270475.7 | D10: 265821.2 | E10: 230598.6 | F10: 28413.2 | G10: 74808.8 | H10: 64.3 | I10: 75907.3 | J10: 45489.2 | K10: 653.4 | L10: 8579.2 | M10: 45045.2 | N10: 36466.1 | P10: 4184.1 | Q10: 16025.4 | R10: 11841.3 | S10: 508575.2 | U10: 495812 | V10: 373762 | W10: 122049.9 | Y10: 148711.3 | AA10: 503673.5
A11: 10-12. | B11: 502220.4 | C11: 269973.9 | D11: 265264.9 | E11: 229560.9 | F11: 27067.4 | G11: 75883 | H11: -1406.9 | I11: 76730.3 | J11: 44663.9 | K11: 702.7 | L11: 8606.2 | M11: 45098.2 | N11: 36492 | P11: 4229.8 | Q11: 16565.2 | R11: 12335.4 | S11: 506450.3 | U11: 493614.2 | V11: 371517.4 | W11: 122096.9 | Y11: 147614.3 | AA11: 502924.7
A12: 1995/ 1- 3. | B12: 504971.9 | C12: 271265.7 | D12: 266488.5 | E12: 230416.7 | F12: 26075.5 | G12: 77722.1 | H12: 1899.6 | I12: 77721.1 | J12: 42705.2 | K12: -174 | L12: 7756.7 | M12: 45059 | N12: 37302.3 | P12: 4237.4 | Q12: 16860.5 | R12: 12623.1 | S12: 509209.3 | U12: 497215.3 | V12: 376962.9 | W12: 120252.4 | Y12: 146502.8 | AA12: 503246.3
A13: 4- 6. | B13: 510326.4 | C13: 273538.6 | D13: 268686.8 | E13: 232275.1 | F13: 25136.2 | G13: 80315.5 | H13: 1130.1 | I13: 78203.9 | J13: 44363.6 | K13: 244.5 | L13: 7394.1 | M13: 44066.3 | N13: 36672.2 | P13: 3483.2 | Q13: 15910 | R13: 12426.8 | S13: 513809.6 | U13: 502932.3 | V13: 380120.4 | W13: 122812 | Y13: 149815.2 | AA13: 508951.9
A14: 7- 9. | B14: 516624.7 | C14: 275117.6 | D14: 270195.9 | E14: 233384 | F14: 24544.2 | G14: 81502.9 | H14: 2090.5 | I14: 79185.4 | J14: 47736.8 | K14: 175.4 | L14: 6271.9 | M14: 46797.9 | N14: 40526 | P14: 5005.9 | Q14: 20060.9 | R14: 15055 | S14: 521630.7 | U14: 510352.9 | V14: 383255.2 | W14: 127097.6 | Y14: 153783.9 | AA14: 514358.7
A15: 10-12. | B15: 517836.1 | C15: 276740.9 | D15: 271775.3 | E15: 234596 | F15: 25106.5 | G15: 82476.5 | H15: 1180.5 | I15: 79766.3 | J15: 47873.2 | K15: 215.5 | L15: 4476.6 | M15: 47873.8 | N15: 43397.2 | P15: 5303.1 | Q15: 20683.2 | R15: 15380.1 | S15: 523139.2 | U15: 513359.5 | V15: 385504.4 | W15: 127855.1 | Y15: 155456.2 | AA15: 516440.1
A16: 1996/ 1- 3. | B16: 521415.5 | C16: 277884.7 | D16: 272896.5 | E16: 235340.8 | F16: 26205.8 | G16: 81422.1 | H16: 1445.6 | I16: 79906.4 | J16: 50261.9 | K16: 474.4 | L16: 3814.5 | M16: 48791.1 | N16: 44976.6 | P16: 5782.4 | Q16: 12756.3 | R16: 6974 | S16: 527197.8 | U16: 517601 | V16: 386958.2 | W16: 130642.8 | Y16: 157889.8 | AA16: 519495.4
A17: 4- 6. | B17: 526228.5 | C17: 279927.8 | D17: 274902.2 | E17: 236900.2 | F17: 27557.3 | G17: 83545.7 | H17: 3353.7 | I17: 80911.9 | J17: 49432.9 | K17: 168.4 | L17: 1330.9 | M17: 48905 | N17: 47574.1 | P17: 6535.3 | Q17: 12954.3 | R17: 6419 | S17: 532763.8 | U17: 524897.6 | V17: 394384.5 | W17: 130513.1 | Y17: 160535.9 | AA17: 522706.4
A18: 7- 9. | B18: 525385.4 | C18: 279640.8 | D18: 274573 | E18: 236141.1 | F18: 28889.1 | G18: 84545.1 | H18: 1389.8 | I18: 81808.6 | J18: 47299.8 | K18: 182.4 | L18: 1629.7 | M18: 49604.3 | N18: 47974.6 | P18: 6247.4 | Q18: 12465.5 | R18: 6218.1 | S18: 531632.8 | U18: 523755.7 | V18: 394464.9 | W18: 129290.8 | Y18: 160734.1 | AA18: 523813.2
A19: 10-12. | B19: 530701.9 | C19: 282766.6 | D19: 277684.8 | E19: 238806.1 | F19: 29856.5 | G19: 84612.6 | H19: 2397 | I19: 82222.8 | J19: 46352.9 | K19: 228.8 | L19: 2264.7 | M19: 51956.4 | N19: 49691.6 | P19: 6308.4 | Q19: 12605.2 | R19: 6296.9 | S19: 537010.3 | U19: 528437.2 | V19: 399632.7 | W19: 128804.5 | Y19: 160822 | AA19: 528076.1
... A101: 4- 6. | B101: 542774.4 | C101: 304695 | D101: 296926.3 | E101: 246990.4 | F101: 17561.6 | G101: 84579.2 | H101: -1427.8 | I101: 106640.6 | J101: 27299.4 | K101: 25.2 | L101: 3401.3 | M101: 93549.7 | N101: 90148.3 | P101: 17982.5 | Q101: 29776.6 | R101: 11794.1 | S101: 560756.9 | U101: 539373.1 | V101: 405408 | W101: 133965.1 | Y101: 129440.2 | AA101: 544177.1

Sheet gaku-jk1722
A1: 実質季節調整系列 | Q1: <参考> | AD1: (単位:2011暦年連鎖価格、10億円)
A2: Real, Seasonally Adjusted Series | Q2: <cf> | AD2: (Billions of Chained (2011) Yen)
B3: 国内総生産(支出側) | C3: 民間最終消費支出 | F3: 民間住宅 | G3: 民間企業設備 | H3: 民間在庫変動 | I3: 政府最終消費支出 | J3: 公的固定資本形成 | K3: 公的在庫変動 | L3: 財貨・サービス | O3: 開差 | Q3: 交易利得 | R3: 国内総所得 | S3: 海外からの所得 | V3: 国民総所得 | X3: 国内需要 | Y3: 民間需要 | Z3: 公的需要 | AB3: 総固定資本形成 | AD3: 最終需要
D4: 家計最終消費支出 | L4: 純輸出 | M4: 輸出 | N4: 輸入 | S4: 純受取 | T4: 受取 | U4: 支払
E5: 除く持ち家の帰属家賃
B6: GDP(Expenditure Approach) | C6: PrivateConsumption | D6: Consumption ofHouseholds | E6: ExcludingImputed Rent | F6: PrivateResidentialInvestment | G6: Private Non-Resi.Investment | H6: Changein PrivateInventories | I6: GovernmentConsumption | J6: PublicInvestment | K6: Changein PublicInventories | L6: Goods & Services | O6: Residual | Q6: TradingGains/Losses | R6: GDI | S6: Income from /to the Rest of the World | V6: GNI | X6: DomesticDemand | Y6: PrivateDemand | Z6: PublicDemand | AB6: Gross Fixed CapitalFormation | AD6: Final Sales of Domestic Product
L7: Net Exports | M7: Exports | N7: Imports | S7: Net | T7: Receipt | U7: Payment
A8: 1994/ 1- 3. | B8: 425598.9 | C8: 243131.5 | D8: 239049.9 | E8: 202446.4 | F8: 24842.4 | G8: 60160.5 | H8: 3808.3 | I8: 70584.5 | J8: 44413.4 | K8: -716.7 | L8: -9150.2 | M8: 33923.4 | N8: 43073.6 | O8: -11474.8 | Q8: 19874.1 | R8: 445473 | S8: 4015.1 | T8: 14219.8 | U8: 10204.7 | V8: 449488.1 | X8: 444360.7 | Y8: 330912.9 | Z8: 113557.1 | AB8: 126536.2 | AD8: 421953.9
A9: 4- 6. | B9: 421812 | C9: 242713.6 | D9: 238591.4 | E9: 201817.8 | F9: 26021 | G9: 59749.4 | H9: -2723.4 | I9: 71541.4 | J9: 45332.2 | K9: 785.3 | L9: -9661 | M9: 34107.3 | N9: 43768.3 | O9: -11946.4 | Q9: 19240.2 | R9: 441052.2 | S9: 3772.1 | T9: 14181.9 | U9: 10409.7 | V9: 444824.4 | X9: 440613.8 | Y9: 324566.3 | Z9: 116378.4 | AB9: 127933.7 | AD9: 423523.2
A10: 7- 9. | B10: 428451.1 | C10: 246283.7 | D10: 242143.6 | E10: 205098.4 | F10: 28366.1 | G10: 59661 | H10: -64.1 | I10: 72019.3 | J10: 43681.3 | K10: 975.1 | L10: -10343.7 | M10: 34735.6 | N10: 45079.3 | O10: -12127.6 | Q10: 18744.3 | R10: 447195.5 | S10: 3777.1 | T10: 14485.7 | U10: 10708.5 | V10: 450972.6 | X10: 447892.9 | Y10: 332705.9 | Z10: 115350.2 | AB10: 128379.6 | AD10: 427516.2
A11: 10-12. | B11: 426034.4 | C11: 245497.6 | D11: 241315.1 | E11: 204118.9 | F11: 27078.9 | G11: 60824.5 | H11: -1409.1 | I11: 72159.5 | J11: 43010.2 | K11: 1015.2 | L11: -10601 | M11: 34897.7 | N11: 45498.7 | O11: -11541.4 | Q11: 19081.3 | R11: 445115.7 | S11: 3832 | T11: 14981.6 | U11: 11149.6 | V11: 448947.7 | X11: 445432.6 | Y11: 330748.3 | Z11: 114855.6 | AB11: 127926.4 | AD11: 426358.9
A12: 1995/ 1- 3. | B12: 430299.9 | C12: 247086.9 | D12: 242841.8 | E12: 205439.5 | F12: 26096.3 | G12: 62462.5 | H12: 2273 | I12: 73635.7 | J12: 41094.9 | K12: -90.3 | L12: -11786.9 | M12: 35325.1 | N12: 47112 | O12: -10472.2 | Q12: 19550.7 | R12: 449850.6 | S12: 3839.3 | T12: 15260.4 | U12: 11421.2 | V12: 453689.8 | X12: 450642.2 | Y12: 336940.3 | Z12: 113731 | AB12: 127132.7 | AD12: 427751.7
A13: 4- 6. | B13: 435620.9 | C13: 250013 | D13: 245698.5 | E13: 208067.5 | F13: 25299.7 | G13: 64990.4 | H13: 1072.5 | I13: 73962 | J13: 42827.1 | K13: 258.1 | L13: -12579.8 | M13: 35877 | N13: 48456.7 | O13: -10222.1 | Q13: 20303.1 | R13: 455924 | S13: 3152.9 | T13: 14486.2 | U13: 11333.2 | V13: 459076.9 | X13: 456630.6 | Y13: 340718.2 | Z13: 115985.2 | AB13: 130740.4 | AD13: 434009.4
A14: 7- 9. | B14: 440854.1 | C14: 251697.5 | D14: 247319.2 | E14: 209492.2 | F14: 24680.7 | G14: 66029.7 | H14: 2011.1 | I14: 74812.5 | J14: 46151 | K14: 183.8 | L14: -14937.4 | M14: 36199.3 | N14: 51136.7 | O14: -9774.9 | Q14: 21210.1 | R14: 462064.2 | S14: 4542.4 | T14: 18239.9 | U14: 13697.5 | V14: 466606.6 | X14: 463762.8 | Y14: 343912 | Z14: 120056 | AB14: 134317.8 | AD14: 438386.4
A15: 10-12. | B15: 441692.5 | C15: 253348.4 | D15: 248939.2 | E15: 210902.8 | F15: 25322.1 | G15: 67046.5 | H15: 1109.4 | I15: 74947.1 | J15: 46285.3 | K15: 265.2 | L15: -17456.1 | M15: 36105 | N15: 53561.1 | O15: -9175.4 | Q15: 21854 | R15: 463546.5 | S15: 4849 | T15: 18842.3 | U15: 13993.4 | V15: 468395.4 | X15: 466518.9 | Y15: 346329.9 | Z15: 120368.7 | AB15: 136093.7 | AD15: 440034.6
A16: 1996/ 1- 3. | B16: 446782.3 | C16: 254442.5 | D16: 250030.3 | E16: 211792.2 | F16: 26364 | G16: 66541.2 | H16: 1852.5 | I16: 75536 | J16: 48665.5 | K16: 719.1 | L16: -17623 | M16: 36675.8 | N16: 54298.8 | O16: -9715.5 | Q16: 21323.9 | R16: 468106.3 | S16: 5268.4 | T16: 11617.8 | U16: 6349.4 | V16: 473374.6 | X16: 471790.1 | Y16: 348503.5 | Z16: 123556.9 | AB16: 138603.3 | AD16: 444164.6
A17: 4- 6. | B17: 450410.1 | C17: 255478.6 | D17: 251053.7 | E17: 212602.3 | F17: 27716.5 | G17: 68710.2 | H17: 3032.4 | I17: 75584.3 | J17: 48045.8 | K17: 238.5 | L17: -19275.3 | M17: 36655.3 | N17: 55930.7 | O17: -9120.9 | Q17: 20552.5 | R17: 470962.6 | S17: 5945.4 | T17: 11799.7 | U17: 5854.3 | V17: 476908 | X17: 476832.9 | Y17: 354294.6 | Z17: 122698.5 | AB17: 141556.4 | AD17: 446943.1
A18: 7- 9. | B18: 450363.8 | C18: 255355.3 | D18: 250902.8 | E18: 212249 | F18: 28849.1 | G18: 69800.7 | H18: 1242.6 | I18: 75960.2 | J18: 45867 | K18: 270.3 | L18: -18130.7 | M18: 37695.6 | N18: 55826.4 | O18: -8850.6 | Q18: 19692.7 | R18: 470056.5 | S18: 5666.3 | T18: 11318.6 | U18: 5652.2 | V18: 475722.8 | X18: 475490.7 | Y18: 354616.9 | Z18: 120963.6 | AB18: 141748.3 | AD18: 448565.9
A19: 10-12. | B19: 455846.1 | C19: 258015.5 | D19: 253565.5 | E19: 214657.3 | F19: 29508.1 | G19: 69858.5 | H19: 2258.5 | I19: 77059.8 | J19: 44753.4 | K19: 315.5 | L19: -17098.8 | M19: 39316.9 | N19: 56415.7 | O19: -8824.3 | Q19: 19231.7 | R19: 475077.8 | S19: 5757.6 | T19: 11476.4 | U19: 5718.8 | V19: 480835.4 | X19: 479855 | Y19: 358888.3 | Z19: 121006.6 | AB19: 141379.5 | AD19: 453059.2
... A101: 4- 6. | B101: 529241.6 | C101: 301186.4 | D101: 293369.8 | E101: 240181.5 | F101: 16517.5 | G101: 82952.6 | H101: -1254.8 | I101: 106215.2 | J101: 26005.6 | K101: 29.4 | L101: -3185.1 | M101: 87955 | N101: 91140.1 | O101: 774.8 | Q101: 6501.2 | R101: 535742.8 | S101: 17812.2 | T101: 29390.4 | U101: 11578.1 | V101: 553555 | X101: 531849.7 | Y101: 399630 | Z101: 132219 | AB101: 125445.9 | AD101: 530241.4
A102: ＊開差＝国内総生産(支出側)－国内総生産(支出側)の内訳項目計
A103: ＊財貨・サービスの純輸出は連鎖方式での計算ができないため、財貨・サービスの輸出－財貨・サービスの輸入により求めている。このため寄与度とは符号が一致しない場合がある。

Sheet kdef-cy1131
A1: 暦年デフレーター | Q1: (2000暦年＝100)
A2: Deflators (calendar year) | R2: (Calendar year of 2000 = 100)
B3: 家計最終消費支出（再掲） | M3: 財貨・サービス
C4: 居住者家計の海外での直接購入 | D4: （控除）非居住者家計の国内での直接購入 | E4: 国内家計最終消費支出 | L4: 純輸出（再掲） | M4: 輸出（再掲） | P4: 輸入（再掲）
A5: 暦年 | F5: 耐久財 | G5: 半耐久財 | H5: 非耐久財 | I5: サービス | N5: 財貨 | O5: サービス（含む非居住者家計の国内での直接購入） | Q5: 財貨 | R5: サービス（含む居住者家計の海外での直接購入）
B6: Consumptionof households(id, at §Ｉ) | C6: Directpurchasesabroad byresidenthouseholds | D6: (Less) Directpurchases inthe domesticmarket bynon-residenthouseholds | E6: Domestic finalconsumptionexpenditure ofhouseholds | F6: Durablegoods | G6: Semi-durablegoods | H6: Non-durablegoods | I6: Services | M6: Goods & Services
L7: Net Exports(id, at §Ｉ) | M7: Exports(id, at §Ｉ) | P7: Imports(id, at §Ｉ)
A8: Calendar Year | N8: Goods | O8: Services（including directpurchases in thedomestic marketby non-residenthouseholds) | Q8: Goods | R8: Services（including directpurchasesabroad byresidenthouseholds)
A9: 1980/1-12. | B9: 79.1 | C9: 88.7 | D9: 76.7 | E9: 79.1 | F9: 168.3 | G9: 81.5 | H9: 83 | I9: 66.6 | L9: *** | M9: 161.9 | N9: 169.3 | O9: 109.5 | P9: 188.9 | Q9: 213.6 | R9: 126.4
A10: 1981/1-12. | B10: 82.7 | C10: 98.8 | D10: 80.5 | E10: 82.6 | F10: 168.6 | G10: 84.3 | H10: 87.8 | I10: 69.6 | L10: *** | M10: 164.7 | N10: 171.8 | O10: 114 | P10: 189.7 | Q10: 216.4 | R10: 121.7
A11: 1982/1-12. | B11: 84.8 | C11: 118.3 | D11: 82.6 | E11: 84.8 | F11: 167.4 | G11: 86 | H11: 89.5 | I11: 72.2 | L11: *** | M11: 168.2 | N11: 175.2 | O11: 117.4 | P11: 198.5 | Q11: 230.9 | R11: 117
A12: 1983/1-12. | B12: 86.5 | C12: 117.3 | D12: 84.1 | E12: 86.4 | F12: 165.7 | G12: 87.4 | H12: 91 | I12: 74.1 | L12: *** | M12: 159.9 | N12: 165.8 | O12: 116.3 | P12: 188.6 | Q12: 216.9 | R12: 117.3
A13: 1984/1-12. | B13: 88.4 | C13: 121.6 | D13: 86 | E13: 88.3 | F13: 163.8 | G13: 88.9 | H13: 93.4 | I13: 75.9 | L13: *** | M13: 159.2 | N13: 164.8 | O13: 117.5 | P13: 183.6 | Q13: 209.4 | R13: 118.8
A14: 1985/1-12. | B14: 89.7 | C14: 124 | D14: 87.7 | E14: 89.6 | F14: 161.8 | G14: 90.6 | H14: 94.2 | I14: 77.7 | L14: *** | M14: 155.5 | N14: 161.3 | O14: 113 | P14: 179.8 | Q14: 204.2 | R14: 118.7
A15: 1986/1-12. | B15: 90.1 | C15: 89.1 | D15: 88 | E15: 90.1 | F15: 156.9 | G15: 91.6 | H15: 93.4 | I15: 79.2 | L15: *** | M15: 135.1 | N15: 139.5 | O15: 102.3 | P15: 122.2 | Q15: 132.3 | R15: 98.4
A16: 1987/1-12. | B16: 90.3 | C16: 79.6 | D16: 87.9 | E16: 90.5 | F16: 151.7 | G16: 92.2 | H16: 92 | I16: 80.9 | L16: *** | M16: 128.6 | N16: 132.4 | O16: 100.1 | P16: 115.9 | Q16: 123.8 | R16: 97.2
A17: 1988/1-12. | B17: 90.7 | C17: 74.3 | D17: 88.3 | E17: 90.9 | F17: 146.3 | G17: 92.7 | H17: 91.8 | I17: 82.2 | L17: *** | M17: 124.7 | N17: 128 | O17: 99.3 | P17: 111.3 | Q17: 117.4 | R17: 96.9
A18: 1989/1-12. | B18: 92.5 | C18: 84.7 | D18: 90.4 | E18: 92.6 | F18: 139.7 | G18: 95.4 | H18: 93.4 | I18: 84.7 | L18: *** | M18: 128.6 | N18: 132.5 | O18: 100 | P18: 116.4 | Q18: 124.1 | R18: 98.5
A19: 1990/1-12. | B19: 94.9 | C19: 94.7 | D19: 93 | E19: 94.9 | F19: 137.1 | G19: 98.2 | H19: 96.1 | I19: 87.2 | L19: *** | M19: 130.2 | N19: 134.1 | O19: 101.5 | P19: 124.6 | Q19: 133.5 | R19: 104.1
A20: 1991/1-12. | B20: 97.5 | C20: 93.7 | D20: 96.1 | E20: 97.6 | F20: 135.6 | G20: 101.3 | H20: 99.5 | I20: 89.9 | L20: *** | M20: 125.9 | N20: 128.6 | O20: 104.9 | P20: 118.2 | Q20: 124.5 | R20: 103.6
... A39: 2010/1-12. | B39: 91.3 | C39: 121.6 | D39: 96.4 | E39: 91 | F39: 45.4 | G39: 91 | H39: 101.9 | I39: 96.3 | L39: *** | M39: 86.9 | N39: 86.1 | O39: 93.4 | P39: 117.9 | Q39: 117.2 | R39: 117.5

Sheet def-cy1131
A1: 暦年デフレーター | P1: <参考> | V1: (2000暦年＝100)
A2: Deflators (calendar year) | P2: <cf> | W2: (Calendar year of 2000 = 100)
B3: 国内総生産(支出側) | C3: 民間最終消費支出 | F3: 民間住宅 | G3: 民間企業設備 | H3: 民間在庫品増加 | I3: 政府最終消費支出 | J3: 公的固定資本形成 | K3: 公的在庫品増加 | L3: 財貨・サービス | P3: 海外からの所得 | S3: 国民総所得 | U3: 国内需要 | V3: 民間需要 | W3: 公的需要 | Y3: 総固定資本形成
A4: 暦年 | D4: 家計最終消費支出 | L4: 純輸出 | M4: 輸出 | N4: 輸入 | P4: 純受取 | Q4: 受取 | R4: 支払
E5: 除く持ち家の帰属家賃
B6: GDP(expenditure approach) | C6: PrivateConsumption | D6: Consumption ofHouseholds | E6: Excludingimputed rent | F6: PrivateResidentialInvestment | G6: PrivateNon-Resi.Investment | H6: PrivateInventory | I6: GovernmentConsumption | J6: PublicInvestment | K6: PublicInventory | L6: Goods & Services | P6: Income from /to the rest of the world | S6: GNI | U6: DomesticDemand | V6: PrivateDemand | W6: PublicDemand | Y6: Gross fixed capitalformation
A7: Calendar Year | L7: Net Exports | M7: Exports | N7: Imports | P7: Net | Q7: Receipt | R7: Payment
A8: 1980/1-12. | B8: 85.4 | C8: 79 | D8: 79.1 | E8: 83 | F8: 82 | G8: 111 | H8: 169.6 | I8: 79.3 | J8: 89.9 | K8: 51.2 | L8: *** | M8: 161.9 | N8: 188.9 | P8: *** | Q8: 85 | R8: 84.9 | S8: 86.3 | U8: 85.2 | V8: 85.2 | W8: 84.6 | Y8: 99.9
A9: 1981/1-12. | B9: 88.1 | C9: 82.6 | D9: 82.7 | E9: 86.7 | F9: 81.5 | G9: 112.3 | H9: 161.7 | I9: 80.8 | J9: 92 | K9: 54.3 | L9: *** | M9: 164.7 | N9: 189.7 | P9: *** | Q9: 87.8 | R9: 87.7 | S9: 89 | U9: 87.7 | V9: 88.1 | W9: 85.9 | Y9: 101.1
A10: 1982/1-12. | B10: 89.5 | C10: 84.8 | D10: 84.8 | E10: 88.9 | F10: 83.1 | G10: 112.7 | H10: 160.4 | I10: 82.2 | J10: 93.3 | K10: 57.5 | L10: *** | M10: 168.2 | N10: 198.5 | P10: *** | Q10: 89.4 | R10: 89.3 | S10: 90.5 | U10: 89.4 | V10: 89.9 | W10: 87.1 | Y10: 102
A11: 1983/1-12. | B11: 90.3 | C11: 86.4 | D11: 86.5 | E11: 90.4 | F11: 83.2 | G11: 111.9 | H11: 155.8 | I11: 82.4 | J11: 93.2 | K11: 60 | L11: *** | M11: 159.9 | N11: 188.6 | P11: *** | Q11: 90.3 | R11: 90.2 | S11: 91.3 | U11: 90.3 | V11: 91.1 | W11: 87 | Y11: 101.6
A12: 1984/1-12. | B12: 91.9 | C12: 88.3 | D12: 88.4 | E12: 92.3 | F12: 84.5 | G12: 111.6 | H12: 153.6 | I12: 83.4 | J12: 94.1 | K12: 63.1 | L12: *** | M12: 159.2 | N12: 183.6 | P12: *** | Q12: 91.7 | R12: 91.6 | S12: 92.8 | U12: 91.7 | V12: 92.5 | W12: 88.3 | Y12: 102
A13: 1985/1-12. | B13: 92.8 | C13: 89.7 | D13: 89.7 | E13: 93.5 | F13: 85.1 | G13: 111.4 | H13: 149.3 | I13: 85.9 | J13: 94 | K13: 67 | L13: *** | M13: 155.5 | N13: 179.8 | P13: *** | Q13: 92.6 | R13: 92.5 | S13: 93.7 | U13: 92.7 | V13: 92.9 | W13: 91.9 | Y13: 102
A14: 1986/1-12. | B14: 94.5 | C14: 90 | D14: 90.1 | E14: 93.5 | F14: 84.7 | G14: 109.9 | H14: 137.3 | I14: 86.9 | J14: 93.4 | K14: 69.2 | L14: *** | M14: 135.1 | N14: 122.2 | P14: *** | Q14: 92.7 | R14: 92.7 | S14: 93.8 | U14: 92.7 | V14: 93.3 | W14: 90.5 | Y14: 101
A15: 1987/1-12. | B15: 94.4 | C15: 90.3 | D15: 90.3 | E15: 93.3 | F15: 86.1 | G15: 108.1 | H15: 134.6 | I15: 87.2 | J15: 93.4 | K15: 75.5 | L15: *** | M15: 128.6 | N15: 115.9 | P15: *** | Q15: 92.7 | R15: 92.7 | S15: 93.7 | U15: 92.7 | V15: 93.3 | W15: 90.6 | Y15: 100.3
A16: 1988/1-12. | B16: 94.7 | C16: 90.7 | D16: 90.7 | E16: 93.3 | F16: 87.5 | G16: 107.5 | H16: 131.2 | I16: 87.6 | J16: 94.5 | K16: 78.5 | L16: *** | M16: 124.7 | N16: 111.3 | P16: *** | Q16: 93 | R16: 93 | S16: 93.9 | U16: 93 | V16: 93.7 | W16: 90.5 | Y16: 100.5
A17: 1989/1-12. | B17: 96.8 | C17: 92.5 | D17: 92.5 | E17: 95 | F17: 92.5 | G17: 108.5 | H17: 129.9 | I17: 90.7 | J17: 98.6 | K17: 81.5 | L17: *** | M17: 128.6 | N17: 116.4 | P17: *** | Q17: 95.2 | R17: 95.2 | S17: 96.1 | U17: 95.2 | V17: 95.6 | W17: 93.9 | Y17: 103
A18: 1990/1-12. | B18: 99 | C18: 94.9 | D18: 94.9 | E18: 97.2 | F18: 95.9 | G18: 111.1 | H18: 129.9 | I18: 94.1 | J18: 102 | K18: 85.2 | L18: *** | M18: 130.2 | N18: 124.6 | P18: *** | Q18: 97.6 | R18: 97.7 | S18: 98.6 | U18: 97.9 | V18: 98.1 | W18: 97.3 | Y18: 105.9
A19: 1991/1-12. | B19: 101.6 | C19: 97.5 | D19: 97.5 | E19: 99.7 | F19: 98.9 | G19: 112.9 | H19: 128.7 | I19: 96.6 | J19: 105.1 | K19: 86 | L19: *** | M19: 125.9 | N19: 118.2 | P19: *** | Q19: 100.2 | R19: 100.2 | S19: 101.1 | U19: 100.4 | V19: 100.5 | W19: 99.8 | Y19: 108.2
... A38: 2010/1-12. | B38: 88.7 | C38: 91.3 | D38: 91.3 | E38: 91.3 | F38: 102.9 | G38: 89.6 | H38: 96.5 | I38: 93.9 | J38: 101.5 | K38: 103.4 | L38: *** | M38: 86.9 | N38: 117.9 | P38: *** | Q38: 92.3 | R38: 92.8 | S38: 92.3 | U38: 92.4 | V38: 91.6 | W38: 95.2 | Y38: 94
A39: ＊在庫デフレーターは暦年平均デフレーターである。

Sheet kdef-cy1722
A1: 暦年デフレーター | Y1: (2011暦年＝100)
A2: Deflators, Calendar Year | Y2: (Calendar Year of 2011 = 100)
B3: 家計最終消費支出（再掲） | K3: 形態別総固定資本形成 | P3: 総資本形成 | S3: 財貨・サービス
C4: 居住者家計の海外での直接購入 | D4: （控除）非居住者家計の国内での直接購入 | E4: 国内家計最終消費支出 | K4: 住宅 | L4: その他の建物・構築物 | M4: 輸送用機械 | N4: その他の機械設備等 | O4: 知的財産生産物 | Q4: うち在庫変動 | S4: 純輸出（再掲） | T4: 輸出（再掲） | W4: 輸入（再掲）
F5: 耐久財 | G5: 半耐久財 | H5: 非耐久財 | I5: サービス | U5: 財貨 | V5: サービス（含む非居住者家計の国内での直接購入） | X5: 財貨 | Y5: サービス（含む居住者家計の海外での直接購入）
B6: Consumptionof Households(id, at §Ｉ) | C6: DirectPurchasesAbroad byResidentHouseholds | D6: (Less) DirectPurchases inthe DomesticMarket byNon-ResidentHouseholds | E6: Domestic FinalConsumptionExpenditure ofHouseholds | F6: DurableGoods | G6: Semi-DurableGoods | H6: Non-DurableGoods | I6: Services | K6: Gross Fixed Capital Formation by Type | P6: Gross CapitalFormation | Q6: Of WhichChange inInventories | S6: Goods & Services
K7: ResidentialInvestment | L7: Other Buildingsand Structures | M7: TransportEquipment | N7: OtherMachinery andEquipment etc. | O7: IntellectualPropertyProducts | S7: Net Exports(id, at §Ｉ) | T7: Exports(id, at §Ｉ) | W7: Imports(id, at §Ｉ)
A8: Calendar Year | U8: Goods | V8: Services（Including DirectPurchases in theDomestic Marketby Non-ResidentHouseholds) | X8: Goods | Y8: Services（Including DirectPurchasesAbroad byResidentHouseholds)
A9: 1994/1-12. | B9: 109.8 | C9: 66.9 | D9: 102.7 | E9: 110.3 | F9: 307.4 | G9: 113.8 | H9: 97.1 | I9: 99.5 | K9: 100 | L9: 98 | M9: 109.5 | N9: 162.7 | O9: 101.7 | P9: 115.5 | Q9: 108.6 | S9: *** | T9: 131.2 | U9: 134.2 | V9: 112.6 | W9: 80.3 | X9: 79.4 | Y9: 88.8
A10: 1995/1-12. | B10: 109.4 | C10: 64.3 | D10: 102.4 | E10: 110 | F10: 291.4 | G10: 113 | H10: 95.7 | I10: 100.7 | K10: 99.4 | L10: 97.8 | M10: 108.6 | N10: 158.2 | O10: 101.1 | P10: 114.2 | Q10: 106.9 | S10: *** | T10: 128.2 | U10: 131.5 | V10: 107.8 | W10: 78.9 | X10: 78 | Y10: 87.5
A11: 1996/1-12. | B11: 109.4 | C11: 76.9 | D11: 102.4 | E11: 109.8 | F11: 275.8 | G11: 112.7 | H11: 95.2 | I11: 101.7 | K11: 100 | L11: 98.3 | M11: 108.9 | N11: 152.1 | O11: 101.4 | P11: 113.2 | Q11: 105.7 | S11: *** | T11: 132.5 | U11: 136.5 | V11: 109.1 | W11: 85.5 | X11: 84.5 | Y11: 94.9
A12: 1997/1-12. | B12: 110.7 | C12: 88 | D12: 104.1 | E12: 110.9 | F12: 268.9 | G12: 114 | H12: 96.7 | I12: 103 | K12: 101.7 | L12: 99.1 | M12: 109.4 | N12: 149.7 | O12: 103 | P12: 113.5 | Q12: 105 | S12: *** | T12: 134.9 | U12: 138.9 | V12: 111.2 | W12: 90.9 | X12: 90 | Y12: 100.3
A13: 1998/1-12. | B13: 110.7 | C13: 97.7 | D13: 104.7 | E13: 110.8 | F13: 261.8 | G13: 114.8 | H13: 96.7 | I13: 103.1 | K13: 99.7 | L13: 97.2 | M13: 108.9 | N13: 147.7 | O13: 103.4 | P13: 112 | Q13: 101.9 | S13: *** | T13: 136.4 | U13: 140.1 | V13: 114 | W13: 88.3 | X13: 85.9 | Y13: 101.8
A14: 1999/1-12. | B14: 109.9 | C14: 86.9 | D14: 104.3 | E14: 110.2 | F14: 255.2 | G14: 113.8 | H14: 96.6 | I14: 102.7 | K14: 98.5 | L14: 95.3 | M14: 106.7 | N14: 142.8 | O14: 103.3 | P14: 109.9 | Q14: 99.2 | S14: *** | T14: 124.5 | U14: 127 | V14: 109.8 | W14: 80.9 | X14: 78.6 | Y14: 93.5
A15: 2000/1-12. | B15: 108.9 | C15: 83.6 | D15: 103.4 | E15: 109.2 | F15: 241.2 | G15: 112.4 | H15: 95.8 | I15: 102.5 | K15: 98.6 | L15: 95.4 | M15: 104.3 | N15: 138.7 | O15: 103.5 | P15: 109.1 | Q15: 98.3 | S15: *** | T15: 119.5 | U15: 121.3 | V15: 108.7 | W15: 82.2 | X15: 80.1 | Y15: 94
A16: 2001/1-12. | B16: 107.7 | C16: 93.6 | D16: 102.5 | E16: 107.9 | F16: 220.2 | G16: 110.3 | H16: 95.3 | I16: 102.4 | K16: 97.5 | L16: 94.3 | M16: 103.5 | N16: 132.6 | O16: 102.7 | P16: 106.9 | Q16: 96.2 | S16: *** | T16: 122.5 | U16: 124.1 | V16: 112.9 | W16: 84.1 | X16: 81 | Y16: 99.4
A17: 2002/1-12. | B17: 106.2 | C17: 99.6 | D17: 101.3 | E17: 106.3 | F17: 204.8 | G17: 107 | H17: 94 | I17: 102 | K17: 96.3 | L17: 93.1 | M17: 102.7 | N17: 126.9 | O17: 101.7 | P17: 104.7 | Q17: 94.5 | S17: *** | T17: 120.8 | U17: 122 | V17: 113.3 | W17: 83.2 | X17: 80.1 | Y17: 98.8
A18: 2003/1-12. | B18: 105.1 | C18: 100 | D18: 101 | E18: 105.2 | F18: 189.8 | G18: 105.1 | H18: 93.9 | I18: 101.6 | K18: 96.2 | L18: 93.2 | M18: 101.2 | N18: 120.9 | O18: 100.5 | P18: 103 | Q18: 93.7 | S18: *** | T18: 116.4 | U18: 117.3 | V18: 110.8 | W18: 82.7 | X18: 79 | Y18: 100.5
A19: 2004/1-12. | B19: 104.6 | C19: 100 | D19: 101 | E19: 104.6 | F19: 176.4 | G19: 104 | H19: 94.7 | I19: 101.5 | K19: 96.6 | L19: 94 | M19: 100.4 | N19: 116.9 | O19: 100.5 | P19: 102.2 | Q19: 94.8 | S19: *** | T19: 114.7 | U19: 115.4 | V19: 110.3 | W19: 85.1 | X19: 81.4 | Y19: 103.4
A20: 2005/1-12. | B20: 104.1 | C20: 106.9 | D20: 100.6 | E20: 104.1 | F20: 165.3 | G20: 103.7 | H20: 94.8 | I20: 101.6 | K20: 97 | L20: 95.2 | M20: 100.2 | N20: 113.8 | O20: 100.4 | P20: 102.2 | Q20: 96.9 | S20: *** | T20: 116.3 | U20: 116.8 | V20: 113 | W20: 92.2 | X20: 89.2 | Y20: 107.1
... A31: 2016/1-12. | B31: 101.3 | C31: 135.4 | D31: 104.7 | E31: 101.1 | F31: 95.9 | G31: 105.5 | H31: 105.1 | I31: 99.7 | K31: 105.1 | L31: 103.4 | M31: 103.6 | N31: 100.3 | O31: 101 | P31: 102.1 | Q31: 93.9 | S31: *** | T31: 103.2 | U31: 102.6 | V31: 106.2 | W31: 92.5 | X31: 89.4 | Y31: 104.5
A32: ＊在庫デフレーターは暦年平均デフレーターである。
A33: ＊暦年デフレーター原系列＝（名目原系列 / 実質原系列）×１００

Sheet def-cy1722
A1: 暦年デフレーター | P1: <参考> | AA1: (2011暦年＝100)
A2: Deflators, Calendar Year | P2: <cf> | AA2: (Calendar Year of 2011 = 100)
B3: 国内総生産(支出側) | C3: 民間最終消費支出 | F3: 民間住宅 | G3: 民間企業設備 | H3: 民間在庫変動 | I3: 政府最終消費支出 | J3: 公的固定資本形成 | K3: 公的在庫変動 | L3: 財貨・サービス | P3: 海外からの所得 | S3: 国民総所得 | U3: 国内需要 | V3: 民間需要 | W3: 公的需要 | Y3: 総固定資本形成 | AA3: 最終需要
D4: 家計最終消費支出 | L4: 純輸出 | M4: 輸出 | N4: 輸入 | P4: 純受取 | Q4: 受取 | R4: 支払
E5: 除く持ち家の帰属家賃
B6: GDP(Expenditure Approach) | C6: PrivateConsumption | D6: Consumption ofHouseholds | E6: ExcludingImputed Rent | F6: PrivateResidentialInvestment | G6: Private Non-Resi.Investment | H6: Changein PrivateInventories | I6: GovernmentConsumption | J6: PublicInvestment | K6: Changein PublicInventories | L6: Goods & Services | P6: Income from /to the Rest of the World | S6: GNI | U6: DomesticDemand | V6: PrivateDemand | W6: PublicDemand | Y6: Gross Fixed CapitalFormation | AA6: Final Sales of Domestic Product
A7: Calendar Year | L7: Net Exports | M7: Exports | N7: Imports | P7: Net | Q7: Receipt | R7: Payment
A8: 1994/1-12. | B8: 117.9 | C8: 109.8 | D8: 109.8 | E8: 112.5 | F8: 100.1 | G8: 125.7 | H8: 112.3 | I8: 105.3 | J8: 104.1 | K8: 67.8 | L8: *** | M8: 131.2 | N8: 80.3 | P8: *** | Q8: 110.6 | R8: 110.5 | S8: 112.8 | U8: 110.7 | V8: 112.3 | W8: 105.8 | Y8: 116 | AA8: 118
A9: 1995/1-12. | B9: 117.3 | C9: 109.4 | D9: 109.4 | E9: 111.6 | F9: 99.5 | G9: 123.6 | H9: 110.7 | I9: 106 | J9: 103.6 | K9: 65.4 | L9: *** | M9: 128.2 | N9: 78.9 | P9: *** | Q9: 110 | R9: 110 | S9: 111.9 | U9: 110.2 | V9: 111.6 | W9: 106 | Y9: 114.6 | AA9: 117.4
A10: 1996/1-12. | B10: 116.7 | C10: 109.5 | D10: 109.4 | E10: 111.3 | F10: 100.1 | G10: 121.6 | H10: 109.1 | I10: 106.9 | J10: 103.2 | K10: 67.4 | L10: *** | M10: 132.5 | N10: 85.5 | P10: *** | Q10: 109.9 | R10: 109.9 | S10: 111.7 | U10: 110 | V10: 111.3 | W10: 106.4 | Y10: 113.6 | AA10: 116.8
A11: 1997/1-12. | B11: 117.3 | C11: 110.8 | D11: 110.7 | E11: 112.4 | F11: 101.8 | G11: 121 | H11: 108.4 | I11: 108.1 | J11: 104.2 | K11: 67.4 | L11: *** | M11: 134.9 | N11: 90.9 | P11: *** | Q11: 110.9 | R11: 110.9 | S11: 112.5 | U11: 111 | V11: 112.2 | W11: 107.5 | Y11: 113.9 | AA11: 117.4
A12: 1998/1-12. | B12: 117.2 | C12: 110.7 | D12: 110.7 | E12: 112.1 | F12: 99.8 | G12: 119.7 | H12: 105.5 | I12: 108 | J12: 102.7 | K12: 63.1 | L12: *** | M12: 136.4 | N12: 88.3 | P12: *** | Q12: 110.3 | R12: 110.4 | S12: 112.2 | U12: 110.6 | V12: 111.8 | W12: 106.9 | Y12: 112.5 | AA12: 117.4
A13: 1999/1-12. | B13: 115.7 | C13: 110 | D13: 109.9 | E13: 111.3 | F13: 98.6 | G13: 117.2 | H13: 102.3 | I13: 106.3 | J13: 100.7 | K13: 64.9 | L13: *** | M13: 124.5 | N13: 80.9 | P13: *** | Q13: 109.2 | R13: 109.2 | S13: 110.6 | U13: 109.3 | V13: 110.7 | W13: 105.1 | Y13: 110.3 | AA13: 115.8
A14: 2000/1-12. | B14: 114.1 | C14: 109 | D14: 108.9 | E14: 110.2 | F14: 98.6 | G14: 115.8 | H14: 100.8 | I14: 105.8 | J14: 100.5 | K14: 70 | L14: *** | M14: 119.5 | N14: 82.2 | P14: *** | Q14: 108.3 | R14: 108.4 | S14: 109.4 | U14: 108.4 | V14: 109.6 | W14: 104.7 | Y14: 109.5 | AA14: 114.2
A15: 2001/1-12. | B15: 112.8 | C15: 107.8 | D15: 107.7 | E15: 108.9 | F15: 97.6 | G15: 112.8 | H15: 98.6 | I15: 105.7 | J15: 98.9 | K15: 69 | L15: *** | M15: 122.5 | N15: 84.1 | P15: *** | Q15: 107.1 | R15: 107.2 | S15: 108.3 | U15: 107.1 | V15: 108.1 | W15: 104.2 | Y15: 107.2 | AA15: 113
A16: 2002/1-12. | B16: 111.2 | C16: 106.3 | D16: 106.2 | E16: 107.3 | F16: 96.3 | G16: 110.1 | H16: 96.6 | I16: 105 | J16: 97.4 | K16: 69.4 | L16: *** | M16: 120.8 | N16: 83.2 | P16: *** | Q16: 105.5 | R16: 105.7 | S16: 106.6 | U16: 105.6 | V16: 106.4 | W16: 103.3 | Y16: 105.1 | AA16: 111.3
A17: 2003/1-12. | B17: 109.4 | C17: 105.2 | D17: 105.1 | E17: 106.1 | F17: 96.2 | G17: 107.4 | H17: 95.7 | I17: 103.4 | J17: 97 | K17: 69.9 | L17: *** | M17: 116.4 | N17: 82.7 | P17: *** | Q17: 104.1 | R17: 104.4 | S17: 105 | U17: 104.3 | V17: 105 | W17: 102 | Y17: 103.4 | AA17: 109.5
A18: 2004/1-12. | B18: 108.2 | C18: 104.6 | D18: 104.6 | E18: 105.4 | F18: 96.6 | G18: 105.8 | H18: 96.8 | I18: 102.8 | J18: 97.5 | K18: 72.2 | L18: *** | M18: 114.7 | N18: 85.1 | P18: *** | Q18: 103.5 | R18: 103.8 | S18: 104.1 | U18: 103.6 | V18: 104.3 | W18: 101.6 | Y18: 102.6 | AA18: 108.3
A19: 2005/1-12. | B19: 107 | C19: 104.1 | D19: 104.1 | E19: 104.7 | F19: 97 | G19: 105.1 | H19: 98 | I19: 102.7 | J19: 98.3 | K19: 83.9 | L19: *** | M19: 116.3 | N19: 92.2 | P19: *** | Q19: 103.3 | R19: 103.6 | S19: 103.7 | U19: 103.3 | V19: 103.9 | W19: 101.7 | Y19: 102.5 | AA19: 107.2
... A30: 2016/1-12. | B30: 103 | C30: 101.2 | D30: 101.3 | E30: 102.7 | F30: 105.1 | G30: 101.3 | H30: 95.6 | I30: 100.2 | J30: 103.9 | K30: 74.1 | L30: *** | M30: 103.2 | N30: 92.5 | P30: *** | Q30: 101.1 | R30: 101.6 | S30: 101.1 | U30: 101.2 | V30: 101.3 | W30: 100.9 | Y30: 102.3 | AA30: 103.1
A31: ＊在庫デフレーターは暦年平均デフレーターである。
A32: ＊暦年デフレーター原系列＝（名目原系列 / 実質原系列）×１００

Sheet call
A1: コード | B1: st'STRACLCOON | C1: st'STRACLUCON
A2: 系列名 | B2: 有担レート・翌日物 月平／金利 | C2: 無担レート・Ｏ／Ｎ 月平／金利
A3: 25628 | B3: 8.4166667
A4: 25720 | B4: 8.25
A5: 25812 | B5: 8.5
A6: 25903 | B6: 7.97
A7: 25993 | B7: 7.2966667
A8: 26085 | B8: 6.5966667
A9: 26177 | B9: 6.2366667
A10: 26268 | B10: 5.5266667
A11: 26359 | B11: 5.1233333
A12: 26451 | B12: 4.8166667
A13: 26543 | B13: 4.4646667
A14: 26634 | B14: 4.4866667
... A64: 31199 | B64: 6.0685667
A65: 31291 | B65: 6.2540333 | C65: 6.3871667
A66: 31382 | B66: 7.2818333 | C66: 7.4403333
A67: 31472 | B67: 6.053 | C67: 6.2754333
A68: 31564 | B68: 4.4357333 | C68: 4.6293
A69: 31656 | B69: 4.5625333 | C69: 4.6884667
A70: 31747 | B70: 4.1207333 | C70: 4.2521
A71: 31837 | B71: 3.9980333 | C71: 4.1998
A72: 31929 | B72: 3.2817667 | C72: 3.4391667
A73: 32021 | B73: 3.2489333 | C73: 3.3747667
A74: 32112 | B74: 3.5249667 | C74: 3.6614333
A75: 32203 | B75: 3.4885667 | C75: 3.686
A76: 32295 | B76: 3.3323667 | C76: 3.5175667
... A188: 42522 | B188: 0.001 | C188: -0.050333333
A189: 42614 | C189: -0.046
A190: 42705 | C190: -0.043333333
A191: 42795 | C191: -0.041666667
A192: 42887 | C192: -0.054333333
A193: 42979
A194: 43070

Sheet fof
A1: データコード | B1: FF'FOF_FFAS122L331 | C1: FF'FOF_FFAS411L331 | E1: 08SNA対応 | F1: ff'FOF_FFAS122L330 | G1: ff'FOF_FFAS122L331 | H1: ff'FOF_FFAS411L330 | I1: ff'FOF_FFAS411L331 | K1: 93SNA対応 | L1: コード | M1: ff'FOF_93FFAS122L330 | N1: ff'FOF_93FFAS122L331 | O1: ff'FOF_93FFAS411L330 | P1: ff'FOF_93FFAS411L331 | R1: ⇒旧々基準 | S1: コード | T1: ff'FFSA122L210 | U1: ff'FFSA260L210
A2: 系列名称 | B2: 負債・－うち株式／国内銀行／ストック | C2: 負債・－うち株式／民間非金融法人企業／ストック | F2: 負債・－株式等／国内銀行／ストック | G2: 負債・－－上場株式／国内銀行／ストック | H2: 負債・－株式等／民間非金融法人企業／ストック | I2: 負債・－－上場株式／民間非金融法人企業／ストック | L2: 系列名 | M2: （更新停止）負債・株式・出資金／国内銀行／ストック | N2: （更新停止）負債・－うち株式／国内銀行／ストック | O2: （更新停止）負債・株式・出資金／民間非金融法人企業／ストック | P2: （更新停止）負債・－うち株式／民間非金融法人企業／ストック | S2: 系列名 | T2: （更新停止）負債/－株式/国内銀行/ストック | U2: （更新停止）負債/－株式/法人企業/ストック
A3: 23437 | E3: 23437 | L3: 23437 | S3: 23437
A4: 23529 | E4: 23529 | L4: 23529 | S4: 23529
A5: 23621 | E5: 23621 | L5: 23621 | S5: 23621
A6: 23712 | E6: 23712 | L6: 23712 | S6: 23712
A7: 23802 | E7: 23802 | L7: 23802 | S7: 23802
A8: 23894 | E8: 23894 | L8: 23894 | S8: 23894
A9: 23986 | E9: 23986 | L9: 23986 | S9: 23986
A10: 24077 | E10: 24077 | L10: 24077 | S10: 24077
A11: 24167 | E11: 24167 | L11: 24167 | S11: 24167
A12: 24259 | E12: 24259 | L12: 24259 | S12: 24259
A13: 24351 | E13: 24351 | L13: 24351 | S13: 24351
A14: 24442 | E14: 24442 | L14: 24442 | S14: 24442
... A66: 29190 | E66: 29190 | L66: 29190 | S66: 29190
A67: 29281 | B67: =T67/T68*B68 -> 6829.3636 | C67: =U67/U68*C68 -> 163819.93 | E67: 29281 | L67: 29281 | S67: 29281 | T67: 17857 | U67: 169965
A68: 29373 | B68: =T68/T69*B69 -> 6841.6019 | C68: =U68/U69*C69 -> 165457.5 | E68: 29373 | L68: 29373 | S68: 29373 | T68: 17889 | U68: 171664
A69: 29465 | B69: =T69/T70*B70 -> 6920.0037 | C69: =U69/U70*C70 -> 167399.65 | E69: 29465 | L69: 29465 | S69: 29465 | T69: 18094 | U69: 173679
A70: 29556 | B70: =T70/T71*B71 -> 7033.5905 | C70: =U70/U71*C71 -> 169698.42 | E70: 29556 | L70: 29556 | S70: 29556 | T70: 18391 | U70: 176064
A71: 29646 | B71: =T71/T72*B72 -> 7098.6066 | C71: =U71/U72*C72 -> 171554.79 | E71: 29646 | L71: 29646 | S71: 29646 | T71: 18561 | U71: 177990
A72: 29738 | B72: =T72/T73*B73 -> 7173.1839 | C72: =U72/U73*C73 -> 173610.67 | E72: 29738 | L72: 29738 | S72: 29738 | T72: 18756 | U72: 180123
A73: 29830 | B73: =T73/T74*B74 -> 7668.0708 | C73: =U73/U74*C74 -> 175425.59 | E73: 29830 | L73: 29830 | S73: 29830 | T73: 20050 | U73: 182006
A74: 29921 | B74: =T74/T75*B75 -> 7840.5546 | C74: =U74/U75*C75 -> 180548.43 | E74: 29921 | L74: 29921 | S74: 29921 | T74: 20501 | U74: 187321
A75: 30011 | B75: =T75/T76*B76 -> 7886.4483 | C75: =U75/U76*C76 -> 182755.63 | E75: 30011 | L75: 30011 | S75: 30011 | T75: 20621 | U75: 189611
A76: 30103 | B76: =T76/T77*B77 -> 7975.1761 | C76: =U76/U77*C77 -> 185227.89 | E76: 30103 | L76: 30103 | S76: 30103 | T76: 20853 | U76: 192176
A77: 30195 | B77: =T77/T78*B78 -> 8004.2421 | C77: =U77/U78*C78 -> 187797.5 | E77: 30195 | L77: 30195 | S77: 30195 | T77: 20929 | U77: 194842
A78: 30286 | B78: =T78/T79*B79 -> 8015.3331 | C78: =U78/U79*C79 -> 191599.87 | E78: 30286 | L78: 30286 | S78: 30286 | T78: 20958 | U78: 198787
... A137: 35674 | B137: =T137/T138*B138 -> 231252.19 | C137: =U137/U138*C138 -> 2694470.4 | E137: 35674 | L137: 35674 | S137: 35674 | T137: 604664 | U137: 2795543
A138: 35765 | B138: =N138/N139*B139 -> 166118.72 | C138: =P138/P139*C139 -> 2361113 | E138: 35765 | F138: 442208 | G138: 438637 | H138: 3172379 | I138: 2361113 | L138: 35765 | M138: 442208 | N138: 438637 | O138: 3172379 | P138: 2361113 | S138: 35765 | T138: 434357 | U138: 2449681
A139: 35855 | B139: =N139/N140*B140 -> 176783.73 | C139: =P139/P140*C140 -> 2528500 | E139: 35855 | F139: 473812 | G139: 466798 | H139: 3385474 | I139: 2528500 | L139: 35855 | M139: 473812 | N139: 466798 | O139: 3385474 | P139: 2528500 | S139: 35855 | T139: 462328 | U139: 2616277
A140: 35947 | B140: =N140/N141*B141 -> 162339.89 | C140: =P140/P141*C141 -> 2521885 | E140: 35947 | F140: 435325 | G140: 428659 | H140: 3367697 | I140: 2521885 | L140: 35947 | M140: 435325 | N140: 428659 | O140: 3367697 | P140: 2521885 | S140: 35947 | T140: 424389 | U140: 2603234
A141: 36039 | B141: =N141/N142*B142 -> 112559.23 | C141: =P141/P142*C142 -> 2225287 | E141: 36039 | F141: 303028 | G141: 297213 | H141: 2950859 | I141: 2225287 | L141: 36039 | M141: 303028 | N141: 297213 | O141: 2950859 | P141: 2225287 | S141: 36039 | T141: 293228 | U141: 2310031
A142: 36130 | B142: =N142/N143*B143 -> 126416.43 | C142: =P142/P143*C143 -> 2393725 | E142: 36130 | F142: 339467 | G142: 333803 | H142: 3139622 | I142: 2393725 | L142: 36130 | M142: 339467 | N142: 333803 | O142: 3139622 | P142: 2393725 | S142: 36130 | T142: 329795 | U142: 2490651
A143: 36220 | B143: =N143/N144*B144 -> 169447.63 | C143: =P143/P144*C144 -> 2799262 | E143: 36220 | F143: 514949 | G143: 447427 | H143: 3614039 | I143: 2799262 | L143: 36220 | M143: 514949 | N143: 447427 | O143: 3614039 | P143: 2799262 | S143: 36220 | T143: 442751 | U143: 2894556
A144: 36312 | B144: =N144/N145*B145 -> 169077.24 | C144: =P144/P145*C145 -> 3257746 | E144: 36312 | F144: 513999 | G144: 446449 | H144: 4212921 | I144: 3257746 | L144: 36312 | M144: 513999 | N144: 446449 | O144: 4212921 | P144: 3257746 | S144: 36312
A145: 36404 | B145: =N145/N146*B146 -> 200985.93 | C145: =P145/P146*C146 -> 3484234 | E145: 36404 | F145: 600256 | G145: 530704 | H145: 4510183 | I145: 3484234 | L145: 36404 | M145: 600256 | N145: 530704 | O145: 4510183 | P145: 3484234 | S145: 36404
A146: 36495 | B146: =N146/N147*B147 -> 170570.9 | C146: =P146/P147*C147 -> 4236337 | E146: 36495 | F146: 520416 | G146: 450393 | H146: 5461807 | I146: 4236337 | L146: 36495 | M146: 520416 | N146: 450393 | O146: 5461807 | P146: 4236337 | S146: 36495
A147: 36586 | B147: =N147/N148*B148 -> 168827.29 | C147: =P147/P148*C148 -> 4233363 | E147: 36586 | F147: 516635 | G147: 445789 | H147: 5404303 | I147: 4233363 | L147: 36586 | M147: 516635 | N147: 445789 | O147: 5404303 | P147: 4233363 | S147: 36586
A148: 36678 | B148: =N148/N149*B149 -> 153384.02 | C148: =P148/P149*C149 -> 3959774 | E148: 36678 | F148: 475690 | G148: 405011 | H148: 5114045 | I148: 3959774 | L148: 36678 | M148: 475690 | N148: 405011 | O148: 5114045 | P148: 3959774 | S148: 36678
A149: 36770 | B149: =N149/N150*B150 -> 159431.35 | C149: =P149/P150*C150 -> 3639159 | E149: 36770 | F149: 574356 | G149: 420979 | H149: 4766668 | I149: 3639159 | L149: 36770 | M149: 574356 | N149: 420979 | O149: 4766668 | P149: 3639159 | S149: 36770
A150: 36861 | B150: =N150/N151*B151 -> 140219.48 | C150: =P150/P151*C151 -> 3181536 | E150: 36861 | F150: 509200 | G150: 370250 | H150: 4285437 | I150: 3181536 | L150: 36861 | M150: 509200 | N150: 370250 | O150: 4285437 | P150: 3181536 | S150: 36861
A151: 36951 | B151: =N151/N152*B152 -> 87824.926 | C151: =P151/P152*C152 -> 3118521 | E151: 36951 | F151: 370847 | G151: 231902 | H151: 4098419 | I151: 3118521 | L151: 36951 | M151: 370847 | N151: 231902 | O151: 4098419 | P151: 3118521 | S151: 36951
A152: 37043 | B152: =N152/N153*B153 -> 129478.35 | C152: =P152/P153*C153 -> 3219051 | E152: 37043 | F152: 564080 | G152: 341888 | H152: 4233709 | I152: 3219051 | L152: 37043 | M152: 564080 | N152: 341888 | O152: 4233709 | P152: 3219051 | S152: 37043
A153: 37135 | B153: =N153/N154*B154 -> 111690.45 | C153: =P153/P154*C154 -> 2516457 | E153: 37135 | F153: 496209 | G153: 294919 | H153: 3129043 | I153: 2516457 | L153: 37135 | M153: 496209 | N153: 294919 | O153: 3129043 | P153: 2516457 | S153: 37135
A154: 37226 | B154: =N154/N155*B155 -> 89189.818 | C154: =P154/P155*C155 -> 2640914 | E154: 37226 | F154: 406340 | G154: 235506 | H154: 3263852 | I154: 2640914 | L154: 37226 | M154: 406340 | N154: 235506 | O154: 3263852 | P154: 2640914 | S154: 37226
A155: 37316 | B155: =N155/N156*B156 -> 88062.76 | C155: =P155/P156*C156 -> 2757835 | E155: 37316 | F155: 405794 | G155: 232530 | H155: 3423537 | I155: 2757835 | L155: 37316 | M155: 405794 | N155: 232530 | O155: 3423537 | P155: 2757835 | S155: 37316
... A166: 38322 | B166: =N166/N167*B167 -> 144878.82 | C166: =P166/P167*C167 -> 3136224 | E166: 38322 | F166: 729935 | G166: 382553 | H166: 4599860 | I166: 3136224 | L166: 38322 | M166: 729935 | N166: 382553 | O166: 4599860 | P166: 3136224 | S166: 38322
A167: 38412 | B167: =G167 -> 145228 | C167: =I167 -> 3251265 | E167: 38412 | F167: 394870 | G167: 145228 | H167: 4870673 | I167: 3251265 | L167: 38412 | M167: 718937 | N167: 383475 | O167: 4903337 | P167: 3251265
A168: 38504 | B168: =G168 -> 137815 | C168: =I168 -> 3259301 | E168: 38504 | F168: 397034 | G168: 137815 | H168: 4872436 | I168: 3259301 | L168: 38504 | M168: 730686 | N168: 385647 | O168: 4904962 | P168: 3259301
A169: 38596 | B169: =G169 -> 168653 | C169: =I169 -> 3779986 | E169: 38596 | F169: 500722 | G169: 168653 | H169: 5693241 | I169: 3779986 | L169: 38596 | M169: 900716 | N169: 488991 | O169: 5732262 | P169: 3779986
A170: 38687 | B170: =G170 -> 194265 | C170: =I170 -> 4575631 | E170: 38687 | F170: 652101 | G170: 194265 | H170: 7254171 | I170: 4575631 | L170: 38687 | M170: 1169163 | N170: 640143 | O170: 7289354 | P170: 4575631
A171: 38777 | B171: =G171 -> 201561 | C171: =I171 -> 4726913 | E171: 38777 | F171: 686627 | G171: 201561 | H171: 7427858 | I171: 4726913 | L171: 38777 | M171: 1227990 | N171: 674905 | O171: 7461661 | P171: 4726913
A172: 38869 | B172: =G172 -> 179985 | C172: =I172 -> 4352075 | E172: 38869 | F172: 636165 | G172: 179985 | H172: 6841212 | I172: 4352075 | L172: 38869 | M172: 1142068 | N172: 624949 | O172: 6872253 | P172: 4352075
A173: 38961 | B173: =G173 -> 178069 | C173: =I173 -> 4409848 | E173: 38961 | F173: 621502 | G173: 178069 | H173: 6933931 | I173: 4409848 | L173: 38961 | M173: 1102843 | N173: 611801 | O173: 6965437 | P173: 4409848
A174: 39052 | B174: =G174 -> 181362 | C174: =I174 -> 4687538 | E174: 39052 | F174: 608938 | G174: 181362 | H174: 7769156 | I174: 4687538 | L174: 39052 | M174: 1073351 | N174: 600116 | O174: 7800831 | P174: 4687538
A175: 39142 | B175: =G175 -> 174437 | C175: =I175 -> 4821935 | E175: 39142 | F175: 564559 | G175: 174437 | H175: 7962967 | I175: 4821935 | L175: 39142 | M175: 986144 | N175: 555690 | O175: 7998433 | P175: 4821935
A176: 39234 | B176: =G176 -> 176995 | C176: =I176 -> 4988707 | E176: 39234 | F176: 588001 | G176: 176995 | H176: 8239388 | I176: 4988707 | L176: 39234 | M176: 1030380 | N176: 579042 | O176: 8276122 | P176: 4988707
A177: 39326 | B177: =G177 -> 154309 | C177: =I177 -> 4635948 | E177: 39326 | F177: 466159 | G177: 154309 | H177: 7612356 | I177: 4635948 | L177: 39326 | M177: 810094 | N177: 458632 | O177: 7645814 | P177: 4635948
A178: 39417 | B178: =G178 -> 147929 | C178: =I178 -> 4248274 | E178: 39417 | F178: 446556 | G178: 147929 | H178: 5930147 | I178: 4248274 | L178: 39417 | M178: 777473 | N178: 439234 | O178: 5952274 | P178: 4248274
... A209: 42248 | B209: =G209 -> 128429 | C209: =I209 -> 4516421 | E209: 42248 | F209: 397025 | G209: 128429 | H209: 7105015 | I209: 4516421 | L209: 42248 | M209: 686785 | N209: 398469 | O209: 7312857 | P209: 4516421
A210: 42339 | B210: =G210 -> 125263 | C210: =I210 -> 4978317 | E210: 42339 | F210: 410726 | G210: 125263 | H210: 7960948 | I210: 4978317 | L210: 42339
A211: 42430 | B211: =G211 -> 83578 | C211: =I211 -> 4444613 | E211: 42430 | F211: 289647 | G211: 83578 | H211: 7408546 | I211: 4444613
A212: 42522 | B212: =G212 -> 75309 | C212: =I212 -> 4165002 | E212: 42522 | F212: 256024 | G212: 75309 | H212: 6916982 | I212: 4165002
A213: 42614 | B213: =G213 -> 81427 | C213: =I213 -> 4384552 | E213: 42614 | F213: 285523 | G213: 81427 | H213: 7295216 | I213: 4384552
A214: 42705 | B214: =G214 -> 99614 | C214: =I214 -> 4940800 | E214: 42705 | F214: 377281 | G214: 99614 | H214: 8257367 | I214: 4940800
A215: 42805 | B215: =G215 -> 94480 | C215: =I215 -> 4977128 | E215: 42805 | F215: 358728 | G215: 94480 | H215: 8299564 | I215: 4977128
A216: 42887 | B216: =G216 -> 100685 | C216: =I216 -> 5299938 | E216: 42887 | F216: 380328 | G216: 100685 | H216: 8837034 | I216: 5299938
A217: 42979 | E217: 42979
A218: 43070 | E218: 43070

Sheet fof_org
A1: データコード | B1: FF'FOF_FFAS122L330 | C1: FF'FOF_FFAS122L331 | D1: FF'FOF_FFAS411L330 | E1: FF'FOF_FFAS411L331 | F1: FF'FFSA260L210 | G1: FF'FFSA122L210 | I1: 08SNA対応 | J1: ff'FOF_FFAS122L330 | K1: ff'FOF_FFAS122L331 | L1: ff'FOF_FFAS411L330 | M1: ff'FOF_FFAS411L331
A2: 系列名称 | B2: 負債・株式・出資金／国内銀行／ストック | C2: 負債・－うち株式／国内銀行／ストック | D2: 負債・株式・出資金／民間非金融法人企業／ストック | E2: 負債・－うち株式／民間非金融法人企業／ストック | F2: （更新停止）負債・－株式／法人企業／ストック | G2: （更新停止）負債・－株式／国内銀行／ストック | J2: 負債・－株式等／国内銀行／ストック | K2: 負債・－－上場株式／国内銀行／ストック | L2: 負債・－株式等／民間非金融法人企業／ストック | M2: 負債・－－上場株式／民間非金融法人企業／ストック | O2: FMMの（総）自己資本CPTLOR
A3: 23437 | I3: 23437
A4: 23529 | I4: 23529
A5: 23621 | I5: 23621
A6: 23712 | F6: 59809 | G6: 3732 | I6: 23712
A7: 23802 | F7: 60703 | G7: 3734 | I7: 23802
A8: 23894 | F8: 60981 | G8: 3734 | I8: 23894
A9: 23986 | F9: 61630 | G9: 3769 | I9: 23986
A10: 24077 | F10: 62685 | G10: 3772 | I10: 24077
A11: 24167 | F11: 63382 | G11: 3817 | I11: 24167
A12: 24259 | F12: 64247 | G12: 4022 | I12: 24259
A13: 24351 | F13: 65315 | G13: 4247 | I13: 24351
A14: 24442 | F14: 66481 | G14: 4340 | I14: 24442
A15: 24532 | F15: 67175 | G15: 4448 | I15: 24532
A16: 24624 | F16: 67986 | G16: 4466 | I16: 24624
A17: 24716 | F17: 68778 | G17: 4667 | I17: 24716
... A102: 32478 | F102: 500101 | G102: 69969 | I102: 32478
A103: 32568 | F103: 524554 | G103: 76838 | I103: 32568 | O103: 57361.524
A104: 32660 | F104: 539798 | G104: 88673 | I104: 32660 | O104: 60448.551
A105: 32752 | F105: 567008 | G105: 94979 | I105: 32752 | O105: 63646.375
A106: 32843 | F106: 601341 | G106: 113939 | I106: 32843 | O106: 62193.401
A107: 32933 | F107: 627054 | G107: 124038 | I107: 32933 | O107: 60740.427
A108: 33025 | F108: 633983 | G108: 129173 | I108: 33025 | O108: 56857.533
A109: 33117 | F109: 641294 | G109: 129560 | I109: 33117 | O109: 52974.639
A110: 33208 | F110: 645723 | G110: 129790 | I110: 33208 | O110: 57581.525
A111: 33298 | F111: 649893 | G111: 130452 | I111: 33298 | O111: 62188.411
A112: 33390 | F112: 653588 | G112: 130749 | I112: 33390 | O112: 62019.76
A113: 33482 | F113: 655675 | G113: 130860 | I113: 33482 | O113: 61851.108
A114: 33573 | F114: 658500 | G114: 130972 | I114: 33573 | O114: 60046.251
... A137: 35674 | F137: 2795543 | G137: 604664 | I137: 35674 | O137: 61178.78
A138: 35765 | B138: 442208 | C138: 438637 | D138: 3172379 | E138: 2361113 | F138: 2449681 | G138: 434357 | I138: 35765 | O138: 60732.081
A139: 35855 | B139: 473812 | C139: 466798 | D139: 3385474 | E139: 2528500 | F139: 2616277 | G139: 462328 | I139: 35855 | O139: 60285.382
A140: 35947 | B140: 435325 | C140: 428659 | D140: 3367697 | E140: 2521885 | F140: 2603234 | G140: 424389 | I140: 35947 | O140: 58378.659
A141: 36039 | B141: 303028 | C141: 297213 | D141: 2950859 | E141: 2225287 | F141: 2310031 | G141: 293228 | I141: 36039 | O141: 56471.935
A142: 36130 | B142: 339467 | C142: 333803 | D142: 3139622 | E142: 2393725 | F142: 2490651 | G142: 329795 | I142: 36130 | O142: 58703.833
A143: 36220 | B143: 514949 | C143: 447427 | D143: 3614039 | E143: 2799262 | F143: 2894556 | G143: 442751 | I143: 36220 | O143: 60935.731
A144: 36312 | B144: 513999 | C144: 446449 | D144: 4212921 | E144: 3257746 | I144: 36312 | O144: 61351.691
A145: 36404 | B145: 600256 | C145: 530704 | D145: 4510183 | E145: 3484234 | I145: 36404 | O145: 61767.651
A146: 36495 | B146: 520416 | C146: 450393 | D146: 5461807 | E146: 4236337 | I146: 36495 | O146: 62400.355
A147: 36586 | B147: 516635 | C147: 445789 | D147: 5404303 | E147: 4233363 | I147: 36586 | O147: 63033.059
A148: 36678 | B148: 475690 | C148: 405011 | D148: 5114045 | E148: 3959774 | I148: 36678 | O148: 62692.641
A149: 36770 | B149: 574356 | C149: 420979 | D149: 4766668 | E149: 3639159 | I149: 36770 | O149: 62352.223
A150: 36861 | B150: 509200 | C150: 370250 | D150: 4285437 | E150: 3181536 | I150: 36861 | O150: 62156.743
A151: 36951 | B151: 370847 | C151: 231902 | D151: 4098419 | E151: 3193886 | I151: 36951 | O151: 61961.262
A152: 37043 | B152: 564080 | C152: 341888 | D152: 4233709 | E152: 3281533 | I152: 37043 | O152: 60022.139
A153: 37135 | B153: 496209 | C153: 294919 | D153: 3129043 | E153: 2570772 | I153: 37135 | O153: 58083.015
A154: 37226 | B154: 406340 | C154: 235506 | D154: 3263852 | E154: 2683694 | I154: 37226 | O154: 56769.332
A155: 37316 | B155: 405794 | C155: 232530 | D155: 3423537 | E155: 2807164 | I155: 37316 | O155: 55455.648
... A166: 38322 | B166: 729935 | C166: 382553 | D166: 4599860 | E166: 3190769 | I166: 38322 | O166: 51208.068
A167: 38412 | B167: 718937 | C167: 145228 | D167: 4903337 | E167: 3251265 | I167: 38412 | J167: 394870 | K167: 145228 | L167: 4870673 | M167: 3251265 | O167: 52272.269
A168: 38504 | B168: 730686 | C168: 137815 | D168: 4904962 | E168: 3259301 | I168: 38504 | J168: 397034 | K168: 137815 | L168: 4872436 | M168: 3259301 | O168: 53001.195
A169: 38596 | B169: 900716 | C169: 168653 | D169: 5732262 | E169: 3779986 | I169: 38596 | J169: 500722 | K169: 168653 | L169: 5693241 | M169: 3779986 | O169: 53730.121
A170: 38687 | B170: 1169163 | C170: 194265 | D170: 7289354 | E170: 4575631 | I170: 38687 | J170: 652101 | K170: 194265 | L170: 7254171 | M170: 4575631 | O170: 55739.766
A171: 38777 | B171: 1227990 | C171: 201561 | D171: 7461661 | E171: 4726913 | I171: 38777 | J171: 686627 | K171: 201561 | L171: 7427858 | M171: 4726913 | O171: 57749.41
A172: 38869 | B172: 1142068 | C172: 179985 | D172: 6872253 | E172: 4352075 | I172: 38869 | J172: 636165 | K172: 179985 | L172: 6841212 | M172: 4352075 | O172: 58644.364
A173: 38961 | B173: 1102843 | C173: 178069 | D173: 6965437 | E173: 4409848 | I173: 38961 | J173: 621502 | K173: 178069 | L173: 6933931 | M173: 4409848 | O173: 59539.317
A174: 39052 | B174: 1073351 | C174: 181362 | D174: 7800831 | E174: 4687538 | I174: 39052 | J174: 608938 | K174: 181362 | L174: 7769156 | M174: 4687538 | O174: 59562.691
A175: 39142 | B175: 986144 | C175: 174437 | D175: 7998433 | E175: 4821935 | I175: 39142 | J175: 564559 | K175: 174437 | L175: 7962967 | M175: 4821935 | O175: 59586.065
A176: 39234 | B176: 1030380 | C176: 176995 | D176: 8276122 | E176: 4988707 | I176: 39234 | J176: 588001 | K176: 176995 | L176: 8239388 | M176: 4988707 | O176: 59543.767
A177: 39326 | B177: 810094 | C177: 154309 | D177: 7645814 | E177: 4635948 | I177: 39326 | J177: 466159 | K177: 154309 | L177: 7612356 | M177: 4635948 | O177: 59501.469
A178: 39417 | B178: 777473 | C178: 147929 | D178: 5952274 | E178: 4248274 | I178: 39417 | J178: 446556 | K178: 147929 | L178: 5930147 | M178: 4248274 | O178: 58042.378
... A209: 42248 | B209: 686785 | C209: 128429 | D209: 7312857 | E209: 4516421 | I209: 42248 | J209: 397025 | K209: 128429 | L209: 7105015 | M209: 4516421 | O209: 69863.121
A210: 42339 | B210: =B209*J210/J209 -> 710485.37 | C210: =K210 -> 125263 | D210: =D209*L210/L209 -> 8193828.5 | E210: =M210 -> 4978317 | I210: 42339 | J210: 410726 | K210: 125263 | L210: 7960948 | M210: 4978317 | O210: 69640.124
A211: 42430 | B211: =B210*J211/J210 -> 501039.52 | C211: =K211 -> 83578 | D211: =D210*L211/L210 -> 7625267.1 | E211: =M211 -> 4444613 | I211: 42430 | J211: 289647 | K211: 83578 | L211: 7408546 | M211: 4444613 | O211: 69439.981
A212: 42522 | B212: =B211*J212/J211 -> 442877.51 | C212: =K212 -> 75309 | D212: =D211*L212/L211 -> 7119323.5 | E212: =M212 -> 4165002 | I212: 42522 | J212: 256024 | K212: 75309 | L212: 6916982 | M212: 4165002
A213: 42614 | B213: =B212*J213/J212 -> 493905.71 | C213: =K213 -> 81427 | D213: =D212*L213/L212 -> 7508621.9 | E213: =M213 -> 4384552 | I213: 42614 | J213: 285523 | K213: 81427 | L213: 7295216 | M213: 4384552
A214: 42705 | B214: =B213*J214/J213 -> 652631.27 | C214: =K214 -> 99614 | D214: =D213*L214/L213 -> 8498918.6 | E214: =M214 -> 4940800 | I214: 42705 | J214: 377281 | K214: 99614 | L214: 8257367 | M214: 4940800
A215: 42805 | B215: =B214*J215/J214 -> 620537.77 | C215: =K215 -> 94480 | D215: =D214*L215/L214 -> 8542350 | E215: =M215 -> 4977128 | I215: 42805 | J215: 358728 | K215: 94480 | L215: 8299564 | M215: 4977128
A216: 42887 | B216: =B215*J216/J215 -> 657902.06 | C216: =K216 -> 100685 | D216: =D215*L216/L215 -> 9095542.5 | E216: =M216 -> 5299938 | I216: 42887 | J216: 380328 | K216: 100685 | L216: 8837034 | M216: 5299938
A217: 42979 | I217: 42979
A218: 43070 | I218: 43070

Sheet jikasougaku
A1: ⑨ 業種別月末時価総額(市場第一部）
B3: (単位：百万円 \mil.)
A4: 現在の業種 | C4: 水産・農林業 | E4: 鉱業 | G4: 建設業 | I4: 食料品 | K4: 繊維製品 | M4: パルプ・紙 | O4: 化学 | Q4: 医薬品 | S4: 石油・石炭製品 | U4: ゴム製品 | W4: ガラス・土石製品 | Y4: 鉄鋼 | AA4: 非鉄金属 | AC4: 金属製品 | AE4: 機械 | AG4: 電気機器 | AI4: 輸送用機器 | AK4: 精密機器 | AM4: その他製品 | AO4: 電気・ガス業 | AQ4: 陸運業 | AS4: 海運業 | AU4: 空運業 | AW4: 倉庫・運輸関連業 | AY4: 情報・通信業 | BA4: 卸売業 | BC4: 小売業 | BE4: 銀行業 | BG4: 証券、商品先物取引業 | BI4: 保険業 | BK4: その他金融業 | BM4: 不動産業 | BO4: サービス業 | BQ4: 合計
C5: 社数 | D5: 時価総額 | E5: 社数 | F5: 時価総額 | G5: 社数 | H5: 時価総額 | I5: 社数 | J5: 時価総額 | K5: 社数 | L5: 時価総額 | M5: 社数 | N5: 時価総額 | O5: 社数 | P5: 時価総額 | Q5: 社数 | R5: 時価総額 | S5: 社数 | T5: 時価総額 | U5: 社数 | V5: 時価総額 | W5: 社数 | X5: 時価総額 | Y5: 社数 | Z5: 時価総額 | AA5: 社数 | AB5: 時価総額 | AC5: 社数 | AD5: 時価総額 | AE5: 社数 | AF5: 時価総額 | AG5: 社数 | AH5: 時価総額 | AI5: 社数 | AJ5: 時価総額 | AK5: 社数 | AL5: 時価総額 | AM5: 社数 | AN5: 時価総額 | AO5: 社数 | AP5: 時価総額 | AQ5: 社数 | AR5: 時価総額 | AS5: 社数 | AT5: 時価総額 | AU5: 社数 | AV5: 時価総額 | AW5: 社数 | AX5: 時価総額 | AY5: 社数 | AZ5: 時価総額 | BA5: 社数 | BB5: 時価総額 | BC5: 社数 | BD5: 時価総額 | BE5: 社数 | BF5: 時価総額 | BG5: 社数 | BH5: 時価総額 | BI5: 社数 | BJ5: 時価総額 | BK5: 社数 | BL5: 時価総額 | BM5: 社数 | BN5: 時価総額 | BO5: 社数 | BP5: 時価総額 | BQ5: 社数 | BR5: 時価総額
C6: 水産 | E6: 鉱業 | G6: 建設業 | I6: 食料品 | K6: 繊維 | M6: パルプ・紙 | O6: 化学工業 | S6: 石油・石炭製品 | U6: ゴム製品 | W6: ガラス・土石製品 | Y6: 第一次金属 | AC6: 金属製品 | AE6: 機械 | AG6: 電気機器 | AI6: 輸送用機器 | AK6: 精密機器 | AM6: その他製造業 | AO6: 電気・ガス | AQ6: 陸運 | AS6: 海運 | AW6: 倉庫 | AY6: 通信業 | BA6: 商業 | BE6: 金融・保険 | BM6: 不動産 | BO6: サービス業 | BQ6: 合計
A7: S32 | B7: 20851 | C7: 6 | D7: 25690 | E7: 29 | F7: 94356 | G7: 1 | H7: 700 | I7: 38 | J7: 83310 | K7: 48 | L7: 204527 | M7: 18 | N7: 56912 | O7: 76 | P7: 151687 | S7: 10 | T7: 55158 | U7: 6 | V7: 5435 | W7: 20 | X7: 66761 | Y7: 50 | Z7: 142541 | AC7: 3 | AD7: 2420 | AE7: 33 | AF7: 23495 | AG7: 41 | AH7: 121138 | AI7: 33 | AJ7: 114049 | AK7: 10 | AL7: 10017 | AM7: 7 | AN7: 4126 | AO7: 13 | AP7: 128144 | AQ7: 22 | AR7: 68117 | AS7: 32 | AT7: 120164 | AW7: 7 | AX7: 4498 | BA7: 30 | BB7: 98742 | BE7: 36 | BF7: 125221 | BM7: 5 | BN7: 21267 | BO7: 22 | BP7: 25972 | BQ7: 596 | BR7: 1754458
A8: S32 | B8: 20879 | C8: 6 | D8: 25394 | E8: 29 | F8: 96173 | G8: 1 | H8: 790 | I8: 38 | J8: 84066 | K8: 48 | L8: 199092 | M8: 18 | N8: 55682 | O8: 76 | P8: 152667 | S8: 11 | T8: 67676 | U8: 6 | V8: 6017 | W8: 20 | X8: 67283 | Y8: 50 | Z8: 161043 | AC8: 3 | AD8: 2460 | AE8: 33 | AF8: 26118 | AG8: 41 | AH8: 131251 | AI8: 33 | AJ8: 125750 | AK8: 10 | AL8: 13547 | AM8: 7 | AN8: 4154 | AO8: 13 | AP8: 134807 | AQ8: 22 | AR8: 77153 | AS8: 32 | AT8: 120381 | AW8: 7 | AX8: 4593 | BA8: 29 | BB8: 99964 | BE8: 36 | BF8: 126011 | BM8: 5 | BN8: 22844 | BO8: 22 | BP8: 25373 | BQ8: 596 | BR8: 1830299
A9: S32 | B9: 20909 | C9: 6 | D9: 24334 | E9: 29 | F9: 94970 | G9: 1 | H9: 790 | I9: 38 | J9: 86828 | K9: 48 | L9: 194480 | M9: 18 | N9: 55627 | O9: 76 | P9: 153202 | S9: 11 | T9: 65814 | U9: 6 | V9: 6342 | W9: 20 | X9: 68996 | Y9: 50 | Z9: 165695 | AC9: 3 | AD9: 2444 | AE9: 33 | AF9: 28661 | AG9: 41 | AH9: 141708 | AI9: 33 | AJ9: 124453 | AK9: 10 | AL9: 14356 | AM9: 7 | AN9: 4715 | AO9: 13 | AP9: 133431 | AQ9: 22 | AR9: 77839 | AS9: 32 | AT9: 116059 | AW9: 7 | AX9: 4698 | BA9: 29 | BB9: 102999 | BE9: 36 | BF9: 126808 | BM9: 5 | BN9: 22075 | BO9: 22 | BP9: 24604 | BQ9: 596 | BR9: 1841939
A10: S32 | B10: 20940 | C10: 6 | D10: 25714 | E10: 29 | F10: 97509 | G10: 1 | H10: 900 | I10: 39 | J10: 90801 | K10: 48 | L10: 198614 | M10: 18 | N10: 57544 | O10: 76 | P10: 161188 | S10: 11 | T10: 72851 | U10: 6 | V10: 7260 | W10: 20 | X10: 73736 | Y10: 50 | Z10: 161011 | AC10: 3 | AD10: 2678 | AE10: 33 | AF10: 30290 | AG10: 42 | AH10: 146982 | AI10: 33 | AJ10: 129541 | AK10: 10 | AL10: 15036 | AM10: 7 | AN10: 5023 | AO10: 13 | AP10: 130451 | AQ10: 22 | AR10: 77670 | AS10: 32 | AT10: 126206 | AW10: 7 | AX10: 4677 | BA10: 29 | BB10: 105504 | BE10: 36 | BF10: 125744 | BM10: 5 | BN10: 22730 | BO10: 22 | BP10: 24713 | BQ10: 598 | BR10: 1894381
A11: S32 | B11: 20971 | C11: 6 | D11: 25616 | E11: 29 | F11: 95431 | G11: 1 | H11: 915 | I11: 39 | J11: 88431 | K11: 48 | L11: 190814 | M11: 18 | N11: 56231 | O11: 76 | P11: 163993 | S11: 11 | T11: 73576 | U11: 6 | V11: 7732 | W11: 20 | X11: 76079 | Y11: 50 | Z11: 160851 | AC11: 3 | AD11: 1896 | AE11: 33 | AF11: 32396 | AG11: 42 | AH11: 149761 | AI11: 33 | AJ11: 135294 | AK11: 10 | AL11: 17055 | AM11: 7 | AN11: 5065 | AO11: 13 | AP11: 131166 | AQ11: 22 | AR11: 77921 | AS11: 32 | AT11: 118903 | AW11: 7 | AX11: 4883 | BA11: 29 | BB11: 107205 | BE11: 36 | BF11: 124400 | BM11: 5 | BN11: 22718 | BO11: 22 | BP11: 23899 | BQ11: 598 | BR11: 1892241
A12: S32 | B12: 21000 | C12: 6 | D12: 23790 | E12: 29 | F12: 83978 | G12: 1 | H12: 790 | I12: 39 | J12: 80378 | K12: 48 | L12: 170084 | M12: 18 | N12: 51355 | O12: 75 | P12: 144885 | S12: 11 | T12: 68339 | U12: 6 | V12: 6920 | W12: 20 | X12: 69404 | Y12: 50 | Z12: 143544 | AC12: 3 | AD12: 1712 | AE12: 34 | AF12: 27715 | AG12: 42 | AH12: 131444 | AI12: 33 | AJ12: 107438 | AK12: 10 | AL12: 15117 | AM12: 7 | AN12: 4729 | AO12: 13 | AP12: 128192 | AQ12: 22 | AR12: 74752 | AS12: 32 | AT12: 94246 | AW12: 7 | AX12: 4258 | BA12: 29 | BB12: 92523 | BE12: 36 | BF12: 121397 | BM12: 5 | BN12: 18142 | BO12: 22 | BP12: 23086 | BQ12: 598 | BR12: 1688230
A13: S32 | B13: 21032 | C13: 6 | D13: 23324 | E13: 29 | F13: 87493 | G13: 1 | H13: 745 | I13: 39 | J13: 79604 | K13: 48 | L13: 172322 | M13: 18 | N13: 49187 | O13: 75 | P13: 144261 | S13: 11 | T13: 71400 | U13: 6 | V13: 5290 | W13: 20 | X13: 69283 | Y13: 49 | Z13: 146114 | AC13: 3 | AD13: 3169 | AE13: 34 | AF13: 25526 | AG13: 42 | AH13: 134666 | AI13: 33 | AJ13: 103780 | AK13: 10 | AL13: 14295 | AM13: 7 | AN13: 4579 | AO13: 13 | AP13: 129617 | AQ13: 22 | AR13: 69737 | AS13: 32 | AT13: 88494 | AW13: 7 | AX13: 3872 | BA13: 29 | BB13: 92500 | BE13: 36 | BF13: 121698 | BM13: 5 | BN13: 18194 | BO13: 22 | BP13: 22623 | BQ13: 597 | BR13: 1681785
A14: S32 | B14: 21063 | C14: 6 | D14: 23328 | E14: 28 | F14: 80940 | G14: 1 | H14: 645 | I14: 39 | J14: 77604 | K14: 48 | L14: 176272 | M14: 19 | N14: 49119 | O14: 75 | P14: 136733 | S14: 11 | T14: 64470 | U14: 6 | V14: 4940 | W14: 20 | X14: 61727 | Y14: 49 | Z14: 132519 | AC14: 3 | AD14: 2902 | AE14: 34 | AF14: 23936 | AG14: 42 | AH14: 127636 | AI14: 33 | AJ14: 105110 | AK14: 10 | AL14: 14981 | AM14: 7 | AN14: 4337 | AO14: 13 | AP14: 127674 | AQ14: 21 | AR14: 69005 | AS14: 32 | AT14: 84700 | AW14: 7 | AX14: 3780 | BA14: 29 | BB14: 80249 | BE14: 36 | BF14: 120853 | BM14: 5 | BN14: 18173 | BO14: 22 | BP14: 22376 | BQ14: 596 | BR14: 1614019
A15: S32 | B15: 21093 | C15: 6 | D15: 25220 | E15: 28 | F15: 88755 | G15: 1 | H15: 835 | I15: 39 | J15: 83604 | K15: 48 | L15: 183677 | M15: 19 | N15: 51112 | O15: 75 | P15: 146169 | S15: 11 | T15: 72638 | U15: 6 | V15: 8816 | W15: 20 | X15: 72488 | Y15: 49 | Z15: 143321 | AC15: 3 | AD15: 3101 | AE15: 34 | AF15: 26864 | AG15: 42 | AH15: 149228 | AI15: 33 | AJ15: 120454 | AK15: 11 | AL15: 18228 | AM15: 7 | AN15: 4699 | AO15: 13 | AP15: 131928 | AQ15: 21 | AR15: 72831 | AS15: 32 | AT15: 87398 | AW15: 7 | AX15: 4246 | BA15: 30 | BB15: 90062 | BE15: 36 | BF15: 120908 | BM15: 5 | BN15: 19047 | BO15: 22 | BP15: 22634 | BQ15: 598 | BR15: 1748275
A16: S32 | B16: 21124 | C16: 6 | D16: 26438 | E16: 28 | F16: 94487 | G16: 2 | H16: 4580 | I16: 39 | J16: 85411 | K16: 48 | L16: 194847 | M16: 19 | N16: 50627 | O16: 75 | P16: 143724 | S16: 11 | T16: 68141 | U16: 6 | V16: 8284 | W16: 20 | X16: 78883 | Y16: 50 | Z16: 146594 | AC16: 3 | AD16: 3026 | AE16: 34 | AF16: 27024 | AG16: 42 | AH16: 164469 | AI16: 32 | AJ16: 118430 | AK16: 11 | AL16: 18064 | AM16: 7 | AN16: 4835 | AO16: 13 | AP16: 127608 | AQ16: 21 | AR16: 71670 | AS16: 32 | AT16: 78131 | AW16: 7 | AX16: 4198 | BA16: 31 | BB16: 89420 | BE16: 36 | BF16: 118314 | BM16: 5 | BN16: 19808 | BO16: 22 | BP16: 21970 | BQ16: 600 | BR16: 1768992
A17: S32 | B17: 21154 | C17: 6 | D17: 25052 | E17: 28 | F17: 88017 | G17: 2 | H17: 4092 | I17: 39 | J17: 83961 | K17: 48 | L17: 181799 | M17: 19 | N17: 48303 | O17: 75 | P17: 137189 | S17: 11 | T17: 66662 | U17: 6 | V17: 7406 | W17: 20 | X17: 77753 | Y17: 50 | Z17: 152844 | AC17: 3 | AD17: 3138 | AE17: 34 | AF17: 26103 | AG17: 42 | AH17: 163977 | AI17: 32 | AJ17: 119077 | AK17: 11 | AL17: 17280 | AM17: 7 | AN17: 4798 | AO17: 13 | AP17: 128259 | AQ17: 21 | AR17: 70171 | AS17: 32 | AT17: 77879 | AW17: 7 | AX17: 4097 | BA17: 31 | BB17: 85497 | BE17: 36 | BF17: 117971 | BM17: 5 | BN17: 19481 | BO17: 22 | BP17: 22315 | BQ17: 600 | BR17: 1733132
A18: S32 | B18: 21182 | C18: 6 | D18: 24124 | E18: 28 | F18: 84976 | G18: 2 | H18: 3728 | I18: 39 | J18: 83143 | K18: 48 | L18: 169498 | M18: 19 | N18: 46393 | O18: 75 | P18: 133392 | S18: 11 | T18: 64386 | U18: 6 | V18: 6475 | W18: 20 | X18: 74990 | Y18: 50 | Z18: 145536 | AC18: 3 | AD18: 2911 | AE18: 34 | AF18: 25692 | AG18: 42 | AH18: 159884 | AI18: 34 | AJ18: 115074 | AK18: 11 | AL18: 16818 | AM18: 7 | AN18: 4678 | AO18: 13 | AP18: 128798 | AQ18: 21 | AR18: 69213 | AS18: 32 | AT18: 70868 | AW18: 7 | AX18: 3858 | BA18: 31 | BB18: 82299 | BE18: 36 | BF18: 117457 | BM18: 5 | BN18: 18558 | BO18: 22 | BP18: 22127 | BQ18: 602 | BR18: 1674886
... A39: S34 | B39: 21823 | C39: 6 | D39: 29438 | E39: 28 | F39: 116209 | G39: 2 | H39: 23060 | I39: 39 | J39: 177253 | K39: 47 | L39: 280951 | M39: 19 | N39: 86182 | O39: 76 | P39: 287308 | S39: 9 | T39: 126986 | U39: 6 | V39: 9840 | W39: 20 | X39: 128529 | Y39: 49 | Z39: 347592 | AC39: 3 | AD39: 6022 | AE39: 34 | AF39: 83315 | AG39: 44 | AH39: 535021 | AI39: 36 | AJ39: 301339 | AK39: 11 | AL39: 31360 | AM39: 7 | AN39: 15388 | AO39: 13 | AP39: 244090 | AQ39: 21 | AR39: 101769 | AS39: 32 | AT39: 63807 | AW39: 7 | AX39: 5761 | BA39: 29 | BB39: 185080 | BE39: 36 | BF39: 145793 | BM39: 5 | BN39: 50142 | BO39: 22 | BP39: 30213 | BQ39: 601 | BR39: 3412459
C40: 水産業 | E40: 鉱業 | G40: 建設業 | I40: 食料品 | K40: 繊維業 | M40: パルプ・紙 | O40: 化学工業 | S40: 石油・石炭製品 | U40: ゴム製品 | W40: ガラス・土石製品 | Y40: 鉄鋼 | AC40: 金属製品 | AE40: 機械 | AG40: 電気機器 | AI40: 輸送用機器 | AK40: 精密機器 | AM40: その他製造業 | AO40: 電気・ガス業 | AQ40: 陸運業 | AS40: 海運業 | AW40: 倉庫業 | AY40: 通信業 | BA40: 商業 | BE40: 金融・保険業 | BM40: 不動産業 | BO40: サービス業 | BQ40: 合計
A41: S34 | B41: 21854 | C41: 6 | D41: 27849 | E41: 27 | F41: 87316 | G41: 2 | H41: 23064 | I41: 39 | J41: 180146 | K41: 47 | L41: 278529 | M41: 19 | N41: 78605 | O41: 77 | P41: 312388 | S41: 9 | T41: 126519 | U41: 6 | V41: 9686 | W41: 20 | X41: 129678 | Y41: 49 | Z41: 337221 | AC41: 3 | AD41: 6048 | AE41: 33 | AF41: 85527 | AG41: 44 | AH41: 621373 | AI41: 37 | AJ41: 346085 | AK41: 11 | AL41: 28552 | AM41: 7 | AN41: 15449 | AO41: 13 | AP41: 232568 | AQ41: 21 | AR41: 101419 | AS41: 32 | AT41: 61323 | AW41: 7 | AX41: 7055 | AY41: 1 | AZ41: 5760 | BA41: 29 | BB41: 189238 | BE41: 36 | BF41: 143330 | BM41: 5 | BN41: 52148 | BO41: 22 | BP41: 29256 | BQ41: 602 | BR41: 3516138
A42: S34 | B42: 21884 | C42: 6 | D42: 34069 | E42: 27 | F42: 101691 | G42: 2 | H42: 23338 | I42: 39 | J42: 175852 | K42: 46 | L42: 269527 | M42: 19 | N42: 78989 | O42: 77 | P42: 331937 | S42: 9 | T42: 128755 | U42: 6 | V42: 10035 | W42: 20 | X42: 130315 | Y42: 49 | Z42: 350146 | AC42: 3 | AD42: 6255 | AE42: 33 | AF42: 87367 | AG42: 44 | AH42: 626146 | AI42: 38 | AJ42: 375256 | AK42: 11 | AL42: 30917 | AM42: 7 | AN42: 14769 | AO42: 13 | AP42: 239972 | AQ42: 21 | AR42: 105843 | AS42: 32 | AT42: 69754 | AW42: 7 | AX42: 7987 | AY42: 1 | AZ42: 5088 | BA42: 29 | BB42: 195552 | BE42: 36 | BF42: 156140 | BM42: 5 | BN42: 50050 | BO42: 22 | BP42: 32567 | BQ42: 602 | BR42: 3638326
A43: S34 | B43: 21912 | C43: 6 | D43: 39180 | E43: 27 | F43: 109325 | G43: 2 | H43: 22870 | I43: 39 | J43: 179032 | K43: 46 | L43: 270555 | M43: 19 | N43: 81286 | O43: 77 | P43: 348173 | S43: 9 | T43: 123448 | U43: 6 | V43: 9290 | W43: 20 | X43: 129301 | Y43: 49 | Z43: 402841 | AC43: 3 | AD43: 6530 | AE43: 33 | AF43: 86442 | AG43: 44 | AH43: 632932 | AI43: 38 | AJ43: 362637 | AK43: 11 | AL43: 40093 | AM43: 7 | AN43: 17991 | AO43: 13 | AP43: 245203 | AQ43: 21 | AR43: 106309 | AS43: 32 | AT43: 95575 | AW43: 7 | AX43: 7642 | AY43: 1 | AZ43: 4920 | BA43: 29 | BB43: 205579 | BE43: 36 | BF43: 166310 | BM43: 5 | BN43: 49891 | BO43: 22 | BP43: 33653 | BQ43: 602 | BR43: 3777018
A44: S35 | B44: 21945 | C44: 6 | D44: 33530 | E44: 27 | F44: 100453 | G44: 2 | H44: 21930 | I44: 39 | J44: 175605 | K44: 46 | L44: 237039 | M44: 19 | N44: 75229 | O44: 77 | P44: 318978 | S44: 9 | T44: 127092 | U44: 6 | V44: 8258 | W44: 20 | X44: 131621 | Y44: 48 | Z44: 425286 | AC44: 3 | AD44: 6234 | AE44: 33 | AF44: 80556 | AG44: 44 | AH44: 599133 | AI44: 38 | AJ44: 357223 | AK44: 11 | AL44: 38218 | AM44: 7 | AN44: 18816 | AO44: 13 | AP44: 255236 | AQ44: 21 | AR44: 107417 | AS44: 32 | AT44: 89012 | AW44: 7 | AX44: 7586 | AY44: 1 | AZ44: 4824 | BA44: 27 | BB44: 203967 | BE44: 36 | BF44: 173964 | BM44: 5 | BN44: 48623 | BO44: 22 | BP44: 32045 | BQ44: 599 | BR44: 3677884
A45: S35 | B45: 21975 | C45: 6 | D45: 31779 | E45: 27 | F45: 98181 | G45: 2 | H45: 23820 | I45: 39 | J45: 199485 | K45: 45 | L45: 238938 | M45: 19 | N45: 71773 | O45: 77 | P45: 334756 | S45: 9 | T45: 130487 | U45: 6 | V45: 8648 | W45: 20 | X45: 140044 | Y45: 48 | Z45: 411033 | AC45: 3 | AD45: 6272 | AE45: 33 | AF45: 86996 | AG45: 44 | AH45: 667531 | AI45: 38 | AJ45: 379547 | AK45: 11 | AL45: 43373 | AM45: 7 | AN45: 22573 | AO45: 13 | AP45: 255076 | AQ45: 21 | AR45: 116066 | AS45: 32 | AT45: 81059 | AW45: 7 | AX45: 7404 | AY45: 1 | AZ45: 5280 | BA45: 27 | BB45: 214917 | BE45: 36 | BF45: 187479 | BM45: 5 | BN45: 53465 | BO45: 22 | BP45: 30993 | BQ45: 598 | BR45: 3846986
A46: S35 | B46: 22006 | C46: 6 | D46: 29381 | E46: 27 | F46: 88677 | G46: 2 | H46: 24270 | I46: 40 | J46: 226386 | K46: 45 | L46: 236064 | M46: 19 | N46: 68443 | O46: 77 | P46: 348386 | S46: 9 | T46: 131079 | U46: 6 | V46: 8145 | W46: 20 | X46: 150858 | Y46: 48 | Z46: 407601 | AC46: 3 | AD46: 6016 | AE46: 33 | AF46: 103943 | AG46: 44 | AH46: 697234 | AI46: 38 | AJ46: 411398 | AK46: 11 | AL46: 51050 | AM46: 7 | AN46: 31266 | AO46: 13 | AP46: 253896 | AQ46: 21 | AR46: 114769 | AS46: 31 | AT46: 71373 | AW46: 7 | AX46: 7526 | AY46: 1 | AZ46: 5040 | BA46: 27 | BB46: 238490 | BE46: 36 | BF46: 195328 | BM46: 5 | BN46: 56912 | BO46: 22 | BP46: 32190 | BQ46: 598 | BR46: 3995730
A47: S35 | B47: 22036 | C47: 6 | D47: 30255 | E47: 27 | F47: 83239 | G47: 2 | H47: 26786 | I47: 40 | J47: 235222 | K47: 45 | L47: 235928 | M47: 19 | N47: 63264 | O47: 77 | P47: 365295 | S47: 9 | T47: 143841 | U47: 6 | V47: 8407 | W47: 20 | X47: 154641 | Y47: 48 | Z47: 399853 | AC47: 3 | AD47: 5528 | AE47: 33 | AF47: 128513 | AG47: 44 | AH47: 835446 | AI47: 39 | AJ47: 472416 | AK47: 11 | AL47: 60546 | AM47: 7 | AN47: 32348 | AO47: 13 | AP47: 241036 | AQ47: 21 | AR47: 110667 | AS47: 31 | AT47: 67507 | AW47: 7 | AX47: 7904 | AY47: 1 | AZ47: 5496 | BA47: 27 | BB47: 273257 | BE47: 36 | BF47: 208970 | BM47: 5 | BN47: 64533 | BO47: 22 | BP47: 32346 | BQ47: 599 | BR47: 4293255
A48: S35 | B48: 22067 | C48: 6 | D48: 33951 | E48: 27 | F48: 85592 | G48: 2 | H48: 24390 | I48: 40 | J48: 241710 | K48: 45 | L48: 260584 | M48: 19 | N48: 64924 | O48: 77 | P48: 405791 | S48: 9 | T48: 153283 | U48: 6 | V48: 10075 | W48: 20 | X48: 158194 | Y48: 48 | Z48: 412996 | AC48: 3 | AD48: 7357 | AE48: 33 | AF48: 136353 | AG48: 44 | AH48: 877172 | AI48: 39 | AJ48: 501502 | AK48: 11 | AL48: 57428 | AM48: 7 | AN48: 30647 | AO48: 13 | AP48: 251231 | AQ48: 21 | AR48: 112032 | AS48: 31 | AT48: 66236 | AW48: 7 | AX48: 9192 | AY48: 1 | AZ48: 5280 | BA48: 27 | BB48: 286212 | BE48: 36 | BF48: 211866 | BM48: 5 | BN48: 60753 | BO48: 22 | BP48: 34833 | BQ48: 599 | BR48: 4499596
A49: S35 | B49: 22097 | C49: 6 | D49: 31034 | E49: 27 | F49: 79951 | G49: 2 | H49: 24076 | I49: 40 | J49: 234485 | K49: 45 | L49: 230742 | M49: 19 | N49: 59539 | O49: 77 | P49: 374861 | S49: 9 | T49: 146824 | U49: 6 | V49: 8476 | W49: 20 | X49: 151215 | Y49: 48 | Z49: 391357 | AC49: 3 | AD49: 6926 | AE49: 33 | AF49: 120701 | AG49: 44 | AH49: 769679 | AI49: 39 | AJ49: 435144 | AK49: 11 | AL49: 48603 | AM49: 7 | AN49: 27374 | AO49: 13 | AP49: 246430 | AQ49: 21 | AR49: 106149 | AS49: 31 | AT49: 61987 | AW49: 7 | AX49: 8132 | AY49: 1 | AZ49: 4776 | BA49: 27 | BB49: 253657 | BE49: 35 | BF49: 202269 | BM49: 5 | BN49: 55407 | BO49: 22 | BP49: 34683 | BQ49: 598 | BR49: 4114488
A50: S35 | B50: 22127 | C50: 6 | D50: 32545 | E50: 27 | F50: 79759 | G50: 2 | H50: 28450 | I50: 40 | J50: 256209 | K50: 45 | L50: 235884 | M50: 19 | N50: 65120 | O50: 77 | P50: 412543 | S50: 9 | T50: 152698 | U50: 6 | V50: 8805 | W50: 20 | X50: 164160 | Y50: 48 | Z50: 420537 | AC50: 3 | AD50: 6956 | AE50: 33 | AF50: 131525 | AG50: 44 | AH50: 833464 | AI50: 39 | AJ50: 532184 | AK50: 11 | AL50: 50221 | AM50: 7 | AN50: 29894 | AO50: 13 | AP50: 241595 | AQ50: 21 | AR50: 106927 | AS50: 31 | AT50: 62179 | AW50: 7 | AX50: 8164 | AY50: 1 | AZ50: 5160 | BA50: 27 | BB50: 276871 | BE50: 35 | BF50: 211431 | BM50: 5 | BN50: 58955 | BO50: 22 | BP50: 35274 | BQ50: 598 | BR50: 4447521
A51: S35 | B51: 22159 | C51: 6 | D51: 40967 | E51: 27 | F51: 83006 | G51: 2 | H51: 27476 | I51: 39 | J51: 262517 | K51: 45 | L51: 256989 | M51: 19 | N51: 68885 | O51: 77 | P51: 437554 | S51: 9 | T51: 145864 | U51: 6 | V51: 10581 | W51: 20 | X51: 163435 | Y51: 48 | Z51: 424439 | AC51: 3 | AD51: 7518 | AE51: 33 | AF51: 162414 | AG51: 44 | AH51: 862958 | AI51: 39 | AJ51: 554308 | AK51: 11 | AL51: 52062 | AM51: 7 | AN51: 29624 | AO51: 13 | AP51: 256117 | AQ51: 21 | AR51: 117668 | AS51: 31 | AT51: 64759 | AW51: 7 | AX51: 8140 | AY51: 1 | AZ51: 5616 | BA51: 27 | BB51: 299075 | BE51: 35 | BF51: 215783 | BM51: 5 | BN51: 58232 | BO51: 22 | BP51: 34963 | BQ51: 597 | BR51: 4650963
A52: S35 | B52: 22189 | C52: 6 | D52: 52774 | E52: 27 | F52: 86712 | G52: 2 | H52: 33268 | I52: 39 | J52: 280744 | K52: 45 | L52: 261068 | M52: 19 | N52: 78427 | O52: 77 | P52: 485042 | S52: 9 | T52: 143353 | U52: 6 | V52: 11972 | W52: 20 | X52: 171610 | Y52: 48 | Z52: 474015 | AC52: 3 | AD52: 9260 | AE52: 33 | AF52: 187794 | AG52: 44 | AH52: 860823 | AI52: 39 | AJ52: 583945 | AK52: 11 | AL52: 54187 | AM52: 7 | AN52: 31335 | AO52: 13 | AP52: 262533 | AQ52: 21 | AR52: 117399 | AS52: 29 | AT52: 70917 | AW52: 7 | AX52: 7955 | AY52: 1 | AZ52: 5688 | BA52: 27 | BB52: 299949 | BE52: 35 | BF52: 217472 | BM52: 5 | BN52: 58901 | BO52: 22 | BP52: 37103 | BQ52: 595 | BR52: 4884255
C53: 水産業 | E53: 鉱業 | G53: 建設業 | I53: 食料品 | K53: 繊維業 | M53: パルプ・紙 | O53: 化学工業 | S53: 石油・石炭製品 | U53: ゴム製品 | W53: ガラス・土石製品 | Y53: 鉄鋼 | AA53: 非鉄金属 | AC53: 金属製品 | AE53: 機械 | AG53: 電気機器 | AI53: 輸送用機器 | AK53: 精密機器 | AM53: その他製造業 | AO53: 電気・ガス業 | AQ53: 陸運業 | AS53: 海運業 | AW53: 倉庫業 | AY53: 通信業 | BA53: 商業 | BE53: 金融・保険業 | BM53: 不動産業 | BO53: サービス業 | BQ53: 合計
A54: S35 | B54: 22220 | C54: 6 | D54: 61096 | E54: 21 | F54: 50957 | G54: 3 | H54: 48600 | I54: 39 | J54: 297433 | K54: 44 | L54: 262053 | M54: 19 | N54: 78537 | O54: 77 | P54: 503335 | S54: 9 | T54: 130102 | U54: 6 | V54: 13265 | W54: 22 | X54: 184198 | Y54: 39 | Z54: 446016 | AA54: 21 | AB54: 153898 | AC54: 4 | AD54: 13498 | AE54: 34 | AF54: 212567 | AG54: 33 | AH54: 834780 | AI54: 39 | AJ54: 678472 | AK54: 11 | AL54: 53319 | AM54: 8 | AN54: 35477 | AO54: 13 | AP54: 264473 | AQ54: 21 | AR54: 124490 | AS54: 29 | AT54: 78923 | AW54: 7 | AX54: 8515 | AY54: 1 | AZ54: 5760 | BA54: 27 | BB54: 300848 | BE54: 35 | BF54: 219413 | BM54: 5 | BN54: 58750 | BO54: 22 | BP54: 39610 | BQ54: 595 | BR54: 5158396
A55: S35 | B55: 22250 | C55: 6 | D55: 60367 | E55: 21 | F55: 50577 | G55: 4 | H55: 84628 | I55: 39 | J55: 311361 | K55: 43 | L55: 258679 | M55: 19 | N55: 83450 | O55: 77 | P55: 515832 | S55: 9 | T55: 134552 | U55: 6 | V55: 13471 | W55: 22 | X55: 195262 | Y55: 39 | Z55: 458458 | AA55: 21 | AB55: 154014 | AC55: 4 | AD55: 17460 | AE55: 34 | AF55: 238790 | AG55: 33 | AH55: 838604 | AI55: 39 | AJ55: 651533 | AK55: 11 | AL55: 56959 | AM55: 9 | AN55: 40215 | AO55: 13 | AP55: 264652 | AQ55: 21 | AR55: 123488 | AS55: 29 | AT55: 79256 | AW55: 7 | AX55: 8929 | AY55: 2 | AZ55: 8730 | BA55: 27 | BB55: 313109 | BE55: 35 | BF55: 223947 | BM55: 5 | BN55: 65081 | BO55: 22 | BP55: 43587 | BQ55: 597 | BR55: 5295004
A56: S35 | B56: 22278 | C56: 6 | D56: 73320 | E56: 21 | F56: 55199 | G56: 4 | H56: 86952 | I56: 39 | J56: 333588 | K56: 43 | L56: 273007 | M56: 19 | N56: 95760 | O56: 78 | P56: 531337 | S56: 9 | T56: 130937 | U56: 6 | V56: 16331 | W56: 22 | X56: 196945 | Y56: 39 | Z56: 461887 | AA56: 21 | AB56: 162339 | AC56: 4 | AD56: 16796 | AE56: 34 | AF56: 227394 | AG56: 34 | AH56: 858226 | AI56: 38 | AJ56: 616287 | AK56: 11 | AL56: 57275 | AM56: 9 | AN56: 42424 | AO56: 13 | AP56: 265359 | AQ56: 21 | AR56: 140514 | AS56: 29 | AT56: 72624 | AW56: 7 | AX56: 9925 | AY56: 2 | AZ56: 8640 | BA56: 27 | BB56: 320923 | BE56: 35 | BF56: 229673 | BM56: 5 | BN56: 73723 | BO56: 22 | BP56: 53963 | BQ56: 598 | BR56: 5411360
A57: S36 | B57: 22312 | C57: 6 | D57: 65591 | E57: 21 | F57: 57999 | G57: 4 | H57: 90330 | I57: 39 | J57: 370983 | K57: 43 | L57: 285655 | M57: 19 | N57: 95555 | O57: 78 | P57: 553436 | S57: 9 | T57: 133172 | U57: 6 | V57: 16213 | W57: 22 | X57: 205151 | Y57: 39 | Z57: 452639 | AA57: 21 | AB57: 161806 | AC57: 4 | AD57: 18628 | AE57: 34 | AF57: 230216 | AG57: 34 | AH57: 856411 | AI57: 38 | AJ57: 610215 | AK57: 11 | AL57: 66609 | AM57: 9 | AN57: 46636 | AO57: 13 | AP57: 296298 | AQ57: 21 | AR57: 171997 | AS57: 30 | AT57: 79743 | AW57: 7 | AX57: 10416 | AY57: 2 | AZ57: 9114 | BA57: 27 | BB57: 332404 | BE57: 35 | BF57: 235840 | BM57: 5 | BN57: 83242 | BO57: 22 | BP57: 56627 | BQ57: 599 | BR57: 5592938
A58: S36 | B58: 22340 | C58: 6 | D58: 84692 | E58: 21 | F58: 71413 | G58: 4 | H58: 113660 | I58: 39 | J58: 399647 | K58: 43 | L58: 321701 | M58: 19 | N58: 104065 | O58: 78 | P58: 597734 | S58: 9 | T58: 132426 | U58: 6 | V58: 20652 | W58: 22 | X58: 219429 | Y58: 39 | Z58: 534254 | AA58: 21 | AB58: 174395 | AC58: 4 | AD58: 20056 | AE58: 34 | AF58: 256953 | AG58: 34 | AH58: 895666 | AI58: 38 | AJ58: 587113 | AK58: 11 | AL58: 76175 | AM58: 9 | AN58: 55298 | AO58: 13 | AP58: 298747 | AQ58: 21 | AR58: 189693 | AS58: 30 | AT58: 83427 | AW58: 7 | AX58: 11497 | AY58: 2 | AZ58: 8829 | BA58: 27 | BB58: 335520 | BE58: 35 | BF58: 236738 | BM58: 5 | BN58: 90949 | BO58: 22 | BP58: 63025 | BQ58: 599 | BR58: 5983763
A59: S36 | B59: 22371 | C59: 6 | D59: 88604 | E59: 21 | F59: 74004 | G59: 4 | H59: 109908 | I59: 39 | J59: 409153 | K59: 43 | L59: 324808 | M59: 19 | N59: 107861 | O59: 78 | P59: 587981 | S59: 9 | T59: 129856 | U59: 6 | V59: 19858 | W59: 22 | X59: 219325 | Y59: 39 | Z59: 527502 | AA59: 21 | AB59: 175745 | AC59: 4 | AD59: 22460 | AE59: 34 | AF59: 268651 | AG59: 34 | AH59: 870347 | AI59: 38 | AJ59: 618014 | AK59: 11 | AL59: 78595 | AM59: 9 | AN59: 59433 | AO59: 13 | AP59: 295127 | AQ59: 21 | AR59: 208379 | AS59: 30 | AT59: 85362 | AW59: 7 | AX59: 13146 | AY59: 2 | AZ59: 8700 | BA59: 27 | BB59: 341885 | BE59: 35 | BF59: 239002 | BM59: 5 | BN59: 90088 | BO59: 22 | BP59: 67310 | BQ59: 599 | BR59: 6041119
A60: S36 | B60: 22399 | C60: 6 | D60: 93407 | E60: 21 | F60: 79428 | G60: 4 | H60: 106060 | I60: 39 | J60: 417452 | K60: 43 | L60: 326290 | M60: 19 | N60: 106382 | O60: 78 | P60: 611012 | S60: 9 | T60: 127076 | U60: 6 | V60: 25630 | W60: 22 | X60: 218775 | Y60: 39 | Z60: 515522 | AA60: 21 | AB60: 177138 | AC60: 4 | AD60: 18728 | AE60: 35 | AF60: 273925 | AG60: 34 | AH60: 892098 | AI60: 39 | AJ60: 622118 | AK60: 11 | AL60: 80978 | AM60: 9 | AN60: 63874 | AO60: 13 | AP60: 291690 | AQ60: 21 | AR60: 200991 | AS60: 30 | AT60: 83185 | AW60: 7 | AX60: 13124 | AY60: 2 | AZ60: 8706 | BA60: 27 | BB60: 318565 | BE60: 35 | BF60: 234323 | BM60: 5 | BN60: 81385 | BO60: 22 | BP60: 67840 | BQ60: 601 | BR60: 6055715
A61: S36 | B61: 22432 | C61: 6 | D61: 101754 | E61: 21 | F61: 93027 | G61: 4 | H61: 103290 | I61: 39 | J61: 449656 | K61: 43 | L61: 353723 | M61: 19 | N61: 130901 | O61: 78 | P61: 654319 | S61: 9 | T61: 123796 | U61: 6 | V61: 31180 | W61: 22 | X61: 220256 | Y61: 39 | Z61: 519468 | AA61: 21 | AB61: 186920 | AC61: 4 | AD61: 24032 | AE61: 35 | AF61: 304263 | AG61: 34 | AH61: 869604 | AI61: 39 | AJ61: 589089 | AK61: 11 | AL61: 84993 | AM61: 9 | AN61: 62254 | AO61: 13 | AP61: 297139 | AQ61: 21 | AR61: 225229 | AS61: 30 | AT61: 88079 | AW61: 7 | AX61: 16137 | AY61: 2 | AZ61: 9210 | BA61: 27 | BB61: 347926 | BE61: 35 | BF61: 231358 | BM61: 5 | BN61: 89712 | BO61: 22 | BP61: 74348 | BQ61: 601 | BR61: 6281672
A62: S36 | B62: 22462 | C62: 6 | D62: 104864 | E62: 21 | F62: 82857 | G62: 4 | H62: 100420 | I62: 40 | J62: 464961 | K62: 43 | L62: 327523 | M62: 19 | N62: 118734 | O62: 78 | P62: 610658 | S62: 9 | T62: 118358 | U62: 6 | V62: 26956 | W62: 22 | X62: 213679 | Y62: 40 | Z62: 510251 | AA62: 21 | AB62: 168880 | AC62: 4 | AD62: 32620 | AE62: 35 | AF62: 288418 | AG62: 34 | AH62: 866825 | AI62: 39 | AJ62: 543922 | AK62: 11 | AL62: 84105 | AM62: 9 | AN62: 66590 | AO62: 13 | AP62: 296394 | AQ62: 21 | AR62: 227804 | AS62: 30 | AT62: 91925 | AW62: 7 | AX62: 15919 | AY62: 2 | AZ62: 9282 | BA62: 27 | BB62: 343397 | BE62: 35 | BF62: 233384 | BM62: 5 | BN62: 85694 | BO62: 22 | BP62: 74993 | BQ62: 603 | BR62: 6109424
A63: S36 | B63: 22493 | C63: 6 | D63: 108101 | E63: 21 | F63: 90956 | G63: 4 | H63: 110350 | I63: 40 | J63: 485448 | K63: 43 | L63: 359129 | M63: 20 | N63: 132332 | O63: 80 | P63: 643807 | S63: 9 | T63: 119473 | U63: 6 | V63: 29085 | W63: 22 | X63: 227356 | Y63: 40 | Z63: 553969 | AA63: 21 | AB63: 179105 | AC63: 4 | AD63: 37812 | AE63: 37 | AF63: 340817 | AG63: 34 | AH63: 952132 | AI63: 39 | AJ63: 622776 | AK63: 11 | AL63: 95513 | AM63: 9 | AN63: 70028 | AO63: 13 | AP63: 300963 | AQ63: 21 | AR63: 224323 | AS63: 30 | AT63: 89774 | AW63: 7 | AX63: 17636 | AY63: 2 | AZ63: 9294 | BA63: 27 | BB63: 386713 | BE63: 35 | BF63: 233312 | BM63: 5 | BN63: 86547 | BO63: 21 | BP63: 79252 | BQ63: 607 | BR63: 6586016
A64: S36 | B64: 22524 | C64: 6 | D64: 98760 | E64: 21 | F64: 94998 | G64: 4 | H64: 100490 | I64: 40 | J64: 495057 | K64: 43 | L64: 342722 | M64: 20 | N64: 150820 | O64: 80 | P64: 633264 | S64: 9 | T64: 111519 | U64: 6 | V64: 27551 | W64: 22 | X64: 212202 | Y64: 40 | Z64: 564787 | AA64: 21 | AB64: 179060 | AC64: 4 | AD64: 35272 | AE64: 37 | AF64: 331721 | AG64: 34 | AH64: 929936 | AI64: 39 | AJ64: 606781 | AK64: 11 | AL64: 97811 | AM64: 9 | AN64: 67881 | AO64: 13 | AP64: 326436 | AQ64: 21 | AR64: 225069 | AS64: 30 | AT64: 96622 | AW64: 7 | AX64: 18036 | AY64: 2 | AZ64: 10130 | BA64: 28 | BB64: 361047 | BE64: 35 | BF64: 237243 | BM64: 5 | BN64: 94137 | BO64: 21 | BP64: 80311 | BQ64: 608 | BR64: 6529674
A65: S36 | B65: 22554 | C65: 6 | D65: 100860 | E65: 21 | F65: 82652 | G65: 5 | H65: 87518 | I65: 40 | J65: 473436 | K65: 44 | L65: 315817 | M65: 21 | N65: 142086 | O65: 81 | P65: 609669 | S65: 9 | T65: 101279 | U65: 6 | V65: 24945 | W65: 22 | X65: 218531 | Y65: 40 | Z65: 537899 | AA65: 21 | AB65: 161365 | AC65: 5 | AD65: 37552 | AE65: 38 | AF65: 304178 | AG65: 36 | AH65: 866311 | AI65: 40 | AJ65: 575326 | AK65: 11 | AL65: 95817 | AM65: 9 | AN65: 67429 | AO65: 13 | AP65: 329322 | AQ65: 21 | AR65: 222414 | AS65: 30 | AT65: 100278 | AW65: 7 | AX65: 17452 | AY65: 2 | AZ65: 9622 | BA65: 30 | BB65: 339714 | BE65: 35 | BF65: 235904 | BM65: 5 | BN65: 88216 | BO65: 21 | BP65: 76741 | BQ65: 619 | BR65: 6222345
... A131: S42 | B131: 24562 | C131: 6 | D131: 55026 | E131: 16 | F131: 50957 | G131: 30 | H131: 327758 | I131: 40 | J131: 491310 | K131: 38 | L131: 426501 | M131: 22 | N131: 124911 | O131: 82 | P131: 754729 | S131: 8 | T131: 128599 | U131: 6 | V131: 80003 | W131: 24 | X131: 275032 | Y131: 38 | Z131: 809393 | AA131: 20 | AB131: 215006 | AC131: 10 | AD131: 51864 | AE131: 46 | AF131: 346627 | AG131: 45 | AH131: 1006143 | AI131: 40 | AJ131: 1085864 | AK131: 14 | AL131: 77400 | AM131: 13 | AN131: 100601 | AO131: 13 | AP131: 931342 | AQ131: 20 | AR131: 354688 | AS131: 16 | AT131: 135868 | AW131: 7 | AX131: 19997 | AY131: 2 | AZ131: 16776 | BA131: 39 | BB131: 482342 | BE131: 43 | BF131: 758918 | BM131: 6 | BN131: 134404 | BO131: 15 | BP131: 71028 | BQ131: 659 | BR131: 9313100
C132: 水産業 | E132: 鉱業 | G132: 建設業 | I132: 食料品 | K132: 繊維業 | M132: パルプ・紙 | O132: 化学工業 | S132: 石油・石炭製品 | U132: ゴム製品 | W132: ガラス・土石製品 | Y132: 鉄鋼 | AA132: 非鉄金属 | AC132: 金属製品 | AE132: 機械 | AG132: 電気機器 | AI132: 輸送用機器 | AK132: 精密機器 | AM132: その他製造業 | AO132: 電気・ガス業 | AQ132: 陸運業 | AS132: 海運業 | AW132: 倉庫・運輸関連業 | AY132: 通信業 | BA132: 商業 | BE132: 金融・保険業 | BM132: 不動産業 | BO132: サービス業 | BQ132: 合計
A133: S42 | B133: 24590 | C133: 6 | D133: 53646 | E133: 16 | F133: 50508 | G133: 30 | H133: 327237 | I133: 40 | J133: 480665 | K133: 38 | L133: 434708 | M133: 22 | N133: 121306 | O133: 82 | P133: 741506 | S133: 8 | T133: 139934 | U133: 6 | V133: 77869 | W133: 24 | X133: 278329 | Y133: 38 | Z133: 786954 | AA133: 20 | AB133: 208101 | AC133: 10 | AD133: 49945 | AE133: 46 | AF133: 338288 | AG133: 45 | AH133: 1021946 | AI133: 40 | AJ133: 1109797 | AK133: 14 | AL133: 75108 | AM133: 13 | AN133: 97182 | AO133: 13 | AP133: 931549 | AQ133: 20 | AR133: 358213 | AS133: 16 | AT133: 134853 | AW133: 7 | AX133: 19330 | AY133: 2 | AZ133: 16648 | BA133: 40 | BB133: 496881 | BE133: 43 | BF133: 763024 | BM133: 6 | BN133: 129526 | BO133: 15 | BP133: 70871 | BQ133: 660 | BR133: 9313937
A134: S42 | B134: 24623 | C134: 6 | D134: 53994 | E134: 16 | F134: 48886 | G134: 31 | H134: 347895 | I134: 40 | J134: 496696 | K134: 37 | L134: 428700 | M134: 22 | N134: 123246 | O134: 82 | P134: 757119 | S134: 8 | T134: 142399 | U134: 6 | V134: 84656 | W134: 24 | X134: 287099 | Y134: 38 | Z134: 843921 | AA134: 20 | AB134: 214463 | AC134: 10 | AD134: 54150 | AE134: 46 | AF134: 378711 | AG134: 45 | AH134: 1087783 | AI134: 40 | AJ134: 1216172 | AK134: 14 | AL134: 85216 | AM134: 13 | AN134: 100985 | AO134: 13 | AP134: 975366 | AQ134: 20 | AR134: 367946 | AS134: 16 | AT134: 141776 | AW134: 7 | AX134: 19834 | AY134: 2 | AZ134: 16624 | BA134: 40 | BB134: 535700 | BE134: 43 | BF134: 766226 | BM134: 6 | BN134: 135982 | BO134: 15 | BP134: 71466 | BQ134: 660 | BR134: 9783024
A135: S42 | B135: 24653 | C135: 6 | D135: 53900 | E135: 16 | F135: 49302 | G135: 31 | H135: 329771 | I135: 40 | J135: 483911 | K135: 37 | L135: 424310 | M135: 22 | N135: 122427 | O135: 82 | P135: 761791 | S135: 8 | T135: 138494 | U135: 6 | V135: 85185 | W135: 24 | X135: 286279 | Y135: 38 | Z135: 830359 | AA135: 19 | AB135: 193133 | AC135: 10 | AD135: 51784 | AE135: 46 | AF135: 377645 | AG135: 45 | AH135: 1109070 | AI135: 40 | AJ135: 1202571 | AK135: 14 | AL135: 84886 | AM135: 13 | AN135: 99400 | AO135: 13 | AP135: 984388 | AQ135: 20 | AR135: 364997 | AS135: 16 | AT135: 128435 | AW135: 7 | AX135: 19839 | AY135: 2 | AZ135: 16448 | BA135: 40 | BB135: 519294 | BE135: 43 | BF135: 778639 | BM135: 6 | BN135: 130342 | BO135: 15 | BP135: 72233 | BQ135: 659 | BR135: 9698841
A136: S42 | B136: 24684 | C136: 6 | D136: 53828 | E136: 16 | F136: 46213 | G136: 31 | H136: 347870 | I136: 41 | J136: 463233 | K136: 37 | L136: 435464 | M136: 22 | N136: 118650 | O136: 82 | P136: 762205 | S136: 8 | T136: 137301 | U136: 6 | V136: 84053 | W136: 24 | X136: 285835 | Y136: 38 | Z136: 816162 | AA136: 19 | AB136: 192100 | AC136: 10 | AD136: 51968 | AE136: 46 | AF136: 370123 | AG136: 45 | AH136: 1095129 | AI136: 40 | AJ136: 1233223 | AK136: 14 | AL136: 84760 | AM136: 13 | AN136: 95892 | AO136: 13 | AP136: 978049 | AQ136: 20 | AR136: 361102 | AS136: 16 | AT136: 124293 | AW136: 7 | AX136: 19439 | AY136: 2 | AZ136: 16144 | BA136: 41 | BB136: 516629 | BE136: 43 | BF136: 773556 | BM136: 6 | BN136: 128237 | BO136: 15 | BP136: 70198 | BQ136: 661 | BR136: 9661667
A137: S42 | B137: 24715 | C137: 6 | D137: 51782 | E137: 16 | F137: 42017 | G137: 32 | H137: 289494 | I137: 42 | J137: 421000 | K137: 37 | L137: 401183 | M137: 22 | N137: 115234 | O137: 83 | P137: 702913 | S137: 8 | T137: 132730 | U137: 6 | V137: 81960 | W137: 24 | X137: 259991 | Y137: 38 | Z137: 763107 | AA137: 19 | AB137: 180971 | AC137: 10 | AD137: 45631 | AE137: 47 | AF137: 321828 | AG137: 46 | AH137: 985999 | AI137: 41 | AJ137: 1092225 | AK137: 14 | AL137: 75512 | AM137: 13 | AN137: 85445 | AO137: 13 | AP137: 935198 | AQ137: 20 | AR137: 359063 | AS137: 16 | AT137: 122588 | AW137: 7 | AX137: 18890 | AY137: 2 | AZ137: 14560 | BA137: 42 | BB137: 482278 | BE137: 43 | BF137: 768995 | BM137: 6 | BN137: 116915 | BO137: 15 | BP137: 64923 | BQ137: 668 | BR137: 8932445
A138: S42 | B138: 24745 | C138: 6 | D138: 51516 | E138: 16 | F138: 41283 | G138: 32 | H138: 274584 | I138: 42 | J138: 420033 | K138: 37 | L138: 403213 | M138: 22 | N138: 113531 | O138: 84 | P138: 690355 | S138: 8 | T138: 137611 | U138: 6 | V138: 76805 | W138: 24 | X138: 261225 | Y138: 38 | Z138: 736895 | AA138: 20 | AB138: 198617 | AC138: 10 | AD138: 44469 | AE138: 47 | AF138: 302134 | AG138: 46 | AH138: 955657 | AI138: 40 | AJ138: 1050877 | AK138: 14 | AL138: 71791 | AM138: 13 | AN138: 84323 | AO138: 13 | AP138: 911715 | AQ138: 20 | AR138: 350577 | AS138: 16 | AT138: 120349 | AW138: 7 | AX138: 18588 | AY138: 2 | AZ138: 14089 | BA138: 42 | BB138: 479574 | BE138: 43 | BF138: 738194 | BM138: 6 | BN138: 118349 | BO138: 15 | BP138: 64394 | BQ138: 669 | BR138: 8730760
A139: S42 | B139: 24776 | C139: 6 | D139: 52216 | E139: 16 | F139: 39474 | G139: 32 | H139: 287389 | I139: 42 | J139: 442450 | K139: 37 | L139: 403453 | M139: 22 | N139: 112060 | O139: 84 | P139: 704322 | S139: 8 | T139: 135214 | U139: 6 | V139: 84481 | W139: 25 | X139: 272847 | Y139: 38 | Z139: 738936 | AA139: 20 | AB139: 198104 | AC139: 10 | AD139: 45001 | AE139: 47 | AF139: 342058 | AG139: 46 | AH139: 1052599 | AI139: 40 | AJ139: 1139290 | AK139: 14 | AL139: 79154 | AM139: 13 | AN139: 90290 | AO139: 13 | AP139: 918098 | AQ139: 20 | AR139: 349768 | AS139: 16 | AT139: 118907 | AW139: 7 | AX139: 18236 | AY139: 2 | AZ139: 14384 | BA139: 42 | BB139: 505512 | BE139: 43 | BF139: 753237 | BM139: 6 | BN139: 119826 | BO139: 15 | BP139: 66359 | BQ139: 670 | BR139: 9083678
A140: S42 | B140: 24806 | C140: 6 | D140: 49916 | E140: 16 | F140: 36199 | G140: 32 | H140: 249814 | I140: 42 | J140: 407290 | K140: 37 | L140: 379899 | M140: 22 | N140: 106057 | O140: 84 | P140: 673602 | S140: 8 | T140: 124279 | U140: 6 | V140: 76011 | W140: 25 | X140: 251614 | Y140: 38 | Z140: 726240 | AA140: 20 | AB140: 191996 | AC140: 10 | AD140: 42676 | AE140: 47 | AF140: 296790 | AG140: 46 | AH140: 958459 | AI140: 40 | AJ140: 1011083 | AK140: 14 | AL140: 70878 | AM140: 13 | AN140: 81617 | AO140: 13 | AP140: 901365 | AQ140: 20 | AR140: 350813 | AS140: 16 | AT140: 111034 | AW140: 7 | AX140: 18085 | AY140: 2 | AZ140: 12996 | BA140: 42 | BB140: 477561 | BE140: 43 | BF140: 749683 | BM140: 6 | BN140: 117564 | BO140: 15 | BP140: 64909 | BQ140: 670 | BR140: 8538445
A141: S42 | B141: 24834 | C141: 6 | D141: 50030 | E141: 16 | F141: 38538 | G141: 32 | H141: 269733 | I141: 43 | J141: 415771 | K141: 37 | L141: 381313 | M141: 22 | N141: 108414 | O141: 84 | P141: 679761 | S141: 8 | T141: 124383 | U141: 6 | V141: 70050 | W141: 25 | X141: 250706 | Y141: 38 | Z141: 725277 | AA141: 20 | AB141: 194665 | AC141: 10 | AD141: 42422 | AE141: 47 | AF141: 293991 | AG141: 47 | AH141: 949097 | AI141: 40 | AJ141: 960958 | AK141: 14 | AL141: 69649 | AM141: 13 | AN141: 79360 | AO141: 13 | AP141: 900998 | AQ141: 20 | AR141: 351428 | AS141: 16 | AT141: 116492 | AW141: 7 | AX141: 18390 | AY141: 2 | AZ141: 13040 | BA141: 42 | BB141: 472450 | BE141: 43 | BF141: 805568 | BM141: 6 | BN141: 138759 | BO141: 15 | BP141: 68853 | BQ141: 672 | BR141: 8590107
A142: S43 | B142: 24868 | C142: 6 | D142: 48110 | E142: 16 | F142: 37604 | G142: 32 | H142: 277817 | I142: 43 | J142: 429517 | K142: 37 | L142: 390864 | M142: 22 | N142: 109621 | O142: 84 | P142: 701939 | S142: 8 | T142: 122114 | U142: 6 | V142: 72353 | W142: 25 | X142: 267716 | Y142: 38 | Z142: 742197 | AA142: 20 | AB142: 194111 | AC142: 10 | AD142: 44811 | AE142: 47 | AF142: 314125 | AG142: 47 | AH142: 1001090 | AI142: 40 | AJ142: 982881 | AK142: 14 | AL142: 74627 | AM142: 13 | AN142: 84634 | AO142: 13 | AP142: 951501 | AQ142: 20 | AR142: 362681 | AS142: 16 | AT142: 111532 | AW142: 7 | AX142: 18260 | AY142: 2 | AZ142: 14728 | BA142: 43 | BB142: 476424 | BE142: 43 | BF142: 802660 | BM142: 6 | BN142: 136455 | BO142: 15 | BP142: 68007 | BQ142: 673 | BR142: 8838390
A143: S43 | B143: 24897 | C143: 6 | D143: 47568 | E143: 16 | F143: 37564 | G143: 32 | H143: 273611 | I143: 43 | J143: 452561 | K143: 37 | L143: 404291 | M143: 22 | N143: 108878 | O143: 84 | P143: 728125 | S143: 8 | T143: 127634 | U143: 6 | V143: 78661 | W143: 25 | X143: 270749 | Y143: 37 | Z143: 740295 | AA143: 20 | AB143: 205794 | AC143: 10 | AD143: 45058 | AE143: 48 | AF143: 331283 | AG143: 49 | AH143: 1058542 | AI143: 40 | AJ143: 1015598 | AK143: 14 | AL143: 78085 | AM143: 13 | AN143: 90356 | AO143: 13 | AP143: 952181 | AQ143: 20 | AR143: 363209 | AS143: 16 | AT143: 109004 | AW143: 7 | AX143: 18141 | AY143: 2 | AZ143: 14240 | BA143: 44 | BB143: 483803 | BE143: 43 | BF143: 848617 | BM143: 6 | BN143: 135276 | BO143: 15 | BP143: 70338 | BQ143: 676 | BR143: 9089473
A144: S43 | B144: 24927 | C144: 6 | D144: 46096 | E144: 16 | F144: 38933 | G144: 32 | H144: 281815 | I144: 43 | J144: 463585 | K144: 37 | L144: 383805 | M144: 21 | N144: 106595 | O144: 84 | P144: 743274 | S144: 8 | T144: 124039 | U144: 6 | V144: 77377 | W144: 25 | X144: 264719 | Y144: 37 | Z144: 712961 | AA144: 20 | AB144: 210887 | AC144: 10 | AD144: 43344 | AE144: 48 | AF144: 314720 | AG144: 49 | AH144: 1046242 | AI144: 38 | AJ144: 997643 | AK144: 14 | AL144: 74952 | AM144: 13 | AN144: 92224 | AO144: 13 | AP144: 999190 | AQ144: 20 | AR144: 395626 | AS144: 16 | AT144: 123255 | AW144: 7 | AX144: 20483 | AY144: 2 | AZ144: 14760 | BA144: 44 | BB144: 485472 | BE144: 43 | BF144: 867738 | BM144: 6 | BN144: 177235 | BO144: 15 | BP144: 76527 | BQ144: 673 | BR144: 9183510
... A166: S45 | B166: 25599 | C166: 6 | D166: 60496 | E166: 11 | F166: 36537 | G166: 35 | H166: 891234 | I166: 45 | J166: 517558 | K166: 36 | L166: 498520 | M166: 20 | N166: 165817 | O166: 88 | P166: 1491789 | S166: 8 | T166: 141262 | U166: 6 | V166: 92665 | W166: 26 | X166: 420258 | Y166: 36 | Z166: 1076951 | AA166: 21 | AB166: 345965 | AC166: 11 | AD166: 66586 | AE166: 53 | AF166: 791374 | AG166: 58 | AH166: 3071528 | AI166: 36 | AJ166: 1190694 | AK166: 14 | AL166: 263505 | AM166: 12 | AN166: 247260 | AO166: 13 | AP166: 1081159 | AQ166: 20 | AR166: 499215 | AS166: 15 | AT166: 173894 | AW166: 7 | AX166: 25031 | AY166: 2 | AZ166: 17680 | BA166: 48 | BB166: 812535 | BE166: 44 | BF166: 2165192 | BM166: 6 | BN166: 272001 | BO166: 15 | BP166: 93223 | BQ166: 692 | BR166: 16509929
C167: 水産・農林業 | E167: 鉱業 | G167: 建設業 | I167: 食料品 | K167: 繊維業 | M167: パルプ・紙 | O167: 化学工業 | S167: 石油・石炭製品 | U167: ゴム製品 | W167: ガラス・土石製品 | Y167: 鉄鋼 | AA167: 非鉄金属 | AC167: 金属製品 | AE167: 機械 | AG167: 電気機器 | AI167: 輸送用機器 | AK167: 精密機器 | AM167: その他製造業 | AO167: 電気・ガス業 | AQ167: 陸運業 | AS167: 海運業 | AU167: 空運業 | AW167: 倉庫・運輸関連業 | AY167: 通信業 | BA167: 商業 | BE167: 金融・保険業 | BM167: 不動産業 | BO167: サービス業 | BQ167: 合計
A168: S45 | B168: 25627 | C168: 6 | D168: 67502 | E168: 11 | F168: 77231 | G168: 36 | H168: 943948 | I168: 45 | J168: 543906 | K168: 36 | L168: 469782 | M168: 20 | N168: 178756 | O168: 89 | P168: 1613403 | S168: 8 | T168: 136310 | U168: 6 | V168: 92045 | W168: 26 | X168: 448169 | Y168: 36 | Z168: 1050410 | AA168: 21 | AB168: 362997 | AC168: 11 | AD168: 64841 | AE168: 55 | AF168: 834232 | AG168: 60 | AH168: 3016756 | AI168: 36 | AJ168: 1125730 | AK168: 14 | AL168: 280876 | AM168: 12 | AN168: 271732 | AO168: 13 | AP168: 1097354 | AQ168: 20 | AR168: 531696 | AS168: 15 | AT168: 164343 | AU168: 1 | AV168: 64629 | AW168: 7 | AX168: 23797 | AY168: 3 | AZ168: 39156 | BA168: 50 | BB168: 840988 | BE168: 48 | BF168: 2377590 | BM168: 6 | BN168: 289899 | BO168: 15 | BP168: 88441 | BQ168: 706 | BR168: 17096519
A169: S45 | B169: 25658 | C169: 6 | D169: 82676 | E169: 11 | F169: 83863 | G169: 38 | H169: 1016197 | I169: 45 | J169: 592215 | K169: 36 | L169: 543380 | M169: 20 | N169: 188176 | O169: 89 | P169: 1641626 | S169: 8 | T169: 155412 | U169: 6 | V169: 103268 | W169: 27 | X169: 473789 | Y169: 35 | Z169: 1091176 | AA169: 21 | AB169: 384973 | AC169: 11 | AD169: 70796 | AE169: 55 | AF169: 887312 | AG169: 61 | AH169: 3129257 | AI169: 36 | AJ169: 1254268 | AK169: 14 | AL169: 273091 | AM169: 12 | AN169: 267722 | AO169: 13 | AP169: 1125039 | AQ169: 20 | AR169: 541805 | AS169: 15 | AT169: 164756 | AU169: 1 | AV169: 65790 | AW169: 7 | AX169: 25708 | AY169: 3 | AZ169: 40756 | BA169: 50 | BB169: 873570 | BE169: 48 | BF169: 2497946 | BM169: 5 | BN169: 283326 | BO169: 15 | BP169: 93071 | BQ169: 708 | BR169: 17950964
A170: S45 | B170: 25688 | C170: 6 | D170: 57678 | E170: 11 | F170: 76023 | G170: 38 | H170: 847606 | I170: 45 | J170: 510866 | K170: 36 | L170: 442993 | M170: 20 | N170: 159129 | O170: 89 | P170: 1357425 | S170: 8 | T170: 130646 | U170: 6 | V170: 85965 | W170: 27 | X170: 391931 | Y170: 35 | Z170: 1004160 | AA170: 21 | AB170: 321408 | AC170: 11 | AD170: 60026 | AE170: 55 | AF170: 712984 | AG170: 62 | AH170: 2559852 | AI170: 36 | AJ170: 1074870 | AK170: 14 | AL170: 213518 | AM170: 12 | AN170: 221334 | AO170: 13 | AP170: 1112559 | AQ170: 20 | AR170: 482652 | AS170: 15 | AT170: 147270 | AU170: 1 | AV170: 55341 | AW170: 7 | AX170: 26184 | AY170: 3 | AZ170: 35082 | BA170: 50 | BB170: 776743 | BE170: 48 | BF170: 2325465 | BM170: 5 | BN170: 231596 | BO170: 15 | BP170: 85265 | BQ170: 709 | BR170: 15506571
A171: S45 | B171: 25718 | C171: 6 | D171: 61550 | E171: 11 | F171: 74824 | G171: 39 | H171: 829174 | I171: 45 | J171: 522088 | K171: 36 | L171: 445037 | M171: 20 | N171: 164616 | O171: 90 | P171: 1440246 | S171: 8 | T171: 132270 | U171: 6 | V171: 87222 | W171: 28 | X171: 402917 | Y171: 35 | Z171: 966588 | AA171: 21 | AB171: 302183 | AC171: 11 | AD171: 54653 | AE171: 55 | AF171: 696276 | AG171: 62 | AH171: 2430795 | AI171: 37 | AJ171: 1133264 | AK171: 14 | AL171: 209047 | AM171: 12 | AN171: 225419 | AO171: 13 | AP171: 1099451 | AQ171: 20 | AR171: 472793 | AS171: 15 | AT171: 146214 | AU171: 1 | AV171: 53986 | AW171: 7 | AX171: 24859 | AY171: 3 | AZ171: 35126 | BA171: 50 | BB171: 774730 | BE171: 48 | BF171: 2226189 | BM171: 5 | BN171: 232074 | BO171: 15 | BP171: 82144 | BQ171: 713 | BR171: 15325735
A172: S45 | B172: 25749 | C172: 6 | D172: 70886 | E172: 11 | F172: 83315 | G172: 39 | H172: 873838 | I172: 45 | J172: 528902 | K172: 36 | L172: 471729 | M172: 20 | N172: 175909 | O172: 90 | P172: 1475437 | S172: 8 | T172: 141504 | U172: 6 | V172: 94154 | W172: 28 | X172: 404446 | Y172: 35 | Z172: 991894 | AA172: 21 | AB172: 353806 | AC172: 11 | AD172: 58377 | AE172: 55 | AF172: 726935 | AG172: 63 | AH172: 2365545 | AI172: 37 | AJ172: 1109912 | AK172: 14 | AL172: 204054 | AM172: 13 | AN172: 239585 | AO172: 13 | AP172: 1135081 | AQ172: 20 | AR172: 462656 | AS172: 15 | AT172: 180649 | AU172: 1 | AV172: 55689 | AW172: 7 | AX172: 24995 | AY172: 3 | AZ172: 35978 | BA172: 50 | BB172: 827296 | BE172: 48 | BF172: 2227701 | BM172: 5 | BN172: 237435 | BO172: 15 | BP172: 90528 | BQ172: 715 | BR172: 15648236
A173: S45 | B173: 25780 | C173: 6 | D173: 59880 | E173: 11 | F173: 79073 | G173: 39 | H173: 909382 | I173: 45 | J173: 519178 | K173: 36 | L173: 453259 | M173: 20 | N173: 163239 | O173: 90 | P173: 1490244 | S173: 8 | T173: 138722 | U173: 6 | V173: 89042 | W173: 28 | X173: 418639 | Y173: 35 | Z173: 1008623 | AA173: 21 | AB173: 331374 | AC173: 12 | AD173: 65174 | AE173: 55 | AF173: 733908 | AG173: 64 | AH173: 2662617 | AI173: 37 | AJ173: 1094050 | AK173: 14 | AL173: 227654 | AM173: 13 | AN173: 252421 | AO173: 13 | AP173: 1162692 | AQ173: 20 | AR173: 471979 | AS173: 15 | AT173: 172338 | AU173: 1 | AV173: 57663 | AW173: 7 | AX173: 27344 | AY173: 3 | AZ173: 37990 | BA173: 51 | BB173: 824462 | BE173: 48 | BF173: 2236736 | BM173: 5 | BN173: 253203 | BO173: 15 | BP173: 87935 | BQ173: 718 | BR173: 16028821
A174: S45 | B174: 25811 | C174: 6 | D174: 62798 | E174: 11 | F174: 82470 | G174: 42 | H174: 904248 | I174: 45 | J174: 546883 | K174: 36 | L174: 456026 | M174: 19 | N174: 168100 | O174: 91 | P174: 1481798 | S174: 8 | T174: 162698 | U174: 6 | V174: 92364 | W174: 28 | X174: 411795 | Y174: 35 | Z174: 1020401 | AA174: 21 | AB174: 332557 | AC174: 13 | AD174: 67659 | AE174: 56 | AF174: 711532 | AG174: 67 | AH174: 2371086 | AI174: 39 | AJ174: 1090844 | AK174: 15 | AL174: 222512 | AM174: 13 | AN174: 243988 | AO174: 13 | AP174: 1167171 | AQ174: 20 | AR174: 475452 | AS174: 15 | AT174: 189902 | AU174: 1 | AV174: 57082 | AW174: 7 | AX174: 27220 | AY174: 3 | AZ174: 39340 | BA174: 53 | BB174: 847396 | BE174: 50 | BF174: 2278969 | BM174: 5 | BN174: 258332 | BO174: 15 | BP174: 90112 | BQ174: 733 | BR174: 15860745
A175: S45 | B175: 25841 | C175: 6 | D175: 60080 | E175: 11 | F175: 84497 | G175: 42 | H175: 897139 | I175: 45 | J175: 514302 | K175: 36 | L175: 433783 | M175: 19 | N175: 155838 | O175: 91 | P175: 1386942 | S175: 8 | T175: 190200 | U175: 6 | V175: 86130 | W175: 28 | X175: 375969 | Y175: 35 | Z175: 989809 | AA175: 21 | AB175: 324862 | AC175: 13 | AD175: 63786 | AE175: 57 | AF175: 650593 | AG175: 67 | AH175: 2283389 | AI175: 39 | AJ175: 1054570 | AK175: 15 | AL175: 205679 | AM175: 13 | AN175: 221112 | AO175: 13 | AP175: 1140746 | AQ175: 20 | AR175: 480513 | AS175: 15 | AT175: 224974 | AU175: 1 | AV175: 54218 | AW175: 7 | AX175: 28393 | AY175: 3 | AZ175: 35154 | BA175: 53 | BB175: 828530 | BE175: 50 | BF175: 2346479 | BM175: 6 | BN175: 250124 | BO175: 15 | BP175: 84006 | BQ175: 735 | BR175: 15451817
A176: S45 | B176: 25872 | C176: 6 | D176: 59250 | E176: 11 | F176: 82991 | G176: 42 | H176: 978311 | I176: 45 | J176: 526309 | K176: 36 | L176: 426965 | M176: 19 | N176: 150359 | O176: 91 | P176: 1405926 | S176: 8 | T176: 189582 | U176: 7 | V176: 85733 | W176: 28 | X176: 390648 | Y176: 34 | Z176: 830081 | AA176: 21 | AB176: 309427 | AC176: 12 | AD176: 59041 | AE176: 59 | AF176: 804262 | AG176: 67 | AH176: 2429542 | AI176: 39 | AJ176: 1057936 | AK176: 15 | AL176: 219264 | AM176: 13 | AN176: 226383 | AO176: 13 | AP176: 1136586 | AQ176: 20 | AR176: 474662 | AS176: 15 | AT176: 238992 | AU176: 1 | AV176: 54760 | AW176: 7 | AX176: 27703 | AY176: 3 | AZ176: 36948 | BA176: 53 | BB176: 843718 | BE176: 50 | BF176: 2363647 | BM176: 7 | BN176: 294305 | BO176: 15 | BP176: 93596 | BQ176: 737 | BR176: 15796927
A177: S45 | B177: 25902 | C177: 6 | D177: 59344 | E177: 11 | F177: 83133 | G177: 42 | H177: 900647 | I177: 44 | J177: 523829 | K177: 36 | L177: 420306 | M177: 19 | N177: 141959 | O177: 91 | P177: 1285897 | S177: 8 | T177: 172436 | U177: 7 | V177: 84704 | W177: 28 | X177: 370069 | Y177: 34 | Z177: 822325 | AA177: 21 | AB177: 315055 | AC177: 12 | AD177: 55654 | AE177: 59 | AF177: 749331 | AG177: 67 | AH177: 2177169 | AI177: 39 | AJ177: 1031072 | AK177: 15 | AL177: 196529 | AM177: 13 | AN177: 209441 | AO177: 13 | AP177: 1150325 | AQ177: 20 | AR177: 468687 | AS177: 15 | AT177: 208485 | AU177: 1 | AV177: 57276 | AW177: 7 | AX177: 28117 | AY177: 3 | AZ177: 35175 | BA177: 54 | BB177: 844677 | BE177: 50 | BF177: 2370386 | BM177: 7 | BN177: 270899 | BO177: 15 | BP177: 88245 | BQ177: 737 | BR177: 15121172
A178: S45 | B178: 25930 | C178: 6 | D178: 58798 | E178: 11 | F178: 84729 | G178: 42 | H178: 900026 | I178: 44 | J178: 530598 | K178: 36 | L178: 431938 | M178: 19 | N178: 137666 | O178: 91 | P178: 1241781 | S178: 8 | T178: 167764 | U178: 7 | V178: 81146 | W178: 28 | X178: 377901 | Y178: 34 | Z178: 836665 | AA178: 21 | AB178: 315468 | AC178: 12 | AD178: 54490 | AE178: 59 | AF178: 718085 | AG178: 67 | AH178: 2101323 | AI178: 39 | AJ178: 1021653 | AK178: 14 | AL178: 180855 | AM178: 13 | AN178: 202405 | AO178: 13 | AP178: 1217884 | AQ178: 20 | AR178: 492561 | AS178: 15 | AT178: 192724 | AU178: 1 | AV178: 56115 | AW178: 7 | AX178: 28482 | AY178: 3 | AZ178: 36464 | BA178: 54 | BB178: 860218 | BE178: 50 | BF178: 2384550 | BM178: 7 | BN178: 287462 | BO178: 15 | BP178: 91609 | BQ178: 736 | BR178: 15091360
A179: S46 | B179: 25963 | C179: 6 | D179: 69428 | E179: 11 | F179: 91589 | G179: 42 | H179: 930900 | I179: 44 | J179: 545041 | K179: 37 | L179: 462486 | M179: 19 | N179: 146171 | O179: 91 | P179: 1271835 | S179: 8 | T179: 168408 | U179: 7 | V179: 87658 | W179: 28 | X179: 397351 | Y179: 34 | Z179: 882246 | AA179: 21 | AB179: 329658 | AC179: 12 | AD179: 62657 | AE179: 59 | AF179: 793387 | AG179: 67 | AH179: 2280563 | AI179: 39 | AJ179: 1203632 | AK179: 14 | AL179: 185570 | AM179: 13 | AN179: 211448 | AO179: 13 | AP179: 1239717 | AQ179: 20 | AR179: 505211 | AS179: 15 | AT179: 207812 | AU179: 1 | AV179: 61339 | AW179: 7 | AX179: 29824 | AY179: 3 | AZ179: 36872 | BA179: 54 | BB179: 877309 | BE179: 50 | BF179: 2405722 | BM179: 7 | BN179: 280400 | BO179: 15 | BP179: 95107 | BQ179: 737 | BR179: 15859341
... A448: H5 | B448: 34150 | C448: 7 | D448: 624036 | E448: 7 | F448: 850255 | G448: 99 | H448: 14658765 | I448: 55 | J448: 9584087 | K448: 43 | L448: 5693844 | M448: 19 | N448: 2932959 | O448: 129 | P448: 24078596 | S448: 10 | T448: 4175523 | U448: 9 | V448: 1791044 | W448: 30 | X448: 5082514 | Y448: 36 | Z448: 10455858 | AA448: 24 | AB448: 4804254 | AC448: 26 | AD448: 3155017 | AE448: 94 | AF448: 10618326 | AG448: 119 | AH448: 32129612 | AI448: 53 | AJ448: 18873740 | AK448: 21 | AL448: 3668258 | AM448: 35 | AN448: 7007128 | AO448: 14 | AP448: 18873890 | AQ448: 28 | AR448: 10533423 | AS448: 13 | AT448: 1961982 | AU448: 4 | AV448: 3132594 | AW448: 10 | AX448: 1052076 | AY448: 5 | AZ448: 5919903 | BA448: 142 | BB448: 25952982 | BE448: 144 | BF448: 104623441 | BM448: 19 | BN448: 4113009 | BO448: 32 | BP448: 3992342 | BQ448: 1227 | BR448: 340339472
C449: 水産・農林業 | E449: 鉱業 | G449: 建設業 | I449: 食料品 | K449: 繊維製品 | M449: パルプ・紙 | O449: 化学 | Q449: 医薬品 | S449: 石油・石炭製品 | U449: ゴム製品 | W449: ガラス・土石製品 | Y449: 鉄鋼 | AA449: 非鉄金属 | AC449: 金属製品 | AE449: 機械 | AG449: 電気機器 | AI449: 輸送用機器 | AK449: 精密機器 | AM449: その他製品 | AO449: 電気・ガス業 | AQ449: 陸運業 | AS449: 海運業 | AU449: 空運業 | AW449: 倉庫・運輸関連業 | AY449: 通信業 | BA449: 卸売業 | BC449: 小売業 | BE449: 銀行業 | BG449: 証券業 | BI449: 保険業 | BK449: その他金融業 | BM449: 不動産業 | BO449: サービス業 | BQ449: 合計
A450: H5 | B450: 34180 | C450: 7 | D450: 635699 | E450: 8 | F450: 906619 | G450: 101 | H450: 15456572 | I450: 56 | J450: 9853952 | K450: 49 | L450: 5618296 | M450: 19 | N450: 2985722 | O450: 102 | P450: 16854809 | Q450: 33 | R450: 9474353 | S450: 10 | T450: 4383707 | U450: 8 | V450: 1835088 | W450: 29 | X450: 5231781 | Y450: 35 | Z450: 10423909 | AA450: 24 | AB450: 5097828 | AC450: 26 | AD450: 3274486 | AE450: 95 | AF450: 10838917 | AG450: 118 | AH450: 33033853 | AI450: 56 | AJ450: 21848585 | AK450: 18 | AL450: 3131410 | AM450: 32 | AN450: 7124251 | AO450: 14 | AP450: 19680699 | AQ450: 27 | AR450: 11215774 | AS450: 13 | AT450: 2036762 | AU450: 4 | AV450: 3191638 | AW450: 13 | AX450: 1274837 | AY450: 2 | AZ450: 5659564 | BA450: 71 | BB450: 11882901 | BC450: 60 | BD450: 13587274 | BE450: 99 | BF450: 92879320 | BG450: 20 | BH450: 10829111 | BI450: 14 | BJ450: 6522152 | BK450: 13 | BL450: 2201458 | BM450: 19 | BN450: 4243532 | BO450: 31 | BP450: 4411292 | BQ450: 1226 | BR450: 357626166
A451: H5 | B451: 34212 | C451: 7 | D451: 651143 | E451: 8 | F451: 916190 | G451: 102 | H451: 16381838 | I451: 56 | J451: 10119255 | K451: 49 | L451: 5701444 | M451: 19 | N451: 3042124 | O451: 102 | P451: 17102866 | Q451: 33 | R451: 9678991 | S451: 10 | T451: 4553213 | U451: 8 | V451: 1880027 | W451: 29 | X451: 5352323 | Y451: 35 | Z451: 10532422 | AA451: 24 | AB451: 5189547 | AC451: 26 | AD451: 3392649 | AE451: 95 | AF451: 10850569 | AG451: 118 | AH451: 33223669 | AI451: 56 | AJ451: 22361042 | AK451: 18 | AL451: 3215035 | AM451: 32 | AN451: 7297477 | AO451: 14 | AP451: 19346186 | AQ451: 27 | AR451: 11361373 | AS451: 13 | AT451: 2102716 | AU451: 4 | AV451: 3236759 | AW451: 13 | AX451: 1424980 | AY451: 2 | AZ451: 6006692 | BA451: 71 | BB451: 12348164 | BC451: 60 | BD451: 13987795 | BE451: 99 | BF451: 94324128 | BG451: 20 | BH451: 11583062 | BI451: 14 | BJ451: 6701872 | BK451: 13 | BL451: 2224363 | BM451: 19 | BN451: 4465812 | BO451: 31 | BP451: 4439783 | BQ451: 1227 | BR451: 364995525
A452: H5 | B452: 34242 | C452: 7 | D452: 623266 | E452: 8 | F452: 846164 | G452: 103 | H452: 15985762 | I452: 56 | J452: 10231054 | K452: 49 | L452: 5395745 | M452: 18 | N452: 2831219 | O452: 102 | P452: 16295668 | Q452: 34 | R452: 10324225 | S452: 10 | T452: 4406661 | U452: 8 | V452: 1809415 | W452: 29 | X452: 5221816 | Y452: 36 | Z452: 9185482 | AA452: 24 | AB452: 4726071 | AC452: 26 | AD452: 3458932 | AE452: 95 | AF452: 10100379 | AG452: 119 | AH452: 32524520 | AI452: 56 | AJ452: 21799211 | AK452: 18 | AL452: 3087213 | AM452: 32 | AN452: 7255126 | AO452: 14 | AP452: 18323780 | AQ452: 27 | AR452: 10916231 | AS452: 13 | AT452: 1923757 | AU452: 4 | AV452: 3092754 | AW452: 13 | AX452: 1389357 | AY452: 2 | AZ452: 5284383 | BA452: 72 | BB452: 12620760 | BC452: 60 | BD452: 15341103 | BE452: 99 | BF452: 88794537 | BG452: 20 | BH452: 10452479 | BI452: 14 | BJ452: 6244070 | BK452: 13 | BL452: 2237017 | BM452: 19 | BN452: 4277998 | BO452: 31 | BP452: 4394346 | BQ452: 1231 | BR452: 351400518
A453: H5 | B453: 34271 | C453: 7 | D453: 591310 | E453: 8 | F453: 811030 | G453: 103 | H453: 15674042 | I453: 56 | J453: 9858739 | K453: 49 | L453: 5291353 | M453: 18 | N453: 2978463 | O453: 102 | P453: 15828662 | Q453: 34 | R453: 9706370 | S453: 10 | T453: 4325913 | U453: 8 | V453: 1843412 | W453: 29 | X453: 5095196 | Y453: 36 | Z453: 9446352 | AA453: 24 | AB453: 4702525 | AC453: 26 | AD453: 3306257 | AE453: 95 | AF453: 10031516 | AG453: 119 | AH453: 33109094 | AI453: 56 | AJ453: 22532562 | AK453: 18 | AL453: 3087357 | AM453: 32 | AN453: 6647424 | AO453: 14 | AP453: 18958762 | AQ453: 28 | AR453: 12573874 | AS453: 13 | AT453: 1836832 | AU453: 4 | AV453: 2987925 | AW453: 13 | AX453: 1314243 | AY453: 2 | AZ453: 5290810 | BA453: 72 | BB453: 12458408 | BC453: 60 | BD453: 14793520 | BE453: 99 | BF453: 92389585 | BG453: 20 | BH453: 10572821 | BI453: 14 | BJ453: 6409884 | BK453: 13 | BL453: 2123939 | BM453: 19 | BN453: 4236588 | BO453: 31 | BP453: 4159734 | BQ453: 1232 | BR453: 354974517
A454: H5 | B454: 34303 | C454: 7 | D454: 499587 | E454: 8 | F454: 625900 | G454: 103 | H454: 13437781 | I454: 56 | J454: 8563668 | K454: 49 | L454: 4418940 | M454: 18 | N454: 2405403 | O454: 102 | P454: 13231426 | Q454: 34 | R454: 8245473 | S454: 10 | T454: 3860073 | U454: 8 | V454: 1642815 | W454: 29 | X454: 4220313 | Y454: 36 | Z454: 8103614 | AA454: 24 | AB454: 3855270 | AC454: 26 | AD454: 2889292 | AE454: 95 | AF454: 8343688 | AG454: 119 | AH454: 28788873 | AI454: 56 | AJ454: 19707747 | AK454: 18 | AL454: 2650862 | AM454: 32 | AN454: 5716799 | AO454: 14 | AP454: 17277763 | AQ454: 28 | AR454: 10857219 | AS454: 13 | AT454: 1580361 | AU454: 4 | AV454: 2713209 | AW454: 13 | AX454: 1050742 | AY454: 2 | AZ454: 4336328 | BA454: 72 | BB454: 10351902 | BC454: 60 | BD454: 13631695 | BE454: 99 | BF454: 73320714 | BG454: 20 | BH454: 8665740 | BI454: 14 | BJ454: 5440554 | BK454: 13 | BL454: 1751322 | BM454: 19 | BN454: 3474251 | BO454: 31 | BP454: 3574185 | BQ454: 1232 | BR454: 299233523
A455: H5 | B455: 34333 | C455: 7 | D455: 513461 | E455: 8 | F455: 651615 | G455: 104 | H455: 13941183 | I455: 56 | J455: 8754745 | K455: 49 | L455: 4572902 | M455: 18 | N455: 2342771 | O455: 102 | P455: 13859242 | Q455: 34 | R455: 8267245 | S455: 10 | T455: 3924867 | U455: 8 | V455: 1662056 | W455: 29 | X455: 4433083 | Y455: 36 | Z455: 8310949 | AA455: 24 | AB455: 4215550 | AC455: 27 | AD455: 2996898 | AE455: 95 | AF455: 8840390 | AG455: 119 | AH455: 31983992 | AI455: 56 | AJ455: 21036337 | AK455: 18 | AL455: 2968413 | AM455: 32 | AN455: 6096004 | AO455: 14 | AP455: 17502846 | AQ455: 28 | AR455: 11187309 | AS455: 13 | AT455: 1580792 | AU455: 4 | AV455: 2675674 | AW455: 13 | AX455: 1138357 | AY455: 2 | AZ455: 4724601 | BA455: 72 | BB455: 10676560 | BC455: 60 | BD455: 13568453 | BE455: 99 | BF455: 77019611 | BG455: 20 | BH455: 9255312 | BI455: 14 | BJ455: 5708228 | BK455: 13 | BL455: 1821918 | BM455: 19 | BN455: 3596243 | BO455: 31 | BP455: 3735732 | BQ455: 1234 | BR455: 313563357
A456: H6 | B456: 34365 | C456: 7 | D456: 564554 | E456: 8 | F456: 764354 | G456: 104 | H456: 16563607 | I456: 56 | J456: 9644114 | K456: 49 | L456: 5197605 | M456: 18 | N456: 2741329 | O456: 102 | P456: 15643587 | Q456: 34 | R456: 9328382 | S456: 10 | T456: 4255883 | U456: 8 | V456: 1873869 | W456: 29 | X456: 5089135 | Y456: 36 | Z456: 9661035 | AA456: 24 | AB456: 5110106 | AC456: 27 | AD456: 3325349 | AE456: 95 | AF456: 10241951 | AG456: 119 | AH456: 36605510 | AI456: 56 | AJ456: 23488114 | AK456: 18 | AL456: 3234258 | AM456: 32 | AN456: 6409763 | AO456: 14 | AP456: 18809095 | AQ456: 28 | AR456: 12620127 | AS456: 13 | AT456: 1856555 | AU456: 4 | AV456: 2934966 | AW456: 13 | AX456: 1311562 | AY456: 2 | AZ456: 6129601 | BA456: 72 | BB456: 12050708 | BC456: 60 | BD456: 14758448 | BE456: 99 | BF456: 85283365 | BG456: 20 | BH456: 12598457 | BI456: 14 | BJ456: 6178102 | BK456: 13 | BL456: 2072564 | BM456: 19 | BN456: 4313781 | BO456: 31 | BP456: 4328165 | BQ456: 1234 | BR456: 354988015
A457: H6 | B457: 34393 | C457: 7 | D457: 562308 | E457: 8 | F457: 740522 | G457: 104 | H457: 16236949 | I457: 56 | J457: 9347224 | K457: 49 | L457: 5184511 | M457: 18 | N457: 2772410 | O457: 102 | P457: 15698724 | Q457: 34 | R457: 9094655 | S457: 10 | T457: 4285767 | U457: 8 | V457: 1930820 | W457: 29 | X457: 4974803 | Y457: 36 | Z457: 9360952 | AA457: 24 | AB457: 5149534 | AC457: 27 | AD457: 3215274 | AE457: 95 | AF457: 10529090 | AG457: 119 | AH457: 37907673 | AI457: 56 | AJ457: 24017804 | AK457: 18 | AL457: 3328431 | AM457: 32 | AN457: 6509529 | AO457: 14 | AP457: 18645087 | AQ457: 28 | AR457: 12531678 | AS457: 13 | AT457: 1880933 | AU457: 4 | AV457: 2857160 | AW457: 13 | AX457: 1279105 | AY457: 2 | AZ457: 6105946 | BA457: 72 | BB457: 12100589 | BC457: 59 | BD457: 15272884 | BE457: 99 | BF457: 84222857 | BG457: 20 | BH457: 12705528 | BI457: 14 | BJ457: 6262583 | BK457: 13 | BL457: 2075806 | BM457: 19 | BN457: 4178430 | BO457: 31 | BP457: 4409831 | BQ457: 1233 | BR457: 355375415
A458: H6 | B458: 34424 | C458: 7 | D458: 563892 | E458: 8 | F458: 761733 | G458: 104 | H458: 15254826 | I458: 56 | J458: 9013186 | K458: 49 | L458: 5158782 | M458: 18 | N458: 2733381 | O458: 102 | P458: 15576700 | Q458: 34 | R458: 8772000 | S458: 10 | T458: 4088687 | U458: 8 | V458: 1928839 | W458: 29 | X458: 4877580 | Y458: 36 | Z458: 8934136 | AA458: 24 | AB458: 4971376 | AC458: 27 | AD458: 3173333 | AE458: 95 | AF458: 10530137 | AG458: 119 | AH458: 36833366 | AI458: 56 | AJ458: 23341006 | AK458: 18 | AL458: 3256045 | AM458: 32 | AN458: 6379726 | AO458: 14 | AP458: 17250432 | AQ458: 28 | AR458: 11886742 | AS458: 13 | AT458: 1768568 | AU458: 4 | AV458: 2684534 | AW458: 13 | AX458: 1246407 | AY458: 2 | AZ458: 5662646 | BA458: 72 | BB458: 11788494 | BC458: 59 | BD458: 14978946 | BE458: 99 | BF458: 79438314 | BG458: 20 | BH458: 11715566 | BI458: 14 | BJ458: 5906597 | BK458: 13 | BL458: 2019161 | BM458: 19 | BN458: 3939244 | BO458: 31 | BP458: 4362683 | BQ458: 1233 | BR458: 340797081
A459: H6 | B459: 34452 | C459: 7 | D459: 580024 | E459: 8 | F459: 821576 | G459: 104 | H459: 15489370 | I459: 56 | J459: 9210037 | K459: 49 | L459: 5556362 | M459: 18 | N459: 2873088 | O459: 102 | P459: 16263177 | Q459: 34 | R459: 8751957 | S459: 10 | T459: 4168332 | U459: 8 | V459: 1972967 | W459: 29 | X459: 5042242 | Y459: 36 | Z459: 9602577 | AA459: 24 | AB459: 4986664 | AC459: 27 | AD459: 3143150 | AE459: 95 | AF459: 10897144 | AG459: 119 | AH459: 37193285 | AI459: 56 | AJ459: 24102658 | AK459: 18 | AL459: 3323777 | AM459: 32 | AN459: 6432373 | AO459: 14 | AP459: 17386622 | AQ459: 28 | AR459: 12260356 | AS459: 13 | AT459: 1844873 | AU459: 4 | AV459: 2889818 | AW459: 13 | AX459: 1250271 | AY459: 2 | AZ459: 5540501 | BA459: 72 | BB459: 12282029 | BC459: 59 | BD459: 14860888 | BE459: 99 | BF459: 82263226 | BG459: 20 | BH459: 11734710 | BI459: 14 | BJ459: 6250762 | BK459: 13 | BL459: 2047602 | BM459: 19 | BN459: 4223825 | BO459: 31 | BP459: 4414322 | BQ459: 1233 | BR459: 349660582
A460: H6 | B460: 34485 | C460: 7 | D460: 600136 | E460: 8 | F460: 844071 | G460: 104 | H460: 15704183 | I460: 56 | J460: 9447058 | K460: 49 | L460: 5853940 | M460: 18 | N460: 3039325 | O460: 102 | P460: 17000062 | Q460: 34 | R460: 8816837 | S460: 10 | T460: 4343757 | U460: 8 | V460: 2095674 | W460: 29 | X460: 5231805 | Y460: 36 | Z460: 10370225 | AA460: 24 | AB460: 5393562 | AC460: 27 | AD460: 3191190 | AE460: 95 | AF460: 11597352 | AG460: 119 | AH460: 39743215 | AI460: 56 | AJ460: 25737640 | AK460: 18 | AL460: 3529086 | AM460: 32 | AN460: 6717603 | AO460: 14 | AP460: 17353060 | AQ460: 28 | AR460: 12566914 | AS460: 13 | AT460: 2045334 | AU460: 4 | AV460: 3015323 | AW460: 13 | AX460: 1315836 | AY460: 2 | AZ460: 5435846 | BA460: 72 | BB460: 12886151 | BC460: 59 | BD460: 15005316 | BE460: 99 | BF460: 87580821 | BG460: 20 | BH460: 12981607 | BI460: 14 | BJ460: 6534837 | BK460: 13 | BL460: 2099141 | BM460: 19 | BN460: 4442591 | BO460: 31 | BP460: 4455537 | BQ460: 1233 | BR460: 366975050
A461: H6 | B461: 34515 | C461: 7 | D461: 607224 | E461: 8 | F461: 834817 | G461: 104 | H461: 15729167 | I461: 56 | J461: 9286015 | K461: 49 | L461: 5868739 | M461: 18 | N461: 3063132 | O461: 102 | P461: 16936745 | Q461: 34 | R461: 8534301 | S461: 10 | T461: 4339797 | U461: 8 | V461: 2102144 | W461: 29 | X461: 5231647 | Y461: 36 | Z461: 10090871 | AA461: 24 | AB461: 5345303 | AC461: 27 | AD461: 3198225 | AE461: 95 | AF461: 12028638 | AG461: 119 | AH461: 40365476 | AI461: 56 | AJ461: 26248006 | AK461: 18 | AL461: 3592307 | AM461: 32 | AN461: 6933916 | AO461: 14 | AP461: 17043298 | AQ461: 28 | AR461: 12309055 | AS461: 13 | AT461: 1983649 | AU461: 4 | AV461: 2947017 | AW461: 13 | AX461: 1269004 | AY461: 2 | AZ461: 5502701 | BA461: 72 | BB461: 13048557 | BC461: 59 | BD461: 15015782 | BE461: 99 | BF461: 85485543 | BG461: 20 | BH461: 12868384 | BI461: 14 | BJ461: 6248738 | BK461: 13 | BL461: 2041814 | BM461: 19 | BN461: 4328919 | BO461: 31 | BP461: 4592256 | BQ461: 1233 | BR461: 365021201
... A529: H12 | B529: 36585 | C529: 8 | D529: 339840 | E529: 8 | F529: 195852 | G529: 115 | H529: 5061078 | I529: 67 | J529: 8652985 | K529: 50 | L529: 3057865 | M529: 17 | N529: 1685215 | O529: 103 | P529: 17093000 | Q529: 33 | R529: 16063772 | S529: 9 | T529: 1335736 | U529: 10 | V529: 2548783 | W529: 24 | X529: 3024858 | Y529: 36 | Z529: 3748735 | AA529: 23 | AB529: 4080020 | AC529: 31 | AD529: 1303524 | AE529: 108 | AF529: 11536285 | AG529: 141 | AH529: 91929975 | AI529: 59 | AJ529: 29906417 | AK529: 20 | AL529: 4885319 | AM529: 40 | AN529: 8533939 | AO529: 14 | AP529: 9959541 | AQ529: 31 | AR529: 10312097 | AS529: 11 | AT529: 801685 | AU529: 4 | AV529: 889131 | AW529: 13 | AX529: 420250 | AY529: 6 | AZ529: 66692851 | BA529: 85 | BB529: 26534539 | BC529: 83 | BD529: 19677539 | BE529: 94 | BF529: 39960292 | BG529: 17 | BH529: 12452712 | BI529: 14 | BJ529: 3601271 | BK529: 23 | BL529: 8381798 | BM529: 22 | BN529: 2632186 | BO529: 53 | BP529: 26537571 | BQ529: 1372 | BR529: 443836677
C530: 水産・農林業 | E530: 鉱業 | G530: 建設業 | I530: 食料品 | K530: 繊維製品 | M530: パルプ・紙 | O530: 化学 | Q530: 医薬品 | S530: 石油・石炭製品 | U530: ゴム製品 | W530: ガラス・土石製品 | Y530: 鉄鋼 | AA530: 非鉄金属 | AC530: 金属製品 | AE530: 機械 | AG530: 電気機器 | AI530: 輸送用機器 | AK530: 精密機器 | AM530: その他製品 | AO530: 電気・ガス業 | AQ530: 陸運業 | AS530: 海運業 | AU530: 空運業 | AW530: 倉庫・運輸関連業 | AY530: 通信業 | BA530: 卸売業 | BC530: 小売業 | BE530: 銀行業 | BG530: 証券、商品先物取引業 | BI530: 保険業 | BK530: その他金融業 | BM530: 不動産業 | BO530: サービス業 | BQ530: 合計
A531: H12 | B531: 36616 | C531: 8 | D531: 365716 | E531: 8 | F531: 218957 | G531: 116 | H531: 5490963 | I531: 67 | J531: 8653917 | K531: 53 | L531: 3430884 | M531: 17 | N531: 2134090 | O531: 104 | P531: 17802961 | Q531: 35 | R531: 18027622 | S531: 9 | T531: 1371640 | U531: 10 | V531: 2412206 | W531: 25 | X531: 3327247 | Y531: 36 | Z531: 4106194 | AA531: 23 | AB531: 4349233 | AC531: 31 | AD531: 1445138 | AE531: 109 | AF531: 12392903 | AG531: 143 | AH531: 91812321 | AI531: 60 | AJ531: 34739487 | AK531: 20 | AL531: 5063458 | AM531: 43 | AN531: 7648549 | AO531: 14 | AP531: 9802116 | AQ531: 31 | AR531: 10635977 | AS531: 11 | AT531: 951671 | AU531: 4 | AV531: 996847 | AW531: 13 | AX531: 472005 | AY531: 6 | AZ531: 60094716 | BA531: 88 | BB531: 19448815 | BC531: 87 | BD531: 21487088 | BE531: 94 | BF531: 44103264 | BG531: 15 | BH531: 13674556 | BI531: 14 | BJ531: 3695035 | BK531: 26 | BL531: 8587878 | BM531: 22 | BN531: 2940146 | BO531: 59 | BP531: 24797151 | BQ531: 1401 | BR531: 446480767
A532: H12 | B532: 36644 | C532: 8 | D532: 333310 | E532: 8 | F532: 196532 | G532: 116 | H532: 5306594 | I532: 67 | J532: 8823577 | K532: 53 | L532: 3450785 | M532: 17 | N532: 2009883 | O532: 104 | P532: 17809428 | Q532: 35 | R532: 18490422 | S532: 9 | T532: 1347447 | U532: 10 | V532: 2461258 | W532: 25 | X532: 3514713 | Y532: 36 | Z532: 4022684 | AA532: 23 | AB532: 4105441 | AC532: 31 | AD532: 1452934 | AE532: 109 | AF532: 12628436 | AG532: 143 | AH532: 89417979 | AI532: 59 | AJ532: 35741027 | AK532: 20 | AL532: 5164832 | AM532: 43 | AN532: 7564750 | AO532: 14 | AP532: 10632449 | AQ532: 31 | AR532: 10624312 | AS532: 11 | AT532: 930748 | AU532: 4 | AV532: 1043707 | AW532: 13 | AX532: 465136 | AY532: 6 | AZ532: 52349360 | BA532: 88 | BB532: 17811105 | BC532: 87 | BD532: 23292181 | BE532: 94 | BF532: 42167781 | BG532: 15 | BH532: 11678247 | BI532: 14 | BJ532: 3777341 | BK532: 25 | BL532: 8832118 | BM532: 22 | BN532: 3177966 | BO532: 61 | BP532: 22639776 | BQ532: 1401 | BR532: 433264274
A533: H12 | B533: 36677 | C533: 8 | D533: 345976 | E533: 8 | F533: 207805 | G533: 116 | H533: 5477003 | I533: 67 | J533: 9108494 | K533: 53 | L533: 3397619 | M533: 17 | N533: 2060079 | O533: 104 | P533: 17323212 | Q533: 35 | R533: 17873470 | S533: 9 | T533: 1495837 | U533: 10 | V533: 2610303 | W533: 25 | X533: 3746345 | Y533: 36 | Z533: 4089548 | AA533: 23 | AB533: 4426057 | AC533: 31 | AD533: 1559619 | AE533: 109 | AF533: 12627821 | AG533: 144 | AH533: 83283522 | AI533: 59 | AJ533: 32877324 | AK533: 20 | AL533: 4940492 | AM533: 43 | AN533: 7204949 | AO533: 14 | AP533: 11363256 | AQ533: 31 | AR533: 10738713 | AS533: 11 | AT533: 997536 | AU533: 4 | AV533: 1024513 | AW533: 13 | AX533: 471656 | AY533: 6 | AZ533: 42745790 | BA533: 89 | BB533: 14055033 | BC533: 87 | BD533: 19597332 | BE533: 94 | BF533: 41551049 | BG533: 15 | BH533: 10170626 | BI533: 14 | BJ533: 4282073 | BK533: 24 | BL533: 8616591 | BM533: 22 | BN533: 3328855 | BO533: 62 | BP533: 23735333 | BQ533: 1403 | BR533: 407333848
A534: H12 | B534: 36707 | C534: 8 | D534: 361090 | E534: 8 | F534: 227923 | G534: 116 | H534: 5935798 | I534: 67 | J534: 9565779 | K534: 53 | L534: 3809240 | M534: 17 | N534: 2211926 | O534: 104 | P534: 18930990 | Q534: 35 | R534: 19223452 | S534: 9 | T534: 1607281 | U534: 10 | V534: 2462649 | W534: 25 | X534: 4694294 | Y534: 36 | Z534: 4040446 | AA534: 23 | AB534: 5420009 | AC534: 31 | AD534: 1633152 | AE534: 110 | AF534: 14200380 | AG534: 146 | AH534: 89396967 | AI534: 59 | AJ534: 33627690 | AK534: 20 | AL534: 5458663 | AM534: 43 | AN534: 7746687 | AO534: 14 | AP534: 11563108 | AQ534: 31 | AR534: 10958582 | AS534: 11 | AT534: 1120625 | AU534: 4 | AV534: 1218908 | AW534: 13 | AX534: 509278 | AY534: 6 | AZ534: 44213123 | BA534: 89 | BB534: 14438185 | BC534: 87 | BD534: 19536512 | BE534: 94 | BF534: 40008869 | BG534: 15 | BH534: 10702617 | BI534: 14 | BJ534: 4340903 | BK534: 24 | BL534: 8994399 | BM534: 22 | BN534: 3399547 | BO534: 62 | BP534: 24308306 | BQ534: 1406 | BR534: 425867395
A535: H12 | B535: 36738 | C535: 8 | D535: 322984 | E535: 8 | F535: 221533 | G535: 116 | H535: 5701589 | I535: 67 | J535: 8748485 | K535: 53 | L535: 3327050 | M535: 17 | N535: 2287854 | O535: 104 | P535: 17464607 | Q535: 35 | R535: 17739885 | S535: 8 | T535: 1645261 | U535: 10 | V535: 2659664 | W535: 25 | X535: 4241796 | Y535: 36 | Z535: 3822729 | AA535: 23 | AB535: 5719449 | AC535: 31 | AD535: 1443700 | AE535: 110 | AF535: 12564750 | AG535: 146 | AH535: 80130375 | AI535: 59 | AJ535: 32671261 | AK535: 20 | AL535: 4853299 | AM535: 43 | AN535: 7270824 | AO535: 14 | AP535: 11320867 | AQ535: 31 | AR535: 11182018 | AS535: 11 | AT535: 1107312 | AU535: 4 | AV535: 1338821 | AW535: 13 | AX535: 481812 | AY535: 6 | AZ535: 41387237 | BA535: 89 | BB535: 11569557 | BC535: 87 | BD535: 17464564 | BE535: 94 | BF535: 36110491 | BG535: 15 | BH535: 8793504 | BI535: 14 | BJ535: 4098819 | BK535: 24 | BL535: 8063588 | BM535: 22 | BN535: 3063766 | BO535: 62 | BP535: 20203237 | BQ535: 1405 | BR535: 389022705
A536: H12 | B536: 36769 | C536: 8 | D536: 319118 | E536: 8 | F536: 230149 | G536: 116 | H536: 5838146 | I536: 68 | J536: 8572970 | K536: 53 | L536: 3194223 | M536: 17 | N536: 2148857 | O536: 105 | P536: 16976422 | Q536: 35 | R536: 17428492 | S536: 8 | T536: 1782872 | U536: 10 | V536: 1700815 | W536: 25 | X536: 4640980 | Y536: 36 | Z536: 3720252 | AA536: 23 | AB536: 6563729 | AC536: 31 | AD536: 1496661 | AE536: 110 | AF536: 12808256 | AG536: 146 | AH536: 88093097 | AI536: 59 | AJ536: 32276729 | AK536: 20 | AL536: 5041956 | AM536: 43 | AN536: 7229274 | AO536: 14 | AP536: 11178791 | AQ536: 31 | AR536: 10922682 | AS536: 11 | AT536: 1024237 | AU536: 4 | AV536: 1250547 | AW536: 13 | AX536: 471256 | AY536: 6 | AZ536: 41482072 | BA536: 89 | BB536: 13235614 | BC536: 90 | BD536: 17321471 | BE536: 94 | BF536: 40574311 | BG536: 15 | BH536: 10153181 | BI536: 14 | BJ536: 4292364 | BK536: 24 | BL536: 8140930 | BM536: 22 | BN536: 3096033 | BO536: 67 | BP536: 25133759 | BQ536: 1415 | BR536: 408340262
A537: H12 | B537: 36798 | C537: 8 | D537: 319056 | E537: 8 | F537: 253082 | G537: 117 | H537: 5746392 | I537: 68 | J537: 8613378 | K537: 53 | L537: 3349387 | M537: 17 | N537: 2038189 | O537: 105 | P537: 16432321 | Q537: 35 | R537: 18530003 | S537: 8 | T537: 1873842 | U537: 10 | V537: 1641027 | W537: 25 | X537: 4659162 | Y537: 36 | Z537: 3633314 | AA537: 23 | AB537: 6067630 | AC537: 30 | AD537: 1478335 | AE537: 112 | AF537: 12790247 | AG537: 147 | AH537: 81033749 | AI537: 59 | AJ537: 31410410 | AK537: 20 | AL537: 4337624 | AM537: 44 | AN537: 7285699 | AO537: 14 | AP537: 11477830 | AQ537: 31 | AR537: 11256090 | AS537: 11 | AT537: 1148773 | AU537: 4 | AV537: 1307043 | AW537: 13 | AX537: 477407 | AY537: 6 | AZ537: 41743759 | BA537: 91 | BB537: 12058966 | BC537: 91 | BD537: 17028608 | BE537: 92 | BF537: 41638282 | BG537: 14 | BH537: 9475765 | BI537: 14 | BJ537: 4218542 | BK537: 25 | BL537: 8311138 | BM537: 24 | BN537: 3665870 | BO537: 70 | BP537: 24026238 | BQ537: 1425 | BR537: 399327176
A538: H12 | B538: 36830 | C538: 8 | D538: 312849 | E538: 8 | F538: 266403 | G538: 116 | H538: 5615071 | I538: 68 | J538: 8486532 | K538: 52 | L538: 3200576 | M538: 17 | N538: 1904545 | O538: 108 | P538: 17308252 | Q538: 35 | R538: 18274916 | S538: 8 | T538: 1874405 | U538: 10 | V538: 1410185 | W538: 25 | X538: 4560761 | Y538: 37 | Z538: 3350369 | AA538: 23 | AB538: 6079426 | AC538: 30 | AD538: 1444673 | AE538: 111 | AF538: 10269345 | AG538: 147 | AH538: 71811031 | AI538: 58 | AJ538: 32116359 | AK538: 20 | AL538: 3910129 | AM538: 44 | AN538: 6847619 | AO538: 14 | AP538: 11468905 | AQ538: 31 | AR538: 11202963 | AS538: 11 | AT538: 1098472 | AU538: 4 | AV538: 1323976 | AW538: 13 | AX538: 464864 | AY538: 6 | AZ538: 37607105 | BA538: 91 | BB538: 10460933 | BC538: 91 | BD538: 17120234 | BE538: 92 | BF538: 40896329 | BG538: 14 | BH538: 9084106 | BI538: 14 | BJ538: 4369706 | BK538: 25 | BL538: 7603690 | BM538: 24 | BN538: 3627220 | BO538: 73 | BP538: 21681862 | BQ538: 1428 | BR538: 377053827
A539: H12 | B539: 36860 | C539: 8 | D539: 326294 | E539: 8 | F539: 322365 | G539: 115 | H539: 5930169 | I539: 69 | J539: 8589825 | K539: 52 | L539: 3273613 | M539: 17 | N539: 1862224 | O539: 108 | P539: 17905418 | Q539: 35 | R539: 18417607 | S539: 8 | T539: 2104456 | U539: 10 | V539: 1667837 | W539: 25 | X539: 4597207 | Y539: 37 | Z539: 3742944 | AA539: 23 | AB539: 5818126 | AC539: 30 | AD539: 1476000 | AE539: 112 | AF539: 10659327 | AG539: 146 | AH539: 70342535 | AI539: 58 | AJ539: 30323151 | AK539: 20 | AL539: 3685576 | AM539: 45 | AN539: 6709043 | AO539: 14 | AP539: 11783276 | AQ539: 31 | AR539: 11590096 | AS539: 11 | AT539: 1037234 | AU539: 4 | AV539: 1423700 | AW539: 13 | AX539: 501445 | AY539: 6 | AZ539: 39014037 | BA539: 93 | BB539: 10292716 | BC539: 92 | BD539: 18183696 | BE539: 92 | BF539: 36674092 | BG539: 14 | BH539: 8929172 | BI539: 14 | BJ539: 4589191 | BK539: 25 | BL539: 6839037 | BM539: 24 | BN539: 3671720 | BO539: 75 | BP539: 21485313 | BQ539: 1434 | BR539: 373768457
A540: H12 | B540: 36889 | C540: 8 | D540: 328307 | E540: 8 | F540: 285434 | G540: 115 | H540: 5905438 | I540: 70 | J540: 8708482 | K540: 52 | L540: 3385372 | M540: 17 | N540: 1910172 | O540: 109 | P540: 17707573 | Q540: 35 | R540: 18746313 | S540: 8 | T540: 1799596 | U540: 10 | V540: 1369030 | W540: 25 | X540: 4211068 | Y540: 37 | Z540: 3499189 | AA540: 23 | AB540: 5210736 | AC540: 31 | AD540: 1387473 | AE540: 113 | AF540: 9944255 | AG540: 148 | AH540: 66048384 | AI540: 58 | AJ540: 29250048 | AK540: 21 | AL540: 3605762 | AM540: 45 | AN540: 6918547 | AO540: 14 | AP540: 12382303 | AQ540: 31 | AR540: 11638537 | AS540: 11 | AT540: 996454 | AU540: 4 | AV540: 1543219 | AW540: 13 | AX540: 486594 | AY540: 6 | AZ540: 29930967 | BA540: 95 | BB540: 9418857 | BC540: 92 | BD540: 16618928 | BE540: 92 | BF540: 36572818 | BG540: 14 | BH540: 8402851 | BI540: 14 | BJ540: 4788534 | BK540: 25 | BL540: 7018019 | BM540: 24 | BN540: 3474402 | BO540: 77 | BP540: 19291007 | BQ540: 1445 | BR540: 352784685

Sheet Maikin30
A1: 毎月勤労統計調査(MONTHLY LABOUR SURVEY) | F1: 季節調整済労働時間指数(Seasonally adjusted hours worked indices) 総実労働時間(Total hours worked)
A2: 事業所規模(Size of establishments)： | F2: ３０人以上(Establishments with 30 employees or more)
A3: 就業形態(Type of Employment): | F3: 就業形態計(Total)
A4: 産業(Industry): | F4: 調査産業計(Industries covered)
A6: 季節調整済指数(Seasonally Adjusted Indices) | E6: 平成27年平均＝１００(2015 average = 100)
A7: 年 | B7: 1-3 | C7: 4-6 | D7: 7-9 | E7: 10-12 | F7: 1 | G7: 2 | H7: 3 | I7: 4 | J7: 5 | K7: 6 | L7: 7 | M7: 8 | N7: 9 | O7: 10 | P7: 11 | Q7: 12
A8: year | B8: 第１四半期 | C8: 第２四半期 | D8: 第３四半期 | E8: 第４四半期 | F8: １月 | G8: ２月 | H8: ３月 | I8: ４月 | J8: ５月 | K8: ６月 | L8: ７月 | M8: ８月 | N8: ９月 | O8: １０月 | P8: １１月 | Q8: １２月
B9: 1st Qr. | C9: 2nd Qr. | D9: 3rd Qr. | E9: 4th Qr. | F9: Jan. | G9: Feb. | H9: Mar. | I9: Apr. | J9: May | K9: Jun. | L9: Jul. | M9: Aug. | N9: Sep. | O9: Oct. | P9: Nov. | Q9: Dec.
A10: 1970 | B10: 124.1 | C10: 125.4 | D10: 124.7 | E10: 124.1 | F10: 123.6 | G10: 124.9 | H10: 123.8 | I10: 125 | J10: 126.1 | K10: 125.2 | L10: 124.9 | M10: 124.9 | N10: 124.2 | O10: 124.8 | P10: 123.9 | Q10: 123.7
A11: 1971 | B11: 124.2 | C11: 122.5 | D11: 123.5 | E11: 123 | F11: 124.4 | G11: 123.4 | H11: 124.7 | I11: 124.1 | J11: 121.2 | K11: 122.3 | L11: 123.6 | M11: 123.8 | N11: 123.2 | O11: 123.4 | P11: 123.2 | Q11: 122.4
A12: 1972 | B12: 123.4 | C12: 122.4 | D12: 122.7 | E12: 122.2 | F12: 123.7 | G12: 122.6 | H12: 124 | I12: 122.8 | J12: 122 | K12: 122.4 | L12: 122 | M12: 122.9 | N12: 123.3 | O12: 121.4 | P12: 122.3 | Q12: 122.9
A13: 1973 | B13: 122.8 | C13: 121.7 | D13: 120.3 | E13: 120.6 | F13: 122.8 | G13: 123.3 | H13: 122.2 | I13: 121.4 | J13: 121.5 | K13: 122.2 | L13: 120.6 | M13: 120.2 | N13: 120 | O13: 120.6 | P13: 121.3 | Q13: 119.9
A14: 1974 | B14: 117.5 | C14: 117.7 | D14: 116.6 | E14: 116.4 | F14: 116.7 | G14: 118.9 | H14: 116.9 | I14: 117.6 | J14: 118 | K14: 117.4 | L14: 117.5 | M14: 116.2 | N14: 116.1 | O14: 115.7 | P14: 118 | Q14: 115.4
A15: 1975 | B15: 113.9 | C15: 114.5 | D15: 115.4 | E15: 115.4 | F15: 114 | G15: 114.5 | H15: 113.2 | I15: 113.8 | J15: 115 | K15: 114.7 | L15: 115.5 | M15: 114.9 | N15: 115.7 | O15: 116 | P15: 114.9 | Q15: 115.3
A16: 1976 | B16: 116.9 | C16: 116.1 | D16: 116.5 | E16: 116.3 | F16: 115.4 | G16: 116.5 | H16: 118.8 | I16: 117.3 | J16: 115 | K16: 116.1 | L16: 117.1 | M16: 116.5 | N16: 115.8 | O16: 115.9 | P16: 116.9 | Q16: 116.1
A17: 1977 | B17: 117.1 | C17: 116.5 | D17: 116.6 | E17: 116.6 | F17: 118.5 | G17: 115.8 | H17: 117.1 | I17: 117.3 | J17: 115.6 | K17: 116.5 | L17: 116 | M17: 117.4 | N17: 116.4 | O17: 115.9 | P17: 116.6 | Q17: 117.2
A18: 1978 | B18: 117 | C18: 116.9 | D18: 117.4 | E18: 117.5 | F18: 117.3 | G18: 116.5 | H18: 117.2 | I18: 116.3 | J18: 117 | K18: 117.3 | L18: 116.5 | M18: 117.3 | N18: 118.3 | O18: 117.1 | P18: 117.8 | Q18: 117.5
A19: 1979 | B19: 117.4 | C19: 117.6 | D19: 117.2 | E19: 118.2 | F19: 117.4 | G19: 117.4 | H19: 117.3 | I19: 116.7 | J19: 118.2 | K19: 117.9 | L19: 117 | M19: 117.5 | N19: 117 | O19: 118.2 | P19: 119.1 | Q19: 117.4
A20: 1980 | B20: 117.6 | C20: 117.7 | D20: 116.8 | E20: 116.8 | F20: 115.7 | G20: 119.9 | H20: 117.1 | I20: 117.4 | J20: 119.2 | K20: 116.5 | L20: 117.1 | M20: 116.3 | N20: 117.1 | O20: 117.5 | P20: 115.9 | Q20: 117.1
A21: 1981 | B21: 116.6 | C21: 116.8 | D21: 116.5 | E21: 117.1 | F21: 116.5 | G21: 117 | H21: 116.3 | I21: 117.2 | J21: 116.2 | K21: 117.1 | L21: 117.3 | M21: 115.8 | N21: 116.4 | O21: 118.9 | P21: 116.1 | Q21: 116.4
... A56: 2016 | B56: 101.1 | C56: 99.6 | D56: 99.4 | E56: 99.5 | F56: 99.8 | G56: 100.9 | H56: 102.7 | I56: 99.7 | J56: 98.6 | K56: 100.5 | L56: 98.2 | M56: 99.5 | N56: 100.6 | O56: 98.3 | P56: 100.1 | Q56: 100
A57: 2017 | B57: 100.3 | C57: 99.9 | F57: 98.9 | G57: 100.8 | H57: 101.3 | I57: 99.2 | J57: 100.1 | K57: 100.5 | L57: 97.4
A74: 毎月勤労統計調査(MONTHLY LABOUR SURVEY) | F74: 季節調整済労働時間指数(Seasonally adjusted hours worked indices) 総実労働時間(Total hours worked)
A75: 事業所規模(Size of establishments)： | F75: ３０人以上(Establishments with 30 employees or more)
A76: 就業形態(Type of Employment): | F76: 就業形態計(Total)
A77: 産業(Industry): | F77: 調査産業計(Industries covered)
A79: 前期比(Ratio to the preceding month or quarter)：％(%)
A80: 年 | B80: 1-3 | C80: 4-6 | D80: 7-9 | E80: 10-12 | F80: 1 | G80: 2 | H80: 3 | I80: 4 | J80: 5 | K80: 6 | L80: 7 | M80: 8 | N80: 9 | O80: 10 | P80: 11 | Q80: 12
A81: year | B81: 第１四半期 | C81: 第２四半期 | D81: 第３四半期 | E81: 第４四半期 | F81: １月 | G81: ２月 | H81: ３月 | I81: ４月 | J81: ５月 | K81: ６月 | L81: ７月 | M81: ８月 | N81: ９月 | O81: １０月 | P81: １１月 | Q81: １２月
B82: 1st Qr. | C82: 2nd Qr. | D82: 3rd Qr. | E82: 4th Qr. | F82: Jan. | G82: Feb. | H82: Mar. | I82: Apr. | J82: May | K82: Jun. | L82: Jul. | M82: Aug. | N82: Sep. | O82: Oct. | P82: Nov. | Q82: Dec.
A83: 1970 | B83: - | C83: 1 | D83: -0.6 | E83: -0.5 | F83: - | G83: 1.1 | H83: -0.9 | I83: 1 | J83: 0.9 | K83: -0.7 | L83: -0.2 | M83: 0 | N83: -0.6 | O83: 0.5 | P83: -0.7 | Q83: -0.2
A84: 1971 | B84: 0.1 | C84: -1.4 | D84: 0.8 | E84: -0.4 | F84: 0.6 | G84: -0.8 | H84: 1.1 | I84: -0.5 | J84: -2.3 | K84: 0.9 | L84: 1.1 | M84: 0.2 | N84: -0.5 | O84: 0.2 | P84: -0.2 | Q84: -0.6
A85: 1972 | B85: 0.3 | C85: -0.8 | D85: 0.2 | E85: -0.4 | F85: 1.1 | G85: -0.9 | H85: 1.1 | I85: -1 | J85: -0.7 | K85: 0.3 | L85: -0.3 | M85: 0.7 | N85: 0.3 | O85: -1.5 | P85: 0.7 | Q85: 0.5
A86: 1973 | B86: 0.5 | C86: -0.9 | D86: -1.2 | E86: 0.2 | F86: -0.1 | G86: 0.4 | H86: -0.9 | I86: -0.7 | J86: 0.1 | K86: 0.6 | L86: -1.3 | M86: -0.3 | N86: -0.2 | O86: 0.5 | P86: 0.6 | Q86: -1.2
A87: 1974 | B87: -2.6 | C87: 0.2 | D87: -0.9 | E87: -0.2 | F87: -2.7 | G87: 1.9 | H87: -1.7 | I87: 0.6 | J87: 0.3 | K87: -0.5 | L87: 0.1 | M87: -1.1 | N87: -0.1 | O87: -0.3 | P87: 2 | Q87: -2.2
A88: 1975 | B88: -2.1 | C88: 0.5 | D88: 0.8 | E88: 0 | F88: -1.2 | G88: 0.4 | H88: -1.1 | I88: 0.5 | J88: 1.1 | K88: -0.3 | L88: 0.7 | M88: -0.5 | N88: 0.7 | O88: 0.3 | P88: -0.9 | Q88: 0.3
A89: 1976 | B89: 1.3 | C89: -0.7 | D89: 0.3 | E89: -0.2 | F89: 0.1 | G89: 1 | H89: 2 | I89: -1.3 | J89: -2 | K89: 1 | L89: 0.9 | M89: -0.5 | N89: -0.6 | O89: 0.1 | P89: 0.9 | Q89: -0.7
A90: 1977 | B90: 0.7 | C90: -0.5 | D90: 0.1 | E90: 0 | F90: 2.1 | G90: -2.3 | H90: 1.1 | I90: 0.2 | J90: -1.4 | K90: 0.8 | L90: -0.4 | M90: 1.2 | N90: -0.9 | O90: -0.4 | P90: 0.6 | Q90: 0.5
A91: 1978 | B91: 0.3 | C91: -0.1 | D91: 0.4 | E91: 0.1 | F91: 0.1 | G91: -0.7 | H91: 0.6 | I91: -0.8 | J91: 0.6 | K91: 0.3 | L91: -0.7 | M91: 0.7 | N91: 0.9 | O91: -1 | P91: 0.6 | Q91: -0.3
A92: 1979 | B92: -0.1 | C92: 0.2 | D92: -0.3 | E92: 0.9 | F92: -0.1 | G92: 0 | H92: -0.1 | I92: -0.5 | J92: 1.3 | K92: -0.3 | L92: -0.8 | M92: 0.4 | N92: -0.4 | O92: 1 | P92: 0.8 | Q92: -1.4
A93: 1980 | B93: -0.5 | C93: 0.1 | D93: -0.8 | E93: 0 | F93: -1.4 | G93: 3.6 | H93: -2.3 | I93: 0.3 | J93: 1.5 | K93: -2.3 | L93: 0.5 | M93: -0.7 | N93: 0.7 | O93: 0.3 | P93: -1.4 | Q93: 1
A94: 1981 | B94: -0.2 | C94: 0.2 | D94: -0.3 | E94: 0.5 | F94: -0.5 | G94: 0.4 | H94: -0.6 | I94: 0.8 | J94: -0.9 | K94: 0.8 | L94: 0.2 | M94: -1.3 | N94: 0.5 | O94: 2.1 | P94: -2.4 | Q94: 0.3
A95: 1982 | B95: -0.5 | C95: -0.1 | D95: 0.3 | E95: -0.3 | F95: 0.3 | G95: -0.8 | H95: 1.1 | I95: -0.3 | J95: -0.3 | K95: -0.1 | L95: 0.8 | M95: -0.3 | N95: -0.3 | O95: -0.4 | P95: 1.3 | Q95: -1.2
... A129: 2016 | B129: 1.6 | C129: -1.5 | D129: -0.2 | E129: 0.1 | F129: -0.1 | G129: 1.1 | H129: 1.8 | I129: -2.9 | J129: -1.1 | K129: 1.9 | L129: -2.3 | M129: 1.3 | N129: 1.1 | O129: -2.3 | P129: 1.8 | Q129: -0.1
A130: 2017 | B130: 0.8 | C130: -0.4 | F130: -1.1 | G130: 1.9 | H130: 0.5 | I130: -2.1 | J130: 0.9 | K130: 0.4 | L130: -3.1

Sheet Maikin05
A1: 毎月勤労統計調査(MONTHLY LABOUR SURVEY) | F1: 季節調整済労働時間指数(Seasonally adjusted hours worked indices) 総実労働時間(Total hours worked)
A2: 事業所規模(Size of establishments)： | F2: ５人以上(Establishments with 5 employees or more)
A3: 就業形態(Type of Employment): | F3: 就業形態計(Total)
A4: 産業(Industry): | F4: 調査産業計(Industries covered)
A6: 季節調整済指数(Seasonally Adjusted Indices) | E6: 平成27年平均＝１００(2015 average = 100)
A7: 年 | B7: 1-3 | C7: 4-6 | D7: 7-9 | E7: 10-12 | F7: 1 | G7: 2 | H7: 3 | I7: 4 | J7: 5 | K7: 6 | L7: 7 | M7: 8 | N7: 9 | O7: 10 | P7: 11 | Q7: 12
A8: year | B8: 第１四半期 | C8: 第２四半期 | D8: 第３四半期 | E8: 第４四半期 | F8: １月 | G8: ２月 | H8: ３月 | I8: ４月 | J8: ５月 | K8: ６月 | L8: ７月 | M8: ８月 | N8: ９月 | O8: １０月 | P8: １１月 | Q8: １２月
B9: 1st Qr. | C9: 2nd Qr. | D9: 3rd Qr. | E9: 4th Qr. | F9: Jan. | G9: Feb. | H9: Mar. | I9: Apr. | J9: May | K9: Jun. | L9: Jul. | M9: Aug. | N9: Sep. | O9: Oct. | P9: Nov. | Q9: Dec.
A10: 1990 | B10: 119.5 | C10: 119.1 | D10: 118.3 | E10: 118 | F10: 120.5 | G10: 118.5 | H10: 119.4 | I10: 118.9 | J10: 119.2 | K10: 119.3 | L10: 118 | M10: 118.7 | N10: 118.2 | O10: 118.7 | P10: 117.4 | Q10: 117.9
A11: 1991 | B11: 116.8 | C11: 116.3 | D11: 115.6 | E11: 115.6 | F11: 117 | G11: 117.7 | H11: 115.8 | I11: 116.7 | J11: 117.1 | K11: 115.2 | L11: 116.5 | M11: 115.2 | N11: 115.2 | O11: 115.5 | P11: 116.2 | Q11: 115.1
A12: 1992 | B12: 114.7 | C12: 114.1 | D12: 112.6 | E12: 112.6 | F12: 114.3 | G12: 115.4 | H12: 114.3 | I12: 114.3 | J12: 114 | K12: 114.1 | L12: 113.6 | M12: 111.6 | N12: 112.5 | O12: 114.9 | P12: 111.5 | Q12: 111.4
A13: 1993 | B13: 111.4 | C13: 109.9 | D13: 110.5 | E13: 109.8 | F13: 111.6 | G13: 110.8 | H13: 111.8 | I13: 112.3 | J13: 108.9 | K13: 108.6 | L13: 110.8 | M13: 110.4 | N13: 110.4 | O13: 109.7 | P13: 110.2 | Q13: 109.5
A14: 1994 | B14: 110.3 | C14: 109.3 | D14: 110.1 | E14: 110 | F14: 112.1 | G14: 108.9 | H14: 110 | I14: 110 | J14: 107.8 | K14: 110.1 | L14: 109.5 | M14: 110.6 | N14: 110.2 | O14: 109.4 | P14: 110.1 | Q14: 110.5
A15: 1995 | B15: 110.1 | C15: 109.7 | D15: 110.1 | E15: 110.4 | F15: 110 | G15: 110.2 | H15: 110.2 | I15: 109.3 | J15: 109.4 | K15: 110.5 | L15: 109.5 | M15: 110.1 | N15: 110.6 | O15: 110.3 | P15: 110.2 | Q15: 110.8
A16: 1996 | B16: 110.5 | C16: 110.2 | D16: 109.7 | E16: 110.4 | F16: 110.4 | G16: 111.3 | H16: 109.8 | I16: 110.5 | J16: 111 | K16: 109 | L16: 110.4 | M16: 109.4 | N16: 109.3 | O16: 109.7 | P16: 111.6 | Q16: 109.8
A17: 1997 | B17: 108.6 | C17: 110 | D17: 108.1 | E17: 108 | F17: 108.7 | G17: 109.8 | H17: 107.4 | I17: 109 | J17: 112.1 | K17: 109 | L17: 108.8 | M17: 106.8 | N17: 108.7 | O17: 109.1 | P17: 107.4 | Q17: 107.5
A18: 1998 | B18: 107.5 | C18: 107.8 | D18: 106.8 | E18: 107.5 | F18: 107.7 | G18: 107.3 | H18: 107.6 | I18: 107.9 | J18: 107.6 | K18: 108 | L18: 107.5 | M18: 106.4 | N18: 106.5 | O18: 109 | P18: 107 | Q18: 106.4
A19: 1999 | B19: 106.4 | C19: 105.7 | D19: 106.6 | E19: 106.1 | F19: 106.8 | G19: 105.6 | H19: 106.9 | I19: 106.4 | J19: 104.9 | K19: 105.9 | L19: 106.2 | M19: 107.1 | N19: 106.4 | O19: 105.4 | P19: 106.5 | Q19: 106.3
A20: 2000 | B20: 107.7 | C20: 106.7 | D20: 106.5 | E20: 106.7 | F20: 106.9 | G20: 107.2 | H20: 109 | I20: 106.9 | J20: 106.3 | K20: 106.9 | L20: 105.5 | M20: 106.7 | N20: 107.3 | O20: 106.8 | P20: 106.2 | Q20: 107.2
A21: 2001 | B21: 106.2 | C21: 106.1 | D21: 105.3 | E21: 105.9 | F21: 106.9 | G21: 105.7 | H21: 105.9 | I21: 105.5 | J21: 106.4 | K21: 106.3 | L21: 105.2 | M21: 105.4 | N21: 105.3 | O21: 105.9 | P21: 106.8 | Q21: 105
... A36: 2016 | B36: 100.7 | C36: 99.2 | D36: 99 | E36: 99 | F36: 99.8 | G36: 100.4 | H36: 101.8 | I36: 99.4 | J36: 98.5 | K36: 99.8 | L36: 98.1 | M36: 99.2 | N36: 99.8 | O36: 98.2 | P36: 99.3 | Q36: 99.4
A37: 2017 | B37: 99.5 | C37: 99.4 | F37: 98.7 | G37: 99.8 | H37: 100.1 | I37: 98.7 | J37: 99.6 | K37: 99.8 | L37: 97.6
A74: 毎月勤労統計調査(MONTHLY LABOUR SURVEY) | F74: 季節調整済労働時間指数(Seasonally adjusted hours worked indices) 総実労働時間(Total hours worked)
A75: 事業所規模(Size of establishments)： | F75: ５人以上(Establishments with 5 employees or more)
A76: 就業形態(Type of Employment): | F76: 就業形態計(Total)
A77: 産業(Industry): | F77: 調査産業計(Industries covered)
A79: 前期比(Ratio to the preceding month or quarter)：％(%)
A80: 年 | B80: 1-3 | C80: 4-6 | D80: 7-9 | E80: 10-12 | F80: 1 | G80: 2 | H80: 3 | I80: 4 | J80: 5 | K80: 6 | L80: 7 | M80: 8 | N80: 9 | O80: 10 | P80: 11 | Q80: 12
A81: year | B81: 第１四半期 | C81: 第２四半期 | D81: 第３四半期 | E81: 第４四半期 | F81: １月 | G81: ２月 | H81: ３月 | I81: ４月 | J81: ５月 | K81: ６月 | L81: ７月 | M81: ８月 | N81: ９月 | O81: １０月 | P81: １１月 | Q81: １２月
B82: 1st Qr. | C82: 2nd Qr. | D82: 3rd Qr. | E82: 4th Qr. | F82: Jan. | G82: Feb. | H82: Mar. | I82: Apr. | J82: May | K82: Jun. | L82: Jul. | M82: Aug. | N82: Sep. | O82: Oct. | P82: Nov. | Q82: Dec.
A83: 1990 | B83: - | C83: -0.3 | D83: -0.7 | E83: -0.3 | F83: - | G83: -1.7 | H83: 0.8 | I83: -0.4 | J83: 0.3 | K83: 0.1 | L83: -1.1 | M83: 0.6 | N83: -0.4 | O83: 0.4 | P83: -1.1 | Q83: 0.4
A84: 1991 | B84: -1 | C84: -0.4 | D84: -0.6 | E84: 0 | F84: -0.8 | G84: 0.6 | H84: -1.6 | I84: 0.8 | J84: 0.3 | K84: -1.6 | L84: 1.1 | M84: -1.1 | N84: 0 | O84: 0.3 | P84: 0.6 | Q84: -0.9
A85: 1992 | B85: -0.8 | C85: -0.5 | D85: -1.3 | E85: 0 | F85: -0.7 | G85: 1 | H85: -1 | I85: 0 | J85: -0.3 | K85: 0.1 | L85: -0.4 | M85: -1.8 | N85: 0.8 | O85: 2.1 | P85: -3 | Q85: -0.1
A86: 1993 | B86: -1.1 | C86: -1.3 | D86: 0.5 | E86: -0.6 | F86: 0.2 | G86: -0.7 | H86: 0.9 | I86: 0.4 | J86: -3 | K86: -0.3 | L86: 2 | M86: -0.4 | N86: 0 | O86: -0.6 | P86: 0.5 | Q86: -0.6
A87: 1994 | B87: 0.5 | C87: -0.9 | D87: 0.7 | E87: -0.1 | F87: 2.4 | G87: -2.9 | H87: 1 | I87: 0 | J87: -2 | K87: 2.1 | L87: -0.5 | M87: 1 | N87: -0.4 | O87: -0.7 | P87: 0.6 | Q87: 0.4
A88: 1995 | B88: 0.1 | C88: -0.4 | D88: 0.4 | E88: 0.3 | F88: -0.5 | G88: 0.2 | H88: 0 | I88: -0.8 | J88: 0.1 | K88: 1 | L88: -0.9 | M88: 0.5 | N88: 0.5 | O88: -0.3 | P88: -0.1 | Q88: 0.5
A89: 1996 | B89: 0.1 | C89: -0.3 | D89: -0.5 | E89: 0.6 | F89: -0.4 | G89: 0.8 | H89: -1.3 | I89: 0.6 | J89: 0.5 | K89: -1.8 | L89: 1.3 | M89: -0.9 | N89: -0.1 | O89: 0.4 | P89: 1.7 | Q89: -1.6
A90: 1997 | B90: -1.6 | C90: 1.3 | D90: -1.7 | E90: -0.1 | F90: -1 | G90: 1 | H90: -2.2 | I90: 1.5 | J90: 2.8 | K90: -2.8 | L90: -0.2 | M90: -1.8 | N90: 1.8 | O90: 0.4 | P90: -1.6 | Q90: 0.1
A91: 1998 | B91: -0.5 | C91: 0.3 | D91: -0.9 | E91: 0.7 | F91: 0.2 | G91: -0.4 | H91: 0.3 | I91: 0.3 | J91: -0.3 | K91: 0.4 | L91: -0.5 | M91: -1 | N91: 0.1 | O91: 2.3 | P91: -1.8 | Q91: -0.6
A92: 1999 | B92: -1 | C92: -0.7 | D92: 0.9 | E92: -0.5 | F92: 0.4 | G92: -1.1 | H92: 1.2 | I92: -0.5 | J92: -1.4 | K92: 1 | L92: 0.3 | M92: 0.8 | N92: -0.7 | O92: -0.9 | P92: 1 | Q92: -0.2
A93: 2000 | B93: 1.5 | C93: -0.9 | D93: -0.2 | E93: 0.2 | F93: 0.6 | G93: 0.3 | H93: 1.7 | I93: -1.9 | J93: -0.6 | K93: 0.6 | L93: -1.3 | M93: 1.1 | N93: 0.6 | O93: -0.5 | P93: -0.6 | Q93: 0.9
A94: 2001 | B94: -0.5 | C94: -0.1 | D94: -0.8 | E94: 0.6 | F94: -0.3 | G94: -1.1 | H94: 0.2 | I94: -0.4 | J94: 0.9 | K94: -0.1 | L94: -1 | M94: 0.2 | N94: -0.1 | O94: 0.6 | P94: 0.8 | Q94: -1.7
A95: 2002 | B95: -1.5 | C95: 0.5 | D95: 0.2 | E95: 0.3 | F95: -1.1 | G95: 1.3 | H95: -1.1 | I95: 0.7 | J95: 1.1 | K95: -1.9 | L95: 2 | M95: -0.9 | N95: -0.6 | O95: 1 | P95: 0.6 | Q95: -1.1
