Workbook
Name IQ_CH: 110000
Name IQ_CQ: 5000
Name IQ_CY: 10000
Name IQ_DAILY: 500000
Name IQ_FH: 100000
Name IQ_FQ: 500
Name IQ_FY: 1000
Name IQ_LTM: 2000
Name IQ_MONTH: 15000
Name IQ_NTM: 6000
Name IQ_WEEK: 50000
Name IQ_YTD: 3000
Name KAN: [1]台風10号!#REF!
Name KIN: [1]台風10号!#REF!
Name NAKA: [1]台風10号!#REF!
Name OA: [1]台風10号!#REF!

Sheet ReadMe
A1: ＜使用している系列＞
A2: 変数名 | B2: 系列名 | C2: 元データ | D2: データシート | F2: ＜推計期間＞
A3: l_pi_c | B3: GDPデフレーター、前期比 | C3: 内閣府 | D3: ・rG（Real GDP、Quarterly、SAAR） ・nG（名目GDP、Quarterly、SAAR） | F3: From | G3: 29587
A4: l_IC | B4: 一人あたり民間企業設備、前期比 | C4: 内閣府、FERIS | D4: ・rG（Private Non-resi. Investment、Quarterly、SAAR） ・L | F4: To | G4: 43830
A5: l_pi_d | B5: 設備投資デフレーター、前期比 | C5: 内閣府 | D5: ・nG（Private Non-resi. Investment、Quarterly、SAAR） ・rG（Private Non-resi. Investment、Quarterly、SAAR）
A6: l_Output | B6: 一人あたりGDP、前期比 | C6: 内閣府、FERIS | D6: ・rG（Real GDP、Quarterly、SAAR） ・L
A7: l_HC | B7: 一人あたり労働時間、前期比 | C7: FERIS | D7: ・HC ・L
A8: l_WC | B8: 労働時間あたり雇用者報酬、前期比 | C8: FERIS | D8: ・HC ・W
A9: l_NSR | B9: O/N無担保コール | C9: FERIS | D9: ・NSR
A10: l_NB | B10: 一人あたり株式・出資金（銀行）、前期比 | C10: FERIS、 TSE | D10: ・FoF ・TSE
A11: l_NEC | B11: 一人あたり株式・出資金（全産業除く金融）、前期比 | C11: FERIS、 TSE | D11: ・FoF ・TSE
A12: fdr、edr | B12: 水害（地震）に伴う資本ストックの毀損率 | C12: 水害統計、内閣府など | D12: ・KC ・Prec

Sheet Est_Input
A1: 0.0027846044 | B1: -0.00045873031 | C1: 0.0067402807 | D1: 0.0010552605 | E1: -0.0017642513 | F1: 0.0052390651 | G1: 0.016002831 | H1: 0.05879122 | I1: 0.032692788 | J1: 0.0016402926 | K1: 1.8811945e-06 | L1: 0 | M1: 1.8816085e-05 | N1: 0
A2: 0.0048072759 | B2: -0.0054417691 | C2: -0.0015149499 | D2: 0.0037915402 | E2: 0.0020069905 | F2: 0.016392131 | G2: 0.012639809 | H2: 0.072590823 | I2: 0.098415782 | J2: 0.0026641167 | K2: 1.0176172e-05 | L2: 0 | M2: 0.0001021931 | N2: 0
A3: 0.0037623024 | B3: 0.0045618017 | C3: 0.00081389227 | D3: -0.0021157097 | E3: -0.0014346438 | F3: 0.0058348398 | G3: 0.012956657 | H3: 0.030722605 | I3: 0.009251296 | J3: -0.0021738097 | K3: 0.00012791863 | L3: 0 | M3: 0.0012825875 | N3: 0
A4: 0.0079386769 | B4: 0.011694605 | C4: 0.0035634008 | D4: -0.00064836801 | E4: 0.0063245614 | F4: 0.015599714 | G4: 0.011985728 | H4: 0.029128466 | I4: -0.050158192 | J4: -0.0034848393 | K4: 3.3841984e-05 | L4: 0 | M4: 0.00033680802 | N4: 0
A5: 0.0081071171 | B5: -0.029581005 | C5: 0.011339683 | D5: 0.0070776947 | E5: -0.0054675138 | F5: -0.0041615862 | G5: 0.011400246 | H5: 0.049196286 | I5: -0.027728394 | J5: 0.01276377 | K5: 3.7262107e-09 | L5: 0 | M5: 1.2790655e-08 | N5: 0
A6: -0.0017829102 | B6: 0.01737315 | C6: -0.0079526696 | D6: -0.00044101021 | E6: -0.00071596527 | F6: 0.010874336 | G6: 0.012766229 | H6: -0.0045379114 | I6: -0.040252156 | J6: -0.0011657143 | K6: 7.9622957e-07 | L6: 0 | M6: 2.7419417e-06 | N6: 0
A7: 0.0039362704 | B7: -0.0096227948 | C7: 0.0079068257 | D7: -0.0033082036 | E7: 0.004771704 | F7: 0.0022155584 | G7: 0.012635611 | H7: -0.010734414 | I7: -0.046932758 | J7: -0.0061293065 | K7: 0.00043801327 | L7: 0 | M7: 0.0015062354 | N7: 0
A8: -0.0017421231 | B8: -0.021995012 | C8: 0.0047791871 | D8: 0.0072819017 | E8: -0.0015997993 | F8: 0.0075961307 | G8: 0.011963804 | H8: 0.030739889 | I8: 0.081193306 | J8: 0.0068826866 | K8: 1.5471717e-05 | L8: 0 | M8: 5.2835882e-05 | N8: 0
A9: 0.0072469827 | B9: 0.00046590275 | C9: 0.0033124437 | D9: -0.002163038 | E9: 0.0013975164 | F9: 0.0080853081 | G9: 0.011464503 | H9: 0.024165133 | I9: 0.039893613 | J9: -0.00093952474 | K9: 7.256219e-08 | L9: 0 | M9: 7.553346e-07 | N9: 0
A10: 0.00092317972 | B10: 0.022306377 | C10: -0.0077632074 | D10: 0.0012869666 | E10: 0.0032787662 | F10: -0.0082680848 | G10: 0.010381764 | H10: 0.012528124 | I10: 0.069357062 | J10: -0.00046467901 | K10: 1.4628971e-05 | L10: 0 | M10: 0.0001526301 | N10: 0
A11: -0.00015568745 | B11: -0.01027704 | C11: -0.0013800356 | D11: 0.0063601784 | E11: 0.0010896921 | F11: 0.0067557518 | G11: 0.01103424 | H11: 0.00065364744 | I11: 0.066873936 | J11: 0.0049601218 | K11: 0.00011627605 | L11: 0 | M11: 0.0012102654 | N11: 0
A12: 0.0033201735 | B12: -0.0043510189 | C12: -4.5299758e-05 | D12: 0.00012712574 | E12: -0.002254558 | F12: 0.000990176 | G12: 0.010607817 | H12: 0.0022150482 | I12: 0.038466924 | J12: 0.0024938241 | K12: 3.0948793e-07 | L12: 0 | M12: 3.198023e-06 | N12: 0
... A156: -0.0026108453 | B156: -0.049459531 | C156: 0.0019070804 | D156: -0.022890649 | E156: -0.0035349156 | F156: 0.0068009114 | G156: -0.0051493551 | H156: 0.079399644 | I156: 0.070758789 | J156: -0.020385128 | K156: 0.0011271662 | L156: 0 | M156: 0.00071660115 | N156: 0

Sheet x-form->

Sheet G
B2: (1) 実質GDP | C2: (2) 実質民間設備投資
B5: (3) インフレ率 | C5: (4) 資本財価格
B8: (5) 名目雇用者報酬（時間当たり） | C8: (6) 労働時間
B12: (7) 政策金利 | C12: (8) ソロー残差
B15: (9) 銀行の実質純資産 | C15: (10) 企業の実質純資産
B18: (11) 水害による民間資本毀損率 | C18: (12) 水害による公的資本毀損率

Sheet E
B2: (1) Real GDP | C2: (2) Real investment
B5: (3) GDP deflator | C5: (4) Investment deflator
B8: (5) Nominal wage | C8: (6) Working hours
B12: (7) Policy rate | C12: (8) Measured TFP (Solow residuals)
B15: (9) Real net worth in FI sector | C15: (10) Real net worth in goods-producing sector
B18: (11) Flood-related capital depreciation rate

Sheet Gdata
B1: =ReadMe!G3 -> 29587 | D1: Aggregate | P1: Additional
B2: =ReadMe!G4 -> 43830 | C2: Avg.
C3: Std
B4: Quarter | C4: Q Name | D4: GDP | E4: I | F4: Pi | G4: QC | H4: W | I4: L | J4: R | K4: Solow | L4: NB | M4: NEC | N4: fdr | O4: fdr_p | P4: Business Cycle
B5: 29221 | C5: =YEAR(B5)&"Q"&QUOTIENT(MONTH(B5)-1,3)+1 -> 1980Q1 | P5: 500 | Q5: 0
B6: =EDATE(B5,3) -> 29312 | C6: =YEAR(B6)&"Q"&QUOTIENT(MONTH(B6)-1,3)+1 -> 1980Q2 | P6: 500 | Q6: 0
B7: =EDATE(B6,3) -> 29403 | C7: =YEAR(B7)&"Q"&QUOTIENT(MONTH(B7)-1,3)+1 -> 1980Q3 | P7: 500 | Q7: 0
B8: =EDATE(B7,3) -> 29495 | C8: =YEAR(B8)&"Q"&QUOTIENT(MONTH(B8)-1,3)+1 -> 1980Q4 | P8: 500 | Q8: 0
A9: =RIGHT(YEAR(B9),2) -> 81 | B9: =EDATE(B8,3) -> 29587 | C9: =YEAR(B9)&"Q"&QUOTIENT(MONTH(B9)-1,3)+1 -> 1981Q1 | D9: =LN(l_Output!C7/l_Output!C3)*100 -> 3.296717 | E9: =LN('l_IC,pi_d'!D7/'l_IC,pi_d'!D3)*100 -> 2.7721612 | F9: =LN(l_pi_c!G7/l_pi_c!G3)*100 -> 4.8680664 | G9: =LN('l_IC,pi_d'!F7/'l_IC,pi_d'!F3)*100 -> 3.9687634 | H9: =LN('l_HC,WC'!M7/'l_HC,WC'!M3)*100 -> 8.6786525 | I9: =LN('l_HC,WC'!K7/'l_HC,WC'!K3)*100 -> -0.73343186 | J9: =l_NSR!B7 -> 8.6965703 | K9: =LN(l_Solow!H7/l_Solow!H3)*100 -> 4.0875575 | L9: =LN('l_NB,NEC'!O7/'l_NB,NEC'!O3)*100 -> 9.6122625 | M9: =LN('l_NB,NEC'!P7/'l_NB,NEC'!P3)*100 -> 14.262669 | N9: ='fdr,edr'!S7*10000 -> 0.018811945 | O9: ='fdr,edr (TFP)'!S7*10000 -> 0.18816085 | P9: 500 | Q9: 0
B10: =EDATE(B9,3) -> 29677 | C10: =YEAR(B10)&"Q"&QUOTIENT(MONTH(B10)-1,3)+1 -> 1981Q2 | D10: =LN(l_Output!C8/l_Output!C4)*100 -> 5.115387 | E10: =LN('l_IC,pi_d'!D8/'l_IC,pi_d'!D4)*100 -> 2.1983172 | F10: =LN(l_pi_c!G8/l_pi_c!G4)*100 -> 2.7712212 | G10: =LN('l_IC,pi_d'!F8/'l_IC,pi_d'!F4)*100 -> 1.7348448 | H10: =LN('l_HC,WC'!M8/'l_HC,WC'!M4)*100 -> 9.0083155 | I10: =LN('l_HC,WC'!K8/'l_HC,WC'!K4)*100 -> -0.67763672 | J10: =l_NSR!B8 -> 7.2716017 | K10: =LN(l_Solow!H8/l_Solow!H4)*100 -> 5.1345523 | L10: =LN('l_NB,NEC'!O8/'l_NB,NEC'!O4)*100 -> 16.706818 | M10: =LN('l_NB,NEC'!P8/'l_NB,NEC'!P4)*100 -> 23.730491 | N10: ='fdr,edr'!S8*10000 -> 0.10176172 | O10: ='fdr,edr (TFP)'!S8*10000 -> 1.021931 | P10: 500 | Q10: 0
B11: =EDATE(B10,3) -> 29768 | C11: =YEAR(B11)&"Q"&QUOTIENT(MONTH(B11)-1,3)+1 -> 1981Q3 | D11: =LN(l_Output!C9/l_Output!C5)*100 -> 3.5260051 | E11: =LN('l_IC,pi_d'!D9/'l_IC,pi_d'!D5)*100 -> 3.9366105 | F11: =LN(l_pi_c!G9/l_pi_c!G5)*100 -> 2.1021767 | G11: =LN('l_IC,pi_d'!F9/'l_IC,pi_d'!F5)*100 -> 0.35175004 | H11: =LN('l_HC,WC'!M9/'l_HC,WC'!M5)*100 -> 6.3450647 | I11: =LN('l_HC,WC'!K9/'l_HC,WC'!K5)*100 -> -0.10861854 | J11: =l_NSR!B9 -> 7.4052542 | K11: =LN(l_Solow!H9/l_Solow!H5)*100 -> 2.9328786 | L11: =LN('l_NB,NEC'!O9/'l_NB,NEC'!O5)*100 -> 18.416873 | M11: =LN('l_NB,NEC'!P9/'l_NB,NEC'!P5)*100 -> 23.238006 | N11: ='fdr,edr'!S9*10000 -> 1.2791863 | O11: ='fdr,edr (TFP)'!S9*10000 -> 12.825875 | P11: 500 | Q11: 0
B12: =EDATE(B11,3) -> 29860 | C12: =YEAR(B12)&"Q"&QUOTIENT(MONTH(B12)-1,3)+1 -> 1981Q4 | D12: =LN(l_Output!C10/l_Output!C6)*100 -> 2.0577792 | E12: =LN('l_IC,pi_d'!D10/'l_IC,pi_d'!D6)*100 -> 3.1943465 | F12: =LN(l_pi_c!G10/l_pi_c!G6)*100 -> 1.9813789 | G12: =LN('l_IC,pi_d'!F10/'l_IC,pi_d'!F6)*100 -> 0.53709854 | H12: =LN('l_HC,WC'!M10/'l_HC,WC'!M6)*100 -> 6.4558006 | I12: =LN('l_HC,WC'!K10/'l_HC,WC'!K6)*100 -> 0.52211624 | J12: =l_NSR!B10 -> 6.9960924 | K12: =LN(l_Solow!H10/l_Solow!H6)*100 -> 1.0501934 | L12: =LN('l_NB,NEC'!O10/'l_NB,NEC'!O6)*100 -> 20.14227 | M12: =LN('l_NB,NEC'!P10/'l_NB,NEC'!P6)*100 -> 14.881329 | N12: ='fdr,edr'!S10*10000 -> 0.33841984 | O12: ='fdr,edr (TFP)'!S10*10000 -> 3.3680802 | P12: 500 | Q12: 0
B13: =EDATE(B12,3) -> 29952 | C13: =YEAR(B13)&"Q"&QUOTIENT(MONTH(B13)-1,3)+1 -> 1982Q1 | D13: =LN(l_Output!C11/l_Output!C7)*100 -> 2.6600226 | E13: =LN('l_IC,pi_d'!D11/'l_IC,pi_d'!D7)*100 -> 0.28211899 | F13: =LN(l_pi_c!G11/l_pi_c!G7)*100 -> 2.5136301 | G13: =LN('l_IC,pi_d'!F11/'l_IC,pi_d'!F7)*100 -> 0.99703873 | H13: =LN('l_HC,WC'!M11/'l_HC,WC'!M7)*100 -> 5.5157355 | I13: =LN('l_HC,WC'!K11/'l_HC,WC'!K7)*100 -> 0.15179 | J13: =l_NSR!B11 -> 6.749928 | K13: =LN(l_Solow!H11/l_Solow!H7)*100 -> 2.1625412 | L13: =LN('l_NB,NEC'!O11/'l_NB,NEC'!O7)*100 -> 19.182776 | M13: =LN('l_NB,NEC'!P11/'l_NB,NEC'!P7)*100 -> 8.8392107 | N13: ='fdr,edr'!S11*10000 -> 3.7262107e-05 | O13: ='fdr,edr (TFP)'!S11*10000 -> 0.00012790655 | P13: 500 | Q13: 0
B14: =EDATE(B13,3) -> 30042 | C14: =YEAR(B14)&"Q"&QUOTIENT(MONTH(B14)-1,3)+1 -> 1982Q2 | D14: =LN(l_Output!C12/l_Output!C8)*100 -> 2.2367676 | E14: =LN('l_IC,pi_d'!D12/'l_IC,pi_d'!D8)*100 -> 2.5636109 | F14: =LN(l_pi_c!G12/l_pi_c!G8)*100 -> 1.8546115 | G14: =LN('l_IC,pi_d'!F12/'l_IC,pi_d'!F8)*100 -> 0.35326676 | H14: =LN('l_HC,WC'!M12/'l_HC,WC'!M8)*100 -> 4.9639559 | I14: =LN('l_HC,WC'!K12/'l_HC,WC'!K8)*100 -> -0.12050558 | J14: =l_NSR!B12 -> 7.3249129 | K14: =LN(l_Solow!H12/l_Solow!H8)*100 -> 1.7795581 | L14: =LN('l_NB,NEC'!O12/'l_NB,NEC'!O8)*100 -> 11.469903 | M14: =LN('l_NB,NEC'!P12/'l_NB,NEC'!P8)*100 -> -5.0275832 | N14: ='fdr,edr'!S12*10000 -> 0.0079622957 | O14: ='fdr,edr (TFP)'!S12*10000 -> 0.027419417 | P14: 500 | Q14: 0
B15: =EDATE(B14,3) -> 30133 | C15: =YEAR(B15)&"Q"&QUOTIENT(MONTH(B15)-1,3)+1 -> 1982Q3 | D15: =LN(l_Output!C13/l_Output!C9)*100 -> 2.1175182 | E15: =LN('l_IC,pi_d'!D13/'l_IC,pi_d'!D9)*100 -> 1.1451512 | F15: =LN(l_pi_c!G13/l_pi_c!G9)*100 -> 1.8720083 | G15: =LN('l_IC,pi_d'!F13/'l_IC,pi_d'!F9)*100 -> 1.0625601 | H15: =LN('l_HC,WC'!M13/'l_HC,WC'!M9)*100 -> 4.6020278 | I15: =LN('l_HC,WC'!K13/'l_HC,WC'!K9)*100 -> 0.5001292 | J15: =l_NSR!B13 -> 7.2698315 | K15: =LN(l_Solow!H13/l_Solow!H9)*100 -> 1.3840084 | L15: =LN('l_NB,NEC'!O13/'l_NB,NEC'!O9)*100 -> 7.324201 | M15: =LN('l_NB,NEC'!P13/'l_NB,NEC'!P9)*100 -> -10.645989 | N15: ='fdr,edr'!S13*10000 -> 4.3801327 | O15: ='fdr,edr (TFP)'!S13*10000 -> 15.062354 | P15: 500 | Q15: 0
B16: =EDATE(B15,3) -> 30225 | C16: =YEAR(B16)&"Q"&QUOTIENT(MONTH(B16)-1,3)+1 -> 1982Q4 | D16: =LN(l_Output!C14/l_Output!C10)*100 -> 2.9105452 | E16: =LN('l_IC,pi_d'!D14/'l_IC,pi_d'!D10)*100 -> -2.2238105 | F16: =LN(l_pi_c!G14/l_pi_c!G10)*100 -> 0.90392833 | G16: =LN('l_IC,pi_d'!F14/'l_IC,pi_d'!F10)*100 -> 1.1841387 | H16: =LN('l_HC,WC'!M14/'l_HC,WC'!M10)*100 -> 3.8016694 | I16: =LN('l_HC,WC'!K14/'l_HC,WC'!K10)*100 -> -0.29230687 | J16: =l_NSR!B14 -> 6.9868667 | K16: =LN(l_Solow!H14/l_Solow!H10)*100 -> 2.420761 | L16: =LN('l_NB,NEC'!O14/'l_NB,NEC'!O10)*100 -> 7.4853433 | M16: =LN('l_NB,NEC'!P14/'l_NB,NEC'!P10)*100 -> 2.4891612 | N16: ='fdr,edr'!S14*10000 -> 0.15471717 | O16: ='fdr,edr (TFP)'!S14*10000 -> 0.52835882 | P16: 500 | Q16: 0
B17: =EDATE(B16,3) -> 30317 | C17: =YEAR(B17)&"Q"&QUOTIENT(MONTH(B17)-1,3)+1 -> 1983Q1 | D17: =LN(l_Output!C15/l_Output!C11)*100 -> 1.9864719 | E17: =LN('l_IC,pi_d'!D15/'l_IC,pi_d'!D11)*100 -> 0.7808803 | F17: =LN(l_pi_c!G15/l_pi_c!G11)*100 -> 0.8179149 | G17: =LN('l_IC,pi_d'!F15/'l_IC,pi_d'!F11)*100 -> 0.38141484 | H17: =LN('l_HC,WC'!M15/'l_HC,WC'!M11)*100 -> 5.0263589 | I17: =LN('l_HC,WC'!K15/'l_HC,WC'!K11)*100 -> 0.39419614 | J17: =l_NSR!B15 -> 6.7769241 | K17: =LN(l_Solow!H15/l_Solow!H11)*100 -> 1.0504315 | L17: =LN('l_NB,NEC'!O15/'l_NB,NEC'!O11)*100 -> 4.9822279 | M17: =LN('l_NB,NEC'!P15/'l_NB,NEC'!P11)*100 -> 9.2513619 | N17: ='fdr,edr'!S15*10000 -> 0.0007256219 | O17: ='fdr,edr (TFP)'!S15*10000 -> 0.007553346 | P17: 500 | Q17: 0
B18: =EDATE(B17,3) -> 30407 | C18: =YEAR(B18)&"Q"&QUOTIENT(MONTH(B18)-1,3)+1 -> 1983Q2 | D18: =LN(l_Output!C16/l_Output!C12)*100 -> 2.1592696 | E18: =LN('l_IC,pi_d'!D16/'l_IC,pi_d'!D12)*100 -> 1.2742031 | F18: =LN(l_pi_c!G16/l_pi_c!G12)*100 -> 1.0885239 | G18: =LN('l_IC,pi_d'!F16/'l_IC,pi_d'!F12)*100 -> 0.40036105 | H18: =LN('l_HC,WC'!M16/'l_HC,WC'!M12)*100 -> 3.1121168 | I18: =LN('l_HC,WC'!K16/'l_HC,WC'!K12)*100 -> 0.79366928 | J18: =l_NSR!B16 -> 6.3227234 | K18: =LN(l_Solow!H16/l_Solow!H12)*100 -> 1.120535 | L18: =LN('l_NB,NEC'!O16/'l_NB,NEC'!O12)*100 -> 6.6888314 | M18: =LN('l_NB,NEC'!P16/'l_NB,NEC'!P12)*100 -> 20.212284 | N18: ='fdr,edr'!S16*10000 -> 0.14628971 | O18: ='fdr,edr (TFP)'!S16*10000 -> 1.526301 | Q18: 0
B19: =EDATE(B18,3) -> 30498 | C19: =YEAR(B19)&"Q"&QUOTIENT(MONTH(B19)-1,3)+1 -> 1983Q3 | D19: =LN(l_Output!C17/l_Output!C13)*100 -> 3.1261078 | E19: =LN('l_IC,pi_d'!D17/'l_IC,pi_d'!D13)*100 -> 1.2087785 | F19: =LN(l_pi_c!G17/l_pi_c!G13)*100 -> 0.6793281 | G19: =LN('l_IC,pi_d'!F17/'l_IC,pi_d'!F13)*100 -> -0.52832507 | H19: =LN('l_HC,WC'!M17/'l_HC,WC'!M13)*100 -> 3.5661362 | I19: =LN('l_HC,WC'!K17/'l_HC,WC'!K13)*100 -> 0.42546809 | J19: =l_NSR!B17 -> 6.5962583 | K19: =LN(l_Solow!H17/l_Solow!H13)*100 -> 2.2294779 | L19: =LN('l_NB,NEC'!O17/'l_NB,NEC'!O13)*100 -> 7.8276376 | M19: =LN('l_NB,NEC'!P17/'l_NB,NEC'!P13)*100 -> 31.592953 | N19: ='fdr,edr'!S17*10000 -> 1.1627605 | O19: ='fdr,edr (TFP)'!S17*10000 -> 12.102654 | Q19: 0
B20: =EDATE(B19,3) -> 30590 | C20: =YEAR(B20)&"Q"&QUOTIENT(MONTH(B20)-1,3)+1 -> 1983Q4 | D20: =LN(l_Output!C18/l_Output!C14)*100 -> 2.4106302 | E20: =LN('l_IC,pi_d'!D18/'l_IC,pi_d'!D14)*100 -> 2.9731779 | F20: =LN(l_pi_c!G18/l_pi_c!G14)*100 -> 1.1855578 | G20: =LN('l_IC,pi_d'!F18/'l_IC,pi_d'!F14)*100 -> -1.0107738 | H20: =LN('l_HC,WC'!M18/'l_HC,WC'!M14)*100 -> 2.9055407 | I20: =LN('l_HC,WC'!K18/'l_HC,WC'!K14)*100 -> 0.35999222 | J20: =l_NSR!B18 -> 6.4174308 | K20: =LN(l_Solow!H18/l_Solow!H14)*100 -> 1.7905916 | L20: =LN('l_NB,NEC'!O18/'l_NB,NEC'!O14)*100 -> 4.9751535 | M20: =LN('l_NB,NEC'!P18/'l_NB,NEC'!P14)*100 -> 27.320315 | N20: ='fdr,edr'!S18*10000 -> 0.0030948793 | O20: ='fdr,edr (TFP)'!S18*10000 -> 0.03198023 | Q20: 0
B21: =EDATE(B20,3) -> 30682 | C21: =YEAR(B21)&"Q"&QUOTIENT(MONTH(B21)-1,3)+1 -> 1984Q1 | D21: =LN(l_Output!C19/l_Output!C15)*100 -> 3.035957 | E21: =LN('l_IC,pi_d'!D19/'l_IC,pi_d'!D15)*100 -> 5.5271422 | F21: =LN(l_pi_c!G19/l_pi_c!G15)*100 -> 1.0490767 | G21: =LN('l_IC,pi_d'!F19/'l_IC,pi_d'!F15)*100 -> -1.2716886 | H21: =LN('l_HC,WC'!M19/'l_HC,WC'!M15)*100 -> 2.2097883 | I21: =LN('l_HC,WC'!K19/'l_HC,WC'!K15)*100 -> 1.0686317 | J21: =l_NSR!B19 -> 6.3133616 | K21: =LN(l_Solow!H19/l_Solow!H15)*100 -> 1.9347712 | L21: =LN('l_NB,NEC'!O19/'l_NB,NEC'!O15)*100 -> 38.187069 | M21: =LN('l_NB,NEC'!P19/'l_NB,NEC'!P15)*100 -> 31.703858 | N21: ='fdr,edr'!S19*10000 -> 0.00074510278 | O21: ='fdr,edr (TFP)'!S19*10000 -> 0.0080741185 | Q21: 0
B22: =EDATE(B21,3) -> 30773 | C22: =YEAR(B22)&"Q"&QUOTIENT(MONTH(B22)-1,3)+1 -> 1984Q2 | D22: =LN(l_Output!C20/l_Output!C16)*100 -> 4.076201 | E22: =LN('l_IC,pi_d'!D20/'l_IC,pi_d'!D16)*100 -> 3.8615445 | F22: =LN(l_pi_c!G20/l_pi_c!G16)*100 -> 1.1989803 | G22: =LN('l_IC,pi_d'!F20/'l_IC,pi_d'!F16)*100 -> -0.19495964 | H22: =LN('l_HC,WC'!M20/'l_HC,WC'!M16)*100 -> 4.2942683 | I22: =LN('l_HC,WC'!K20/'l_HC,WC'!K16)*100 -> 0.42079363 | J22: =l_NSR!B20 -> 5.9687111 | K22: =LN(l_Solow!H20/l_Solow!H16)*100 -> 3.4527965 | L22: =LN('l_NB,NEC'!O20/'l_NB,NEC'!O16)*100 -> 47.581958 | M22: =LN('l_NB,NEC'!P20/'l_NB,NEC'!P16)*100 -> 21.40981 | N22: ='fdr,edr'!S20*10000 -> 0.83741228 | O22: ='fdr,edr (TFP)'!S20*10000 -> 9.0863814 | Q22: 0
B23: =EDATE(B22,3) -> 30864 | C23: =YEAR(B23)&"Q"&QUOTIENT(MONTH(B23)-1,3)+1 -> 1984Q3 | D23: =LN(l_Output!C21/l_Output!C17)*100 -> 3.4739641 | E23: =LN('l_IC,pi_d'!D21/'l_IC,pi_d'!D17)*100 -> 7.9604454 | F23: =LN(l_pi_c!G21/l_pi_c!G17)*100 -> 1.6301791 | G23: =LN('l_IC,pi_d'!F21/'l_IC,pi_d'!F17)*100 -> 0.69798083 | H23: =LN('l_HC,WC'!M21/'l_HC,WC'!M17)*100 -> 3.7589327 | I23: =LN('l_HC,WC'!K21/'l_HC,WC'!K17)*100 -> -0.10524092 | J23: =l_NSR!B21 -> 6.2837443 | K23: =LN(l_Solow!H21/l_Solow!H17)*100 -> 3.3117531 | L23: =LN('l_NB,NEC'!O21/'l_NB,NEC'!O17)*100 -> 41.834149 | M23: =LN('l_NB,NEC'!P21/'l_NB,NEC'!P17)*100 -> 14.014149 | N23: ='fdr,edr'!S21*10000 -> 0.39354193 | O23: ='fdr,edr (TFP)'!S21*10000 -> 4.2708745 | Q23: 0
B24: =EDATE(B23,3) -> 30956 | C24: =YEAR(B24)&"Q"&QUOTIENT(MONTH(B24)-1,3)+1 -> 1984Q4 | D24: =LN(l_Output!C22/l_Output!C18)*100 -> 3.156924 | E24: =LN('l_IC,pi_d'!D22/'l_IC,pi_d'!D18)*100 -> 11.173818 | F24: =LN(l_pi_c!G22/l_pi_c!G18)*100 -> 1.9117243 | G24: =LN('l_IC,pi_d'!F22/'l_IC,pi_d'!F18)*100 -> 1.1866407 | H24: =LN('l_HC,WC'!M22/'l_HC,WC'!M18)*100 -> 3.9303724 | I24: =LN('l_HC,WC'!K22/'l_HC,WC'!K18)*100 -> 1.1592971 | J24: =l_NSR!B22 -> 6.3535323 | K24: =LN(l_Solow!H22/l_Solow!H18)*100 -> 2.2301405 | L24: =LN('l_NB,NEC'!O22/'l_NB,NEC'!O18)*100 -> 61.587174 | M24: =LN('l_NB,NEC'!P22/'l_NB,NEC'!P18)*100 -> 15.963998 | N24: ='fdr,edr'!S22*10000 -> 0.0011767324 | O24: ='fdr,edr (TFP)'!S22*10000 -> 0.012721827 | Q24: 0
A25: =RIGHT(YEAR(B25),2) -> 85 | B25: =EDATE(B24,3) -> 31048 | C25: =YEAR(B25)&"Q"&QUOTIENT(MONTH(B25)-1,3)+1 -> 1985Q1 | D25: =LN(l_Output!C23/l_Output!C19)*100 -> 3.2938283 | E25: =LN('l_IC,pi_d'!D23/'l_IC,pi_d'!D19)*100 -> 9.5859077 | F25: =LN(l_pi_c!G23/l_pi_c!G19)*100 -> 1.729712 | G25: =LN('l_IC,pi_d'!F23/'l_IC,pi_d'!F19)*100 -> 1.2110191 | H25: =LN('l_HC,WC'!M23/'l_HC,WC'!M19)*100 -> 5.3673552 | I25: =LN('l_HC,WC'!K23/'l_HC,WC'!K19)*100 -> -1.5730653 | J25: =l_NSR!B23 -> 6.3817538 | K25: =LN(l_Solow!H23/l_Solow!H19)*100 -> 3.994314 | L25: =LN('l_NB,NEC'!O23/'l_NB,NEC'!O19)*100 -> 49.615598 | M25: =LN('l_NB,NEC'!P23/'l_NB,NEC'!P19)*100 -> 10.336728 | N25: ='fdr,edr'!S23*10000 -> 0.022474263 | O25: ='fdr,edr (TFP)'!S23*10000 -> 0.16268931 | Q25: 0
B26: =EDATE(B25,3) -> 31138 | C26: =YEAR(B26)&"Q"&QUOTIENT(MONTH(B26)-1,3)+1 -> 1985Q2 | D26: =LN(l_Output!C24/l_Output!C20)*100 -> 3.393217 | E26: =LN('l_IC,pi_d'!D24/'l_IC,pi_d'!D20)*100 -> 7.3864095 | F26: =LN(l_pi_c!G24/l_pi_c!G20)*100 -> 1.6377352 | G26: =LN('l_IC,pi_d'!F24/'l_IC,pi_d'!F20)*100 -> 0.49525613 | H26: =LN('l_HC,WC'!M24/'l_HC,WC'!M20)*100 -> 3.4990541 | I26: =LN('l_HC,WC'!K24/'l_HC,WC'!K20)*100 -> -0.39948415 | J26: =l_NSR!B24 -> 6.1977519 | K26: =LN(l_Solow!H24/l_Solow!H20)*100 -> 3.265507 | L26: =LN('l_NB,NEC'!O24/'l_NB,NEC'!O20)*100 -> 44.949099 | M26: =LN('l_NB,NEC'!P24/'l_NB,NEC'!P20)*100 -> 14.613948 | N26: ='fdr,edr'!S24*10000 -> 1.2846545 | O26: ='fdr,edr (TFP)'!S24*10000 -> 9.3340517 | Q26: 0
B27: =EDATE(B26,3) -> 31229 | C27: =YEAR(B27)&"Q"&QUOTIENT(MONTH(B27)-1,3)+1 -> 1985Q3 | D27: =LN(l_Output!C25/l_Output!C21)*100 -> 4.1549242 | E27: =LN('l_IC,pi_d'!D25/'l_IC,pi_d'!D21)*100 -> 8.2984879 | F27: =LN(l_pi_c!G25/l_pi_c!G21)*100 -> 1.0064912 | G27: =LN('l_IC,pi_d'!F25/'l_IC,pi_d'!F21)*100 -> -0.0077643672 | H27: =LN('l_HC,WC'!M25/'l_HC,WC'!M21)*100 -> 4.6047286 | I27: =LN('l_HC,WC'!K25/'l_HC,WC'!K21)*100 -> -0.44601423 | J27: =l_NSR!B25 -> 6.3871667 | K27: =LN(l_Solow!H25/l_Solow!H21)*100 -> 3.7861445 | L27: =LN('l_NB,NEC'!O25/'l_NB,NEC'!O21)*100 -> 56.277206 | M27: =LN('l_NB,NEC'!P25/'l_NB,NEC'!P21)*100 -> 13.912145 | N27: ='fdr,edr'!S25*10000 -> 0.66663324 | O27: ='fdr,edr (TFP)'!S25*10000 -> 4.8505742 | P27: 500 | Q27: 0
B28: =EDATE(B27,3) -> 31321 | C28: =YEAR(B28)&"Q"&QUOTIENT(MONTH(B28)-1,3)+1 -> 1985Q4 | D28: =LN(l_Output!C26/l_Output!C22)*100 -> 5.4153789 | E28: =LN('l_IC,pi_d'!D26/'l_IC,pi_d'!D22)*100 -> 6.3427203 | F28: =LN(l_pi_c!G26/l_pi_c!G22)*100 -> 0.72067786 | G28: =LN('l_IC,pi_d'!F26/'l_IC,pi_d'!F22)*100 -> -0.83469028 | H28: =LN('l_HC,WC'!M26/'l_HC,WC'!M22)*100 -> 4.5304726 | I28: =LN('l_HC,WC'!K26/'l_HC,WC'!K22)*100 -> -1.2058157 | J28: =l_NSR!B26 -> 7.4403333 | K28: =LN(l_Solow!H26/l_Solow!H22)*100 -> 5.4100054 | L28: =LN('l_NB,NEC'!O26/'l_NB,NEC'!O22)*100 -> 29.886142 | M28: =LN('l_NB,NEC'!P26/'l_NB,NEC'!P22)*100 -> 12.122801 | N28: ='fdr,edr'!S26*10000 -> 0.040842875 | O28: ='fdr,edr (TFP)'!S26*10000 -> 0.29630704 | P28: 500 | Q28: 0
B29: =EDATE(B28,3) -> 31413 | C29: =YEAR(B29)&"Q"&QUOTIENT(MONTH(B29)-1,3)+1 -> 1986Q1 | D29: =LN(l_Output!C27/l_Output!C23)*100 -> 4.0547095 | E29: =LN('l_IC,pi_d'!D27/'l_IC,pi_d'!D23)*100 -> 4.1143887 | F29: =LN(l_pi_c!G27/l_pi_c!G23)*100 -> 1.2186317 | G29: =LN('l_IC,pi_d'!F27/'l_IC,pi_d'!F23)*100 -> -1.2688331 | H29: =LN('l_HC,WC'!M27/'l_HC,WC'!M23)*100 -> 5.0850821 | I29: =LN('l_HC,WC'!K27/'l_HC,WC'!K23)*100 -> -0.40093833 | J29: =l_NSR!B27 -> 6.2754333 | K29: =LN(l_Solow!H27/l_Solow!H23)*100 -> 3.7236742 | L29: =LN('l_NB,NEC'!O27/'l_NB,NEC'!O23)*100 -> 14.01065 | M29: =LN('l_NB,NEC'!P27/'l_NB,NEC'!P23)*100 -> 18.483226 | N29: ='fdr,edr'!S27*10000 -> 0.00060848468 | O29: ='fdr,edr (TFP)'!S27*10000 -> 0.0025313408 | P29: 500 | Q29: 0
B30: =EDATE(B29,3) -> 31503 | C30: =YEAR(B30)&"Q"&QUOTIENT(MONTH(B30)-1,3)+1 -> 1986Q2 | D30: =LN(l_Output!C28/l_Output!C24)*100 -> 2.4390061 | E30: =LN('l_IC,pi_d'!D28/'l_IC,pi_d'!D24)*100 -> 8.6162632 | F30: =LN(l_pi_c!G28/l_pi_c!G24)*100 -> 1.6050091 | G30: =LN('l_IC,pi_d'!F28/'l_IC,pi_d'!F24)*100 -> -1.1106946 | H30: =LN('l_HC,WC'!M28/'l_HC,WC'!M24)*100 -> 3.8083676 | I30: =LN('l_HC,WC'!K28/'l_HC,WC'!K24)*100 -> -0.53035824 | J30: =l_NSR!B28 -> 4.6293 | K30: =LN(l_Solow!H28/l_Solow!H24)*100 -> 2.3274265 | L30: =LN('l_NB,NEC'!O28/'l_NB,NEC'!O24)*100 -> 18.581521 | M30: =LN('l_NB,NEC'!P28/'l_NB,NEC'!P24)*100 -> 31.849991 | N30: ='fdr,edr'!S28*10000 -> 0.13485414 | O30: ='fdr,edr (TFP)'!S28*10000 -> 0.56335523 | P30: 500 | Q30: 0
B31: =EDATE(B30,3) -> 31594 | C31: =YEAR(B31)&"Q"&QUOTIENT(MONTH(B31)-1,3)+1 -> 1986Q3 | D31: =LN(l_Output!C29/l_Output!C25)*100 -> 1.5976988 | E31: =LN('l_IC,pi_d'!D29/'l_IC,pi_d'!D25)*100 -> 4.0140386 | F31: =LN(l_pi_c!G29/l_pi_c!G25)*100 -> 2.1545448 | G31: =LN('l_IC,pi_d'!F29/'l_IC,pi_d'!F25)*100 -> -1.9514486 | H31: =LN('l_HC,WC'!M29/'l_HC,WC'!M25)*100 -> 3.5981882 | I31: =LN('l_HC,WC'!K29/'l_HC,WC'!K25)*100 -> -0.62031285 | J31: =l_NSR!B29 -> 4.6884667 | K31: =LN(l_Solow!H29/l_Solow!H25)*100 -> 1.7436746 | L31: =LN('l_NB,NEC'!O29/'l_NB,NEC'!O25)*100 -> 34.123214 | M31: =LN('l_NB,NEC'!P29/'l_NB,NEC'!P25)*100 -> 43.146808 | N31: ='fdr,edr'!S29*10000 -> 4.4946044 | O31: ='fdr,edr (TFP)'!S29*10000 -> 18.799125 | P31: 500 | Q31: 0
B32: =EDATE(B31,3) -> 31686 | C32: =YEAR(B32)&"Q"&QUOTIENT(MONTH(B32)-1,3)+1 -> 1986Q4 | D32: =LN(l_Output!C30/l_Output!C26)*100 -> 1.1777353 | E32: =LN('l_IC,pi_d'!D30/'l_IC,pi_d'!D26)*100 -> 4.0306093 | F32: =LN(l_pi_c!G30/l_pi_c!G26)*100 -> 1.4652653 | G32: =LN('l_IC,pi_d'!F30/'l_IC,pi_d'!F26)*100 -> -1.9845137 | H32: =LN('l_HC,WC'!M30/'l_HC,WC'!M26)*100 -> 3.5112953 | I32: =LN('l_HC,WC'!K30/'l_HC,WC'!K26)*100 -> -1.2551567 | J32: =l_NSR!B30 -> 4.2521 | K32: =LN(l_Solow!H30/l_Solow!H26)*100 -> 1.4545508 | L32: =LN('l_NB,NEC'!O30/'l_NB,NEC'!O26)*100 -> 38.550195 | M32: =LN('l_NB,NEC'!P30/'l_NB,NEC'!P26)*100 -> 38.341168 | N32: ='fdr,edr'!S30*10000 -> 0.04607891 | O32: ='fdr,edr (TFP)'!S30*10000 -> 0.19209311 | P32: 500 | Q32: 0
B33: =EDATE(B32,3) -> 31778 | C33: =YEAR(B33)&"Q"&QUOTIENT(MONTH(B33)-1,3)+1 -> 1987Q1 | D33: =LN(l_Output!C31/l_Output!C27)*100 -> 1.4807594 | E33: =LN('l_IC,pi_d'!D31/'l_IC,pi_d'!D27)*100 -> 4.5625476 | F33: =LN(l_pi_c!G31/l_pi_c!G27)*100 -> 0.39861365 | G33: =LN('l_IC,pi_d'!F31/'l_IC,pi_d'!F27)*100 -> -1.8158203 | H33: =LN('l_HC,WC'!M31/'l_HC,WC'!M27)*100 -> 1.7422287 | I33: =LN('l_HC,WC'!K31/'l_HC,WC'!K27)*100 -> -0.091444413 | J33: =l_NSR!B31 -> 4.1998 | K33: =LN(l_Solow!H31/l_Solow!H27)*100 -> 0.57758863 | L33: =LN('l_NB,NEC'!O31/'l_NB,NEC'!O27)*100 -> 72.344522 | M33: =LN('l_NB,NEC'!P31/'l_NB,NEC'!P27)*100 -> 37.333257 | N33: ='fdr,edr'!S31*10000 -> 0.0098800487 | O33: ='fdr,edr (TFP)'!S31*10000 -> 0.03139051 | Q33: 0
B34: =EDATE(B33,3) -> 31868 | C34: =YEAR(B34)&"Q"&QUOTIENT(MONTH(B34)-1,3)+1 -> 1987Q2 | D34: =LN(l_Output!C32/l_Output!C28)*100 -> 3.0186528 | E34: =LN('l_IC,pi_d'!D32/'l_IC,pi_d'!D28)*100 -> 4.1546792 | F34: =LN(l_pi_c!G32/l_pi_c!G28)*100 -> -0.44949298 | G34: =LN('l_IC,pi_d'!F32/'l_IC,pi_d'!F28)*100 -> -2.228216 | H34: =LN('l_HC,WC'!M32/'l_HC,WC'!M28)*100 -> 2.7924887 | I34: =LN('l_HC,WC'!K32/'l_HC,WC'!K28)*100 -> -0.21900774 | J34: =l_NSR!B32 -> 3.4391667 | K34: =LN(l_Solow!H32/l_Solow!H28)*100 -> 1.8348968 | L34: =LN('l_NB,NEC'!O32/'l_NB,NEC'!O28)*100 -> 83.423185 | M34: =LN('l_NB,NEC'!P32/'l_NB,NEC'!P28)*100 -> 32.696784 | N34: ='fdr,edr'!S32*10000 -> 0.81888621 | O34: ='fdr,edr (TFP)'!S32*10000 -> 2.614856 | Q34: 0
B35: =EDATE(B34,3) -> 31959 | C35: =YEAR(B35)&"Q"&QUOTIENT(MONTH(B35)-1,3)+1 -> 1987Q3 | D35: =LN(l_Output!C33/l_Output!C29)*100 -> 4.180343 | E35: =LN('l_IC,pi_d'!D33/'l_IC,pi_d'!D29)*100 -> 6.622639 | F35: =LN(l_pi_c!G33/l_pi_c!G29)*100 -> -0.4085586 | G35: =LN('l_IC,pi_d'!F33/'l_IC,pi_d'!F29)*100 -> -1.4005425 | H35: =LN('l_HC,WC'!M33/'l_HC,WC'!M29)*100 -> 1.3821711 | I35: =LN('l_HC,WC'!K33/'l_HC,WC'!K29)*100 -> 0.58498056 | J35: =l_NSR!B33 -> 3.3747667 | K35: =LN(l_Solow!H33/l_Solow!H29)*100 -> 2.4128633 | L35: =LN('l_NB,NEC'!O33/'l_NB,NEC'!O29)*100 -> 53.863242 | M35: =LN('l_NB,NEC'!P33/'l_NB,NEC'!P29)*100 -> 28.130853 | N35: ='fdr,edr'!S33*10000 -> 2.8761271 | O35: ='fdr,edr (TFP)'!S33*10000 -> 9.2090843 | Q35: 0
B36: =EDATE(B35,3) -> 32051 | C36: =YEAR(B36)&"Q"&QUOTIENT(MONTH(B36)-1,3)+1 -> 1987Q4 | D36: =LN(l_Output!C34/l_Output!C30)*100 -> 5.5926263 | E36: =LN('l_IC,pi_d'!D34/'l_IC,pi_d'!D30)*100 -> 7.0064977 | F36: =LN(l_pi_c!G34/l_pi_c!G30)*100 -> -0.2354861 | G36: =LN('l_IC,pi_d'!F34/'l_IC,pi_d'!F30)*100 -> -0.917259 | H36: =LN('l_HC,WC'!M34/'l_HC,WC'!M30)*100 -> 1.0207388 | I36: =LN('l_HC,WC'!K34/'l_HC,WC'!K30)*100 -> 1.8516297 | J36: =l_NSR!B34 -> 3.6614333 | K36: =LN(l_Solow!H34/l_Solow!H30)*100 -> 2.9760004 | L36: =LN('l_NB,NEC'!O34/'l_NB,NEC'!O30)*100 -> 37.682196 | M36: =LN('l_NB,NEC'!P34/'l_NB,NEC'!P30)*100 -> 18.575808 | N36: ='fdr,edr'!S34*10000 -> 0.13361484 | O36: ='fdr,edr (TFP)'!S34*10000 -> 0.42656479 | Q36: 0
B37: =EDATE(B36,3) -> 32143 | C37: =YEAR(B37)&"Q"&QUOTIENT(MONTH(B37)-1,3)+1 -> 1988Q1 | D37: =LN(l_Output!C35/l_Output!C31)*100 -> 7.0800517 | E37: =LN('l_IC,pi_d'!D35/'l_IC,pi_d'!D31)*100 -> 11.809084 | F37: =LN(l_pi_c!G35/l_pi_c!G31)*100 -> 0.46779474 | G37: =LN('l_IC,pi_d'!F35/'l_IC,pi_d'!F31)*100 -> -0.72541314 | H37: =LN('l_HC,WC'!M35/'l_HC,WC'!M31)*100 -> 0.64163567 | I37: =LN('l_HC,WC'!K35/'l_HC,WC'!K31)*100 -> 2.9741871 | J37: =l_NSR!B35 -> 3.686 | K37: =LN(l_Solow!H35/l_Solow!H31)*100 -> 3.8459373 | L37: =LN('l_NB,NEC'!O35/'l_NB,NEC'!O31)*100 -> 10.948475 | M37: =LN('l_NB,NEC'!P35/'l_NB,NEC'!P31)*100 -> 20.264537 | N37: ='fdr,edr'!S35*10000 -> 0.00019487743 | O37: ='fdr,edr (TFP)'!S35*10000 -> 0.0025358281 | Q37: 0
B38: =EDATE(B37,3) -> 32234 | C38: =YEAR(B38)&"Q"&QUOTIENT(MONTH(B38)-1,3)+1 -> 1988Q2 | D38: =LN(l_Output!C36/l_Output!C32)*100 -> 5.7615167 | E38: =LN('l_IC,pi_d'!D36/'l_IC,pi_d'!D32)*100 -> 13.354511 | F38: =LN(l_pi_c!G36/l_pi_c!G32)*100 -> 0.39600923 | G38: =LN('l_IC,pi_d'!F36/'l_IC,pi_d'!F32)*100 -> -0.079298519 | H38: =LN('l_HC,WC'!M36/'l_HC,WC'!M32)*100 -> 3.8575027 | I38: =LN('l_HC,WC'!K36/'l_HC,WC'!K32)*100 -> 0.22966159 | J38: =l_NSR!B36 -> 3.5175667 | K38: =LN(l_Solow!H36/l_Solow!H32)*100 -> 4.1552979 | L38: =LN('l_NB,NEC'!O36/'l_NB,NEC'!O32)*100 -> -12.149433 | M38: =LN('l_NB,NEC'!P36/'l_NB,NEC'!P32)*100 -> 18.626097 | N38: ='fdr,edr'!S36*10000 -> 0.22743185 | O38: ='fdr,edr (TFP)'!S36*10000 -> 2.981655 | Q38: 0
B39: =EDATE(B38,3) -> 32325 | C39: =YEAR(B39)&"Q"&QUOTIENT(MONTH(B39)-1,3)+1 -> 1988Q3 | D39: =LN(l_Output!C37/l_Output!C33)*100 -> 5.7634393 | E39: =LN('l_IC,pi_d'!D37/'l_IC,pi_d'!D33)*100 -> 16.935978 | F39: =LN(l_pi_c!G37/l_pi_c!G33)*100 -> 0.53325625 | G39: =LN('l_IC,pi_d'!F37/'l_IC,pi_d'!F33)*100 -> -0.33895656 | H39: =LN('l_HC,WC'!M37/'l_HC,WC'!M33)*100 -> 4.8048741 | I39: =LN('l_HC,WC'!K37/'l_HC,WC'!K33)*100 -> 0.7200512 | J39: =l_NSR!B37 -> 3.9766 | K39: =LN(l_Solow!H37/l_Solow!H33)*100 -> 3.7702477 | L39: =LN('l_NB,NEC'!O37/'l_NB,NEC'!O33)*100 -> -6.9001981 | M39: =LN('l_NB,NEC'!P37/'l_NB,NEC'!P33)*100 -> 14.513579 | N39: ='fdr,edr'!S37*10000 -> 0.15885252 | O39: ='fdr,edr (TFP)'!S37*10000 -> 2.0975875 | Q39: 0
B40: =EDATE(B39,3) -> 32417 | C40: =YEAR(B40)&"Q"&QUOTIENT(MONTH(B40)-1,3)+1 -> 1988Q4 | D40: =LN(l_Output!C38/l_Output!C34)*100 -> 4.3002685 | E40: =LN('l_IC,pi_d'!D38/'l_IC,pi_d'!D34)*100 -> 18.057692 | F40: =LN(l_pi_c!G38/l_pi_c!G34)*100 -> 1.0398713 | G40: =LN('l_IC,pi_d'!F38/'l_IC,pi_d'!F34)*100 -> -0.37371655 | H40: =LN('l_HC,WC'!M38/'l_HC,WC'!M34)*100 -> 5.6298863 | I40: =LN('l_HC,WC'!K38/'l_HC,WC'!K34)*100 -> -0.34763427 | J40: =l_NSR!B38 -> 4.1589667 | K40: =LN(l_Solow!H38/l_Solow!H34)*100 -> 3.0662268 | L40: =LN('l_NB,NEC'!O38/'l_NB,NEC'!O34)*100 -> 18.063933 | M40: =LN('l_NB,NEC'!P38/'l_NB,NEC'!P34)*100 -> 28.348148 | N40: ='fdr,edr'!S38*10000 -> 0.033382003 | O40: ='fdr,edr (TFP)'!S38*10000 -> 0.44185114 | Q40: 0
B41: =EDATE(B40,3) -> 32509 | C41: =YEAR(B41)&"Q"&QUOTIENT(MONTH(B41)-1,3)+1 -> 1989Q1 | D41: =LN(l_Output!C39/l_Output!C35)*100 -> 4.7160299 | E41: =LN('l_IC,pi_d'!D39/'l_IC,pi_d'!D35)*100 -> 17.584153 | F41: =LN(l_pi_c!G39/l_pi_c!G35)*100 -> 0.91450499 | G41: =LN('l_IC,pi_d'!F39/'l_IC,pi_d'!F35)*100 -> -0.23918149 | H41: =LN('l_HC,WC'!M39/'l_HC,WC'!M35)*100 -> 6.5366713 | I41: =LN('l_HC,WC'!K39/'l_HC,WC'!K35)*100 -> -1.5046878 | J41: =l_NSR!B39 -> 4.1757633 | K41: =LN(l_Solow!H39/l_Solow!H35)*100 -> 4.0941977 | L41: =LN('l_NB,NEC'!O39/'l_NB,NEC'!O35)*100 -> 9.9594537 | M41: =LN('l_NB,NEC'!P39/'l_NB,NEC'!P35)*100 -> 26.932567 | N41: ='fdr,edr'!S39*10000 -> 0.033633326 | O41: ='fdr,edr (TFP)'!S39*10000 -> 0.11164188 | Q41: 0
B42: =EDATE(B41,3) -> 32599 | C42: =YEAR(B42)&"Q"&QUOTIENT(MONTH(B42)-1,3)+1 -> 1989Q2 | D42: =LN(l_Output!C40/l_Output!C36)*100 -> 3.0909108 | E42: =LN('l_IC,pi_d'!D40/'l_IC,pi_d'!D36)*100 -> 9.791038 | F42: =LN(l_pi_c!G40/l_pi_c!G36)*100 -> 0.86410062 | G42: =LN('l_IC,pi_d'!F40/'l_IC,pi_d'!F36)*100 -> 0.3894606 | H42: =LN('l_HC,WC'!M40/'l_HC,WC'!M36)*100 -> 6.1204369 | I42: =LN('l_HC,WC'!K40/'l_HC,WC'!K36)*100 -> 0.28726897 | J42: =l_NSR!B40 -> 4.7443633 | K42: =LN(l_Solow!H40/l_Solow!H36)*100 -> 1.2982897 | L42: =LN('l_NB,NEC'!O40/'l_NB,NEC'!O36)*100 -> 8.2057081 | M42: =LN('l_NB,NEC'!P40/'l_NB,NEC'!P36)*100 -> 21.608298 | N42: ='fdr,edr'!S40*10000 -> 0.1600074 | O42: ='fdr,edr (TFP)'!S40*10000 -> 0.53544385 | Q42: 0
B43: =EDATE(B42,3) -> 32690 | C43: =YEAR(B43)&"Q"&QUOTIENT(MONTH(B43)-1,3)+1 -> 1989Q3 | D43: =LN(l_Output!C41/l_Output!C37)*100 -> 2.8335659 | E43: =LN('l_IC,pi_d'!D41/'l_IC,pi_d'!D37)*100 -> 6.0387688 | F43: =LN(l_pi_c!G41/l_pi_c!G37)*100 -> 1.0068773 | G43: =LN('l_IC,pi_d'!F41/'l_IC,pi_d'!F37)*100 -> 1.1076149 | H43: =LN('l_HC,WC'!M41/'l_HC,WC'!M37)*100 -> 5.8431303 | I43: =LN('l_HC,WC'!K41/'l_HC,WC'!K37)*100 -> -0.080085382 | J43: =l_NSR!B41 -> 5.34546 | K43: =LN(l_Solow!H41/l_Solow!H37)*100 -> 1.3545245 | L43: =LN('l_NB,NEC'!O41/'l_NB,NEC'!O37)*100 -> 20.242571 | M43: =LN('l_NB,NEC'!P41/'l_NB,NEC'!P37)*100 -> 24.571151 | N43: ='fdr,edr'!S41*10000 -> 4.1377499 | O43: ='fdr,edr (TFP)'!S41*10000 -> 13.925998 | Q43: 0
B44: =EDATE(B43,3) -> 32782 | C44: =YEAR(B44)&"Q"&QUOTIENT(MONTH(B44)-1,3)+1 -> 1989Q4 | D44: =LN(l_Output!C42/l_Output!C38)*100 -> 4.5289736 | E44: =LN('l_IC,pi_d'!D42/'l_IC,pi_d'!D38)*100 -> 7.576402 | F44: =LN(l_pi_c!G42/l_pi_c!G38)*100 -> 1.2433512 | G44: =LN('l_IC,pi_d'!F42/'l_IC,pi_d'!F38)*100 -> 1.6055189 | H44: =LN('l_HC,WC'!M42/'l_HC,WC'!M38)*100 -> 6.363126 | I44: =LN('l_HC,WC'!K42/'l_HC,WC'!K38)*100 -> 0.16533249 | J44: =l_NSR!B42 -> 6.2028033 | K44: =LN(l_Solow!H42/l_Solow!H38)*100 -> 2.9852836 | L44: =LN('l_NB,NEC'!O42/'l_NB,NEC'!O38)*100 -> 20.523638 | M44: =LN('l_NB,NEC'!P42/'l_NB,NEC'!P38)*100 -> 26.428601 | N44: ='fdr,edr'!S42*10000 -> 0.0010295603 | O44: ='fdr,edr (TFP)'!S42*10000 -> 0.003469444 | Q44: 0
A45: =RIGHT(YEAR(B45),2) -> 90 | B45: =EDATE(B44,3) -> 32874 | C45: =YEAR(B45)&"Q"&QUOTIENT(MONTH(B45)-1,3)+1 -> 1990Q1 | D45: =LN(l_Output!C43/l_Output!C39)*100 -> 1.7989957 | E45: =LN('l_IC,pi_d'!D43/'l_IC,pi_d'!D39)*100 -> 3.6998831 | F45: =LN(l_pi_c!G43/l_pi_c!G39)*100 -> 1.4503471 | G45: =LN('l_IC,pi_d'!F43/'l_IC,pi_d'!F39)*100 -> 2.6430123 | H45: =LN('l_HC,WC'!M43/'l_HC,WC'!M39)*100 -> 6.782603 | I45: =LN('l_HC,WC'!K43/'l_HC,WC'!K39)*100 -> -0.17566271 | J45: =l_NSR!B43 -> 6.6802133 | K45: =LN(l_Solow!H43/l_Solow!H39)*100 -> 0.58647625 | L45: =LN('l_NB,NEC'!O43/'l_NB,NEC'!O39)*100 -> 0.70025181 | M45: =LN('l_NB,NEC'!P43/'l_NB,NEC'!P39)*100 -> 7.3426166 | N45: ='fdr,edr'!S43*10000 -> 0.00030860607 | O45: ='fdr,edr (TFP)'!S43*10000 -> 0.0015980995 | Q45: 0
B46: =EDATE(B45,3) -> 32964 | C46: =YEAR(B46)&"Q"&QUOTIENT(MONTH(B46)-1,3)+1 -> 1990Q2 | D46: =LN(l_Output!C44/l_Output!C40)*100 -> 5.5507098 | E46: =LN('l_IC,pi_d'!D44/'l_IC,pi_d'!D40)*100 -> 11.086798 | F46: =LN(l_pi_c!G44/l_pi_c!G40)*100 -> 2.496006 | G46: =LN('l_IC,pi_d'!F44/'l_IC,pi_d'!F40)*100 -> 2.8813607 | H46: =LN('l_HC,WC'!M44/'l_HC,WC'!M40)*100 -> 6.794442 | I46: =LN('l_HC,WC'!K44/'l_HC,WC'!K40)*100 -> 0.18351771 | J46: =l_NSR!B44 -> 7.2620033 | K46: =LN(l_Solow!H44/l_Solow!H40)*100 -> 4.4561062 | L46: =LN('l_NB,NEC'!O44/'l_NB,NEC'!O40)*100 -> -7.8572208 | M46: =LN('l_NB,NEC'!P44/'l_NB,NEC'!P40)*100 -> -1.8924179 | N46: ='fdr,edr'!S44*10000 -> 0.047677632 | O46: ='fdr,edr (TFP)'!S44*10000 -> 0.24894872 | Q46: 0
B47: =EDATE(B46,3) -> 33055 | C47: =YEAR(B47)&"Q"&QUOTIENT(MONTH(B47)-1,3)+1 -> 1990Q3 | D47: =LN(l_Output!C45/l_Output!C41)*100 -> 5.9996317 | E47: =LN('l_IC,pi_d'!D45/'l_IC,pi_d'!D41)*100 -> 10.689595 | F47: =LN(l_pi_c!G45/l_pi_c!G41)*100 -> 2.1309507 | G47: =LN('l_IC,pi_d'!F45/'l_IC,pi_d'!F41)*100 -> 2.7088022 | H47: =LN('l_HC,WC'!M45/'l_HC,WC'!M41)*100 -> 7.2249442 | I47: =LN('l_HC,WC'!K45/'l_HC,WC'!K41)*100 -> -0.45573128 | J47: =l_NSR!B45 -> 7.6102633 | K47: =LN(l_Solow!H45/l_Solow!H41)*100 -> 5.1341557 | L47: =LN('l_NB,NEC'!O45/'l_NB,NEC'!O41)*100 -> -38.845125 | M47: =LN('l_NB,NEC'!P45/'l_NB,NEC'!P41)*100 -> -24.573086 | N47: ='fdr,edr'!S45*10000 -> 0.76404025 | O47: ='fdr,edr (TFP)'!S45*10000 -> 4.0166057 | Q47: 0
B48: =EDATE(B47,3) -> 33147 | C48: =YEAR(B48)&"Q"&QUOTIENT(MONTH(B48)-1,3)+1 -> 1990Q4 | D48: =LN(l_Output!C46/l_Output!C42)*100 -> 3.1262624 | E48: =LN('l_IC,pi_d'!D46/'l_IC,pi_d'!D42)*100 -> 7.5694462 | F48: =LN(l_pi_c!G46/l_pi_c!G42)*100 -> 2.7264912 | G48: =LN('l_IC,pi_d'!F46/'l_IC,pi_d'!F42)*100 -> 2.8734218 | H48: =LN('l_HC,WC'!M46/'l_HC,WC'!M42)*100 -> 8.7431093 | I48: =LN('l_HC,WC'!K46/'l_HC,WC'!K42)*100 -> -0.53202561 | J48: =l_NSR!B46 -> 8.03911 | K48: =LN(l_Solow!H46/l_Solow!H42)*100 -> 2.5130921 | L48: =LN('l_NB,NEC'!O46/'l_NB,NEC'!O42)*100 -> -50.383008 | M48: =LN('l_NB,NEC'!P46/'l_NB,NEC'!P42)*100 -> -42.612949 | N48: ='fdr,edr'!S46*10000 -> 0.23177389 | O48: ='fdr,edr (TFP)'!S46*10000 -> 1.219338 | Q48: 0
B49: =EDATE(B48,3) -> 33239 | C49: =YEAR(B49)&"Q"&QUOTIENT(MONTH(B49)-1,3)+1 -> 1991Q1 | D49: =LN(l_Output!C47/l_Output!C43)*100 -> 4.8876882 | E49: =LN('l_IC,pi_d'!D47/'l_IC,pi_d'!D43)*100 -> 10.690847 | F49: =LN(l_pi_c!G47/l_pi_c!G43)*100 -> 2.7605049 | G49: =LN('l_IC,pi_d'!F47/'l_IC,pi_d'!F43)*100 -> 2.2124282 | H49: =LN('l_HC,WC'!M47/'l_HC,WC'!M43)*100 -> 8.6947852 | I49: =LN('l_HC,WC'!K47/'l_HC,WC'!K43)*100 -> -0.88280599 | J49: =l_NSR!B47 -> 8.1508267 | K49: =LN(l_Solow!H47/l_Solow!H43)*100 -> 4.4704239 | L49: =LN('l_NB,NEC'!O47/'l_NB,NEC'!O43)*100 -> -25.213251 | M49: =LN('l_NB,NEC'!P47/'l_NB,NEC'!P43)*100 -> -27.823001 | N49: ='fdr,edr'!S47*10000 -> 0.0067458227 | O49: ='fdr,edr (TFP)'!S47*10000 -> 0.054939549 | Q49: 0
B50: =EDATE(B49,3) -> 33329 | C50: =YEAR(B50)&"Q"&QUOTIENT(MONTH(B50)-1,3)+1 -> 1991Q2 | D50: =LN(l_Output!C48/l_Output!C44)*100 -> 3.1858891 | E50: =LN('l_IC,pi_d'!D48/'l_IC,pi_d'!D44)*100 -> 4.9157944 | F50: =LN(l_pi_c!G48/l_pi_c!G44)*100 -> 2.9399875 | G50: =LN('l_IC,pi_d'!F48/'l_IC,pi_d'!F44)*100 -> 1.6686643 | H50: =LN('l_HC,WC'!M48/'l_HC,WC'!M44)*100 -> 8.4815181 | I50: =LN('l_HC,WC'!K48/'l_HC,WC'!K44)*100 -> -1.079493 | J50: =l_NSR!B48 -> 8.1023333 | K50: =LN(l_Solow!H48/l_Solow!H44)*100 -> 2.9858462 | L50: =LN('l_NB,NEC'!O48/'l_NB,NEC'!O44)*100 -> -9.4830134 | M50: =LN('l_NB,NEC'!P48/'l_NB,NEC'!P44)*100 -> -21.802784 | N50: ='fdr,edr'!S48*10000 -> 0.1964077 | O50: ='fdr,edr (TFP)'!S48*10000 -> 1.6115741 | P50: 500 | Q50: 0
B51: =EDATE(B50,3) -> 33420 | C51: =YEAR(B51)&"Q"&QUOTIENT(MONTH(B51)-1,3)+1 -> 1991Q3 | D51: =LN(l_Output!C49/l_Output!C45)*100 -> 1.2581898 | E51: =LN('l_IC,pi_d'!D49/'l_IC,pi_d'!D45)*100 -> 2.6209239 | F51: =LN(l_pi_c!G49/l_pi_c!G45)*100 -> 3.1282562 | G51: =LN('l_IC,pi_d'!F49/'l_IC,pi_d'!F45)*100 -> 1.8044732 | H51: =LN('l_HC,WC'!M49/'l_HC,WC'!M45)*100 -> 8.8059579 | I51: =LN('l_HC,WC'!K49/'l_HC,WC'!K45)*100 -> -0.98543855 | J51: =l_NSR!B49 -> 7.33144 | K51: =LN(l_Solow!H49/l_Solow!H45)*100 -> 1.1481422 | L51: =LN('l_NB,NEC'!O49/'l_NB,NEC'!O45)*100 -> 8.0834503 | M51: =LN('l_NB,NEC'!P49/'l_NB,NEC'!P45)*100 -> -10.754238 | N51: ='fdr,edr'!S49*10000 -> 1.2566088 | O51: ='fdr,edr (TFP)'!S49*10000 -> 10.358866 | P51: 500 | Q51: 0
B52: =EDATE(B51,3) -> 33512 | C52: =YEAR(B52)&"Q"&QUOTIENT(MONTH(B52)-1,3)+1 -> 1991Q4 | D52: =LN(l_Output!C50/l_Output!C46)*100 -> 2.1779139 | E52: =LN('l_IC,pi_d'!D50/'l_IC,pi_d'!D46)*100 -> 0.97962109 | F52: =LN(l_pi_c!G50/l_pi_c!G46)*100 -> 2.8378653 | G52: =LN('l_IC,pi_d'!F50/'l_IC,pi_d'!F46)*100 -> 1.3538019 | H52: =LN('l_HC,WC'!M50/'l_HC,WC'!M46)*100 -> 7.0287373 | I52: =LN('l_HC,WC'!K50/'l_HC,WC'!K46)*100 -> -0.76827275 | J52: =l_NSR!B50 -> 6.51676 | K52: =LN(l_Solow!H50/l_Solow!H46)*100 -> 1.9025702 | L52: =LN('l_NB,NEC'!O50/'l_NB,NEC'!O46)*100 -> 13.462508 | M52: =LN('l_NB,NEC'!P50/'l_NB,NEC'!P46)*100 -> -1.7053648 | N52: ='fdr,edr'!S50*10000 -> 0.070693035 | O52: ='fdr,edr (TFP)'!S50*10000 -> 0.58147215 | P52: 500 | Q52: 0
B53: =EDATE(B52,3) -> 33604 | C53: =YEAR(B53)&"Q"&QUOTIENT(MONTH(B53)-1,3)+1 -> 1992Q1 | D53: =LN(l_Output!C51/l_Output!C47)*100 -> 1.4008363 | E53: =LN('l_IC,pi_d'!D51/'l_IC,pi_d'!D47)*100 -> -7.4423361 | F53: =LN(l_pi_c!G51/l_pi_c!G47)*100 -> 2.1622285 | G53: =LN('l_IC,pi_d'!F51/'l_IC,pi_d'!F47)*100 -> 0.98605399 | H53: =LN('l_HC,WC'!M51/'l_HC,WC'!M47)*100 -> 5.7602707 | I53: =LN('l_HC,WC'!K51/'l_HC,WC'!K47)*100 -> -0.76567375 | J53: =l_NSR!B51 -> 5.62072 | K53: =LN(l_Solow!H51/l_Solow!H47)*100 -> 1.0406499 | L53: =LN('l_NB,NEC'!O51/'l_NB,NEC'!O47)*100 -> -21.40936 | M53: =LN('l_NB,NEC'!P51/'l_NB,NEC'!P47)*100 -> -18.337127 | N53: ='fdr,edr'!S51*10000 -> 0.0001183732 | O53: ='fdr,edr (TFP)'!S51*10000 -> 0.00089127697 | P53: 500 | Q53: 0
B54: =EDATE(B53,3) -> 33695 | C54: =YEAR(B54)&"Q"&QUOTIENT(MONTH(B54)-1,3)+1 -> 1992Q2 | D54: =LN(l_Output!C52/l_Output!C48)*100 -> 0.60066394 | E54: =LN('l_IC,pi_d'!D52/'l_IC,pi_d'!D48)*100 -> -5.7612196 | F54: =LN(l_pi_c!G52/l_pi_c!G48)*100 -> 2.1973282 | G54: =LN('l_IC,pi_d'!F52/'l_IC,pi_d'!F48)*100 -> 1.0643012 | H54: =LN('l_HC,WC'!M52/'l_HC,WC'!M48)*100 -> 4.1984877 | I54: =LN('l_HC,WC'!K52/'l_HC,WC'!K48)*100 -> -0.9438888 | J54: =l_NSR!B52 -> 4.75476 | K54: =LN(l_Solow!H52/l_Solow!H48)*100 -> 0.48083771 | L54: =LN('l_NB,NEC'!O52/'l_NB,NEC'!O48)*100 -> -52.347612 | M54: =LN('l_NB,NEC'!P52/'l_NB,NEC'!P48)*100 -> -30.881227 | N54: ='fdr,edr'!S52*10000 -> 0.024212691 | O54: ='fdr,edr (TFP)'!S52*10000 -> 0.18243989 | P54: 500 | Q54: 0
B55: =EDATE(B54,3) -> 33786 | C55: =YEAR(B55)&"Q"&QUOTIENT(MONTH(B55)-1,3)+1 -> 1992Q3 | D55: =LN(l_Output!C53/l_Output!C49)*100 -> 1.0838887 | E55: =LN('l_IC,pi_d'!D53/'l_IC,pi_d'!D49)*100 -> -7.8691535 | F55: =LN(l_pi_c!G53/l_pi_c!G49)*100 -> 1.5301627 | G55: =LN('l_IC,pi_d'!F53/'l_IC,pi_d'!F49)*100 -> 0.24541485 | H55: =LN('l_HC,WC'!M53/'l_HC,WC'!M49)*100 -> 4.6436686 | I55: =LN('l_HC,WC'!K53/'l_HC,WC'!K49)*100 -> -1.9527175 | J55: =l_NSR!B53 -> 4.2922867 | K55: =LN(l_Solow!H53/l_Solow!H49)*100 -> 1.4843713 | L55: =LN('l_NB,NEC'!O53/'l_NB,NEC'!O49)*100 -> -37.246596 | M55: =LN('l_NB,NEC'!P53/'l_NB,NEC'!P49)*100 -> -29.355537 | N55: ='fdr,edr'!S53*10000 -> 0.24780934 | O55: ='fdr,edr (TFP)'!S53*10000 -> 1.8665218 | P55: 500 | Q55: 0
B56: =EDATE(B55,3) -> 33878 | C56: =YEAR(B56)&"Q"&QUOTIENT(MONTH(B56)-1,3)+1 -> 1992Q4 | D56: =LN(l_Output!C54/l_Output!C50)*100 -> -0.33462938 | E56: =LN('l_IC,pi_d'!D54/'l_IC,pi_d'!D50)*100 -> -11.005261 | F56: =LN(l_pi_c!G54/l_pi_c!G50)*100 -> 0.78157345 | G56: =LN('l_IC,pi_d'!F54/'l_IC,pi_d'!F50)*100 -> -0.1049406 | H56: =LN('l_HC,WC'!M54/'l_HC,WC'!M50)*100 -> 4.0106245 | I56: =LN('l_HC,WC'!K54/'l_HC,WC'!K50)*100 -> -2.2230108 | J56: =l_NSR!B54 -> 3.97149 | K56: =LN(l_Solow!H54/l_Solow!H50)*100 -> 0.14559719 | L56: =LN('l_NB,NEC'!O54/'l_NB,NEC'!O50)*100 -> -35.353852 | M56: =LN('l_NB,NEC'!P54/'l_NB,NEC'!P50)*100 -> -28.459749 | N56: ='fdr,edr'!S54*10000 -> 0.066162743 | O56: ='fdr,edr (TFP)'!S54*10000 -> 0.49435813 | P56: 500 | Q56: 0
B57: =EDATE(B56,3) -> 33970 | C57: =YEAR(B57)&"Q"&QUOTIENT(MONTH(B57)-1,3)+1 -> 1993Q1 | D57: =LN(l_Output!C55/l_Output!C51)*100 -> 0.028374271 | E57: =LN('l_IC,pi_d'!D55/'l_IC,pi_d'!D51)*100 -> -6.9708415 | F57: =LN(l_pi_c!G55/l_pi_c!G51)*100 -> 1.0861969 | G57: =LN('l_IC,pi_d'!F55/'l_IC,pi_d'!F51)*100 -> -0.36101519 | H57: =LN('l_HC,WC'!M55/'l_HC,WC'!M51)*100 -> 4.5121849 | I57: =LN('l_HC,WC'!K55/'l_HC,WC'!K51)*100 -> -2.6277744 | J57: =l_NSR!B55 -> 3.4726133 | K57: =LN(l_Solow!H55/l_Solow!H51)*100 -> 1.0077129 | L57: =LN('l_NB,NEC'!O55/'l_NB,NEC'!O51)*100 -> -11.117246 | M57: =LN('l_NB,NEC'!P55/'l_NB,NEC'!P51)*100 -> -14.28923 | N57: ='fdr,edr'!S55*10000 -> 0.00019819176 | O57: ='fdr,edr (TFP)'!S55*10000 -> 0.00086588267 | P57: 500 | Q57: 0
B58: =EDATE(B57,3) -> 34060 | C58: =YEAR(B58)&"Q"&QUOTIENT(MONTH(B58)-1,3)+1 -> 1993Q2 | D58: =LN(l_Output!C56/l_Output!C52)*100 -> -0.85867961 | E58: =LN('l_IC,pi_d'!D56/'l_IC,pi_d'!D52)*100 -> -13.167106 | F58: =LN(l_pi_c!G56/l_pi_c!G52)*100 -> 0.055115489 | G58: =LN('l_IC,pi_d'!F56/'l_IC,pi_d'!F52)*100 -> -1.044182 | H58: =LN('l_HC,WC'!M56/'l_HC,WC'!M52)*100 -> 5.4496569 | I58: =LN('l_HC,WC'!K56/'l_HC,WC'!K52)*100 -> -3.7117086 | J58: =l_NSR!B56 -> 3.19982 | K58: =LN(l_Solow!H56/l_Solow!H52)*100 -> 0.59809277 | L58: =LN('l_NB,NEC'!O56/'l_NB,NEC'!O52)*100 -> 35.452062 | M58: =LN('l_NB,NEC'!P56/'l_NB,NEC'!P52)*100 -> 15.555634 | N58: ='fdr,edr'!S56*10000 -> 0.074252435 | O58: ='fdr,edr (TFP)'!S56*10000 -> 0.32311037 | P58: 500 | Q58: 0
B59: =EDATE(B58,3) -> 34151 | C59: =YEAR(B59)&"Q"&QUOTIENT(MONTH(B59)-1,3)+1 -> 1993Q3 | D59: =LN(l_Output!C57/l_Output!C53)*100 -> -1.7346374 | E59: =LN('l_IC,pi_d'!D57/'l_IC,pi_d'!D53)*100 -> -16.480488 | F59: =LN(l_pi_c!G57/l_pi_c!G53)*100 -> 0.55071173 | G59: =LN('l_IC,pi_d'!F57/'l_IC,pi_d'!F53)*100 -> -1.0881755 | H59: =LN('l_HC,WC'!M57/'l_HC,WC'!M53)*100 -> 4.6530482 | I59: =LN('l_HC,WC'!K57/'l_HC,WC'!K53)*100 -> -1.8554642 | J59: =l_NSR!B57 -> 3.0832833 | K59: =LN(l_Solow!H57/l_Solow!H53)*100 -> -1.1099907 | L59: =LN('l_NB,NEC'!O57/'l_NB,NEC'!O53)*100 -> 32.924584 | M59: =LN('l_NB,NEC'!P57/'l_NB,NEC'!P53)*100 -> 20.771314 | N59: ='fdr,edr'!S57*10000 -> 1.0851614 | O59: ='fdr,edr (TFP)'!S57*10000 -> 4.6903097 | P59: 500 | Q59: 0
B60: =EDATE(B59,3) -> 34243 | C60: =YEAR(B60)&"Q"&QUOTIENT(MONTH(B60)-1,3)+1 -> 1993Q4 | D60: =LN(l_Output!C58/l_Output!C54)*100 -> -0.63562762 | E60: =LN('l_IC,pi_d'!D58/'l_IC,pi_d'!D54)*100 -> -18.174536 | F60: =LN(l_pi_c!G58/l_pi_c!G54)*100 -> 0.65525826 | G60: =LN('l_IC,pi_d'!F58/'l_IC,pi_d'!F54)*100 -> -1.3787984 | H60: =LN('l_HC,WC'!M58/'l_HC,WC'!M54)*100 -> 4.0873487 | I60: =LN('l_HC,WC'!K58/'l_HC,WC'!K54)*100 -> -2.4231471 | J60: =l_NSR!B58 -> 2.4816933 | K60: =LN(l_Solow!H58/l_Solow!H54)*100 -> 0.15723424 | L60: =LN('l_NB,NEC'!O58/'l_NB,NEC'!O54)*100 -> 16.999332 | M60: =LN('l_NB,NEC'!P58/'l_NB,NEC'!P54)*100 -> 12.72933 | N60: ='fdr,edr'!S58*10000 -> 0.040208768 | O60: ='fdr,edr (TFP)'!S58*10000 -> 0.17663874 | P60: 500 | Q60: 0
B61: =EDATE(B60,3) -> 34335 | C61: =YEAR(B61)&"Q"&QUOTIENT(MONTH(B61)-1,3)+1 -> 1994Q1 | D61: =LN(l_Output!C59/l_Output!C55)*100 -> -0.060396517 | E61: =LN('l_IC,pi_d'!D59/'l_IC,pi_d'!D55)*100 -> -14.296192 | F61: =LN(l_pi_c!G59/l_pi_c!G55)*100 -> 0.20109268 | G61: =LN('l_IC,pi_d'!F59/'l_IC,pi_d'!F55)*100 -> -1.4948194 | H61: =LN('l_HC,WC'!M59/'l_HC,WC'!M55)*100 -> 3.3141415 | I61: =LN('l_HC,WC'!K59/'l_HC,WC'!K55)*100 -> -0.87753812 | J61: =l_NSR!B59 -> 2.2737933 | K61: =LN(l_Solow!H59/l_Solow!H55)*100 -> -0.44020345 | L61: =LN('l_NB,NEC'!O59/'l_NB,NEC'!O55)*100 -> 17.812574 | M61: =LN('l_NB,NEC'!P59/'l_NB,NEC'!P55)*100 -> 19.177733 | N61: ='fdr,edr'!S59*10000 -> 0.03781317 | O61: ='fdr,edr (TFP)'!S59*10000 -> 0.064862375 | Q61: 0
B62: =EDATE(B61,3) -> 34425 | C62: =YEAR(B62)&"Q"&QUOTIENT(MONTH(B62)-1,3)+1 -> 1994Q2 | D62: =LN(l_Output!C60/l_Output!C56)*100 -> 0.30315388 | E62: =LN('l_IC,pi_d'!D60/'l_IC,pi_d'!D56)*100 -> -8.4461211 | F62: =LN(l_pi_c!G60/l_pi_c!G56)*100 -> 0.7253455 | G62: =LN('l_IC,pi_d'!F60/'l_IC,pi_d'!F56)*100 -> -1.3557323 | H62: =LN('l_HC,WC'!M60/'l_HC,WC'!M56)*100 -> 5.0987422 | I62: =LN('l_HC,WC'!K60/'l_HC,WC'!K56)*100 -> -0.48903259 | J62: =l_NSR!B60 -> 2.10932 | K62: =LN(l_Solow!H60/l_Solow!H56)*100 -> -0.12784823 | L62: =LN('l_NB,NEC'!O60/'l_NB,NEC'!O56)*100 -> 0.49929662 | M62: =LN('l_NB,NEC'!P60/'l_NB,NEC'!P56)*100 -> 3.9686878 | N62: ='fdr,edr'!S60*10000 -> 1.08057 | O62: ='fdr,edr (TFP)'!S60*10000 -> 1.8428034 | Q62: 0
B63: =EDATE(B62,3) -> 34516 | C63: =YEAR(B63)&"Q"&QUOTIENT(MONTH(B63)-1,3)+1 -> 1994Q3 | D63: =LN(l_Output!C61/l_Output!C57)*100 -> 1.9925815 | E63: =LN('l_IC,pi_d'!D61/'l_IC,pi_d'!D57)*100 -> -2.6600197 | F63: =LN(l_pi_c!G61/l_pi_c!G57)*100 -> 0.052230367 | G63: =LN('l_IC,pi_d'!F61/'l_IC,pi_d'!F57)*100 -> -1.6371623 | H63: =LN('l_HC,WC'!M61/'l_HC,WC'!M57)*100 -> 1.5165762 | I63: =LN('l_HC,WC'!K61/'l_HC,WC'!K57)*100 -> -0.42248531 | J63: =l_NSR!B61 -> 2.13378 | K63: =LN(l_Solow!H61/l_Solow!H57)*100 -> 1.2510541 | L63: =LN('l_NB,NEC'!O61/'l_NB,NEC'!O57)*100 -> -12.216636 | M63: =LN('l_NB,NEC'!P61/'l_NB,NEC'!P57)*100 -> 2.3058253 | N63: ='fdr,edr'!S61*10000 -> 4.4679912 | O63: ='fdr,edr (TFP)'!S61*10000 -> 7.5833944 | Q63: 0
B64: =EDATE(B63,3) -> 34608 | C64: =YEAR(B64)&"Q"&QUOTIENT(MONTH(B64)-1,3)+1 -> 1994Q4 | D64: =LN(l_Output!C62/l_Output!C58)*100 -> 1.2072134 | E64: =LN('l_IC,pi_d'!D62/'l_IC,pi_d'!D58)*100 -> 4.0473647 | F64: =LN(l_pi_c!G62/l_pi_c!G58)*100 -> -0.067650323 | G64: =LN('l_IC,pi_d'!F62/'l_IC,pi_d'!F58)*100 -> -1.6363072 | H64: =LN('l_HC,WC'!M62/'l_HC,WC'!M58)*100 -> 3.0428049 | I64: =LN('l_HC,WC'!K62/'l_HC,WC'!K58)*100 -> 0.036326701 | J64: =l_NSR!B62 -> 2.2659467 | K64: =LN(l_Solow!H62/l_Solow!H58)*100 -> 0.45981841 | L64: =LN('l_NB,NEC'!O62/'l_NB,NEC'!O58)*100 -> -3.4104327 | M64: =LN('l_NB,NEC'!P62/'l_NB,NEC'!P58)*100 -> 8.6113109 | N64: ='fdr,edr'!S62*10000 -> 0.0040514958 | O64: ='fdr,edr (TFP)'!S62*10000 -> 0.0068082441 | Q64: 0
A65: =RIGHT(YEAR(B65),2) -> 95 | B65: =EDATE(B64,3) -> 34700 | C65: =YEAR(B65)&"Q"&QUOTIENT(MONTH(B65)-1,3)+1 -> 1995Q1 | D65: =LN(l_Output!C63/l_Output!C59)*100 -> 1.2618021 | E65: =LN('l_IC,pi_d'!D63/'l_IC,pi_d'!D59)*100 -> 3.5111484 | F65: =LN(l_pi_c!G63/l_pi_c!G59)*100 -> -0.35634836 | G65: =LN('l_IC,pi_d'!F63/'l_IC,pi_d'!F59)*100 -> -1.5516438 | H65: =LN('l_HC,WC'!M63/'l_HC,WC'!M59)*100 -> 2.3777723 | I65: =LN('l_HC,WC'!K63/'l_HC,WC'!K59)*100 -> -0.29517773 | J65: =l_NSR!B63 -> 2.2187033 | K65: =LN(l_Solow!H63/l_Solow!H59)*100 -> 0.89723029 | L65: =LN('l_NB,NEC'!O63/'l_NB,NEC'!O59)*100 -> -14.277196 | M65: =LN('l_NB,NEC'!P63/'l_NB,NEC'!P59)*100 -> -14.228347 | N65: ='fdr,edr'!S63*10000 -> 0.0014610214 | O65: ='fdr,edr (TFP)'!S63*10000 -> 0.003760037 | Q65: 0
B66: =EDATE(B65,3) -> 34790 | C66: =YEAR(B66)&"Q"&QUOTIENT(MONTH(B66)-1,3)+1 -> 1995Q2 | D66: =LN(l_Output!C64/l_Output!C60)*100 -> 2.7757749 | E66: =LN('l_IC,pi_d'!D64/'l_IC,pi_d'!D60)*100 -> 7.316925 | F66: =LN(l_pi_c!G64/l_pi_c!G60)*100 -> -0.88684342 | G66: =LN('l_IC,pi_d'!F64/'l_IC,pi_d'!F60)*100 -> -1.9270591 | H66: =LN('l_HC,WC'!M64/'l_HC,WC'!M60)*100 -> -0.22862436 | I66: =LN('l_HC,WC'!K64/'l_HC,WC'!K60)*100 -> 0.4160134 | J66: =l_NSR!B64 -> 1.3716667 | K66: =LN(l_Solow!H64/l_Solow!H60)*100 -> 1.7296748 | L66: =LN('l_NB,NEC'!O64/'l_NB,NEC'!O60)*100 -> -23.424977 | M66: =LN('l_NB,NEC'!P64/'l_NB,NEC'!P60)*100 -> -25.954709 | N66: ='fdr,edr'!S64*10000 -> 0.710876 | O66: ='fdr,edr (TFP)'!S64*10000 -> 1.8233952 | Q66: 0
B67: =EDATE(B66,3) -> 34881 | C67: =YEAR(B67)&"Q"&QUOTIENT(MONTH(B67)-1,3)+1 -> 1995Q3 | D67: =LN(l_Output!C65/l_Output!C61)*100 -> 2.8220551 | E67: =LN('l_IC,pi_d'!D65/'l_IC,pi_d'!D61)*100 -> 9.1839038 | F67: =LN(l_pi_c!G65/l_pi_c!G61)*100 -> -0.4190528 | G67: =LN('l_IC,pi_d'!F65/'l_IC,pi_d'!F61)*100 -> -1.4869465 | H67: =LN('l_HC,WC'!M65/'l_HC,WC'!M61)*100 -> 2.5494977 | I67: =LN('l_HC,WC'!K65/'l_HC,WC'!K61)*100 -> 0.024185331 | J67: =l_NSR!B65 -> 0.8 | K67: =LN(l_Solow!H65/l_Solow!H61)*100 -> 2.1746399 | L67: =LN('l_NB,NEC'!O65/'l_NB,NEC'!O61)*100 -> -12.33102 | M67: =LN('l_NB,NEC'!P65/'l_NB,NEC'!P61)*100 -> -5.4998479 | N67: ='fdr,edr'!S65*10000 -> 3.0884438 | O67: ='fdr,edr (TFP)'!S65*10000 -> 7.8846039 | Q67: 0
B68: =EDATE(B67,3) -> 34973 | C68: =YEAR(B68)&"Q"&QUOTIENT(MONTH(B68)-1,3)+1 -> 1995Q4 | D68: =LN(l_Output!C66/l_Output!C62)*100 -> 3.5087965 | E68: =LN('l_IC,pi_d'!D66/'l_IC,pi_d'!D62)*100 -> 9.3116306 | F68: =LN(l_pi_c!G66/l_pi_c!G62)*100 -> -0.47242688 | G68: =LN('l_IC,pi_d'!F66/'l_IC,pi_d'!F62)*100 -> -1.342569 | H68: =LN('l_HC,WC'!M66/'l_HC,WC'!M62)*100 -> 1.4950692 | I68: =LN('l_HC,WC'!K66/'l_HC,WC'!K62)*100 -> 0.54491217 | J68: =l_NSR!B66 -> 0.46333333 | K68: =LN(l_Solow!H66/l_Solow!H62)*100 -> 2.4634122 | L68: =LN('l_NB,NEC'!O66/'l_NB,NEC'!O62)*100 -> -4.1586842 | M68: =LN('l_NB,NEC'!P66/'l_NB,NEC'!P62)*100 -> 5.9615668 | N68: ='fdr,edr'!S66*10000 -> 0.021619189 | O68: ='fdr,edr (TFP)'!S66*10000 -> 0.054651584 | Q68: 0
B69: =EDATE(B68,3) -> 35065 | C69: =YEAR(B69)&"Q"&QUOTIENT(MONTH(B69)-1,3)+1 -> 1996Q1 | D69: =LN(l_Output!C67/l_Output!C63)*100 -> 3.2687761 | E69: =LN('l_IC,pi_d'!D67/'l_IC,pi_d'!D63)*100 -> 6.635237 | F69: =LN(l_pi_c!G67/l_pi_c!G63)*100 -> -0.43610699 | G69: =LN('l_IC,pi_d'!F67/'l_IC,pi_d'!F63)*100 -> -1.5641766 | H69: =LN('l_HC,WC'!M67/'l_HC,WC'!M63)*100 -> 1.1377946 | I69: =LN('l_HC,WC'!K67/'l_HC,WC'!K63)*100 -> 0.62839336 | J69: =l_NSR!B67 -> 0.46333333 | K69: =LN(l_Solow!H67/l_Solow!H63)*100 -> 1.9455733 | L69: =LN('l_NB,NEC'!O67/'l_NB,NEC'!O63)*100 -> 7.5400699 | M69: =LN('l_NB,NEC'!P67/'l_NB,NEC'!P63)*100 -> 24.642479 | N69: ='fdr,edr'!S67*10000 -> 0.052749071 | O69: ='fdr,edr (TFP)'!S67*10000 -> 0.026169796 | Q69: 0
B70: =EDATE(B69,3) -> 35156 | C70: =YEAR(B70)&"Q"&QUOTIENT(MONTH(B70)-1,3)+1 -> 1996Q2 | D70: =LN(l_Output!C68/l_Output!C64)*100 -> 3.6023246 | E70: =LN('l_IC,pi_d'!D68/'l_IC,pi_d'!D64)*100 -> 6.537653 | F70: =LN(l_pi_c!G68/l_pi_c!G64)*100 -> -0.21625727 | G70: =LN('l_IC,pi_d'!F68/'l_IC,pi_d'!F64)*100 -> -1.526203 | H70: =LN('l_HC,WC'!M68/'l_HC,WC'!M64)*100 -> 1.0247783 | I70: =LN('l_HC,WC'!K68/'l_HC,WC'!K64)*100 -> 0.83291225 | J70: =l_NSR!B68 -> 0.47666667 | K70: =LN(l_Solow!H68/l_Solow!H64)*100 -> 2.1754027 | L70: =LN('l_NB,NEC'!O68/'l_NB,NEC'!O64)*100 -> 21.361084 | M70: =LN('l_NB,NEC'!P68/'l_NB,NEC'!P64)*100 -> 39.822425 | N70: ='fdr,edr'!S68*10000 -> 1.5340938 | O70: ='fdr,edr (TFP)'!S68*10000 -> 0.75860452 | Q70: 0
B71: =EDATE(B70,3) -> 35247 | C71: =YEAR(B71)&"Q"&QUOTIENT(MONTH(B71)-1,3)+1 -> 1996Q3 | D71: =LN(l_Output!C69/l_Output!C65)*100 -> 2.5386441 | E71: =LN('l_IC,pi_d'!D69/'l_IC,pi_d'!D65)*100 -> 6.1522151 | F71: =LN(l_pi_c!G69/l_pi_c!G65)*100 -> -0.42746575 | G71: =LN('l_IC,pi_d'!F69/'l_IC,pi_d'!F65)*100 -> -1.6839715 | H71: =LN('l_HC,WC'!M69/'l_HC,WC'!M65)*100 -> 1.7555779 | I71: =LN('l_HC,WC'!K69/'l_HC,WC'!K65)*100 -> 0.42125553 | J71: =l_NSR!B69 -> 0.46333333 | K71: =LN(l_Solow!H69/l_Solow!H65)*100 -> 1.2387892 | L71: =LN('l_NB,NEC'!O69/'l_NB,NEC'!O65)*100 -> 9.6694028 | M71: =LN('l_NB,NEC'!P69/'l_NB,NEC'!P65)*100 -> 15.850652 | N71: ='fdr,edr'!S69*10000 -> 5.7882259 | O71: ='fdr,edr (TFP)'!S69*10000 -> 2.8563731 | Q71: 0
B72: =EDATE(B71,3) -> 35339 | C72: =YEAR(B72)&"Q"&QUOTIENT(MONTH(B72)-1,3)+1 -> 1996Q4 | D72: =LN(l_Output!C70/l_Output!C66)*100 -> 3.3349855 | E72: =LN('l_IC,pi_d'!D70/'l_IC,pi_d'!D66)*100 -> 4.5068692 | F72: =LN(l_pi_c!G70/l_pi_c!G66)*100 -> -0.67229474 | G72: =LN('l_IC,pi_d'!F70/'l_IC,pi_d'!F66)*100 -> -1.3337011 | H72: =LN('l_HC,WC'!M70/'l_HC,WC'!M66)*100 -> 0.6477924 | I72: =LN('l_HC,WC'!K70/'l_HC,WC'!K66)*100 -> 0.94531959 | J72: =l_NSR!B70 -> 0.48333333 | K72: =LN(l_Solow!H70/l_Solow!H66)*100 -> 1.4712874 | L72: =LN('l_NB,NEC'!O70/'l_NB,NEC'!O66)*100 -> -11.028581 | M72: =LN('l_NB,NEC'!P70/'l_NB,NEC'!P66)*100 -> 0.083887221 | N72: ='fdr,edr'!S70*10000 -> 0.014795261 | O72: ='fdr,edr (TFP)'!S70*10000 -> 0.0073196601 | Q72: 0
B73: =EDATE(B72,3) -> 35431 | C73: =YEAR(B73)&"Q"&QUOTIENT(MONTH(B73)-1,3)+1 -> 1997Q1 | D73: =LN(l_Output!C71/l_Output!C67)*100 -> 2.6953021 | E73: =LN('l_IC,pi_d'!D71/'l_IC,pi_d'!D67)*100 -> 5.7423589 | F73: =LN(l_pi_c!G71/l_pi_c!G67)*100 -> -0.32498008 | G73: =LN('l_IC,pi_d'!F71/'l_IC,pi_d'!F67)*100 -> -1.020342 | H73: =LN('l_HC,WC'!M71/'l_HC,WC'!M67)*100 -> 4.202482 | I73: =LN('l_HC,WC'!K71/'l_HC,WC'!K67)*100 -> -0.65442919 | J73: =l_NSR!B71 -> 0.49666667 | K73: =LN(l_Solow!H71/l_Solow!H67)*100 -> 1.9980262 | L73: =LN('l_NB,NEC'!O71/'l_NB,NEC'!O67)*100 -> -32.172312 | M73: =LN('l_NB,NEC'!P71/'l_NB,NEC'!P67)*100 -> -9.8414345 | N73: ='fdr,edr'!S71*10000 -> 1.9875923e-06 | O73: ='fdr,edr (TFP)'!S71*10000 -> 1.5301783e-05 | Q73: 0
B74: =EDATE(B73,3) -> 35521 | C74: =YEAR(B74)&"Q"&QUOTIENT(MONTH(B74)-1,3)+1 -> 1997Q2 | D74: =LN(l_Output!C72/l_Output!C68)*100 -> 0.62629458 | E74: =LN('l_IC,pi_d'!D72/'l_IC,pi_d'!D68)*100 -> 2.4906375 | F74: =LN(l_pi_c!G72/l_pi_c!G68)*100 -> -0.18872438 | G74: =LN('l_IC,pi_d'!F72/'l_IC,pi_d'!F68)*100 -> -0.38166449 | H74: =LN('l_HC,WC'!M72/'l_HC,WC'!M68)*100 -> 2.4441291 | I74: =LN('l_HC,WC'!K72/'l_HC,WC'!K68)*100 -> 0.90245045 | J74: =l_NSR!B72 -> 0.49666667 | K74: =LN(l_Solow!H72/l_Solow!H68)*100 -> -0.95480278 | L74: =LN('l_NB,NEC'!O72/'l_NB,NEC'!O68)*100 -> -21.539664 | M74: =LN('l_NB,NEC'!P72/'l_NB,NEC'!P68)*100 -> -5.1530846 | N74: ='fdr,edr'!S72*10000 -> 0.027823039 | O74: ='fdr,edr (TFP)'!S72*10000 -> 0.21371221 | Q74: 0
B75: =EDATE(B74,3) -> 35612 | C75: =YEAR(B75)&"Q"&QUOTIENT(MONTH(B75)-1,3)+1 -> 1997Q3 | D75: =LN(l_Output!C73/l_Output!C69)*100 -> 0.70916785 | E75: =LN('l_IC,pi_d'!D73/'l_IC,pi_d'!D69)*100 -> 1.671008 | F75: =LN(l_pi_c!G73/l_pi_c!G69)*100 -> -0.28117528 | G75: =LN('l_IC,pi_d'!F73/'l_IC,pi_d'!F69)*100 -> -0.46139135 | H75: =LN('l_HC,WC'!M73/'l_HC,WC'!M69)*100 -> 3.4425312 | I75: =LN('l_HC,WC'!K73/'l_HC,WC'!K69)*100 -> -0.74815311 | J75: =l_NSR!B73 -> 0.49 | K75: =LN(l_Solow!H73/l_Solow!H69)*100 -> 0.22314876 | L75: =LN('l_NB,NEC'!O73/'l_NB,NEC'!O69)*100 -> -27.068755 | M75: =LN('l_NB,NEC'!P73/'l_NB,NEC'!P69)*100 -> -12.650855 | N75: ='fdr,edr'!S73*10000 -> 0.39845435 | O75: ='fdr,edr (TFP)'!S73*10000 -> 3.0520697 | P75: 500 | Q75: 0
B76: =EDATE(B75,3) -> 35704 | C76: =YEAR(B76)&"Q"&QUOTIENT(MONTH(B76)-1,3)+1 -> 1997Q4 | D76: =LN(l_Output!C74/l_Output!C70)*100 -> -0.30217626 | E76: =LN('l_IC,pi_d'!D74/'l_IC,pi_d'!D70)*100 -> 3.7985168 | F76: =LN(l_pi_c!G74/l_pi_c!G70)*100 -> 0.035208279 | G76: =LN('l_IC,pi_d'!F74/'l_IC,pi_d'!F70)*100 -> -0.40794374 | H76: =LN('l_HC,WC'!M74/'l_HC,WC'!M70)*100 -> 3.9196866 | I76: =LN('l_HC,WC'!K74/'l_HC,WC'!K70)*100 -> -1.7877758 | J76: =l_NSR!B74 -> 0.45333333 | K76: =LN(l_Solow!H74/l_Solow!H70)*100 -> 0.076412638 | L76: =LN('l_NB,NEC'!O74/'l_NB,NEC'!O70)*100 -> -43.547327 | M76: =LN('l_NB,NEC'!P74/'l_NB,NEC'!P70)*100 -> -18.503879 | N76: ='fdr,edr'!S74*10000 -> 0.079422727 | O76: ='fdr,edr (TFP)'!S74*10000 -> 0.60849173 | P76: 500 | Q76: 0
B77: =EDATE(B76,3) -> 35796 | C77: =YEAR(B77)&"Q"&QUOTIENT(MONTH(B77)-1,3)+1 -> 1998Q1 | D77: =LN(l_Output!C75/l_Output!C71)*100 -> -1.7205773 | E77: =LN('l_IC,pi_d'!D75/'l_IC,pi_d'!D71)*100 -> 1.3303652 | F77: =LN(l_pi_c!G75/l_pi_c!G71)*100 -> 0.035475468 | G77: =LN('l_IC,pi_d'!F75/'l_IC,pi_d'!F71)*100 -> -0.65964884 | H77: =LN('l_HC,WC'!M75/'l_HC,WC'!M71)*100 -> 1.1783521 | I77: =LN('l_HC,WC'!K75/'l_HC,WC'!K71)*100 -> -1.0414799 | J77: =l_NSR!B75 -> 0.43333333 | K77: =LN(l_Solow!H75/l_Solow!H71)*100 -> -1.720814 | L77: =LN('l_NB,NEC'!O75/'l_NB,NEC'!O71)*100 -> -19.499848 | M77: =LN('l_NB,NEC'!P75/'l_NB,NEC'!P71)*100 -> -7.0683334 | N77: ='fdr,edr'!S75*10000 -> 0.0023643526 | O77: ='fdr,edr (TFP)'!S75*10000 -> 0.010025065 | P77: 500 | Q77: 0
B78: =EDATE(B77,3) -> 35886 | C78: =YEAR(B78)&"Q"&QUOTIENT(MONTH(B78)-1,3)+1 -> 1998Q2 | D78: =LN(l_Output!C76/l_Output!C72)*100 -> -1.3424904 | E78: =LN('l_IC,pi_d'!D76/'l_IC,pi_d'!D72)*100 -> 0.25815789 | F78: =LN(l_pi_c!G76/l_pi_c!G72)*100 -> -0.28263233 | G78: =LN('l_IC,pi_d'!F76/'l_IC,pi_d'!F72)*100 -> -0.98223243 | H78: =LN('l_HC,WC'!M76/'l_HC,WC'!M72)*100 -> 1.514711 | I78: =LN('l_HC,WC'!K76/'l_HC,WC'!K72)*100 -> -2.3796036 | J78: =l_NSR!B76 -> 0.43666667 | K78: =LN(l_Solow!H76/l_Solow!H72)*100 -> -0.55279559 | L78: =LN('l_NB,NEC'!O76/'l_NB,NEC'!O72)*100 -> -45.824338 | M78: =LN('l_NB,NEC'!P76/'l_NB,NEC'!P72)*100 -> -18.471639 | N78: ='fdr,edr'!S76*10000 -> 0.34811661 | O78: ='fdr,edr (TFP)'!S76*10000 -> 1.4727499 | P78: 500 | Q78: 0
B79: =EDATE(B78,3) -> 35977 | C79: =YEAR(B79)&"Q"&QUOTIENT(MONTH(B79)-1,3)+1 -> 1998Q3 | D79: =LN(l_Output!C77/l_Output!C73)*100 -> -1.3439512 | E79: =LN('l_IC,pi_d'!D77/'l_IC,pi_d'!D73)*100 -> -0.95859513 | F79: =LN(l_pi_c!G77/l_pi_c!G73)*100 -> -0.43132741 | G79: =LN('l_IC,pi_d'!F77/'l_IC,pi_d'!F73)*100 -> -0.89805069 | H79: =LN('l_HC,WC'!M77/'l_HC,WC'!M73)*100 -> -0.42093624 | I79: =LN('l_HC,WC'!K77/'l_HC,WC'!K73)*100 -> -1.8685618 | J79: =l_NSR!B77 -> 0.38666667 | K79: =LN(l_Solow!H77/l_Solow!H73)*100 -> -0.87924351 | L79: =LN('l_NB,NEC'!O77/'l_NB,NEC'!O73)*100 -> -71.898112 | M79: =LN('l_NB,NEC'!P77/'l_NB,NEC'!P73)*100 -> -19.02676 | N79: ='fdr,edr'!S77*10000 -> 0.41576938 | O79: ='fdr,edr (TFP)'!S77*10000 -> 1.7539858 | P79: 500 | Q79: 0
B80: =EDATE(B79,3) -> 36069 | C80: =YEAR(B80)&"Q"&QUOTIENT(MONTH(B80)-1,3)+1 -> 1998Q4 | D80: =LN(l_Output!C78/l_Output!C74)*100 -> -0.56041024 | E80: =LN('l_IC,pi_d'!D78/'l_IC,pi_d'!D74)*100 -> -5.7484664 | F80: =LN(l_pi_c!G78/l_pi_c!G74)*100 -> -0.36161999 | G80: =LN('l_IC,pi_d'!F78/'l_IC,pi_d'!F74)*100 -> -1.7441465 | H80: =LN('l_HC,WC'!M78/'l_HC,WC'!M74)*100 -> -0.92143088 | I80: =LN('l_HC,WC'!K78/'l_HC,WC'!K74)*100 -> -1.3183369 | J80: =l_NSR!B78 -> 0.23 | K80: =LN(l_Solow!H78/l_Solow!H74)*100 -> -0.25801942 | L80: =LN('l_NB,NEC'!O78/'l_NB,NEC'!O74)*100 -> -27.18873 | M80: =LN('l_NB,NEC'!P78/'l_NB,NEC'!P74)*100 -> 1.4951503 | N80: ='fdr,edr'!S78*10000 -> 0.070425351 | O80: ='fdr,edr (TFP)'!S78*10000 -> 0.29414783 | P80: 500 | Q80: 0
B81: =EDATE(B80,3) -> 36161 | C81: =YEAR(B81)&"Q"&QUOTIENT(MONTH(B81)-1,3)+1 -> 1999Q1 | D81: =LN(l_Output!C79/l_Output!C75)*100 -> -0.70636283 | E81: =LN('l_IC,pi_d'!D79/'l_IC,pi_d'!D75)*100 -> -7.0364464 | F81: =LN(l_pi_c!G79/l_pi_c!G75)*100 -> -0.82881865 | G81: =LN('l_IC,pi_d'!F79/'l_IC,pi_d'!F75)*100 -> -1.8356351 | H81: =LN('l_HC,WC'!M79/'l_HC,WC'!M75)*100 -> -0.46212177 | I81: =LN('l_HC,WC'!K79/'l_HC,WC'!K75)*100 -> -1.9653821 | J81: =l_NSR!B79 -> 0.15 | K81: =LN(l_Solow!H79/l_Solow!H75)*100 -> -0.089808126 | L81: =LN('l_NB,NEC'!O79/'l_NB,NEC'!O75)*100 -> -4.100817 | M81: =LN('l_NB,NEC'!P79/'l_NB,NEC'!P75)*100 -> 10.310462 | N81: ='fdr,edr'!S79*10000 -> 7.0120567e-05 | O81: ='fdr,edr (TFP)'!S79*10000 -> 0.0001898692 | P81: 500 | Q81: 0
B82: =EDATE(B81,3) -> 36251 | C82: =YEAR(B82)&"Q"&QUOTIENT(MONTH(B82)-1,3)+1 -> 1999Q2 | D82: =LN(l_Output!C80/l_Output!C76)*100 -> 0.12416721 | E82: =LN('l_IC,pi_d'!D80/'l_IC,pi_d'!D76)*100 -> -5.2834207 | F82: =LN(l_pi_c!G80/l_pi_c!G76)*100 -> -1.0575867 | G82: =LN('l_IC,pi_d'!F80/'l_IC,pi_d'!F76)*100 -> -2.1643088 | H82: =LN('l_HC,WC'!M80/'l_HC,WC'!M76)*100 -> 0.26435405 | I82: =LN('l_HC,WC'!K80/'l_HC,WC'!K76)*100 -> -2.705861 | J82: =l_NSR!B80 -> 0.03 | K82: =LN(l_Solow!H80/l_Solow!H76)*100 -> 1.1771687 | L82: =LN('l_NB,NEC'!O80/'l_NB,NEC'!O76)*100 -> 4.2152533 | M82: =LN('l_NB,NEC'!P80/'l_NB,NEC'!P76)*100 -> 25.7518 | N82: ='fdr,edr'!S80*10000 -> 0.13469226 | O82: ='fdr,edr (TFP)'!S80*10000 -> 0.36284771 | Q82: 0
B83: =EDATE(B82,3) -> 36342 | C83: =YEAR(B83)&"Q"&QUOTIENT(MONTH(B83)-1,3)+1 -> 1999Q3 | D83: =LN(l_Output!C81/l_Output!C77)*100 -> 0.48303208 | E83: =LN('l_IC,pi_d'!D81/'l_IC,pi_d'!D77)*100 -> -5.1621334 | F83: =LN(l_pi_c!G81/l_pi_c!G77)*100 -> -1.3291397 | G83: =LN('l_IC,pi_d'!F81/'l_IC,pi_d'!F77)*100 -> -2.0609884 | H83: =LN('l_HC,WC'!M81/'l_HC,WC'!M77)*100 -> -0.57657082 | I83: =LN('l_HC,WC'!K81/'l_HC,WC'!K77)*100 -> -0.76157119 | J83: =l_NSR!B81 -> 0.03 | K83: =LN(l_Solow!H81/l_Solow!H77)*100 -> 0.14321807 | L83: =LN('l_NB,NEC'!O81/'l_NB,NEC'!O77)*100 -> 58.134091 | M83: =LN('l_NB,NEC'!P81/'l_NB,NEC'!P77)*100 -> 44.994786 | N83: ='fdr,edr'!S81*10000 -> 0.86047878 | O83: ='fdr,edr (TFP)'!S81*10000 -> 2.3234807 | Q83: 0
B84: =EDATE(B83,3) -> 36434 | C84: =YEAR(B84)&"Q"&QUOTIENT(MONTH(B84)-1,3)+1 -> 1999Q4 | D84: =LN(l_Output!C82/l_Output!C78)*100 -> -0.27389055 | E84: =LN('l_IC,pi_d'!D82/'l_IC,pi_d'!D78)*100 -> -1.3984915 | F84: =LN(l_pi_c!G82/l_pi_c!G78)*100 -> -1.7008878 | G84: =LN('l_IC,pi_d'!F82/'l_IC,pi_d'!F78)*100 -> -1.574108 | H84: =LN('l_HC,WC'!M82/'l_HC,WC'!M78)*100 -> 0.50359188 | I84: =LN('l_HC,WC'!K82/'l_HC,WC'!K78)*100 -> -1.7067498 | J84: =l_NSR!B82 -> 0.023333333 | K84: =LN(l_Solow!H82/l_Solow!H78)*100 -> -0.1218089 | L84: =LN('l_NB,NEC'!O82/'l_NB,NEC'!O78)*100 -> 30.12438 | M84: =LN('l_NB,NEC'!P82/'l_NB,NEC'!P78)*100 -> 57.252251 | N84: ='fdr,edr'!S82*10000 -> 0.023609774 | O84: ='fdr,edr (TFP)'!S82*10000 -> 0.063172723 | Q84: 0
A85: 00 | B85: =EDATE(B84,3) -> 36526 | C85: =YEAR(B85)&"Q"&QUOTIENT(MONTH(B85)-1,3)+1 -> 2000Q1 | D85: =LN(l_Output!C83/l_Output!C79)*100 -> 2.8161647 | E85: =LN('l_IC,pi_d'!D83/'l_IC,pi_d'!D79)*100 -> 5.1542086 | F85: =LN(l_pi_c!G83/l_pi_c!G79)*100 -> -1.4749549 | G85: =LN('l_IC,pi_d'!F83/'l_IC,pi_d'!F79)*100 -> -0.85921105 | H85: =LN('l_HC,WC'!M83/'l_HC,WC'!M79)*100 -> -1.3738416 | I85: =LN('l_HC,WC'!K83/'l_HC,WC'!K79)*100 -> 1.0389082 | J85: =l_NSR!B83 -> 0.023333333 | K85: =LN(l_Solow!H83/l_Solow!H79)*100 -> 1.2311941 | L85: =LN('l_NB,NEC'!O83/'l_NB,NEC'!O79)*100 -> -0.18980909 | M85: =LN('l_NB,NEC'!P83/'l_NB,NEC'!P79)*100 -> 41.541046 | N85: ='fdr,edr'!S83*10000 -> 0.00039832044 | O85: ='fdr,edr (TFP)'!S83*10000 -> 0.00018825481 | Q85: 0
B86: =EDATE(B85,3) -> 36617 | C86: =YEAR(B86)&"Q"&QUOTIENT(MONTH(B86)-1,3)+1 -> 2000Q2 | D86: =LN(l_Output!C84/l_Output!C80)*100 -> 2.9312354 | E86: =LN('l_IC,pi_d'!D84/'l_IC,pi_d'!D80)*100 -> 2.9642222 | F86: =LN(l_pi_c!G84/l_pi_c!G80)*100 -> -1.526613 | G86: =LN('l_IC,pi_d'!F84/'l_IC,pi_d'!F80)*100 -> -1.0178827 | H86: =LN('l_HC,WC'!M84/'l_HC,WC'!M80)*100 -> -0.55005641 | I86: =LN('l_HC,WC'!K84/'l_HC,WC'!K80)*100 -> 0.78675596 | J86: =l_NSR!B84 -> 0.02 | K86: =LN(l_Solow!H84/l_Solow!H80)*100 -> 1.4709019 | L86: =LN('l_NB,NEC'!O84/'l_NB,NEC'!O80)*100 -> -9.5318314 | M86: =LN('l_NB,NEC'!P84/'l_NB,NEC'!P80)*100 -> 19.724404 | N86: ='fdr,edr'!S84*10000 -> 0.19309651 | O86: ='fdr,edr (TFP)'!S84*10000 -> 0.090973214 | Q86: 0
B87: =EDATE(B86,3) -> 36708 | C87: =YEAR(B87)&"Q"&QUOTIENT(MONTH(B87)-1,3)+1 -> 2000Q3 | D87: =LN(l_Output!C85/l_Output!C81)*100 -> 2.486412 | E87: =LN('l_IC,pi_d'!D85/'l_IC,pi_d'!D81)*100 -> 6.9666478 | F87: =LN(l_pi_c!G85/l_pi_c!G81)*100 -> -1.1218716 | G87: =LN('l_IC,pi_d'!F85/'l_IC,pi_d'!F81)*100 -> -1.1185912 | H87: =LN('l_HC,WC'!M85/'l_HC,WC'!M81)*100 -> 0.47538069 | I87: =LN('l_HC,WC'!K85/'l_HC,WC'!K81)*100 -> 0.077600769 | J87: =l_NSR!B85 -> 0.14333333 | K87: =LN(l_Solow!H85/l_Solow!H81)*100 -> 1.6591402 | L87: =LN('l_NB,NEC'!O85/'l_NB,NEC'!O81)*100 -> -22.89471 | M87: =LN('l_NB,NEC'!P85/'l_NB,NEC'!P81)*100 -> 4.6178767 | N87: ='fdr,edr'!S85*10000 -> 6.6112115 | O87: ='fdr,edr (TFP)'!S85*10000 -> 3.1092564 | Q87: 0
B88: =EDATE(B87,3) -> 36800 | C88: =YEAR(B88)&"Q"&QUOTIENT(MONTH(B88)-1,3)+1 -> 2000Q4 | D88: =LN(l_Output!C86/l_Output!C82)*100 -> 3.4729503 | E88: =LN('l_IC,pi_d'!D86/'l_IC,pi_d'!D82)*100 -> 8.9151369 | F88: =LN(l_pi_c!G86/l_pi_c!G82)*100 -> -1.2738907 | G88: =LN('l_IC,pi_d'!F86/'l_IC,pi_d'!F82)*100 -> -1.4042704 | H88: =LN('l_HC,WC'!M86/'l_HC,WC'!M82)*100 -> 0.27989262 | I88: =LN('l_HC,WC'!K86/'l_HC,WC'!K82)*100 -> 0.9601681 | J88: =l_NSR!B86 -> 0.24666667 | K88: =LN(l_Solow!H86/l_Solow!H82)*100 -> 1.9513875 | L88: =LN('l_NB,NEC'!O86/'l_NB,NEC'!O82)*100 -> -19.270567 | M88: =LN('l_NB,NEC'!P86/'l_NB,NEC'!P82)*100 -> -28.309847 | N88: ='fdr,edr'!S86*10000 -> 0.097329789 | O88: ='fdr,edr (TFP)'!S86*10000 -> 0.045556435 | Q88: 0
B89: =EDATE(B88,3) -> 36892 | C89: =YEAR(B89)&"Q"&QUOTIENT(MONTH(B89)-1,3)+1 -> 2001Q1 | D89: =LN(l_Output!C87/l_Output!C83)*100 -> 2.5561116 | E89: =LN('l_IC,pi_d'!D87/'l_IC,pi_d'!D83)*100 -> 5.7923092 | F89: =LN(l_pi_c!G87/l_pi_c!G83)*100 -> -0.84516907 | G89: =LN('l_IC,pi_d'!F87/'l_IC,pi_d'!F83)*100 -> -2.4607444 | H89: =LN('l_HC,WC'!M87/'l_HC,WC'!M83)*100 -> 2.6300382 | I89: =LN('l_HC,WC'!K87/'l_HC,WC'!K83)*100 -> -1.1880942 | J89: =l_NSR!B87 -> 0.20333333 | K89: =LN(l_Solow!H87/l_Solow!H83)*100 -> 2.5424572 | L89: =LN('l_NB,NEC'!O87/'l_NB,NEC'!O83)*100 -> -64.992121 | M89: =LN('l_NB,NEC'!P87/'l_NB,NEC'!P83)*100 -> -30.20282 | N89: ='fdr,edr'!S87*10000 -> 0.00092003174 | O89: ='fdr,edr (TFP)'!S87*10000 -> 0.0067055762 | P89: 500 | Q89: 0
B90: =EDATE(B89,3) -> 36982 | C90: =YEAR(B90)&"Q"&QUOTIENT(MONTH(B90)-1,3)+1 -> 2001Q2 | D90: =LN(l_Output!C88/l_Output!C84)*100 -> 1.3448073 | E90: =LN('l_IC,pi_d'!D88/'l_IC,pi_d'!D84)*100 -> 4.52361 | F90: =LN(l_pi_c!G88/l_pi_c!G84)*100 -> -1.1836979 | G90: =LN('l_IC,pi_d'!F88/'l_IC,pi_d'!F84)*100 -> -2.4102289 | H90: =LN('l_HC,WC'!M88/'l_HC,WC'!M84)*100 -> 0.83790684 | I90: =LN('l_HC,WC'!K88/'l_HC,WC'!K84)*100 -> -0.54533969 | J90: =l_NSR!B88 -> 0.02 | K90: =LN(l_Solow!H88/l_Solow!H84)*100 -> 0.80468771 | L90: =LN('l_NB,NEC'!O88/'l_NB,NEC'!O84)*100 -> -16.575272 | M90: =LN('l_NB,NEC'!P88/'l_NB,NEC'!P84)*100 -> -20.342205 | N90: ='fdr,edr'!S88*10000 -> 0.1853677 | O90: ='fdr,edr (TFP)'!S88*10000 -> 1.3476179 | P90: 500 | Q90: 0
B91: =EDATE(B90,3) -> 37073 | C91: =YEAR(B91)&"Q"&QUOTIENT(MONTH(B91)-1,3)+1 -> 2001Q3 | D91: =LN(l_Output!C89/l_Output!C85)*100 -> 0.22275943 | E91: =LN('l_IC,pi_d'!D89/'l_IC,pi_d'!D85)*100 -> -0.70434123 | F91: =LN(l_pi_c!G89/l_pi_c!G85)*100 -> -1.2613716 | G91: =LN('l_IC,pi_d'!F89/'l_IC,pi_d'!F85)*100 -> -2.6462551 | H91: =LN('l_HC,WC'!M89/'l_HC,WC'!M85)*100 -> 0.41966841 | I91: =LN('l_HC,WC'!K89/'l_HC,WC'!K85)*100 -> -1.5582556 | J91: =l_NSR!B89 -> 0.0083333333 | K91: =LN(l_Solow!H89/l_Solow!H85)*100 -> 0.337741 | L91: =LN('l_NB,NEC'!O89/'l_NB,NEC'!O85)*100 -> -35.225687 | M91: =LN('l_NB,NEC'!P89/'l_NB,NEC'!P85)*100 -> -36.527531 | N91: ='fdr,edr'!S89*10000 -> 0.29056918 | O91: ='fdr,edr (TFP)'!S89*10000 -> 2.1083619 | P91: 500 | Q91: 0
B92: =EDATE(B91,3) -> 37165 | C92: =YEAR(B92)&"Q"&QUOTIENT(MONTH(B92)-1,3)+1 -> 2001Q4 | D92: =LN(l_Output!C90/l_Output!C86)*100 -> -1.0720442 | E92: =LN('l_IC,pi_d'!D90/'l_IC,pi_d'!D86)*100 -> -7.6605701 | F92: =LN(l_pi_c!G90/l_pi_c!G86)*100 -> -1.1658894 | G92: =LN('l_IC,pi_d'!F90/'l_IC,pi_d'!F86)*100 -> -2.7330181 | H92: =LN('l_HC,WC'!M90/'l_HC,WC'!M86)*100 -> -1.7824998 | I92: =LN('l_HC,WC'!K90/'l_HC,WC'!K86)*100 -> -1.6235563 | J92: =l_NSR!B90 -> 0.0023333333 | K92: =LN(l_Solow!H90/l_Solow!H86)*100 -> -0.81072127 | L92: =LN('l_NB,NEC'!O90/'l_NB,NEC'!O86)*100 -> -44.865646 | M92: =LN('l_NB,NEC'!P90/'l_NB,NEC'!P86)*100 -> -18.245343 | N92: ='fdr,edr'!S90*10000 -> 0.0087759835 | O92: ='fdr,edr (TFP)'!S90*10000 -> 0.063297747 | P92: 500 | Q92: 0
B93: =EDATE(B92,3) -> 37257 | C93: =YEAR(B93)&"Q"&QUOTIENT(MONTH(B93)-1,3)+1 -> 2002Q1 | D93: =LN(l_Output!C91/l_Output!C87)*100 -> -1.6015994 | E93: =LN('l_IC,pi_d'!D91/'l_IC,pi_d'!D87)*100 -> -9.0033282 | F93: =LN(l_pi_c!G91/l_pi_c!G87)*100 -> -1.1791479 | G93: =LN('l_IC,pi_d'!F91/'l_IC,pi_d'!F87)*100 -> -2.184132 | H93: =LN('l_HC,WC'!M91/'l_HC,WC'!M87)*100 -> -0.57912172 | I93: =LN('l_HC,WC'!K91/'l_HC,WC'!K87)*100 -> -2.6716444 | J93: =l_NSR!B91 -> 0.0013333333 | K93: =LN(l_Solow!H91/l_Solow!H87)*100 -> -0.57073467 | L93: =LN('l_NB,NEC'!O91/'l_NB,NEC'!O87)*100 -> 0.69165758 | M93: =LN('l_NB,NEC'!P91/'l_NB,NEC'!P87)*100 -> -11.87007 | N93: ='fdr,edr'!S91*10000 -> 0.002510247 | O93: ='fdr,edr (TFP)'!S91*10000 -> 0.010011023 | P93: 500 | Q93: 0
B94: =EDATE(B93,3) -> 37347 | C94: =YEAR(B94)&"Q"&QUOTIENT(MONTH(B94)-1,3)+1 -> 2002Q2 | D94: =LN(l_Output!C92/l_Output!C88)*100 -> 0.025515853 | E94: =LN('l_IC,pi_d'!D92/'l_IC,pi_d'!D88)*100 -> -7.6355873 | F94: =LN(l_pi_c!G92/l_pi_c!G88)*100 -> -1.4324432 | G94: =LN('l_IC,pi_d'!F92/'l_IC,pi_d'!F88)*100 -> -2.1832482 | H94: =LN('l_HC,WC'!M92/'l_HC,WC'!M88)*100 -> -2.5317739 | I94: =LN('l_HC,WC'!K92/'l_HC,WC'!K88)*100 -> -2.0357904 | J94: =l_NSR!B92 -> 0.001 | K94: =LN(l_Solow!H92/l_Solow!H88)*100 -> 0.59453803 | L94: =LN('l_NB,NEC'!O92/'l_NB,NEC'!O88)*100 -> -38.37539 | M94: =LN('l_NB,NEC'!P92/'l_NB,NEC'!P88)*100 -> -18.361324 | N94: ='fdr,edr'!S92*10000 -> 0.012156681 | O94: ='fdr,edr (TFP)'!S92*10000 -> 0.048310744 | Q94: 0
B95: =EDATE(B94,3) -> 37438 | C95: =YEAR(B95)&"Q"&QUOTIENT(MONTH(B95)-1,3)+1 -> 2002Q3 | D95: =LN(l_Output!C93/l_Output!C89)*100 -> 1.5261896 | E95: =LN('l_IC,pi_d'!D93/'l_IC,pi_d'!D89)*100 -> -4.0625283 | F95: =LN(l_pi_c!G93/l_pi_c!G89)*100 -> -1.4835547 | G95: =LN('l_IC,pi_d'!F93/'l_IC,pi_d'!F89)*100 -> -2.2595155 | H95: =LN('l_HC,WC'!M93/'l_HC,WC'!M89)*100 -> -1.7516157 | I95: =LN('l_HC,WC'!K93/'l_HC,WC'!K89)*100 -> -0.88611067 | J95: =l_NSR!B93 -> 0.003 | K95: =LN(l_Solow!H93/l_Solow!H89)*100 -> 1.3520012 | L95: =LN('l_NB,NEC'!O93/'l_NB,NEC'!O89)*100 -> -15.349344 | M95: =LN('l_NB,NEC'!P93/'l_NB,NEC'!P89)*100 -> -6.5207172 | N95: ='fdr,edr'!S93*10000 -> 0.70238985 | O95: ='fdr,edr (TFP)'!S93*10000 -> 2.7849503 | Q95: 0
B96: =EDATE(B95,3) -> 37530 | C96: =YEAR(B96)&"Q"&QUOTIENT(MONTH(B96)-1,3)+1 -> 2002Q4 | D96: =LN(l_Output!C94/l_Output!C90)*100 -> 2.1501825 | E96: =LN('l_IC,pi_d'!D94/'l_IC,pi_d'!D90)*100 -> 0.025409719 | F96: =LN(l_pi_c!G94/l_pi_c!G90)*100 -> -1.4733719 | G96: =LN('l_IC,pi_d'!F94/'l_IC,pi_d'!F90)*100 -> -1.9511338 | H96: =LN('l_HC,WC'!M94/'l_HC,WC'!M90)*100 -> -0.95597529 | I96: =LN('l_HC,WC'!K94/'l_HC,WC'!K90)*100 -> -0.92216606 | J96: =l_NSR!B94 -> 0.002 | K96: =LN(l_Solow!H94/l_Solow!H90)*100 -> 2.0203265 | L96: =LN('l_NB,NEC'!O94/'l_NB,NEC'!O90)*100 -> -24.372268 | M96: =LN('l_NB,NEC'!P94/'l_NB,NEC'!P90)*100 -> -16.988657 | N96: ='fdr,edr'!S94*10000 -> 0.096324562 | O96: ='fdr,edr (TFP)'!S94*10000 -> 0.3797753 | Q96: 0
B97: =EDATE(B96,3) -> 37622 | C97: =YEAR(B97)&"Q"&QUOTIENT(MONTH(B97)-1,3)+1 -> 2003Q1 | D97: =LN(l_Output!C95/l_Output!C91)*100 -> 2.0051584 | E97: =LN('l_IC,pi_d'!D95/'l_IC,pi_d'!D91)*100 -> 1.2358154 | F97: =LN(l_pi_c!G95/l_pi_c!G91)*100 -> -2.2432488 | G97: =LN('l_IC,pi_d'!F95/'l_IC,pi_d'!F91)*100 -> -2.504395 | H97: =LN('l_HC,WC'!M95/'l_HC,WC'!M91)*100 -> -0.61803767 | I97: =LN('l_HC,WC'!K95/'l_HC,WC'!K91)*100 -> 0.11365559 | J97: =l_NSR!B95 -> 0.0016666667 | K97: =LN(l_Solow!H95/l_Solow!H91)*100 -> 0.93466828 | L97: =LN('l_NB,NEC'!O95/'l_NB,NEC'!O91)*100 -> -34.947323 | M97: =LN('l_NB,NEC'!P95/'l_NB,NEC'!P91)*100 -> -26.468386 | N97: ='fdr,edr'!S95*10000 -> 0.0024102244 | O97: ='fdr,edr (TFP)'!S95*10000 -> 0.0061859544 | Q97: 0
B98: =EDATE(B97,3) -> 37712 | C98: =YEAR(B98)&"Q"&QUOTIENT(MONTH(B98)-1,3)+1 -> 2003Q2 | D98: =LN(l_Output!C96/l_Output!C92)*100 -> 1.8259059 | E98: =LN('l_IC,pi_d'!D96/'l_IC,pi_d'!D92)*100 -> 4.1023718 | F98: =LN(l_pi_c!G96/l_pi_c!G92)*100 -> -1.2858763 | G98: =LN('l_IC,pi_d'!F96/'l_IC,pi_d'!F92)*100 -> -2.5015814 | H98: =LN('l_HC,WC'!M96/'l_HC,WC'!M92)*100 -> -0.43201938 | I98: =LN('l_HC,WC'!K96/'l_HC,WC'!K92)*100 -> 0.81704798 | J98: =l_NSR!B96 -> 0.001 | K98: =LN(l_Solow!H96/l_Solow!H92)*100 -> 0.6574646 | L98: =LN('l_NB,NEC'!O96/'l_NB,NEC'!O92)*100 -> -18.921716 | M98: =LN('l_NB,NEC'!P96/'l_NB,NEC'!P92)*100 -> -9.4538628 | N98: ='fdr,edr'!S96*10000 -> 0.18034416 | O98: ='fdr,edr (TFP)'!S96*10000 -> 0.46170231 | Q98: 0
B99: =EDATE(B98,3) -> 37803 | C99: =YEAR(B99)&"Q"&QUOTIENT(MONTH(B99)-1,3)+1 -> 2003Q3 | D99: =LN(l_Output!C97/l_Output!C93)*100 -> 1.6900789 | E99: =LN('l_IC,pi_d'!D97/'l_IC,pi_d'!D93)*100 -> 0.78621637 | F99: =LN(l_pi_c!G97/l_pi_c!G93)*100 -> -1.2806351 | G99: =LN('l_IC,pi_d'!F97/'l_IC,pi_d'!F93)*100 -> -2.2765452 | H99: =LN('l_HC,WC'!M97/'l_HC,WC'!M93)*100 -> -1.4908727 | I99: =LN('l_HC,WC'!K97/'l_HC,WC'!K93)*100 -> -0.15261161 | J99: =l_NSR!B97 -> 0.0016666667 | K99: =LN(l_Solow!H97/l_Solow!H93)*100 -> 1.1877833 | L99: =LN('l_NB,NEC'!O97/'l_NB,NEC'!O93)*100 -> 2.7551906 | M99: =LN('l_NB,NEC'!P97/'l_NB,NEC'!P93)*100 -> 14.402597 | N99: ='fdr,edr'!S97*10000 -> 0.80676529 | O99: ='fdr,edr (TFP)'!S97*10000 -> 2.0628122 | Q99: 0
B100: =EDATE(B99,3) -> 37895 | C100: =YEAR(B100)&"Q"&QUOTIENT(MONTH(B100)-1,3)+1 -> 2003Q4 | D100: =LN(l_Output!C98/l_Output!C94)*100 -> 2.409202 | E100: =LN('l_IC,pi_d'!D98/'l_IC,pi_d'!D94)*100 -> 4.5690166 | F100: =LN(l_pi_c!G98/l_pi_c!G94)*100 -> -1.7509641 | G100: =LN('l_IC,pi_d'!F98/'l_IC,pi_d'!F94)*100 -> -2.3394654 | H100: =LN('l_HC,WC'!M98/'l_HC,WC'!M94)*100 -> -0.4138754 | I100: =LN('l_HC,WC'!K98/'l_HC,WC'!K94)*100 -> 0.054815 | J100: =l_NSR!B98 -> 0.001 | K100: =LN(l_Solow!H98/l_Solow!H94)*100 -> 1.6117667 | L100: =LN('l_NB,NEC'!O98/'l_NB,NEC'!O94)*100 -> 44.494502 | M100: =LN('l_NB,NEC'!P98/'l_NB,NEC'!P94)*100 -> 22.184066 | N100: ='fdr,edr'!S98*10000 -> 0.01520554 | O100: ='fdr,edr (TFP)'!S98*10000 -> 0.038738342 | Q100: 0
...

Sheet Agg
A1: =ReadMe!G3 -> 29587 | C1: Aggregate | M1: Deviation from average | W1: Level | AB1: Level | AG1: Level
A2: =ReadMe!G4 -> 43830 | B2: Avg. | C2: =AVERAGEIFS(C$6:C$168,$A$6:$A$168,">="&$A$1,$A$6:$A$168,"<"&$A$2) -> 0.00013023228 | D2: =AVERAGEIFS(D$6:D$168,$A$6:$A$168,">="&$A$1,$A$6:$A$168,"<"&$A$2) -> 0.0053968894 | E2: =AVERAGEIFS(E$6:E$168,$A$6:$A$168,">="&$A$1,$A$6:$A$168,"<"&$A$2) -> -0.0010579096 | F2: =AVERAGEIFS(F$6:F$168,$A$6:$A$168,">="&$A$1,$A$6:$A$168,"<"&$A$2) -> 0.0046237673 | G2: =AVERAGEIFS(G$6:G$168,$A$6:$A$168,">="&$A$1,$A$6:$A$168,"<"&$A$2) -> 2.2126388e-05 | H2: =AVERAGEIFS(H$6:H$168,$A$6:$A$168,">="&$A$1,$A$6:$A$168,"<"&$A$2) -> 0.005373064 | I2: =AVERAGEIFS(I$6:I$168,$A$6:$A$168,">="&$A$1,$A$6:$A$168,"<"&$A$2) -> 0.0050635107 | J2: =AVERAGEIFS(J$6:J$168,$A$6:$A$168,">="&$A$1,$A$6:$A$168,"<"&$A$2) -> 0.0025473957 | ... L2: =AVERAGEIFS(L$6:L$168,$A$6:$A$168,">="&$A$1,$A$6:$A$168,"<"&$A$2) -> 0.0029640435 | M2: =AVERAGE(M6:M168) -> -2.3991448e-18 | N2: =AVERAGE(N6:N168) -> 1.7792036e-18 | O2: =AVERAGE(O6:O168) -> 9.9246199e-19 | P2: =AVERAGE(P6:P168) -> 0 | Q2: =AVERAGE(Q6:Q168) -> -1.8181236e-18 | R2: =AVERAGE(R6:R168) -> -3.6974074e-18 | S2: =AVERAGE(S6:S168) -> 2.0905642e-18 | T2: =AVERAGE(T6:T168) -> 1.7703075e-17 | ... Z2: =AVERAGE(Z6:Z168) -> 6.9965905e-05 | AB2: =AVERAGE(AB6:AB168) -> 0.0053982753 | AC2: =AVERAGE(AC6:AC168) -> 0.0017674491 | AD2: =AVERAGE(AD6:AD168) -> 0.008807976 | AE2: =AVERAGE(AE6:AE168) -> 0.0012818179 | AG2: =AVERAGE(AG6:AG168) -> 3.1136062e-19 | AH2: =AVERAGE(AH6:AH168) -> 1.4122428e-18 | AI2: =AVERAGE(AI6:AI168) -> 0 | AJ2: =AVERAGE(AJ6:AJ168) -> -6.6720134e-19
B3: Std | C3: =_xlfn.STDEV.S(C6:C168) -> 0.0047735265 | D3: =_xlfn.STDEV.S(D6:D168) -> 0.023496297 | E3: =_xlfn.STDEV.S(E6:E168) -> 0.0046391663 | F3: =_xlfn.STDEV.S(F6:F168) -> 0.012438568 | G3: =_xlfn.STDEV.S(G6:G168) -> 0.0093981957 | H3: =_xlfn.STDEV.S(H6:H168) -> 0.011857607 | I3: =_xlfn.STDEV.S(I6:I168) -> 0.0073769186 | J3: =_xlfn.STDEV.S(J6:J168) -> 0.13684142 | ... Z3: =_xlfn.STDEV.S(Z6:Z168) -> 0.00049551165 | AB3: =_xlfn.STDEV.S(AB6:AB168) -> 0.0064607331 | AC3: =_xlfn.STDEV.S(AC6:AC168) -> 0.01204077 | AD3: =_xlfn.STDEV.S(AD6:AD168) -> 0.0095570974 | AE3: =_xlfn.STDEV.S(AE6:AE168) -> 0.0082923845 | AG3: =_xlfn.STDEV.S(AG6:AG168) -> 0.0064607331 | AH3: =_xlfn.STDEV.S(AH6:AH168) -> 0.01204077 | AI3: =_xlfn.STDEV.S(AI6:AI168) -> 0.0095570974 | AJ3: =_xlfn.STDEV.S(AJ6:AJ168) -> 0.0082923845
A4: Quarter | B4: Q Name | C4: l_pi_c | D4: l_IC | E4: l_pi_d | F4: l_Output | G4: l_HC | H4: l_WC | I4: l_NSR | J4: l_NB | K4: l_NEC | L4: l_Solow | M4: l_pi_c | N4: l_IC | O4: l_pi_d | P4: l_Output | Q4: l_HC | R4: l_WC | S4: l_NSR | T4: l_NB | U4: l_NEC | V4: l_Solow | W4: fdr | X4: edr | Y4: fdr_p | Z4: edr_p | AB4: nu_fdr | AC4: nu_edr | AD4: nu_fdr_p | AE4: nu_edr_p | AG4: nu_fdr | AH4: nu_edr | AI4: nu_fdr_p | AJ4: nu_edr_p
A5: 29221 | B5: =YEAR(A5)&"Q"&QUOTIENT(MONTH(A5)-1,3)+1 -> 1980Q1 | M5: =IF(AND($A5>=$A$1,$A5<$A$2),C5-C$2,"") | N5: =IF(AND($A5>=$A$1,$A5<$A$2),D5-D$2,"") | O5: =IF(AND($A5>=$A$1,$A5<$A$2),E5-E$2,"") | P5: =IF(AND($A5>=$A$1,$A5<$A$2),F5-F$2,"") | Q5: =IF(AND($A5>=$A$1,$A5<$A$2),G5-G$2,"") | R5: =IF(AND($A5>=$A$1,$A5<$A$2),H5-H$2,"") | S5: =IF(AND($A5>=$A$1,$A5<$A$2),I5-I$2,"") | T5: =IF(AND($A5>=$A$1,$A5<$A$2),J5-J$2,"") | U5: =IF(AND($A5>=$A$1,$A5<$A$2),K5-K$2,"")
A6: =EDATE(A5,3) -> 29312 | B6: =YEAR(A6)&"Q"&QUOTIENT(MONTH(A6)-1,3)+1 -> 1980Q2 | C6: =l_pi_c!H4 -> 0.02590596 | D6: ='l_IC,pi_d'!E4 -> 0.0056935603 | E6: ='l_IC,pi_d'!G4 -> 0.019766327 | F6: =l_Output!D4 -> -0.0097713917 | G6: ='l_HC,WC'!L4 -> 0.0014711655 | H6: ='l_HC,WC'!N4 -> 0.018468565 | I6: =l_NSR!C4 -> 0.030425911 | J6: ='l_NB,NEC'!Q4 -> 0.0041926592 | K6: ='l_NB,NEC'!R4 -> 0.018390464 | L6: =l_Solow!I4 -> -0.004841788 | M6: =IF(AND($A6>=$A$1,$A6<$A$2),C6-C$2,"") | N6: =IF(AND($A6>=$A$1,$A6<$A$2),D6-D$2,"") | O6: =IF(AND($A6>=$A$1,$A6<$A$2),E6-E$2,"") | P6: =IF(AND($A6>=$A$1,$A6<$A$2),F6-F$2,"") | Q6: =IF(AND($A6>=$A$1,$A6<$A$2),G6-G$2,"") | R6: =IF(AND($A6>=$A$1,$A6<$A$2),H6-H$2,"") | S6: =IF(AND($A6>=$A$1,$A6<$A$2),I6-I$2,"") | T6: =IF(AND($A6>=$A$1,$A6<$A$2),J6-J$2,"") | ... V6: =IF(AND($A6>=$A$1,$A6<$A$2),L6-L$2,"")
A7: =EDATE(A6,3) -> 29403 | B7: =YEAR(A7)&"Q"&QUOTIENT(MONTH(A7)-1,3)+1 -> 1980Q3 | C7: =l_pi_c!H5 -> 0.010582979 | D7: ='l_IC,pi_d'!E5 -> -0.0074242424 | E7: ='l_IC,pi_d'!G5 -> 0.01358693 | F7: =l_Output!D5 -> 0.018401877 | G7: ='l_HC,WC'!L5 -> -0.0071026992 | H7: ='l_HC,WC'!N5 -> 0.037840412 | I7: =l_NSR!C5 -> 0.029472845 | J7: ='l_NB,NEC'!Q5 -> 0.016169455 | K7: ='l_NB,NEC'!R5 -> 0.028829053 | L7: =l_Solow!I5 -> 0.022806971 | M7: =IF(AND($A7>=$A$1,$A7<$A$2),C7-C$2,"") | N7: =IF(AND($A7>=$A$1,$A7<$A$2),D7-D$2,"") | O7: =IF(AND($A7>=$A$1,$A7<$A$2),E7-E$2,"") | P7: =IF(AND($A7>=$A$1,$A7<$A$2),F7-F$2,"") | Q7: =IF(AND($A7>=$A$1,$A7<$A$2),G7-G$2,"") | R7: =IF(AND($A7>=$A$1,$A7<$A$2),H7-H$2,"") | S7: =IF(AND($A7>=$A$1,$A7<$A$2),I7-I$2,"") | T7: =IF(AND($A7>=$A$1,$A7<$A$2),J7-J$2,"") | ... V7: =IF(AND($A7>=$A$1,$A7<$A$2),L7-L$2,"")
A8: =EDATE(A7,3) -> 29495 | B8: =YEAR(A8)&"Q"&QUOTIENT(MONTH(A8)-1,3)+1 -> 1980Q4 | C8: =l_pi_c!H6 -> 0.0092768876 | D8: ='l_IC,pi_d'!E6 -> 0.024514135 | E8: ='l_IC,pi_d'!G6 -> 0.00065200617 | F8: =l_Output!D6 -> 0.018657658 | G8: ='l_HC,WC'!L6 -> 3.9340002e-05 | H8: ='l_HC,WC'!N6 -> 0.019865419 | I8: =l_NSR!C6 -> 0.024628189 | J8: ='l_NB,NEC'!Q6 -> 0.014421895 | K8: ='l_NB,NEC'!R6 -> 0.04806148 | L8: =l_Solow!I6 -> 0.018306056 | M8: =IF(AND($A8>=$A$1,$A8<$A$2),C8-C$2,"") | N8: =IF(AND($A8>=$A$1,$A8<$A$2),D8-D$2,"") | O8: =IF(AND($A8>=$A$1,$A8<$A$2),E8-E$2,"") | P8: =IF(AND($A8>=$A$1,$A8<$A$2),F8-F$2,"") | Q8: =IF(AND($A8>=$A$1,$A8<$A$2),G8-G$2,"") | R8: =IF(AND($A8>=$A$1,$A8<$A$2),H8-H$2,"") | S8: =IF(AND($A8>=$A$1,$A8<$A$2),I8-I$2,"") | T8: =IF(AND($A8>=$A$1,$A8<$A$2),J8-J$2,"") | ... V8: =IF(AND($A8>=$A$1,$A8<$A$2),L8-L$2,"")
A9: =EDATE(A8,3) -> 29587 | B9: =YEAR(A9)&"Q"&QUOTIENT(MONTH(A9)-1,3)+1 -> 1981Q1 | C9: =l_pi_c!H7 -> 0.0029148367 | D9: ='l_IC,pi_d'!E7 -> 0.0049381591 | E9: ='l_IC,pi_d'!G7 -> 0.0056823711 | F9: =l_Output!D7 -> 0.0056790277 | G9: ='l_HC,WC'!L7 -> -0.0017421249 | H9: ='l_HC,WC'!N7 -> 0.010612129 | I9: =l_NSR!C7 -> 0.021066341 | J9: ='l_NB,NEC'!Q7 -> 0.061338615 | K9: ='l_NB,NEC'!R7 -> 0.047345692 | L9: =l_Solow!I7 -> 0.0046043361 | M9: =IF(AND($A9>=$A$1,$A9<$A$2),C9-C$2,"") -> 0.0027846044 | N9: =IF(AND($A9>=$A$1,$A9<$A$2),D9-D$2,"") -> -0.00045873031 | O9: =IF(AND($A9>=$A$1,$A9<$A$2),E9-E$2,"") -> 0.0067402807 | P9: =IF(AND($A9>=$A$1,$A9<$A$2),F9-F$2,"") -> 0.0010552605 | Q9: =IF(AND($A9>=$A$1,$A9<$A$2),G9-G$2,"") -> -0.0017642513 | R9: =IF(AND($A9>=$A$1,$A9<$A$2),H9-H$2,"") -> 0.0052390651 | S9: =IF(AND($A9>=$A$1,$A9<$A$2),I9-I$2,"") -> 0.016002831 | T9: =IF(AND($A9>=$A$1,$A9<$A$2),J9-J$2,"") -> 0.05879122 | ... V9: =IF(AND($A9>=$A$1,$A9<$A$2),L9-L$2,"") -> 0.0016402926 | W9: ='fdr,edr'!S7 -> 1.8811945e-06 | X9: ='fdr,edr'!T7 -> 0 | Y9: ='fdr,edr (TFP)'!S7 -> 1.8816085e-05 | Z9: ='fdr,edr (TFP)'!T7 -> 0 | AB9: =SQRT(W9) -> 0.0013715664 | AC9: =SQRT(X9) -> 0 | AD9: =SQRT(Y9) -> 0.0043377512 | AE9: =SQRT(Z9) -> 0 | AG9: =AB9-AB$2 -> -0.0040267089 | AH9: =AC9-AC$2 -> -0.0017674491 | AI9: =AD9-AD$2 -> -0.0044702248 | AJ9: =AE9-AE$2 -> -0.0012818179
A10: =EDATE(A9,3) -> 29677 | B10: =YEAR(A10)&"Q"&QUOTIENT(MONTH(A10)-1,3)+1 -> 1981Q2 | C10: =l_pi_c!H8 -> 0.0049375082 | D10: ='l_IC,pi_d'!E8 -> -4.4879673e-05 | E10: ='l_IC,pi_d'!G8 -> -0.0025728595 | F10: =l_Output!D8 -> 0.0084153075 | G10: ='l_HC,WC'!L8 -> 0.0020291169 | H10: ='l_HC,WC'!N8 -> 0.021765195 | I10: =l_NSR!C8 -> 0.01770332 | J10: ='l_NB,NEC'!Q8 -> 0.075138219 | K10: ='l_NB,NEC'!R8 -> 0.11306869 | L10: =l_Solow!I8 -> 0.0056281602 | M10: =IF(AND($A10>=$A$1,$A10<$A$2),C10-C$2,"") -> 0.0048072759 | N10: =IF(AND($A10>=$A$1,$A10<$A$2),D10-D$2,"") -> -0.0054417691 | O10: =IF(AND($A10>=$A$1,$A10<$A$2),E10-E$2,"") -> -0.0015149499 | P10: =IF(AND($A10>=$A$1,$A10<$A$2),F10-F$2,"") -> 0.0037915402 | Q10: =IF(AND($A10>=$A$1,$A10<$A$2),G10-G$2,"") -> 0.0020069905 | R10: =IF(AND($A10>=$A$1,$A10<$A$2),H10-H$2,"") -> 0.016392131 | S10: =IF(AND($A10>=$A$1,$A10<$A$2),I10-I$2,"") -> 0.012639809 | T10: =IF(AND($A10>=$A$1,$A10<$A$2),J10-J$2,"") -> 0.072590823 | ... V10: =IF(AND($A10>=$A$1,$A10<$A$2),L10-L$2,"") -> 0.0026641167 | W10: ='fdr,edr'!S8 -> 1.0176172e-05 | X10: ='fdr,edr'!T8 -> 0 | Y10: ='fdr,edr (TFP)'!S8 -> 0.0001021931 | Z10: ='fdr,edr (TFP)'!T8 -> 0 | AB10: =SQRT(W10) -> 0.0031900112 | AC10: =SQRT(X10) -> 0 | AD10: =SQRT(Y10) -> 0.01010906 | AE10: =SQRT(Z10) -> 0 | AG10: =AB10-AB$2 -> -0.0022082641 | AH10: =AC10-AC$2 -> -0.0017674491 | AI10: =AD10-AD$2 -> 0.0013010842 | AJ10: =AE10-AE$2 -> -0.0012818179
A11: =EDATE(A10,3) -> 29768 | B11: =YEAR(A11)&"Q"&QUOTIENT(MONTH(A11)-1,3)+1 -> 1981Q3 | C11: =l_pi_c!H9 -> 0.0038925346 | D11: ='l_IC,pi_d'!E9 -> 0.0099586911 | E11: ='l_IC,pi_d'!G9 -> -0.00024401736 | F11: =l_Output!D9 -> 0.0025080576 | G11: ='l_HC,WC'!L9 -> -0.0014125174 | H11: ='l_HC,WC'!N9 -> 0.011207904 | I11: =l_NSR!C9 -> 0.018020168 | J11: ='l_NB,NEC'!Q9 -> 0.03327 | K11: ='l_NB,NEC'!R9 -> 0.0239042 | L11: =l_Solow!I9 -> 0.0007902338 | M11: =IF(AND($A11>=$A$1,$A11<$A$2),C11-C$2,"") -> 0.0037623024 | N11: =IF(AND($A11>=$A$1,$A11<$A$2),D11-D$2,"") -> 0.0045618017 | O11: =IF(AND($A11>=$A$1,$A11<$A$2),E11-E$2,"") -> 0.00081389227 | P11: =IF(AND($A11>=$A$1,$A11<$A$2),F11-F$2,"") -> -0.0021157097 | Q11: =IF(AND($A11>=$A$1,$A11<$A$2),G11-G$2,"") -> -0.0014346438 | R11: =IF(AND($A11>=$A$1,$A11<$A$2),H11-H$2,"") -> 0.0058348398 | S11: =IF(AND($A11>=$A$1,$A11<$A$2),I11-I$2,"") -> 0.012956657 | T11: =IF(AND($A11>=$A$1,$A11<$A$2),J11-J$2,"") -> 0.030722605 | ... V11: =IF(AND($A11>=$A$1,$A11<$A$2),L11-L$2,"") -> -0.0021738097 | W11: ='fdr,edr'!S9 -> 0.00012791863 | X11: ='fdr,edr'!T9 -> 0 | Y11: ='fdr,edr (TFP)'!S9 -> 0.0012825875 | Z11: ='fdr,edr (TFP)'!T9 -> 0 | AB11: =SQRT(W11) -> 0.011310112 | AC11: =SQRT(X11) -> 0 | AD11: =SQRT(Y11) -> 0.035813231 | AE11: =SQRT(Z11) -> 0 | AG11: =AB11-AB$2 -> 0.0059118364 | AH11: =AC11-AC$2 -> -0.0017674491 | AI11: =AD11-AD$2 -> 0.027005255 | AJ11: =AE11-AE$2 -> -0.0012818179
A12: =EDATE(A11,3) -> 29860 | B12: =YEAR(A12)&"Q"&QUOTIENT(MONTH(A12)-1,3)+1 -> 1981Q4 | C12: =l_pi_c!H10 -> 0.0080689092 | D12: ='l_IC,pi_d'!E10 -> 0.017091494 | E12: ='l_IC,pi_d'!G10 -> 0.0025054911 | F12: =l_Output!D10 -> 0.0039753993 | G12: ='l_HC,WC'!L10 -> 0.0063466878 | H12: ='l_HC,WC'!N10 -> 0.020972778 | I12: =l_NSR!C10 -> 0.017049239 | J12: ='l_NB,NEC'!Q10 -> 0.031675862 | K12: ='l_NB,NEC'!R10 -> -0.035505288 | L12: =l_Solow!I10 -> -0.00052079572 | M12: =IF(AND($A12>=$A$1,$A12<$A$2),C12-C$2,"") -> 0.0079386769 | N12: =IF(AND($A12>=$A$1,$A12<$A$2),D12-D$2,"") -> 0.011694605 | O12: =IF(AND($A12>=$A$1,$A12<$A$2),E12-E$2,"") -> 0.0035634008 | P12: =IF(AND($A12>=$A$1,$A12<$A$2),F12-F$2,"") -> -0.00064836801 | Q12: =IF(AND($A12>=$A$1,$A12<$A$2),G12-G$2,"") -> 0.0063245614 | R12: =IF(AND($A12>=$A$1,$A12<$A$2),H12-H$2,"") -> 0.015599714 | S12: =IF(AND($A12>=$A$1,$A12<$A$2),I12-I$2,"") -> 0.011985728 | T12: =IF(AND($A12>=$A$1,$A12<$A$2),J12-J$2,"") -> 0.029128466 | ... V12: =IF(AND($A12>=$A$1,$A12<$A$2),L12-L$2,"") -> -0.0034848393 | W12: ='fdr,edr'!S10 -> 3.3841984e-05 | X12: ='fdr,edr'!T10 -> 0 | Y12: ='fdr,edr (TFP)'!S10 -> 0.00033680802 | Z12: ='fdr,edr (TFP)'!T10 -> 0 | AB12: =SQRT(W12) -> 0.0058173863 | AC12: =SQRT(X12) -> 0 | AD12: =SQRT(Y12) -> 0.01835233 | AE12: =SQRT(Z12) -> 0 | AG12: =AB12-AB$2 -> 0.00041911099 | AH12: =AC12-AC$2 -> -0.0017674491 | AI12: =AD12-AD$2 -> 0.0095443542 | AJ12: =AE12-AE$2 -> -0.0012818179
A13: =EDATE(A12,3) -> 29952 | B13: =YEAR(A13)&"Q"&QUOTIENT(MONTH(A13)-1,3)+1 -> 1982Q1 | C13: =l_pi_c!H11 -> 0.0082373494 | D13: ='l_IC,pi_d'!E11 -> -0.024184116 | E13: ='l_IC,pi_d'!G11 -> 0.010281773 | F13: =l_Output!D11 -> 0.011701462 | G13: ='l_HC,WC'!L11 -> -0.0054453874 | H13: ='l_HC,WC'!N11 -> 0.0012114778 | I13: =l_NSR!C11 -> 0.016463756 | J13: ='l_NB,NEC'!Q11 -> 0.051743682 | K13: ='l_NB,NEC'!R11 -> -0.013075491 | L13: =l_Solow!I11 -> 0.015727813 | M13: =IF(AND($A13>=$A$1,$A13<$A$2),C13-C$2,"") -> 0.0081071171 | N13: =IF(AND($A13>=$A$1,$A13<$A$2),D13-D$2,"") -> -0.029581005 | O13: =IF(AND($A13>=$A$1,$A13<$A$2),E13-E$2,"") -> 0.011339683 | P13: =IF(AND($A13>=$A$1,$A13<$A$2),F13-F$2,"") -> 0.0070776947 | Q13: =IF(AND($A13>=$A$1,$A13<$A$2),G13-G$2,"") -> -0.0054675138 | R13: =IF(AND($A13>=$A$1,$A13<$A$2),H13-H$2,"") -> -0.0041615862 | S13: =IF(AND($A13>=$A$1,$A13<$A$2),I13-I$2,"") -> 0.011400246 | T13: =IF(AND($A13>=$A$1,$A13<$A$2),J13-J$2,"") -> 0.049196286 | ... V13: =IF(AND($A13>=$A$1,$A13<$A$2),L13-L$2,"") -> 0.01276377 | W13: ='fdr,edr'!S11 -> 3.7262107e-09 | X13: ='fdr,edr'!T11 -> 0 | Y13: ='fdr,edr (TFP)'!S11 -> 1.2790655e-08 | Z13: ='fdr,edr (TFP)'!T11 -> 0 | AB13: =SQRT(W13) -> 6.1042695e-05 | AC13: =SQRT(X13) -> 0 | AD13: =SQRT(Y13) -> 0.00011309578 | AE13: =SQRT(Z13) -> 0 | AG13: =AB13-AB$2 -> -0.0053372326 | AH13: =AC13-AC$2 -> -0.0017674491 | AI13: =AD13-AD$2 -> -0.0086948802 | AJ13: =AE13-AE$2 -> -0.0012818179
A14: =EDATE(A13,3) -> 30042 | B14: =YEAR(A14)&"Q"&QUOTIENT(MONTH(A14)-1,3)+1 -> 1982Q2 | C14: =l_pi_c!H12 -> -0.0016526779 | D14: ='l_IC,pi_d'!E12 -> 0.022770039 | E14: ='l_IC,pi_d'!G12 -> -0.0090105792 | F14: =l_Output!D12 -> 0.004182757 | G14: ='l_HC,WC'!L12 -> -0.00069383888 | H14: ='l_HC,WC'!N12 -> 0.0162474 | I14: =l_NSR!C12 -> 0.01782974 | J14: ='l_NB,NEC'!Q12 -> -0.0019905157 | K14: ='l_NB,NEC'!R12 -> -0.025599253 | L14: =l_Solow!I12 -> 0.0017983292 | M14: =IF(AND($A14>=$A$1,$A14<$A$2),C14-C$2,"") -> -0.0017829102 | N14: =IF(AND($A14>=$A$1,$A14<$A$2),D14-D$2,"") -> 0.01737315 | O14: =IF(AND($A14>=$A$1,$A14<$A$2),E14-E$2,"") -> -0.0079526696 | P14: =IF(AND($A14>=$A$1,$A14<$A$2),F14-F$2,"") -> -0.00044101021 | Q14: =IF(AND($A14>=$A$1,$A14<$A$2),G14-G$2,"") -> -0.00071596527 | R14: =IF(AND($A14>=$A$1,$A14<$A$2),H14-H$2,"") -> 0.010874336 | S14: =IF(AND($A14>=$A$1,$A14<$A$2),I14-I$2,"") -> 0.012766229 | T14: =IF(AND($A14>=$A$1,$A14<$A$2),J14-J$2,"") -> -0.0045379114 | ... V14: =IF(AND($A14>=$A$1,$A14<$A$2),L14-L$2,"") -> -0.0011657143 | W14: ='fdr,edr'!S12 -> 7.9622957e-07 | X14: ='fdr,edr'!T12 -> 0 | Y14: ='fdr,edr (TFP)'!S12 -> 2.7419417e-06 | Z14: ='fdr,edr (TFP)'!T12 -> 0 | AB14: =SQRT(W14) -> 0.00089231697 | AC14: =SQRT(X14) -> 0 | AD14: =SQRT(Y14) -> 0.0016558809 | AE14: =SQRT(Z14) -> 0 | AG14: =AB14-AB$2 -> -0.0045059584 | AH14: =AC14-AC$2 -> -0.0017674491 | AI14: =AD14-AD$2 -> -0.007152095 | AJ14: =AE14-AE$2 -> -0.0012818179
A15: =EDATE(A14,3) -> 30133 | B15: =YEAR(A15)&"Q"&QUOTIENT(MONTH(A15)-1,3)+1 -> 1982Q3 | C15: =l_pi_c!H13 -> 0.0040665027 | D15: ='l_IC,pi_d'!E13 -> -0.0042259054 | E15: ='l_IC,pi_d'!G13 -> 0.0068489161 | F15: =l_Output!D13 -> 0.0013155637 | G15: ='l_HC,WC'!L13 -> 0.0047938304 | H15: ='l_HC,WC'!N13 -> 0.0075886223 | I15: =l_NSR!C13 -> 0.017699121 | J15: ='l_NB,NEC'!Q13 -> -0.0081870184 | K15: ='l_NB,NEC'!R13 -> -0.032279855 | L15: =l_Solow!I13 -> -0.003165263 | M15: =IF(AND($A15>=$A$1,$A15<$A$2),C15-C$2,"") -> 0.0039362704 | N15: =IF(AND($A15>=$A$1,$A15<$A$2),D15-D$2,"") -> -0.0096227948 | O15: =IF(AND($A15>=$A$1,$A15<$A$2),E15-E$2,"") -> 0.0079068257 | P15: =IF(AND($A15>=$A$1,$A15<$A$2),F15-F$2,"") -> -0.0033082036 | Q15: =IF(AND($A15>=$A$1,$A15<$A$2),G15-G$2,"") -> 0.004771704 | R15: =IF(AND($A15>=$A$1,$A15<$A$2),H15-H$2,"") -> 0.0022155584 | S15: =IF(AND($A15>=$A$1,$A15<$A$2),I15-I$2,"") -> 0.012635611 | T15: =IF(AND($A15>=$A$1,$A15<$A$2),J15-J$2,"") -> -0.010734414 | ... V15: =IF(AND($A15>=$A$1,$A15<$A$2),L15-L$2,"") -> -0.0061293065 | W15: ='fdr,edr'!S13 -> 0.00043801327 | X15: ='fdr,edr'!T13 -> 0 | Y15: ='fdr,edr (TFP)'!S13 -> 0.0015062354 | Z15: ='fdr,edr (TFP)'!T13 -> 0 | AB15: =SQRT(W15) -> 0.020928766 | AC15: =SQRT(X15) -> 0 | AD15: =SQRT(Y15) -> 0.038810249 | AE15: =SQRT(Z15) -> 0 | AG15: =AB15-AB$2 -> 0.015530491 | AH15: =AC15-AC$2 -> -0.0017674491 | AI15: =AD15-AD$2 -> 0.030002273 | AJ15: =AE15-AE$2 -> -0.0012818179
A16: =EDATE(A15,3) -> 30225 | B16: =YEAR(A16)&"Q"&QUOTIENT(MONTH(A16)-1,3)+1 -> 1982Q4 | C16: =l_pi_c!H14 -> -0.0016118908 | D16: ='l_IC,pi_d'!E14 -> -0.016598123 | E16: ='l_IC,pi_d'!G14 -> 0.0037212774 | F16: =l_Output!D14 -> 0.011905669 | G16: ='l_HC,WC'!L14 -> -0.0015776729 | H16: ='l_HC,WC'!N14 -> 0.012969195 | I16: =l_NSR!C14 -> 0.017027315 | J16: ='l_NB,NEC'!Q14 -> 0.033287285 | K16: ='l_NB,NEC'!R14 -> 0.09584621 | L16: =l_Solow!I14 -> 0.0098467301 | M16: =IF(AND($A16>=$A$1,$A16<$A$2),C16-C$2,"") -> -0.0017421231 | N16: =IF(AND($A16>=$A$1,$A16<$A$2),D16-D$2,"") -> -0.021995012 | O16: =IF(AND($A16>=$A$1,$A16<$A$2),E16-E$2,"") -> 0.0047791871 | P16: =IF(AND($A16>=$A$1,$A16<$A$2),F16-F$2,"") -> 0.0072819017 | Q16: =IF(AND($A16>=$A$1,$A16<$A$2),G16-G$2,"") -> -0.0015997993 | R16: =IF(AND($A16>=$A$1,$A16<$A$2),H16-H$2,"") -> 0.0075961307 | S16: =IF(AND($A16>=$A$1,$A16<$A$2),I16-I$2,"") -> 0.011963804 | T16: =IF(AND($A16>=$A$1,$A16<$A$2),J16-J$2,"") -> 0.030739889 | ... V16: =IF(AND($A16>=$A$1,$A16<$A$2),L16-L$2,"") -> 0.0068826866 | W16: ='fdr,edr'!S14 -> 1.5471717e-05 | X16: ='fdr,edr'!T14 -> 0 | Y16: ='fdr,edr (TFP)'!S14 -> 5.2835882e-05 | Z16: ='fdr,edr (TFP)'!T14 -> 0 | AB16: =SQRT(W16) -> 0.0039334104 | AC16: =SQRT(X16) -> 0 | AD16: =SQRT(Y16) -> 0.0072688295 | AE16: =SQRT(Z16) -> 0 | AG16: =AB16-AB$2 -> -0.001464865 | AH16: =AC16-AC$2 -> -0.0017674491 | AI16: =AD16-AD$2 -> -0.0015391465 | AJ16: =AE16-AE$2 -> -0.0012818179
A17: =EDATE(A16,3) -> 30317 | B17: =YEAR(A17)&"Q"&QUOTIENT(MONTH(A17)-1,3)+1 -> 1983Q1 | C17: =l_pi_c!H15 -> 0.007377215 | D17: ='l_IC,pi_d'!E15 -> 0.0058627922 | E17: ='l_IC,pi_d'!G15 -> 0.0022545341 | F17: =l_Output!D15 -> 0.0024607292 | G17: ='l_HC,WC'!L15 -> 0.0014196428 | H17: ='l_HC,WC'!N15 -> 0.013458372 | I17: =l_NSR!C15 -> 0.016528014 | J17: ='l_NB,NEC'!Q15 -> 0.026712529 | K17: ='l_NB,NEC'!R15 -> 0.054546516 | L17: =l_Solow!I15 -> 0.0020245188 | M17: =IF(AND($A17>=$A$1,$A17<$A$2),C17-C$2,"") -> 0.0072469827 | N17: =IF(AND($A17>=$A$1,$A17<$A$2),D17-D$2,"") -> 0.00046590275 | O17: =IF(AND($A17>=$A$1,$A17<$A$2),E17-E$2,"") -> 0.0033124437 | P17: =IF(AND($A17>=$A$1,$A17<$A$2),F17-F$2,"") -> -0.002163038 | Q17: =IF(AND($A17>=$A$1,$A17<$A$2),G17-G$2,"") -> 0.0013975164 | R17: =IF(AND($A17>=$A$1,$A17<$A$2),H17-H$2,"") -> 0.0080853081 | S17: =IF(AND($A17>=$A$1,$A17<$A$2),I17-I$2,"") -> 0.011464503 | T17: =IF(AND($A17>=$A$1,$A17<$A$2),J17-J$2,"") -> 0.024165133 | ... V17: =IF(AND($A17>=$A$1,$A17<$A$2),L17-L$2,"") -> -0.00093952474 | W17: ='fdr,edr'!S15 -> 7.256219e-08 | X17: ='fdr,edr'!T15 -> 0 | Y17: ='fdr,edr (TFP)'!S15 -> 7.553346e-07 | Z17: ='fdr,edr (TFP)'!T15 -> 0 | AB17: =SQRT(W17) -> 0.0002693737 | AC17: =SQRT(X17) -> 0 | AD17: =SQRT(Y17) -> 0.00086909988 | AE17: =SQRT(Z17) -> 0 | AG17: =AB17-AB$2 -> -0.0051289016 | AH17: =AC17-AC$2 -> -0.0017674491 | AI17: =AD17-AD$2 -> -0.0079388761 | AJ17: =AE17-AE$2 -> -0.0012818179
A18: =EDATE(A17,3) -> 30407 | B18: =YEAR(A18)&"Q"&QUOTIENT(MONTH(A18)-1,3)+1 -> 1983Q2 | C18: =l_pi_c!H16 -> 0.001053412 | D18: ='l_IC,pi_d'!E16 -> 0.027703267 | E18: ='l_IC,pi_d'!G16 -> -0.008821117 | F18: =l_Output!D16 -> 0.0059107339 | G18: ='l_HC,WC'!L16 -> 0.0033008926 | H18: ='l_HC,WC'!N16 -> -0.0028950208 | I18: =l_NSR!C16 -> 0.015445275 | J18: ='l_NB,NEC'!Q16 -> 0.015075519 | K18: ='l_NB,NEC'!R16 -> 0.084009966 | L18: =l_Solow!I16 -> 0.0024993645 | M18: =IF(AND($A18>=$A$1,$A18<$A$2),C18-C$2,"") -> 0.00092317972 | N18: =IF(AND($A18>=$A$1,$A18<$A$2),D18-D$2,"") -> 0.022306377 | O18: =IF(AND($A18>=$A$1,$A18<$A$2),E18-E$2,"") -> -0.0077632074 | P18: =IF(AND($A18>=$A$1,$A18<$A$2),F18-F$2,"") -> 0.0012869666 | Q18: =IF(AND($A18>=$A$1,$A18<$A$2),G18-G$2,"") -> 0.0032787662 | R18: =IF(AND($A18>=$A$1,$A18<$A$2),H18-H$2,"") -> -0.0082680848 | S18: =IF(AND($A18>=$A$1,$A18<$A$2),I18-I$2,"") -> 0.010381764 | T18: =IF(AND($A18>=$A$1,$A18<$A$2),J18-J$2,"") -> 0.012528124 | ... V18: =IF(AND($A18>=$A$1,$A18<$A$2),L18-L$2,"") -> -0.00046467901 | W18: ='fdr,edr'!S16 -> 1.4628971e-05 | X18: ='fdr,edr'!T16 -> 0 | Y18: ='fdr,edr (TFP)'!S16 -> 0.0001526301 | Z18: ='fdr,edr (TFP)'!T16 -> 0 | AB18: =SQRT(W18) -> 0.0038247838 | AC18: =SQRT(X18) -> 0 | AD18: =SQRT(Y18) -> 0.012354355 | AE18: =SQRT(Z18) -> 0 | AG18: =AB18-AB$2 -> -0.0015734916 | AH18: =AC18-AC$2 -> -0.0017674491 | AI18: =AD18-AD$2 -> 0.0035463794 | AJ18: =AE18-AE$2 -> -0.0012818179
A19: =EDATE(A18,3) -> 30498 | B19: =YEAR(A19)&"Q"&QUOTIENT(MONTH(A19)-1,3)+1 -> 1983Q3 | C19: =l_pi_c!H17 -> -2.5455171e-05 | D19: ='l_IC,pi_d'!E17 -> -0.0048801509 | E19: ='l_IC,pi_d'!G17 -> -0.0024379452 | F19: =l_Output!D17 -> 0.010983946 | G19: ='l_HC,WC'!L17 -> 0.0011118185 | H19: ='l_HC,WC'!N17 -> 0.012128816 | I19: =l_NSR!C17 -> 0.016097751 | J19: ='l_NB,NEC'!Q17 -> 0.0032010432 | K19: ='l_NB,NEC'!R17 -> 0.081526839 | L19: =l_Solow!I17 -> 0.0079241653 | M19: =IF(AND($A19>=$A$1,$A19<$A$2),C19-C$2,"") -> -0.00015568745 | N19: =IF(AND($A19>=$A$1,$A19<$A$2),D19-D$2,"") -> -0.01027704 | O19: =IF(AND($A19>=$A$1,$A19<$A$2),E19-E$2,"") -> -0.0013800356 | P19: =IF(AND($A19>=$A$1,$A19<$A$2),F19-F$2,"") -> 0.0063601784 | Q19: =IF(AND($A19>=$A$1,$A19<$A$2),G19-G$2,"") -> 0.0010896921 | R19: =IF(AND($A19>=$A$1,$A19<$A$2),H19-H$2,"") -> 0.0067557518 | S19: =IF(AND($A19>=$A$1,$A19<$A$2),I19-I$2,"") -> 0.01103424 | T19: =IF(AND($A19>=$A$1,$A19<$A$2),J19-J$2,"") -> 0.00065364744 | ... V19: =IF(AND($A19>=$A$1,$A19<$A$2),L19-L$2,"") -> 0.0049601218 | W19: ='fdr,edr'!S17 -> 0.00011627605 | X19: ='fdr,edr'!T17 -> 0 | Y19: ='fdr,edr (TFP)'!S17 -> 0.0012102654 | Z19: ='fdr,edr (TFP)'!T17 -> 0 | AB19: =SQRT(W19) -> 0.010783137 | AC19: =SQRT(X19) -> 0 | AD19: =SQRT(Y19) -> 0.034788869 | AE19: =SQRT(Z19) -> 0 | AG19: =AB19-AB$2 -> 0.0053848621 | AH19: =AC19-AC$2 -> -0.0017674491 | AI19: =AD19-AD$2 -> 0.025980893 | AJ19: =AE19-AE$2 -> -0.0012818179
A20: =EDATE(A19,3) -> 30590 | B20: =YEAR(A20)&"Q"&QUOTIENT(MONTH(A20)-1,3)+1 -> 1983Q4 | C20: =l_pi_c!H18 -> 0.0034504058 | D20: ='l_IC,pi_d'!E18 -> 0.0010458705 | E20: ='l_IC,pi_d'!G18 -> -0.0011032094 | F20: =l_Output!D18 -> 0.004750893 | G20: ='l_HC,WC'!L18 -> -0.0022324316 | H20: ='l_HC,WC'!N18 -> 0.00636324 | I20: =l_NSR!C18 -> 0.015671327 | J20: ='l_NB,NEC'!Q18 -> 0.0047624439 | K20: ='l_NB,NEC'!R18 -> 0.053119827 | L20: =l_Solow!I18 -> 0.0054578677 | M20: =IF(AND($A20>=$A$1,$A20<$A$2),C20-C$2,"") -> 0.0033201735 | N20: =IF(AND($A20>=$A$1,$A20<$A$2),D20-D$2,"") -> -0.0043510189 | O20: =IF(AND($A20>=$A$1,$A20<$A$2),E20-E$2,"") -> -4.5299758e-05 | P20: =IF(AND($A20>=$A$1,$A20<$A$2),F20-F$2,"") -> 0.00012712574 | Q20: =IF(AND($A20>=$A$1,$A20<$A$2),G20-G$2,"") -> -0.002254558 | R20: =IF(AND($A20>=$A$1,$A20<$A$2),H20-H$2,"") -> 0.000990176 | S20: =IF(AND($A20>=$A$1,$A20<$A$2),I20-I$2,"") -> 0.010607817 | T20: =IF(AND($A20>=$A$1,$A20<$A$2),J20-J$2,"") -> 0.0022150482 | ... V20: =IF(AND($A20>=$A$1,$A20<$A$2),L20-L$2,"") -> 0.0024938241 | W20: ='fdr,edr'!S18 -> 3.0948793e-07 | X20: ='fdr,edr'!T18 -> 0 | Y20: ='fdr,edr (TFP)'!S18 -> 3.198023e-06 | Z20: ='fdr,edr (TFP)'!T18 -> 0 | AB20: =SQRT(W20) -> 0.0005563164 | AC20: =SQRT(X20) -> 0 | AD20: =SQRT(Y20) -> 0.0017883017 | AE20: =SQRT(Z20) -> 0 | AG20: =AB20-AB$2 -> -0.0048419589 | AH20: =AC20-AC$2 -> -0.0017674491 | AI20: =AD20-AD$2 -> -0.0070196743 | AJ20: =AE20-AE$2 -> -0.0012818179
... A164: =EDATE(A163,3) -> 43739 | B164: =YEAR(A164)&"Q"&QUOTIENT(MONTH(A164)-1,3)+1 -> 2019Q4 | C164: =l_pi_c!H162 -> -0.002480613 | D164: ='l_IC,pi_d'!E162 -> -0.044062641 | E164: ='l_IC,pi_d'!G162 -> 0.00084917077 | F164: =l_Output!D162 -> -0.018266882 | G164: ='l_HC,WC'!L162 -> -0.0035127892 | H164: ='l_HC,WC'!N162 -> 0.012173975 | I164: =l_NSR!C162 -> -8.5844387e-05 | J164: ='l_NB,NEC'!Q162 -> 0.081947039 | K164: ='l_NB,NEC'!R162 -> 0.085411693 | L164: =l_Solow!I162 -> -0.017421084 | M164: =IF(AND($A164>=$A$1,$A164<$A$2),C164-C$2,"") -> -0.0026108453 | N164: =IF(AND($A164>=$A$1,$A164<$A$2),D164-D$2,"") -> -0.049459531 | O164: =IF(AND($A164>=$A$1,$A164<$A$2),E164-E$2,"") -> 0.0019070804 | P164: =IF(AND($A164>=$A$1,$A164<$A$2),F164-F$2,"") -> -0.022890649 | Q164: =IF(AND($A164>=$A$1,$A164<$A$2),G164-G$2,"") -> -0.0035349156 | R164: =IF(AND($A164>=$A$1,$A164<$A$2),H164-H$2,"") -> 0.0068009114 | S164: =IF(AND($A164>=$A$1,$A164<$A$2),I164-I$2,"") -> -0.0051493551 | T164: =IF(AND($A164>=$A$1,$A164<$A$2),J164-J$2,"") -> 0.079399644 | ... V164: =IF(AND($A164>=$A$1,$A164<$A$2),L164-L$2,"") -> -0.020385128 | W164: ='fdr,edr'!S162 -> 0.0011271662 | X164: ='fdr,edr'!T162 -> 0 | Y164: ='fdr,edr (TFP)'!S162 -> 0.00071660115 | Z164: ='fdr,edr (TFP)'!T162 -> 0 | AB164: =SQRT(W164) -> 0.033573296 | AC164: =SQRT(X164) -> 0 | AD164: =SQRT(Y164) -> 0.026769407 | AE164: =SQRT(Z164) -> 0 | AG164: =AB164-AB$2 -> 0.028175021 | AH164: =AC164-AC$2 -> -0.0017674491 | AI164: =AD164-AD$2 -> 0.017961431 | AJ164: =AE164-AE$2 -> -0.0012818179
A165: =EDATE(A164,3) -> 43831 | B165: =YEAR(A165)&"Q"&QUOTIENT(MONTH(A165)-1,3)+1 -> 2020Q1 | C165: =l_pi_c!H163 -> 0.00056170954 | D165: ='l_IC,pi_d'!E163 -> 0.012346076 | E165: ='l_IC,pi_d'!G163 -> 0.0033306458 | F165: =l_Output!D163 -> -0.0045584806 | G165: ='l_HC,WC'!L163 -> -0.0057101229 | H165: ='l_HC,WC'!N163 -> 0.0088783463 | I165: =l_NSR!C163 -> -7.9176069e-05 | J165: ='l_NB,NEC'!Q163 -> -0.20412564 | K165: ='l_NB,NEC'!R163 -> -0.1978419 | L165: =l_Solow!I163 -> #N/A | M165: =IF(AND($A165>=$A$1,$A165<$A$2),C165-C$2,"") | N165: =IF(AND($A165>=$A$1,$A165<$A$2),D165-D$2,"") | O165: =IF(AND($A165>=$A$1,$A165<$A$2),E165-E$2,"") | P165: =IF(AND($A165>=$A$1,$A165<$A$2),F165-F$2,"") | Q165: =IF(AND($A165>=$A$1,$A165<$A$2),G165-G$2,"") | R165: =IF(AND($A165>=$A$1,$A165<$A$2),H165-H$2,"") | S165: =IF(AND($A165>=$A$1,$A165<$A$2),I165-I$2,"") | T165: =IF(AND($A165>=$A$1,$A165<$A$2),J165-J$2,"") | ... V165: =IF(AND($A165>=$A$1,$A165<$A$2),L165-L$2,"")
A166: =EDATE(A165,3) -> 43922 | B166: =YEAR(A166)&"Q"&QUOTIENT(MONTH(A166)-1,3)+1 -> 2020Q2 | C166: =l_pi_c!H164 -> 0.0035253428 | D166: ='l_IC,pi_d'!E164 -> -0.060248436 | E166: ='l_IC,pi_d'!G164 -> -0.0093376765 | F166: =l_Output!D164 -> -0.081093737 | G166: ='l_HC,WC'!L164 -> -0.05392376 | H166: ='l_HC,WC'!N164 -> 0.017162791 | I166: =l_NSR!C164 -> -0.00010918455 | J166: ='l_NB,NEC'!Q164 -> 0.019298495 | K166: ='l_NB,NEC'!R164 -> 0.12005635 | L166: =l_Solow!I164 -> #N/A | M166: =IF(AND($A166>=$A$1,$A166<$A$2),C166-C$2,"") | N166: =IF(AND($A166>=$A$1,$A166<$A$2),D166-D$2,"") | O166: =IF(AND($A166>=$A$1,$A166<$A$2),E166-E$2,"") | P166: =IF(AND($A166>=$A$1,$A166<$A$2),F166-F$2,"") | Q166: =IF(AND($A166>=$A$1,$A166<$A$2),G166-G$2,"") | R166: =IF(AND($A166>=$A$1,$A166<$A$2),H166-H$2,"") | S166: =IF(AND($A166>=$A$1,$A166<$A$2),I166-I$2,"") | T166: =IF(AND($A166>=$A$1,$A166<$A$2),J166-J$2,"") | ... V166: =IF(AND($A166>=$A$1,$A166<$A$2),L166-L$2,"")
A167: =EDATE(A166,3) -> 44013 | B167: =YEAR(A167)&"Q"&QUOTIENT(MONTH(A167)-1,3)+1 -> 2020Q3 | C167: =l_pi_c!H165 -> 0.00062294724 | D167: ='l_IC,pi_d'!E165 -> -0.019145108 | E167: ='l_IC,pi_d'!G165 -> 0.0020070516 | F167: =l_Output!D165 -> 0.054054686 | G167: ='l_HC,WC'!L165 -> 0.027864587 | H167: ='l_HC,WC'!N165 -> -0.019719411 | I167: =l_NSR!C165 -> -9.7514263e-05 | J167: ='l_NB,NEC'!Q165 -> 0.010844113 | K167: ='l_NB,NEC'!R165 -> 0.056811569 | L167: =l_Solow!I165 -> #N/A | M167: =IF(AND($A167>=$A$1,$A167<$A$2),C167-C$2,"") | N167: =IF(AND($A167>=$A$1,$A167<$A$2),D167-D$2,"") | O167: =IF(AND($A167>=$A$1,$A167<$A$2),E167-E$2,"") | P167: =IF(AND($A167>=$A$1,$A167<$A$2),F167-F$2,"") | Q167: =IF(AND($A167>=$A$1,$A167<$A$2),G167-G$2,"") | R167: =IF(AND($A167>=$A$1,$A167<$A$2),H167-H$2,"") | S167: =IF(AND($A167>=$A$1,$A167<$A$2),I167-I$2,"") | T167: =IF(AND($A167>=$A$1,$A167<$A$2),J167-J$2,"") | ... V167: =IF(AND($A167>=$A$1,$A167<$A$2),L167-L$2,"")
A168: =EDATE(A167,3) -> 44105 | B168: =YEAR(A168)&"Q"&QUOTIENT(MONTH(A168)-1,3)+1 -> 2020Q4 | C168: =l_pi_c!H166 -> -0.0048855172 | D168: ='l_IC,pi_d'!E166 -> 0.043904312 | E168: ='l_IC,pi_d'!G166 -> -0.0045104401 | F168: =l_Output!D166 -> 0.029982953 | G168: ='l_HC,WC'!L166 -> 0.012399969 | H168: ='l_HC,WC'!N166 -> -0.0068111193 | I168: =l_NSR!C166 -> -6.5006338e-05 | J168: ='l_NB,NEC'!Q166 -> -0.067115952 | K168: ='l_NB,NEC'!R166 -> 0.080885299 | L168: =l_Solow!I166 -> #N/A | M168: =IF(AND($A168>=$A$1,$A168<$A$2),C168-C$2,"") | N168: =IF(AND($A168>=$A$1,$A168<$A$2),D168-D$2,"") | O168: =IF(AND($A168>=$A$1,$A168<$A$2),E168-E$2,"") | P168: =IF(AND($A168>=$A$1,$A168<$A$2),F168-F$2,"") | Q168: =IF(AND($A168>=$A$1,$A168<$A$2),G168-G$2,"") | R168: =IF(AND($A168>=$A$1,$A168<$A$2),H168-H$2,"") | S168: =IF(AND($A168>=$A$1,$A168<$A$2),I168-I$2,"") | T168: =IF(AND($A168>=$A$1,$A168<$A$2),J168-J$2,"") | ... V168: =IF(AND($A168>=$A$1,$A168<$A$2),L168-L$2,"")

Sheet l_pi_c
B1: GDP | D1: Deflator | J1: https://www.sangiin.go.jp/japanese/annai/chousa/rippou_chousa/backnumber/2014pdf/20140203034.pdf
B2: Nominal | C2: Real | D2: Level (incl. VAT) | E2: YoY (incl. VAT) | F2: YoY (excl. VAT) | G2: Level (excl. VAT) | H2: QoQ (excl. VAT)
A3: 29281 | B3: =nG_h23!B8*nG!$B$8/nG_h23!$B$64 -> 245801.57 | C3: =rG_h23!B8*rG!$B$8/rG_h23!$B$64 -> 270758.12 | D3: =B3/C3*100 -> 90.782713 | G3: =D3 -> 90.782713 | J3: ＜消費税調整用＞
A4: =EDATE(A3,3) -> 29373 | B4: =nG_h23!B9*nG!$B$8/nG_h23!$B$64 -> 250409.15 | C4: =rG_h23!B9*rG!$B$8/rG_h23!$B$64 -> 268779.55 | D4: =B4/C4*100 -> 93.165254 | G4: =D4 -> 93.165254 | H4: =LN(G4)-LN(G3) -> 0.02590596 | J4: 2014年増税の寄与 | K4: 0.014
A5: =EDATE(A4,3) -> 29465 | B5: =nG_h23!B10*nG!$B$8/nG_h23!$B$64 -> 258384.02 | C5: =rG_h23!B10*rG!$B$8/rG_h23!$B$64 -> 274419.87 | D5: =B5/C5*100 -> 94.156456 | G5: =D5 -> 94.156456 | H5: =LN(G5)-LN(G4) -> 0.010582979 | J5: 1％あたり寄与分 | K5: =K4/3 -> 0.0046666667
A6: =EDATE(A5,3) -> 29556 | B6: =nG_h23!B11*nG!$B$8/nG_h23!$B$64 -> 266236.92 | C6: =rG_h23!B11*rG!$B$8/rG_h23!$B$64 -> 280149.13 | D6: =B6/C6*100 -> 95.033999 | G6: =D6 -> 95.033999 | H6: =LN(G6)-LN(G5) -> 0.0092768876
A7: =EDATE(A6,3) -> 29646 | B7: =nG_h23!B12*nG!$B$8/nG_h23!$B$64 -> 268962.66 | C7: =rG_h23!B12*rG!$B$8/rG_h23!$B$64 -> 282193.55 | D7: =B7/C7*100 -> 95.311411 | E7: =LN(D7)-LN(D3) -> 0.048680664 | F7: =E7-SUMIFS($L$15:$L$18,$J$15:$J$18,"<"&$A7,$K$15:$K$18,">"&$A7) -> 0.048680664 | G7: =EXP(LN(G3)+F7) -> 95.311411 | H7: =LN(G7)-LN(G6) -> 0.0029148367 | J7: ＜消費税の増税幅＞
A8: =EDATE(A7,3) -> 29738 | B8: =nG_h23!B13*nG!$B$8/nG_h23!$B$64 -> 272900.73 | C8: =rG_h23!B13*rG!$B$8/rG_h23!$B$64 -> 284915.1 | D8: =B8/C8*100 -> 95.783176 | E8: =LN(D8)-LN(D4) -> 0.027712212 | F8: =E8-SUMIFS($L$15:$L$18,$J$15:$J$18,"<"&$A8,$K$15:$K$18,">"&$A8) -> 0.027712212 | G8: =EXP(LN(G4)+F8) -> 95.783176 | H8: =LN(G8)-LN(G7) -> 0.0049375082 | J8: 32599 | K8: 3
A9: =EDATE(A8,3) -> 29830 | B9: =nG_h23!B14*nG!$B$8/nG_h23!$B$64 -> 274959.41 | C9: =rG_h23!B14*rG!$B$8/rG_h23!$B$64 -> 285949.18 | D9: =B9/C9*100 -> 96.156742 | E9: =LN(D9)-LN(D5) -> 0.021021767 | F9: =E9-SUMIFS($L$15:$L$18,$J$15:$J$18,"<"&$A9,$K$15:$K$18,">"&$A9) -> 0.021021767 | G9: =EXP(LN(G5)+F9) -> 96.156742 | H9: =LN(G9)-LN(G8) -> 0.0038925346 | J9: 35521 | K9: 2
A10: =EDATE(A9,3) -> 29921 | B10: =nG_h23!B15*nG!$B$8/nG_h23!$B$64 -> 278731.36 | C10: =rG_h23!B15*rG!$B$8/rG_h23!$B$64 -> 287542.35 | D10: =B10/C10*100 -> 96.93576 | E10: =LN(D10)-LN(D6) -> 0.019813789 | F10: =E10-SUMIFS($L$15:$L$18,$J$15:$J$18,"<"&$A10,$K$15:$K$18,">"&$A10) -> 0.019813789 | G10: =EXP(LN(G6)+F10) -> 96.93576 | H10: =LN(G10)-LN(G9) -> 0.0080689092 | J10: 41730 | K10: 3
A11: =EDATE(A10,3) -> 30011 | B11: =nG_h23!B16*nG!$B$8/nG_h23!$B$64 -> 284931.57 | C11: =rG_h23!B16*rG!$B$8/rG_h23!$B$64 -> 291527.22 | D11: =B11/C11*100 -> 97.737552 | E11: =LN(D11)-LN(D7) -> 0.025136301 | F11: =E11-SUMIFS($L$15:$L$18,$J$15:$J$18,"<"&$A11,$K$15:$K$18,">"&$A11) -> 0.025136301 | G11: =EXP(LN(G7)+F11) -> 97.737552 | H11: =LN(G11)-LN(G10) -> 0.0082373494 | J11: 43739 | K11: 2
A12: =EDATE(A11,3) -> 30103 | B12: =nG_h23!B17*nG!$B$8/nG_h23!$B$64 -> 286359.4 | C12: =rG_h23!B17*rG!$B$8/rG_h23!$B$64 -> 293472.72 | D12: =B12/C12*100 -> 97.576157 | E12: =LN(D12)-LN(D8) -> 0.018546115 | F12: =E12-SUMIFS($L$15:$L$18,$J$15:$J$18,"<"&$A12,$K$15:$K$18,">"&$A12) -> 0.018546115 | G12: =EXP(LN(G8)+F12) -> 97.576157 | H12: =LN(G12)-LN(G11) -> -0.0016526779
A13: =EDATE(A12,3) -> 30195 | B13: =nG_h23!B18*nG!$B$8/nG_h23!$B$64 -> 288685.27 | C13: =rG_h23!B18*rG!$B$8/rG_h23!$B$64 -> 294655.71 | D13: =B13/C13*100 -> 97.973758 | E13: =LN(D13)-LN(D9) -> 0.018720083 | F13: =E13-SUMIFS($L$15:$L$18,$J$15:$J$18,"<"&$A13,$K$15:$K$18,">"&$A13) -> 0.018720083 | G13: =EXP(LN(G9)+F13) -> 97.973758 | H13: =LN(G13)-LN(G12) -> 0.0040665027 | J13: ＜消費税の押し下げ分算出＞
A14: =EDATE(A13,3) -> 30286 | B14: =nG_h23!B19*nG!$B$8/nG_h23!$B$64 -> 292426.42 | C14: =rG_h23!B19*rG!$B$8/rG_h23!$B$64 -> 298955.73 | D14: =B14/C14*100 -> 97.815962 | E14: =LN(D14)-LN(D10) -> 0.0090392833 | F14: =E14-SUMIFS($L$15:$L$18,$J$15:$J$18,"<"&$A14,$K$15:$K$18,">"&$A14) -> 0.0090392833 | G14: =EXP(LN(G10)+F14) -> 97.815962 | H14: =LN(G14)-LN(G13) -> -0.0016118908 | J14: From | K14: To | L14: %pt
A15: =EDATE(A14,3) -> 30376 | B15: =nG_h23!B20*nG!$B$8/nG_h23!$B$64 -> 296066.82 | C15: =rG_h23!B20*rG!$B$8/rG_h23!$B$64 -> 300452.71 | D15: =B15/C15*100 -> 98.54024 | E15: =LN(D15)-LN(D11) -> 0.008179149 | F15: =E15-SUMIFS($L$15:$L$18,$J$15:$J$18,"<"&$A15,$K$15:$K$18,">"&$A15) -> 0.008179149 | G15: =EXP(LN(G11)+F15) -> 98.54024 | H15: =LN(G15)-LN(G14) -> 0.007377215 | J15: =J8 -> 32599 | K15: =EDATE(J15,12) -> 32964 | L15: =$K$5*K8 -> 0.014
A16: =EDATE(A15,3) -> 30468 | B16: =nG_h23!B21*nG!$B$8/nG_h23!$B$64 -> 298893 | C16: =rG_h23!B21*rG!$B$8/rG_h23!$B$64 -> 303001.4 | D16: =B16/C16*100 -> 98.644098 | E16: =LN(D16)-LN(D12) -> 0.010885239 | F16: =E16-SUMIFS($L$15:$L$18,$J$15:$J$18,"<"&$A16,$K$15:$K$18,">"&$A16) -> 0.010885239 | G16: =EXP(LN(G12)+F16) -> 98.644098 | H16: =LN(G16)-LN(G15) -> 0.001053412 | J16: =J9 -> 35521 | K16: =EDATE(J16,12) -> 35886 | L16: =$K$5*K9 -> 0.0093333333
A17: =EDATE(A16,3) -> 30560 | B17: =nG_h23!B22*nG!$B$8/nG_h23!$B$64 -> 302957.64 | C17: =rG_h23!B22*rG!$B$8/rG_h23!$B$64 -> 307129.73 | D17: =B17/C17*100 -> 98.641587 | E17: =LN(D17)-LN(D13) -> 0.006793281 | F17: =E17-SUMIFS($L$15:$L$18,$J$15:$J$18,"<"&$A17,$K$15:$K$18,">"&$A17) -> 0.006793281 | G17: =EXP(LN(G13)+F17) -> 98.641587 | H17: =LN(G17)-LN(G16) -> -2.5455171e-05 | J17: =J10 -> 41730 | K17: =EDATE(J17,12) -> 42095 | L17: =$K$5*K10 -> 0.014
A18: =EDATE(A17,3) -> 30651 | B18: =nG_h23!B23*nG!$B$8/nG_h23!$B$64 -> 306259.46 | C18: =rG_h23!B23*rG!$B$8/rG_h23!$B$64 -> 309407.59 | D18: =B18/C18*100 -> 98.982529 | E18: =LN(D18)-LN(D14) -> 0.011855578 | F18: =E18-SUMIFS($L$15:$L$18,$J$15:$J$18,"<"&$A18,$K$15:$K$18,">"&$A18) -> 0.011855578 | G18: =EXP(LN(G14)+F18) -> 98.982529 | H18: =LN(G18)-LN(G17) -> 0.0034504058 | J18: =J11 -> 43739 | K18: =EDATE(J18,12) -> 44105 | L18: =$K$5*K11 -> 0.0093333333
A19: =EDATE(A18,3) -> 30742 | B19: =nG_h23!B24*nG!$B$8/nG_h23!$B$64 -> 311651.17 | C19: =rG_h23!B24*rG!$B$8/rG_h23!$B$64 -> 312967.37 | D19: =B19/C19*100 -> 99.579444 | E19: =LN(D19)-LN(D15) -> 0.010490767 | F19: =E19-SUMIFS($L$15:$L$18,$J$15:$J$18,"<"&$A19,$K$15:$K$18,">"&$A19) -> 0.010490767 | G19: =EXP(LN(G15)+F19) -> 99.579444 | H19: =LN(G19)-LN(G18) -> 0.006012404
A20: =EDATE(A19,3) -> 30834 | B20: =nG_h23!B25*nG!$B$8/nG_h23!$B$64 -> 318436.74 | C20: =rG_h23!B25*rG!$B$8/rG_h23!$B$64 -> 318966.42 | D20: =B20/C20*100 -> 99.83394 | E20: =LN(D20)-LN(D16) -> 0.011989803 | F20: =E20-SUMIFS($L$15:$L$18,$J$15:$J$18,"<"&$A20,$K$15:$K$18,">"&$A20) -> 0.011989803 | G20: =EXP(LN(G16)+F20) -> 99.83394 | H20: =LN(G20)-LN(G19) -> 0.0025524482 | J20: ＜算出方法＞
A21: =EDATE(A20,3) -> 30926 | B21: =nG_h23!B26*nG!$B$8/nG_h23!$B$64 -> 322197.07 | C21: =rG_h23!B26*rG!$B$8/rG_h23!$B$64 -> 321352.55 | D21: =B21/C21*100 -> 100.2628 | E21: =LN(D21)-LN(D17) -> 0.016301791 | F21: =E21-SUMIFS($L$15:$L$18,$J$15:$J$18,"<"&$A21,$K$15:$K$18,">"&$A21) -> 0.016301791 | G21: =EXP(LN(G17)+F21) -> 100.2628 | H21: =LN(G21)-LN(G20) -> 0.0042865328 | J21: ・GDPは1994年以前は平成23年基準を接続
A22: =EDATE(A21,3) -> 31017 | B22: =nG_h23!B27*nG!$B$8/nG_h23!$B$64 -> 325502.25 | C22: =rG_h23!B27*rG!$B$8/rG_h23!$B$64 -> 322621.23 | D22: =B22/C22*100 -> 100.89301 | E22: =LN(D22)-LN(D18) -> 0.019117243 | F22: =E22-SUMIFS($L$15:$L$18,$J$15:$J$18,"<"&$A22,$K$15:$K$18,">"&$A22) -> 0.019117243 | G22: =EXP(LN(G18)+F22) -> 100.89301 | H22: =LN(G22)-LN(G21) -> 0.0062658584 | J22: ・デフレーターは前年比から消費税の影響を除いて水準に戻し、前期比を算出
A23: =EDATE(A22,3) -> 31107 | B23: =nG_h23!B28*nG!$B$8/nG_h23!$B$64 -> 330940.26 | C23: =rG_h23!B28*rG!$B$8/rG_h23!$B$64 -> 326638.87 | D23: =B23/C23*100 -> 101.31686 | E23: =LN(D23)-LN(D19) -> 0.01729712 | F23: =E23-SUMIFS($L$15:$L$18,$J$15:$J$18,"<"&$A23,$K$15:$K$18,">"&$A23) -> 0.01729712 | G23: =EXP(LN(G19)+F23) -> 101.31686 | H23: =LN(G23)-LN(G22) -> 0.0041922806 | J23: ―― 軽減税率は煩雑なので考慮しない
A24: =EDATE(A23,3) -> 31199 | B24: =nG_h23!B29*nG!$B$8/nG_h23!$B$64 -> 338023.31 | C24: =rG_h23!B29*rG!$B$8/rG_h23!$B$64 -> 333085.59 | D24: =B24/C24*100 -> 101.48242 | E24: =LN(D24)-LN(D20) -> 0.016377352 | F24: =E24-SUMIFS($L$15:$L$18,$J$15:$J$18,"<"&$A24,$K$15:$K$18,">"&$A24) -> 0.016377352 | G24: =EXP(LN(G20)+F24) -> 101.48242 | H24: =LN(G24)-LN(G23) -> 0.0016326806
A25: =EDATE(A24,3) -> 31291 | B25: =nG_h23!B30*nG!$B$8/nG_h23!$B$64 -> 342399.81 | C25: =rG_h23!B30*rG!$B$8/rG_h23!$B$64 -> 338082.38 | D25: =B25/C25*100 -> 101.27703 | E25: =LN(D25)-LN(D21) -> 0.010064912 | F25: =E25-SUMIFS($L$15:$L$18,$J$15:$J$18,"<"&$A25,$K$15:$K$18,">"&$A25) -> 0.010064912 | G25: =EXP(LN(G21)+F25) -> 101.27703 | H25: =LN(G25)-LN(G24) -> -0.0020259076
A26: =EDATE(A25,3) -> 31382 | B26: =nG_h23!B31*nG!$B$8/nG_h23!$B$64 -> 349329.58 | C26: =rG_h23!B31*rG!$B$8/rG_h23!$B$64 -> 343751.37 | D26: =B26/C26*100 -> 101.62275 | E26: =LN(D26)-LN(D22) -> 0.0072067786 | F26: =E26-SUMIFS($L$15:$L$18,$J$15:$J$18,"<"&$A26,$K$15:$K$18,">"&$A26) -> 0.0072067786 | G26: =EXP(LN(G22)+F26) -> 101.62275 | H26: =LN(G26)-LN(G25) -> 0.003407725
A27: =EDATE(A26,3) -> 31472 | B27: =nG_h23!B32*nG!$B$8/nG_h23!$B$64 -> 352194.72 | C27: =rG_h23!B32*rG!$B$8/rG_h23!$B$64 -> 343406.61 | D27: =B27/C27*100 -> 102.5591 | E27: =LN(D27)-LN(D23) -> 0.012186317 | F27: =E27-SUMIFS($L$15:$L$18,$J$15:$J$18,"<"&$A27,$K$15:$K$18,">"&$A27) -> 0.012186317 | G27: =EXP(LN(G23)+F27) -> 102.5591 | H27: =LN(G27)-LN(G26) -> 0.0091718189
A28: =EDATE(A27,3) -> 31564 | B28: =nG_h23!B33*nG!$B$8/nG_h23!$B$64 -> 355481.55 | C28: =rG_h23!B33*rG!$B$8/rG_h23!$B$64 -> 344711.52 | D28: =B28/C28*100 -> 103.12436 | E28: =LN(D28)-LN(D24) -> 0.016050091 | F28: =E28-SUMIFS($L$15:$L$18,$J$15:$J$18,"<"&$A28,$K$15:$K$18,">"&$A28) -> 0.016050091 | G28: =EXP(LN(G24)+F28) -> 103.12436 | H28: =LN(G28)-LN(G27) -> 0.0054964548
A29: =EDATE(A28,3) -> 31656 | B29: =nG_h23!B34*nG!$B$8/nG_h23!$B$64 -> 359132.25 | C29: =rG_h23!B34*rG!$B$8/rG_h23!$B$64 -> 347045.46 | D29: =B29/C29*100 -> 103.48277 | E29: =LN(D29)-LN(D25) -> 0.021545448 | F29: =E29-SUMIFS($L$15:$L$18,$J$15:$J$18,"<"&$A29,$K$15:$K$18,">"&$A29) -> 0.021545448 | G29: =EXP(LN(G25)+F29) -> 103.48277 | H29: =LN(G29)-LN(G28) -> 0.0034694497
A30: =EDATE(A29,3) -> 31747 | B30: =nG_h23!B35*nG!$B$8/nG_h23!$B$64 -> 362367.38 | C30: =rG_h23!B35*rG!$B$8/rG_h23!$B$64 -> 351394.21 | D30: =B30/C30*100 -> 103.12275 | E30: =LN(D30)-LN(D26) -> 0.014652653 | F30: =E30-SUMIFS($L$15:$L$18,$J$15:$J$18,"<"&$A30,$K$15:$K$18,">"&$A30) -> 0.014652653 | G30: =EXP(LN(G26)+F30) -> 103.12275 | H30: =LN(G30)-LN(G29) -> -0.0034850701
A31: =EDATE(A30,3) -> 31837 | B31: =nG_h23!B36*nG!$B$8/nG_h23!$B$64 -> 362504.03 | C31: =rG_h23!B36*rG!$B$8/rG_h23!$B$64 -> 352052.55 | D31: =B31/C31*100 -> 102.96873 | E31: =LN(D31)-LN(D27) -> 0.0039861365 | F31: =E31-SUMIFS($L$15:$L$18,$J$15:$J$18,"<"&$A31,$K$15:$K$18,">"&$A31) -> 0.0039861365 | G31: =EXP(LN(G27)+F31) -> 102.96873 | H31: =LN(G31)-LN(G30) -> -0.0014946979
A32: =EDATE(A31,3) -> 31929 | B32: =nG_h23!B37*nG!$B$8/nG_h23!$B$64 -> 368304.98 | C32: =rG_h23!B37*rG!$B$8/rG_h23!$B$64 -> 358755.4 | D32: =B32/C32*100 -> 102.66186 | E32: =LN(D32)-LN(D28) -> -0.0044949298 | F32: =E32-SUMIFS($L$15:$L$18,$J$15:$J$18,"<"&$A32,$K$15:$K$18,">"&$A32) -> -0.0044949298 | G32: =EXP(LN(G28)+F32) -> 102.66186 | H32: =LN(G32)-LN(G31) -> -0.0029846116
A33: =EDATE(A32,3) -> 32021 | B33: =nG_h23!B38*nG!$B$8/nG_h23!$B$64 -> 376536.23 | C33: =rG_h23!B38*rG!$B$8/rG_h23!$B$64 -> 365353.35 | D33: =B33/C33*100 -> 103.06084 | E33: =LN(D33)-LN(D29) -> -0.004085586 | F33: =E33-SUMIFS($L$15:$L$18,$J$15:$J$18,"<"&$A33,$K$15:$K$18,">"&$A33) -> -0.004085586 | G33: =EXP(LN(G29)+F33) -> 103.06084 | H33: =LN(G33)-LN(G32) -> 0.0038787935
A34: =EDATE(A33,3) -> 32112 | B34: =nG_h23!B39*nG!$B$8/nG_h23!$B$64 -> 385976.26 | C34: =rG_h23!B39*rG!$B$8/rG_h23!$B$64 -> 375170.61 | D34: =B34/C34*100 -> 102.8802 | E34: =LN(D34)-LN(D30) -> -0.002354861 | F34: =E34-SUMIFS($L$15:$L$18,$J$15:$J$18,"<"&$A34,$K$15:$K$18,">"&$A34) -> -0.002354861 | G34: =EXP(LN(G30)+F34) -> 102.8802 | H34: =LN(G34)-LN(G33) -> -0.0017543451
A35: =EDATE(A34,3) -> 32203 | B35: =nG_h23!B40*nG!$B$8/nG_h23!$B$64 -> 394674.17 | C35: =rG_h23!B40*rG!$B$8/rG_h23!$B$64 -> 381506.33 | D35: =B35/C35*100 -> 103.45154 | E35: =LN(D35)-LN(D31) -> 0.0046779474 | F35: =E35-SUMIFS($L$15:$L$18,$J$15:$J$18,"<"&$A35,$K$15:$K$18,">"&$A35) -> 0.0046779474 | G35: =EXP(LN(G31)+F35) -> 103.45154 | H35: =LN(G35)-LN(G34) -> 0.0055381105
... A58: =EDATE(A57,3) -> 34304 | B58: =nG_h23!B63*nG!$B$8/nG_h23!$B$64 -> 505531.52 | C58: =rG_h23!B63*rG!$B$8/rG_h23!$B$64 -> 441585.34 | D58: =B58/C58*100 -> 114.48105 | E58: =LN(D58)-LN(D54) -> 0.0065525826 | F58: =E58-SUMIFS($L$15:$L$18,$J$15:$J$18,"<"&$A58,$K$15:$K$18,">"&$A58) -> 0.0065525826 | G58: =EXP(LN(G54)+F58) -> 112.88948 | H58: =LN(G58)-LN(G57) -> 0.002287612
A59: =EDATE(A58,3) -> 34394 | B59: =nG!B8 -> 510113.2 | C59: =rG!B8 -> 446281.9 | D59: =B59/C59*100 -> 114.30291 | E59: =LN(D59)-LN(D55) -> 0.0020109268 | F59: =E59-SUMIFS($L$15:$L$18,$J$15:$J$18,"<"&$A59,$K$15:$K$18,">"&$A59) -> 0.0020109268 | G59: =EXP(LN(G55)+F59) -> 112.71382 | H59: =LN(G59)-LN(G58) -> -0.0015572447
A60: =EDATE(A59,3) -> 34486 | B60: =nG!B9 -> 508973.8 | C60: =rG!B9 -> 443805.8 | D60: =B60/C60*100 -> 114.6839 | E60: =LN(D60)-LN(D56) -> 0.007253455 | F60: =E60-SUMIFS($L$15:$L$18,$J$15:$J$18,"<"&$A60,$K$15:$K$18,">"&$A60) -> 0.007253455 | G60: =EXP(LN(G56)+F60) -> 113.08951 | H60: =LN(G60)-LN(G59) -> 0.0033276156
A61: =EDATE(A60,3) -> 34578 | B61: =nG!B10 -> 513046.1 | C61: =rG!B10 -> 448941.2 | D61: =B61/C61*100 -> 114.27913 | E61: =LN(D61)-LN(D57) -> 0.00052230367 | F61: =E61-SUMIFS($L$15:$L$18,$J$15:$J$18,"<"&$A61,$K$15:$K$18,">"&$A61) -> 0.00052230367 | G61: =EXP(LN(G57)+F61) -> 112.69037 | H61: =LN(G61)-LN(G60) -> -0.0035356792
A62: =EDATE(A61,3) -> 34669 | B62: =nG!B11 -> 511528.7 | C62: =rG!B11 -> 447126.3 | D62: =B62/C62*100 -> 114.40363 | E62: =LN(D62)-LN(D58) -> -0.00067650323 | F62: =E62-SUMIFS($L$15:$L$18,$J$15:$J$18,"<"&$A62,$K$15:$K$18,">"&$A62) -> -0.00067650323 | G62: =EXP(LN(G58)+F62) -> 112.81313 | H62: =LN(G62)-LN(G61) -> 0.0010888051
A63: =EDATE(A62,3) -> 34759 | B63: =nG!B12 -> 514908.4 | C63: =rG!B12 -> 452085.2 | D63: =B63/C63*100 -> 113.89632 | E63: =LN(D63)-LN(D59) -> -0.0035634836 | F63: =E63-SUMIFS($L$15:$L$18,$J$15:$J$18,"<"&$A63,$K$15:$K$18,">"&$A63) -> -0.0035634836 | G63: =EXP(LN(G59)+F63) -> 112.31288 | H63: =LN(G63)-LN(G62) -> -0.0044442251
A64: =EDATE(A63,3) -> 34851 | B64: =nG!B13 -> 518736.5 | C64: =rG!B13 -> 456347.7 | D64: =B64/C64*100 -> 113.67133 | E64: =LN(D64)-LN(D60) -> -0.0088684342 | F64: =E64-SUMIFS($L$15:$L$18,$J$15:$J$18,"<"&$A64,$K$15:$K$18,">"&$A64) -> -0.0088684342 | G64: =EXP(LN(G60)+F64) -> 112.09102 | H64: =LN(G64)-LN(G63) -> -0.001977335
A65: =EDATE(A64,3) -> 34943 | B65: =nG!B14 -> 525429.1 | C65: =rG!B14 -> 461707.7 | D65: =B65/C65*100 -> 113.80124 | E65: =LN(D65)-LN(D61) -> -0.004190528 | F65: =E65-SUMIFS($L$15:$L$18,$J$15:$J$18,"<"&$A65,$K$15:$K$18,">"&$A65) -> -0.004190528 | G65: =EXP(LN(G61)+F65) -> 112.21913 | H65: =LN(G65)-LN(G64) -> 0.0011422271
A66: =EDATE(A65,3) -> 35034 | B66: =nG!B15 -> 526975.5 | C66: =rG!B15 -> 462809.6 | D66: =B66/C66*100 -> 113.86443 | E66: =LN(D66)-LN(D62) -> -0.0047242688 | F66: =E66-SUMIFS($L$15:$L$18,$J$15:$J$18,"<"&$A66,$K$15:$K$18,">"&$A66) -> -0.0047242688 | G66: =EXP(LN(G62)+F66) -> 112.28143 | H66: =LN(G66)-LN(G65) -> 0.00055506427
A67: =EDATE(A66,3) -> 35125 | B67: =nG!B16 -> 529181.6 | C67: =rG!B16 -> 466647.6 | D67: =B67/C67*100 -> 113.40069 | E67: =LN(D67)-LN(D63) -> -0.0043610699 | F67: =E67-SUMIFS($L$15:$L$18,$J$15:$J$18,"<"&$A67,$K$15:$K$18,">"&$A67) -> -0.0043610699 | G67: =EXP(LN(G63)+F67) -> 111.82414 | H67: =LN(G67)-LN(G66) -> -0.0040810263
A68: =EDATE(A67,3) -> 35217 | B68: =nG!B17 -> 535988.5 | C68: =rG!B17 -> 472545.6 | D68: =B68/C68*100 -> 113.42577 | E68: =LN(D68)-LN(D64) -> -0.0021625727 | F68: =E68-SUMIFS($L$15:$L$18,$J$15:$J$18,"<"&$A68,$K$15:$K$18,">"&$A68) -> -0.0021625727 | G68: =EXP(LN(G64)+F68) -> 111.84888 | H68: =LN(G68)-LN(G67) -> 0.00022116219
A69: =EDATE(A68,3) -> 35309 | B69: =nG!B18 -> 536155.5 | C69: =rG!B18 -> 473151.5 | D69: =B69/C69*100 -> 113.31582 | E69: =LN(D69)-LN(D65) -> -0.0042746575 | F69: =E69-SUMIFS($L$15:$L$18,$J$15:$J$18,"<"&$A69,$K$15:$K$18,">"&$A69) -> -0.0042746575 | G69: =EXP(LN(G65)+F69) -> 111.74045 | H69: =LN(G69)-LN(G68) -> -0.00096985766
A70: =EDATE(A69,3) -> 35400 | B70: =nG!B19 -> 541098 | C70: =rG!B19 -> 478418.1 | D70: =B70/C70*100 -> 113.10149 | E70: =LN(D70)-LN(D66) -> -0.0067229474 | F70: =E70-SUMIFS($L$15:$L$18,$J$15:$J$18,"<"&$A70,$K$15:$K$18,">"&$A70) -> -0.0067229474 | G70: =EXP(LN(G66)+F70) -> 111.5291 | H70: =LN(G70)-LN(G69) -> -0.0018932256
... A168: =EDATE(A167,3) -> 44348 | B168: =nG!B117 -> 544417.2 | C168: =rG!B117 -> 539309.3 | D168: =B168/C168*100 -> 100.94712 | E168: =LN(D168)-LN(D164) -> -0.010707857 | F168: =E168-SUMIFS($L$15:$L$18,$J$15:$J$18,"<"&$A168,$K$15:$K$18,">"&$A168) -> -0.010707857 | G168: =EXP(LN(G164)+F168) -> 96.344483 | H168: =LN(G168)-LN(G167) -> -0.0060156161

Sheet l_IC,pi_d
B1: Private Non-resi. Investment | D1: Per-capita | F1: Deflator
B2: Nominal | C2: Real | D2: Real | E2: QoQ | F2: 2015=100 | G2: QoQ
A3: 29281 | B3: =nG_h23!G8*nG!$G$8/nG_h23!$G$64 -> 44928.754 | C3: =rG_h23!G8*rG!$G$8/rG_h23!$G$64 -> 38995.739 | D3: =C3/Pop!G3 -> 4.9715244 | F3: =B3/C3*100 -> 115.21452 | I3: ＜算出方法＞
A4: =EDATE(A3,3) -> 29373 | B4: =nG_h23!G9*nG!$G$8/nG_h23!$G$64 -> 46199.774 | C4: =rG_h23!G9*rG!$G$8/rG_h23!$G$64 -> 39314.09 | D4: =C4/Pop!G4 -> 4.9999108 | E4: =LN(D4)-LN(D3) -> 0.0056935603 | F4: =B4/C4*100 -> 117.51454 | G4: =LN(F4)-LN(F3) -> 0.019766327 | I4: ・実質民間企業設備投資を、トレンド化した生産年齢人口で除す
A5: =EDATE(A4,3) -> 29465 | B5: =nG_h23!G10*nG!$G$8/nG_h23!$G$64 -> 46595.478 | C5: =rG_h23!G10*rG!$G$8/rG_h23!$G$64 -> 39115.728 | D5: =C5/Pop!G5 -> 4.9629277 | E5: =LN(D5)-LN(D4) -> -0.0074242424 | F5: =B5/C5*100 -> 119.1221 | G5: =LN(F5)-LN(F4) -> 0.01358693
A6: =EDATE(A5,3) -> 29556 | B6: =nG_h23!G11*nG!$G$8/nG_h23!$G$64 -> 47878.893 | C6: =rG_h23!G11*rG!$G$8/rG_h23!$G$64 -> 40166.925 | D6: =C6/Pop!G6 -> 5.086093 | E6: =LN(D6)-LN(D5) -> 0.024514135 | F6: =B6/C6*100 -> 119.1998 | G6: =LN(F6)-LN(F5) -> 0.00065200617
A7: =EDATE(A6,3) -> 29646 | B7: =nG_h23!G12*nG!$G$8/nG_h23!$G$64 -> 48467.204 | C7: =rG_h23!G12*rG!$G$8/rG_h23!$G$64 -> 40430.083 | D7: =C7/Pop!G7 -> 5.1112711 | E7: =LN(D7)-LN(D6) -> 0.0049381591 | F7: =B7/C7*100 -> 119.87906 | G7: =LN(F7)-LN(F6) -> 0.0056823711
A8: =EDATE(A7,3) -> 29738 | B8: =nG_h23!G13*nG!$G$8/nG_h23!$G$64 -> 48397.705 | C8: =rG_h23!G13*rG!$G$8/rG_h23!$G$64 -> 40476.114 | D8: =C8/Pop!G8 -> 5.1110417 | E8: =LN(D8)-LN(D7) -> -4.4879673e-05 | F8: =B8/C8*100 -> 119.57103 | G8: =LN(F8)-LN(F7) -> -0.0025728595
A9: =EDATE(A8,3) -> 29830 | B9: =nG_h23!G14*nG!$G$8/nG_h23!$G$64 -> 48924.674 | C9: =rG_h23!G14*rG!$G$8/rG_h23!$G$64 -> 40926.816 | D9: =C9/Pop!G9 -> 5.1621953 | E9: =LN(D9)-LN(D8) -> 0.0099586911 | F9: =B9/C9*100 -> 119.54185 | G9: =LN(F9)-LN(F8) -> -0.00024401736
A10: =EDATE(A9,3) -> 29921 | B10: =nG_h23!G15*nG!$G$8/nG_h23!$G$64 -> 49971.833 | C10: =rG_h23!G15*rG!$G$8/rG_h23!$G$64 -> 41698.187 | D10: =C10/Pop!G10 -> 5.2511832 | E10: =LN(D10)-LN(D9) -> 0.017091494 | F10: =B10/C10*100 -> 119.84174 | G10: =LN(F10)-LN(F9) -> 0.0025054911
A11: =EDATE(A10,3) -> 30011 | B11: =nG_h23!G16*nG!$G$8/nG_h23!$G$64 -> 49383.627 | C11: =rG_h23!G16*rG!$G$8/rG_h23!$G$64 -> 40785.854 | D11: =C11/Pop!G11 -> 5.1257113 | E11: =LN(D11)-LN(D10) -> -0.024184116 | F11: =B11/C11*100 -> 121.08028 | G11: =LN(F11)-LN(F10) -> 0.010281773
A12: =EDATE(A11,3) -> 30103 | B12: =nG_h23!G17*nG!$G$8/nG_h23!$G$64 -> 50191.562 | C12: =rG_h23!G17*rG!$G$8/rG_h23!$G$64 -> 41828.331 | D12: =C12/Pop!G12 -> 5.2437629 | E12: =LN(D12)-LN(D11) -> 0.022770039 | F12: =B12/C12*100 -> 119.99418 | G12: =LN(F12)-LN(F11) -> -0.0090105792
A13: =EDATE(A12,3) -> 30195 | B13: =nG_h23!G18*nG!$G$8/nG_h23!$G$64 -> 50459.814 | C13: =rG_h23!G18*rG!$G$8/rG_h23!$G$64 -> 41764.86 | D13: =C13/Pop!G13 -> 5.22165 | E13: =LN(D13)-LN(D12) -> -0.0042259054 | F13: =B13/C13*100 -> 120.81883 | G13: =LN(F13)-LN(F12) -> 0.0068489161
A14: =EDATE(A13,3) -> 30286 | B14: =nG_h23!G19*nG!$G$8/nG_h23!$G$64 -> 49943.016 | C14: =rG_h23!G19*rG!$G$8/rG_h23!$G$64 -> 41183.572 | D14: =C14/Pop!G14 -> 5.1356957 | E14: =LN(D14)-LN(D13) -> -0.016598123 | F14: =B14/C14*100 -> 121.26927 | G14: =LN(F14)-LN(F13) -> 0.0037212774
A15: =EDATE(A14,3) -> 30376 | B15: =nG_h23!G20*nG!$G$8/nG_h23!$G$64 -> 50477.825 | C15: =rG_h23!G20*rG!$G$8/rG_h23!$G$64 -> 41530.843 | D15: =C15/Pop!G15 -> 5.1658937 | E15: =LN(D15)-LN(D14) -> 0.0058627922 | F15: =B15/C15*100 -> 121.54298 | G15: =LN(F15)-LN(F14) -> 0.0022545341
A16: =EDATE(A15,3) -> 30468 | B16: =nG_h23!G21*nG!$G$8/nG_h23!$G$64 -> 51570.646 | C16: =rG_h23!G21*rG!$G$8/rG_h23!$G$64 -> 42805.901 | D16: =C16/Pop!G16 -> 5.3110066 | E16: =LN(D16)-LN(D15) -> 0.027703267 | F16: =B16/C16*100 -> 120.47555 | G16: =LN(F16)-LN(F15) -> -0.008821117
... A58: =EDATE(A57,3) -> 34304 | B58: =nG_h23!G63*nG!$G$8/nG_h23!$G$64 -> 78354.445 | C58: =rG_h23!G63*rG!$G$8/rG_h23!$G$64 -> 64344.571 | D58: =C58/Pop!G58 -> 7.4002752 | E58: =LN(D58)-LN(D57) -> -0.051696387 | F58: =B58/C58*100 -> 121.7732 | G58: =LN(F58)-LN(F57) -> -0.0046225438
A59: =EDATE(A58,3) -> 34394 | B59: =nG!G8 -> 80433.4 | C59: =rG!G8 -> 66259.2 | D59: =C59/Pop!G59 -> 7.6196006 | E59: =LN(D59)-LN(D58) -> 0.029206761 | F59: =B59/C59*100 -> 121.39205 | G59: =LN(F59)-LN(F58) -> -0.0031349532
A60: =EDATE(A59,3) -> 34486 | B60: =nG!G9 -> 79979.9 | C60: =rG!G9 -> 66065 | D60: =C60/Pop!G60 -> 7.5966494 | E60: =LN(D60)-LN(D59) -> -0.0030166701 | F60: =B60/C60*100 -> 121.06244 | G60: =LN(F60)-LN(F59) -> -0.0027189424
A61: =EDATE(A60,3) -> 34578 | B61: =nG!G10 -> 79430.6 | C61: =rG!G10 -> 65999.2 | D61: =C61/Pop!G61 -> 7.588344 | E61: =LN(D61)-LN(D60) -> -0.0010939003 | F61: =B61/C61*100 -> 120.35085 | G61: =LN(F61)-LN(F60) -> -0.0058951835
A62: =EDATE(A61,3) -> 34669 | B62: =nG!G11 -> 80298.5 | C62: =rG!G11 -> 67028.9 | D62: =C62/Pop!G62 -> 7.7059352 | E62: =LN(D62)-LN(D61) -> 0.015377456 | F62: =B62/C62*100 -> 119.79683 | G62: =LN(F62)-LN(F61) -> -0.0046139925
A63: =EDATE(A62,3) -> 34759 | B63: =nG!G12 -> 82049.8 | C63: =rG!G12 -> 68647.7 | D63: =C63/Pop!G63 -> 7.8918883 | E63: =LN(D63)-LN(D62) -> 0.023844598 | F63: =B63/C63*100 -> 119.52301 | G63: =LN(F63)-LN(F62) -> -0.0022883195
A64: =EDATE(A63,3) -> 34851 | B64: =nG!G13 -> 84418.3 | C64: =rG!G13 -> 71088 | D64: =C64/Pop!G64 -> 8.1733309 | E64: =LN(D64)-LN(D63) -> 0.035041096 | F64: =B64/C64*100 -> 118.75183 | G64: =LN(F64)-LN(F63) -> -0.0064730951
A65: =EDATE(A64,3) -> 34943 | B65: =nG!G14 -> 85770.3 | C65: =rG!G14 -> 72334.5 | D65: =C65/Pop!G65 -> 8.3182543 | E65: =LN(D65)-LN(D64) -> 0.017575888 | F65: =B65/C65*100 -> 118.57454 | G65: =LN(F65)-LN(F64) -> -0.0014940576
A66: =EDATE(A65,3) -> 35034 | B66: =nG!G15 -> 86906.1 | C66: =rG!G15 -> 73525.1 | D66: =C66/Pop!G66 -> 8.4579527 | E66: =LN(D66)-LN(D65) -> 0.016654724 | F66: =B66/C66*100 -> 118.19923 | G66: =LN(F66)-LN(F65) -> -0.003170218
A67: =EDATE(A66,3) -> 35125 | B67: =nG!G16 -> 86233 | C67: =rG!G16 -> 73285 | D67: =C67/Pop!G67 -> 8.4332971 | E67: =LN(D67)-LN(D66) -> -0.0029193377 | F67: =B67/C67*100 -> 117.66801 | G67: =LN(F67)-LN(F66) -> -0.0045043954
A68: =EDATE(A67,3) -> 35217 | B68: =nG!G17 -> 88655.2 | C68: =rG!G17 -> 75804 | D68: =C68/Pop!G68 -> 8.7255287 | E68: =LN(D68)-LN(D67) -> 0.034065256 | F68: =B68/C68*100 -> 116.9532 | G68: =LN(F68)-LN(F67) -> -0.0060933588
A69: =EDATE(A68,3) -> 35309 | B69: =nG!G18 -> 89608.7 | C69: =rG!G18 -> 76855 | D69: =C69/Pop!G69 -> 8.8460813 | E69: =LN(D69)-LN(D68) -> 0.013721508 | F69: =B69/C69*100 -> 116.5945 | G69: =LN(F69)-LN(F68) -> -0.0030717429
A70: =EDATE(A69,3) -> 35400 | B70: =nG!G19 -> 89691.8 | C70: =rG!G19 -> 76900.7 | D70: =C70/Pop!G70 -> 8.8478619 | E70: =LN(D70)-LN(D69) -> 0.00020126535 | F70: =B70/C70*100 -> 116.63327 | G70: =LN(F70)-LN(F69) -> 0.00033248605
... A168: =EDATE(A167,3) -> 44348 | B168: =nG!G117 -> 88376.7 | C168: =rG!G117 -> 86753.5 | D168: =C168/Pop!G168 -> #DIV/0! | E168: =LN(D168)-LN(D167) -> #DIV/0! | F168: =B168/C168*100 -> 101.87105 | G168: =LN(F168)-LN(F167) -> 0.0062879511

Sheet l_Output
B1: GDP | C1: Per-capita
B2: Real | C2: Real | D2: QoQ
A3: 29281 | B3: =rG_h23!B8*rG!$B$8/rG_h23!$B$64 -> 270758.12 | C3: =B3/Pop!G3 -> 34.518658 | F3: ＜算出方法＞
A4: =EDATE(A3,3) -> 29373 | B4: =rG_h23!B9*rG!$B$8/rG_h23!$B$64 -> 268779.55 | C4: =B4/Pop!G4 -> 34.183005 | D4: =LN(C4)-LN(C3) -> -0.0097713917 | F4: ・実質GDPを、トレンド化した生産年齢人口で除す
A5: =EDATE(A4,3) -> 29465 | B5: =rG_h23!B10*rG!$B$8/rG_h23!$B$64 -> 274419.87 | C5: =B5/Pop!G5 -> 34.81786 | D5: =LN(C5)-LN(C4) -> 0.018401877
A6: =EDATE(A5,3) -> 29556 | B6: =rG_h23!B11*rG!$B$8/rG_h23!$B$64 -> 280149.13 | C6: =B6/Pop!G6 -> 35.473578 | D6: =LN(C6)-LN(C5) -> 0.018657658
A7: =EDATE(A6,3) -> 29646 | B7: =rG_h23!B12*rG!$B$8/rG_h23!$B$64 -> 282193.55 | C7: =B7/Pop!G7 -> 35.675606 | D7: =LN(C7)-LN(C6) -> 0.0056790277
A8: =EDATE(A7,3) -> 29738 | B8: =rG_h23!B13*rG!$B$8/rG_h23!$B$64 -> 284915.1 | C8: =B8/Pop!G8 -> 35.977094 | D8: =LN(C8)-LN(C7) -> 0.0084153075
A9: =EDATE(A8,3) -> 29830 | B9: =rG_h23!B14*rG!$B$8/rG_h23!$B$64 -> 285949.18 | C9: =B9/Pop!G9 -> 36.06744 | D9: =LN(C9)-LN(C8) -> 0.0025080576
A10: =EDATE(A9,3) -> 29921 | B10: =rG_h23!B15*rG!$B$8/rG_h23!$B$64 -> 287542.35 | C10: =B10/Pop!G10 -> 36.211108 | D10: =LN(C10)-LN(C9) -> 0.0039753993
A11: =EDATE(A10,3) -> 30011 | B11: =rG_h23!B16*rG!$B$8/rG_h23!$B$64 -> 291527.22 | C11: =B11/Pop!G11 -> 36.63732 | D11: =LN(C11)-LN(C10) -> 0.011701462
A12: =EDATE(A11,3) -> 30103 | B12: =rG_h23!B17*rG!$B$8/rG_h23!$B$64 -> 293472.72 | C12: =B12/Pop!G12 -> 36.790886 | D12: =LN(C12)-LN(C11) -> 0.004182757
A13: =EDATE(A12,3) -> 30195 | B13: =rG_h23!B18*rG!$B$8/rG_h23!$B$64 -> 294655.71 | C13: =B13/Pop!G13 -> 36.839318 | D13: =LN(C13)-LN(C12) -> 0.0013155637
A14: =EDATE(A13,3) -> 30286 | B14: =rG_h23!B19*rG!$B$8/rG_h23!$B$64 -> 298955.73 | C14: =B14/Pop!G14 -> 37.280536 | D14: =LN(C14)-LN(C13) -> 0.011905669
A15: =EDATE(A14,3) -> 30376 | B15: =rG_h23!B20*rG!$B$8/rG_h23!$B$64 -> 300452.71 | C15: =B15/Pop!G15 -> 37.372387 | D15: =LN(C15)-LN(C14) -> 0.0024607292
A16: =EDATE(A15,3) -> 30468 | B16: =rG_h23!B21*rG!$B$8/rG_h23!$B$64 -> 303001.4 | C16: =B16/Pop!G16 -> 37.593939 | D16: =LN(C16)-LN(C15) -> 0.0059107339
... A58: =EDATE(A57,3) -> 34304 | B58: =rG_h23!B63*rG!$B$8/rG_h23!$B$64 -> 441585.34 | C58: =B58/Pop!G58 -> 50.786773 | D58: =LN(C58)-LN(C57) -> 0.0036990719
A59: =EDATE(A58,3) -> 34394 | B59: =rG!B8 -> 446281.9 | C59: =B59/Pop!G59 -> 51.321021 | D59: =LN(C59)-LN(C58) -> 0.010464505
A60: =EDATE(A59,3) -> 34486 | B60: =rG!B9 -> 443805.8 | C60: =B60/Pop!G60 -> 51.032121 | D60: =LN(C60)-LN(C59) -> -0.0056451886
A61: =EDATE(A60,3) -> 34578 | B61: =rG!B10 -> 448941.2 | C61: =B61/Pop!G61 -> 51.617599 | D61: =LN(C61)-LN(C60) -> 0.011407427
A62: =EDATE(A61,3) -> 34669 | B62: =rG!B11 -> 447126.3 | C62: =B62/Pop!G62 -> 51.403593 | D62: =LN(C62)-LN(C61) -> -0.0041546091
A63: =EDATE(A62,3) -> 34759 | B63: =rG!B12 -> 452085.2 | C63: =B63/Pop!G63 -> 51.972694 | D63: =LN(C63)-LN(C62) -> 0.011010392
A64: =EDATE(A63,3) -> 34851 | B64: =rG!B13 -> 456347.7 | C64: =B64/Pop!G64 -> 52.468501 | D64: =LN(C64)-LN(C63) -> 0.0094945395
A65: =EDATE(A64,3) -> 34943 | B65: =rG!B14 -> 461707.7 | C65: =B65/Pop!G65 -> 53.095025 | D65: =LN(C65)-LN(C64) -> 0.011870228
A66: =EDATE(A65,3) -> 35034 | B66: =rG!B15 -> 462809.6 | C66: =B66/Pop!G66 -> 53.239257 | D66: =LN(C66)-LN(C65) -> 0.002712805
A67: =EDATE(A66,3) -> 35125 | B67: =rG!B16 -> 466647.6 | C67: =B67/Pop!G67 -> 53.699636 | D67: =LN(C67)-LN(C66) -> 0.0086101879
A68: =EDATE(A67,3) -> 35217 | B68: =rG!B17 -> 472545.6 | C68: =B68/Pop!G68 -> 54.393042 | D68: =LN(C68)-LN(C67) -> 0.012830025
A69: =EDATE(A68,3) -> 35309 | B69: =rG!B18 -> 473151.5 | C69: =B69/Pop!G69 -> 54.460173 | D69: =LN(C69)-LN(C68) -> 0.0012334231
A70: =EDATE(A69,3) -> 35400 | B70: =rG!B19 -> 478418.1 | C70: =B70/Pop!G70 -> 55.044717 | D70: =LN(C70)-LN(C69) -> 0.010676219
... A168: =EDATE(A167,3) -> 44348 | B168: =rG!B117 -> 539309.3 | C168: =B168/Pop!G168 -> #DIV/0! | D168: =LN(C168)-LN(C167) -> #DIV/0!

Sheet l_Solow
B1: GDP (bn JPY) | D1: KC (bn JPY) | F1: L (10k) | G1: HC | H1: Solow | K1: Share_Labor
B2: Nominal | C2: Real | D2: Nominal | E2: Real | H2: Level | I2: ldif | K2: 0.64
A3: 29281 | B3: =nG_h23!B8*nG!$B$8/nG_h23!$B$64 -> 245801.57 | C3: =rG_h23!B8*rG!$B$8/rG_h23!$B$64 -> 270758.12 | D3: ='fdr,edr'!P3 -> 487337.26 | E3: ='fdr,edr'!Q3 -> 536817.24 | F3: ='l_HC,WC'!F3 -> 5514.5833 | G3: ='l_HC,WC'!I3 -> 122.82896 | H3: =C3/(E3^(1-$K$2)*(F3*G3)^$K$2) -> 0.43463365
A4: =EDATE(A3,3) -> 29373 | B4: =nG_h23!B9*nG!$B$8/nG_h23!$B$64 -> 250409.15 | C4: =rG_h23!B9*rG!$B$8/rG_h23!$B$64 -> 268779.55 | D4: ='fdr,edr'!P4 -> 493237.42 | E4: ='fdr,edr'!Q4 -> 529422.07 | F4: ='l_HC,WC'!F4 -> 5529.9167 | G4: ='l_HC,WC'!I4 -> 122.96802 | H4: =C4/(E4^(1-$K$2)*(F4*G4)^$K$2) -> 0.43253433 | I4: =LN(H4/H3) -> -0.004841788
A5: =EDATE(A4,3) -> 29465 | B5: =nG_h23!B10*nG!$B$8/nG_h23!$B$64 -> 258384.02 | C5: =rG_h23!B10*rG!$B$8/rG_h23!$B$64 -> 274419.87 | D5: ='fdr,edr'!P5 -> 499861.05 | E5: ='fdr,edr'!Q5 -> 530883.46 | F5: ='l_HC,WC'!F5 -> 5544.5417 | G5: ='l_HC,WC'!I5 -> 122.0641 | H5: =C5/(E5^(1-$K$2)*(F5*G5)^$K$2) -> 0.44251248 | I5: =LN(H5/H4) -> 0.022806971
A6: =EDATE(A5,3) -> 29556 | B6: =nG_h23!B11*nG!$B$8/nG_h23!$B$64 -> 266236.92 | C6: =rG_h23!B11*rG!$B$8/rG_h23!$B$64 -> 280149.13 | D6: ='fdr,edr'!P6 -> 505991.02 | E6: ='fdr,edr'!Q6 -> 532431.58 | F6: ='l_HC,WC'!F6 -> 5559.0556 | G6: ='l_HC,WC'!I6 -> 121.99457 | H6: =C6/(E6^(1-$K$2)*(F6*G6)^$K$2) -> 0.45068774 | I6: =LN(H6/H5) -> 0.018306056
A7: =EDATE(A6,3) -> 29646 | B7: =nG_h23!B12*nG!$B$8/nG_h23!$B$64 -> 268962.66 | C7: =rG_h23!B12*rG!$B$8/rG_h23!$B$64 -> 282193.55 | D7: ='fdr,edr'!P7 -> 511377.57 | E7: ='fdr,edr'!Q7 -> 536533.42 | F7: ='l_HC,WC'!F7 -> 5566.1528 | G7: ='l_HC,WC'!I7 -> 121.82074 | H7: =C7/(E7^(1-$K$2)*(F7*G7)^$K$2) -> 0.45276764 | I7: =LN(H7/H6) -> 0.0046043361
A8: =EDATE(A7,3) -> 29738 | B8: =nG_h23!B13*nG!$B$8/nG_h23!$B$64 -> 272900.73 | C8: =rG_h23!B13*rG!$B$8/rG_h23!$B$64 -> 284915.1 | D8: ='fdr,edr'!P8 -> 516648.74 | E8: ='fdr,edr'!Q8 -> 539394.04 | F8: ='l_HC,WC'!F8 -> 5574.5139 | G8: ='l_HC,WC'!I8 -> 122.02933 | H8: =C8/(E8^(1-$K$2)*(F8*G8)^$K$2) -> 0.45532308 | I8: =LN(H8/H7) -> 0.0056281602
A9: =EDATE(A8,3) -> 29830 | B9: =nG_h23!B14*nG!$B$8/nG_h23!$B$64 -> 274959.41 | C9: =rG_h23!B14*rG!$B$8/rG_h23!$B$64 -> 285949.18 | D9: ='fdr,edr'!P9 -> 523037.64 | E9: ='fdr,edr'!Q9 -> 543942.76 | F9: ='l_HC,WC'!F9 -> 5587.1806 | G9: ='l_HC,WC'!I9 -> 121.71644 | H9: =C9/(E9^(1-$K$2)*(F9*G9)^$K$2) -> 0.45568303 | I9: =LN(H9/H8) -> 0.0007902338
A10: =EDATE(A9,3) -> 29921 | B10: =nG_h23!B15*nG!$B$8/nG_h23!$B$64 -> 278731.36 | C10: =rG_h23!B15*rG!$B$8/rG_h23!$B$64 -> 287542.35 | D10: ='fdr,edr'!P10 -> 528746.66 | E10: ='fdr,edr'!Q10 -> 545460.89 | F10: ='l_HC,WC'!F10 -> 5601.25 | G10: ='l_HC,WC'!I10 -> 122.377 | H10: =C10/(E10^(1-$K$2)*(F10*G10)^$K$2) -> 0.45544577 | I10: =LN(H10/H9) -> -0.00052079572
A11: =EDATE(A10,3) -> 30011 | B11: =nG_h23!B16*nG!$B$8/nG_h23!$B$64 -> 284931.57 | C11: =rG_h23!B16*rG!$B$8/rG_h23!$B$64 -> 291527.22 | D11: ='fdr,edr'!P11 -> 533417.77 | E11: ='fdr,edr'!Q11 -> 545765.43 | F11: ='l_HC,WC'!F11 -> 5612.625 | G11: ='l_HC,WC'!I11 -> 121.71644 | H11: =C11/(E11^(1-$K$2)*(F11*G11)^$K$2) -> 0.46266557 | I11: =LN(H11/H10) -> 0.015727813
A12: =EDATE(A11,3) -> 30103 | B12: =nG_h23!B17*nG!$B$8/nG_h23!$B$64 -> 286359.4 | C12: =rG_h23!B17*rG!$B$8/rG_h23!$B$64 -> 293472.72 | D12: ='fdr,edr'!P12 -> 538064.09 | E12: ='fdr,edr'!Q12 -> 551429.89 | F12: ='l_HC,WC'!F12 -> 5627.4167 | G12: ='l_HC,WC'!I12 -> 121.61214 | H12: =C12/(E12^(1-$K$2)*(F12*G12)^$K$2) -> 0.46349834 | I12: =LN(H12/H11) -> 0.0017983292
A13: =EDATE(A12,3) -> 30195 | B13: =nG_h23!B18*nG!$B$8/nG_h23!$B$64 -> 288685.27 | C13: =rG_h23!B18*rG!$B$8/rG_h23!$B$64 -> 294655.71 | D13: ='fdr,edr'!P13 -> 543851.31 | E13: ='fdr,edr'!Q13 -> 555098.96 | F13: ='l_HC,WC'!F13 -> 5652.0139 | G13: ='l_HC,WC'!I13 -> 121.99457 | H13: =C13/(E13^(1-$K$2)*(F13*G13)^$K$2) -> 0.46203357 | I13: =LN(H13/H12) -> -0.003165263
A14: =EDATE(A13,3) -> 30286 | B14: =nG_h23!B19*nG!$B$8/nG_h23!$B$64 -> 292426.42 | C14: =rG_h23!B19*rG!$B$8/rG_h23!$B$64 -> 298955.73 | D14: ='fdr,edr'!P14 -> 549039.44 | E14: ='fdr,edr'!Q14 -> 561298.41 | F14: ='l_HC,WC'!F14 -> 5675.4861 | G14: ='l_HC,WC'!I14 -> 121.61214 | H14: =C14/(E14^(1-$K$2)*(F14*G14)^$K$2) -> 0.46660556 | I14: =LN(H14/H13) -> 0.0098467301
A15: =EDATE(A14,3) -> 30376 | B15: =nG_h23!B20*nG!$B$8/nG_h23!$B$64 -> 296066.82 | C15: =rG_h23!B20*rG!$B$8/rG_h23!$B$64 -> 300452.71 | D15: ='fdr,edr'!P15 -> 553781.12 | E15: ='fdr,edr'!Q15 -> 561984.74 | F15: ='l_HC,WC'!F15 -> 5702.8611 | G15: ='l_HC,WC'!I15 -> 121.50784 | H15: =C15/(E15^(1-$K$2)*(F15*G15)^$K$2) -> 0.46755117 | I15: =LN(H15/H14) -> 0.0020245188
... A58: =EDATE(A57,3) -> 34304 | B58: =nG_h23!B63*nG!$B$8/nG_h23!$B$64 -> 505531.52 | C58: =rG_h23!B63*rG!$B$8/rG_h23!$B$64 -> 441585.34 | D58: ='fdr,edr'!P58 -> 897640.6 | E58: ='fdr,edr'!Q58 -> 795149.92 | F58: ='l_HC,WC'!F58 -> 6457.4583 | G58: ='l_HC,WC'!I58 -> 110 | H58: =C58/(E58^(1-$K$2)*(F58*G58)^$K$2) -> 0.59692842 | I58: =LN(H58/H57) -> 0.0035060192
A59: =EDATE(A58,3) -> 34394 | B59: =nG!B8 -> 510113.2 | C59: =rG!B8 -> 446281.9 | D59: ='fdr,edr'!P59 -> 904279.29 | E59: ='fdr,edr'!Q59 -> 802278.99 | F59: ='l_HC,WC'!F59 -> 6459.5139 | G59: ='l_HC,WC'!I59 -> 110.53333 | H59: =C59/(E59^(1-$K$2)*(F59*G59)^$K$2) -> 0.59936108 | I59: =LN(H59/H58) -> 0.0040670157
A60: =EDATE(A59,3) -> 34486 | B60: =nG!B9 -> 508973.8 | C60: =rG!B9 -> 443805.8 | D60: ='fdr,edr'!P60 -> 906746.34 | E60: ='fdr,edr'!Q60 -> 801795.26 | F60: ='l_HC,WC'!F60 -> 6455.8611 | G60: ='l_HC,WC'!I60 -> 109.43333 | H60: =C60/(E60^(1-$K$2)*(F60*G60)^$K$2) -> 0.60021063 | I60: =LN(H60/H59) -> 0.0014164294
A61: =EDATE(A60,3) -> 34578 | B61: =nG!B10 -> 513046.1 | C61: =rG!B10 -> 448941.2 | D61: ='fdr,edr'!P61 -> 911504.26 | E61: ='fdr,edr'!Q61 -> 808857.27 | F61: ='l_HC,WC'!F61 -> 6453.625 | G61: ='l_HC,WC'!I61 -> 110.3 | H61: =C61/(E61^(1-$K$2)*(F61*G61)^$K$2) -> 0.60232774 | I61: =LN(H61/H60) -> 0.0035210763
A62: =EDATE(A61,3) -> 34669 | B62: =nG!B11 -> 511528.7 | C62: =rG!B11 -> 447126.3 | D62: ='fdr,edr'!P62 -> 915624.27 | E62: ='fdr,edr'!Q62 -> 811629.13 | F62: ='l_HC,WC'!F62 -> 6452.5972 | G62: ='l_HC,WC'!I62 -> 110.16667 | H62: =C62/(E62^(1-$K$2)*(F62*G62)^$K$2) -> 0.59967952 | I62: =LN(H62/H61) -> -0.0044063372
A63: =EDATE(A62,3) -> 34759 | B63: =nG!B12 -> 514908.4 | C63: =rG!B12 -> 452085.2 | D63: ='fdr,edr'!P63 -> 915299.38 | E63: ='fdr,edr'!Q63 -> 814954.95 | F63: ='l_HC,WC'!F63 -> 6454.0972 | G63: ='l_HC,WC'!I63 -> 110.33333 | H63: =C63/(E63^(1-$K$2)*(F63*G63)^$K$2) -> 0.60476292 | I63: =LN(H63/H62) -> 0.0084411345
A64: =EDATE(A63,3) -> 34851 | B64: =nG!B13 -> 518736.5 | C64: =rG!B13 -> 456347.7 | D64: ='fdr,edr'!P64 -> 918523.09 | E64: ='fdr,edr'!Q64 -> 819443.96 | F64: ='l_HC,WC'!F64 -> 6457.9167 | G64: ='l_HC,WC'!I64 -> 109.86667 | H64: =C64/(E64^(1-$K$2)*(F64*G64)^$K$2) -> 0.61068263 | I64: =LN(H64/H63) -> 0.0097408745
A65: =EDATE(A64,3) -> 34943 | B65: =nG!B14 -> 525429.1 | C65: =rG!B14 -> 461707.7 | D65: ='fdr,edr'!P65 -> 923599.99 | E65: ='fdr,edr'!Q65 -> 823032.6 | F65: ='l_HC,WC'!F65 -> 6455.9722 | G65: ='l_HC,WC'!I65 -> 110.26667 | H65: =C65/(E65^(1-$K$2)*(F65*G65)^$K$2) -> 0.61556966 | I65: =LN(H65/H64) -> 0.0079707276
A66: =EDATE(A65,3) -> 35034 | B66: =nG!B15 -> 526975.5 | C66: =rG!B15 -> 462809.6 | D66: ='fdr,edr'!P66 -> 928545.71 | E66: ='fdr,edr'!Q66 -> 826980.65 | F66: ='l_HC,WC'!F66 -> 6458.4722 | G66: ='l_HC,WC'!I66 -> 110.6 | H66: =C66/(E66^(1-$K$2)*(F66*G66)^$K$2) -> 0.61463556 | I66: =LN(H66/H65) -> -0.0015186143
A67: =EDATE(A66,3) -> 35125 | B67: =nG!B16 -> 529181.6 | C67: =rG!B16 -> 466647.6 | D67: ='fdr,edr'!P67 -> 934012.92 | E67: ='fdr,edr'!Q67 -> 835251.59 | F67: ='l_HC,WC'!F67 -> 6466.9028 | G67: ='l_HC,WC'!I67 -> 110.7 | H67: =C67/(E67^(1-$K$2)*(F67*G67)^$K$2) -> 0.61664423 | I67: =LN(H67/H66) -> 0.0032627448
A68: =EDATE(A67,3) -> 35217 | B68: =nG!B17 -> 535988.5 | C68: =rG!B17 -> 472545.6 | D68: ='fdr,edr'!P68 -> 938506.56 | E68: ='fdr,edr'!Q68 -> 839084.48 | F68: ='l_HC,WC'!F68 -> 6478.9306 | G68: ='l_HC,WC'!I68 -> 110.3 | H68: =C68/(E68^(1-$K$2)*(F68*G68)^$K$2) -> 0.62411299 | I68: =LN(H68/H67) -> 0.012039169
A69: =EDATE(A68,3) -> 35309 | B69: =nG!B18 -> 536155.5 | C69: =rG!B18 -> 473151.5 | D69: ='fdr,edr'!P69 -> 945505.48 | E69: ='fdr,edr'!Q69 -> 846162.22 | F69: ='l_HC,WC'!F69 -> 6498.9861 | G69: ='l_HC,WC'!I69 -> 109.9 | H69: =C69/(E69^(1-$K$2)*(F69*G69)^$K$2) -> 0.6232427 | I69: =LN(H69/H68) -> -0.0013954074
A70: =EDATE(A69,3) -> 35400 | B70: =nG!B19 -> 541098 | C70: =rG!B19 -> 478418.1 | D70: ='fdr,edr'!P70 -> 954969.9 | E70: ='fdr,edr'!Q70 -> 856251.76 | F70: ='l_HC,WC'!F70 -> 6522.5694 | G70: ='l_HC,WC'!I70 -> 110.53333 | H70: =C70/(E70^(1-$K$2)*(F70*G70)^$K$2) -> 0.62374547 | I70: =LN(H70/H69) -> 0.00080636775
... A166: =EDATE(A165,3) -> 44166 | B166: =nG!B115 -> 551223.4 | C166: =rG!B115 -> 542543.5 | D166: ='fdr,edr'!P166 -> #N/A | E166: ='fdr,edr'!Q166 -> #N/A | F166: ='l_HC,WC'!F166 -> 6667.1944 | G166: ='l_HC,WC'!I166 -> 94.4 | H166: =C166/(E166^(1-$K$2)*(F166*G166)^$K$2) -> #N/A | I166: =LN(H166/H165) -> #N/A
A167: =EDATE(A166,3) -> 44256 | B167: =nG!B116 -> 545158.6 | C167: =rG!B116 -> 536804.8 | D167: ='fdr,edr'!P167 -> 0 | E167: ='fdr,edr'!Q167 -> 0
A168: =EDATE(A167,3) -> 44348 | B168: =nG!B117 -> 544417.2 | C168: =rG!B117 -> 539309.3

Sheet l_HC,WC
B1: Labor | C1: Labor (Trend) | F1: Labor | I1: Hour worked | J1: Wage | K1: Hour worked per capita | M1: Comp. per hour worked
B2: 10k | C2: 10k | F2: 10k | I2: 2015=100 | J2: Real | K2: Level | L2: QoQ | M2: Level | N2: QoQ
A3: 27395 | B3: =HC!F18 -> 5016 | E3: 29221 | F3: =AVERAGEIFS($C:$C,$A:$A,">="&$E3,$A:$A,"<"&$E4) -> 5514.5833 | H3: 29221 | I3: =HC!C18*HC!$B$58/HC!$C$58 -> 122.82896 | J3: =W_h23!E9*W!$D$9/W_h23!$E$65 -> 121575.93 | K3: =F3*I3/Pop!G3 -> 86.35468 | M3: =J3/(I3*F3) -> 0.17948747 | P3: ＜算出方法＞
A4: =EDATE(A3,1) -> 27426 | B4: =HC!F19 -> 5027 | E4: =EDATE(E3,3) -> 29312 | F4: =AVERAGEIFS($C:$C,$A:$A,">="&$E4,$A:$A,"<"&$E5) -> 5529.9167 | H4: =EDATE(H3,3) -> 29312 | I4: =HC!C19*HC!$B$58/HC!$C$58 -> 122.96802 | J4: =W_h23!E10*W!$D$9/W_h23!$E$65 -> 124327.07 | K4: =F4*I4/Pop!G4 -> 86.481816 | L4: =LN(K4)-LN(K3) -> 0.0014711655 | M4: =J4/(I4*F4) -> 0.18283314 | N4: =LN(M4)-LN(M3) -> 0.018468565 | P4: ・季節調整済み労働時間指数に労働者数を乗じ、生産年齢人口で除す
A5: =EDATE(A4,1) -> 27454 | B5: =HC!F20 -> 5121 | E5: =EDATE(E4,3) -> 29403 | F5: =AVERAGEIFS($C:$C,$A:$A,">="&$E5,$A:$A,"<"&$E6) -> 5544.5417 | H5: =EDATE(H4,3) -> 29403 | I5: =HC!C20*HC!$B$58/HC!$C$58 -> 122.0641 | J5: =W_h23!E11*W!$D$9/W_h23!$E$65 -> 128511.62 | K5: =F5*I5/Pop!G5 -> 85.869738 | L5: =LN(K5)-LN(K4) -> -0.0071026992 | M5: =J5/(I5*F5) -> 0.18988419 | N5: =LN(M5)-LN(M4) -> 0.037840412 | P5: ・雇用者報酬を総労働時間で除す
A6: =EDATE(A5,1) -> 27485 | B6: =HC!F21 -> 5206 | E6: =EDATE(E5,3) -> 29495 | F6: =AVERAGEIFS($C:$C,$A:$A,">="&$E6,$A:$A,"<"&$E7) -> 5559.0556 | H6: =EDATE(H5,3) -> 29495 | I6: =HC!C21*HC!$B$58/HC!$C$58 -> 121.99457 | J6: =W_h23!E12*W!$D$9/W_h23!$E$65 -> 131358.37 | K6: =F6*I6/Pop!G6 -> 85.873116 | L6: =LN(K6)-LN(K5) -> 3.9340002e-05 | M6: =J6/(I6*F6) -> 0.19369403 | N6: =LN(M6)-LN(M5) -> 0.019865419
A7: =EDATE(A6,1) -> 27515 | B7: =HC!F22 -> 5325 | E7: =EDATE(E6,3) -> 29587 | F7: =AVERAGEIFS($C:$C,$A:$A,">="&$E7,$A:$A,"<"&$E8) -> 5566.1528 | H7: =EDATE(H6,3) -> 29587 | I7: =HC!C22*HC!$B$58/HC!$C$58 -> 121.82074 | J7: =W_h23!E13*W!$D$9/W_h23!$E$65 -> 132739.87 | K7: =F7*I7/Pop!G7 -> 85.723645 | L7: =LN(K7)-LN(K6) -> -0.0017421249 | M7: =J7/(I7*F7) -> 0.19576049 | N7: =LN(M7)-LN(M6) -> 0.010612129
A8: =EDATE(A7,1) -> 27546 | B8: =HC!F23 -> 5339 | E8: =EDATE(E7,3) -> 29677 | F8: =AVERAGEIFS($C:$C,$A:$A,">="&$E8,$A:$A,"<"&$E9) -> 5574.5139 | H8: =EDATE(H7,3) -> 29677 | I8: =HC!C23*HC!$B$58/HC!$C$58 -> 122.02933 | J8: =W_h23!E14*W!$D$9/W_h23!$E$65 -> 136097.07 | K8: =F8*I8/Pop!G8 -> 85.897764 | L8: =LN(K8)-LN(K7) -> 0.0020291169 | M8: =J8/(I8*F8) -> 0.20006796 | N8: =LN(M8)-LN(M7) -> 0.021765195
A9: =EDATE(A8,1) -> 27576 | B9: =HC!F24 -> 5331 | C9: 5225.3333 | E9: =EDATE(E8,3) -> 29768 | F9: =AVERAGEIFS($C:$C,$A:$A,">="&$E9,$A:$A,"<"&$E10) -> 5587.1806 | H9: =EDATE(H8,3) -> 29768 | I9: =HC!C24*HC!$B$58/HC!$C$58 -> 121.71644 | J9: =W_h23!E15*W!$D$9/W_h23!$E$65 -> 137590.05 | K9: =F9*I9/Pop!G9 -> 85.776518 | L9: =LN(K9)-LN(K8) -> -0.0014125174 | M9: =J9/(I9*F9) -> 0.20232291 | N9: =LN(M9)-LN(M8) -> 0.011207904
A10: =EDATE(A9,1) -> 27607 | B10: =HC!F25 -> 5294 | C10: 5230.5833 | E10: =EDATE(E9,3) -> 29860 | F10: =AVERAGEIFS($C:$C,$A:$A,">="&$E10,$A:$A,"<"&$E11) -> 5601.25 | H10: =EDATE(H9,3) -> 29860 | I10: =HC!C25*HC!$B$58/HC!$C$58 -> 122.377 | J10: =W_h23!E16*W!$D$9/W_h23!$E$65 -> 141624.43 | K10: =F10*I10/Pop!G10 -> 86.322646 | L10: =LN(K10)-LN(K9) -> 0.0063466878 | M10: =J10/(I10*F10) -> 0.206611 | N10: =LN(M10)-LN(M9) -> 0.020972778
A11: =EDATE(A10,1) -> 27638 | B11: =HC!F26 -> 5290 | C11: 5236.375 | E11: =EDATE(E10,3) -> 29952 | F11: =AVERAGEIFS($C:$C,$A:$A,">="&$E11,$A:$A,"<"&$E12) -> 5612.625 | H11: =EDATE(H10,3) -> 29952 | I11: =HC!C26*HC!$B$58/HC!$C$58 -> 121.71644 | J11: =W_h23!E17*W!$D$9/W_h23!$E$65 -> 141317.14 | K11: =F11*I11/Pop!G11 -> 85.853863 | L11: =LN(K11)-LN(K10) -> -0.0054453874 | M11: =J11/(I11*F11) -> 0.20686145 | N11: =LN(M11)-LN(M10) -> 0.0012114778
A12: =EDATE(A11,1) -> 27668 | B12: =HC!F27 -> 5293 | C12: 5242.375 | E12: =EDATE(E11,3) -> 30042 | F12: =AVERAGEIFS($C:$C,$A:$A,">="&$E12,$A:$A,"<"&$E13) -> 5627.4167 | H12: =EDATE(H11,3) -> 30042 | I12: =HC!C27*HC!$B$58/HC!$C$58 -> 121.61214 | J12: =W_h23!E18*W!$D$9/W_h23!$E$65 -> 143887.06 | K12: =F12*I12/Pop!G12 -> 85.794315 | L12: =LN(K12)-LN(K11) -> -0.00069383888 | M12: =J12/(I12*F12) -> 0.21024986 | N12: =LN(M12)-LN(M11) -> 0.0162474
A13: =EDATE(A12,1) -> 27699 | B13: =HC!F28 -> 5245 | C13: 5245.4167 | E13: =EDATE(E12,3) -> 30133 | F13: =AVERAGEIFS($C:$C,$A:$A,">="&$E13,$A:$A,"<"&$E14) -> 5652.0139 | H13: =EDATE(H12,3) -> 30133 | I13: =HC!C28*HC!$B$58/HC!$C$58 -> 121.99457 | J13: =W_h23!E19*W!$D$9/W_h23!$E$65 -> 146074.75 | K13: =F13*I13/Pop!G13 -> 86.206586 | L13: =LN(K13)-LN(K12) -> 0.0047938304 | M13: =J13/(I13*F13) -> 0.21185144 | N13: =LN(M13)-LN(M12) -> 0.0075886223
A14: =EDATE(A13,1) -> 27729 | B14: =HC!F29 -> 5185 | C14: 5246 | E14: =EDATE(E13,3) -> 30225 | F14: =AVERAGEIFS($C:$C,$A:$A,">="&$E14,$A:$A,"<"&$E15) -> 5675.4861 | H14: =EDATE(H13,3) -> 30225 | I14: =HC!C29*HC!$B$58/HC!$C$58 -> 121.61214 | J14: =W_h23!E20*W!$D$9/W_h23!$E$65 -> 148130.29 | K14: =F14*I14/Pop!G14 -> 86.070687 | L14: =LN(K14)-LN(K13) -> -0.0015776729 | M14: =J14/(I14*F14) -> 0.21461688 | N14: =LN(M14)-LN(M13) -> 0.012969195
A15: =EDATE(A14,1) -> 27760 | B15: =HC!F30 -> 5080 | C15: 5247.4583 | E15: =EDATE(E14,3) -> 30317 | F15: =AVERAGEIFS($C:$C,$A:$A,">="&$E15,$A:$A,"<"&$E16) -> 5702.8611 | H15: =EDATE(H14,3) -> 30317 | I15: =HC!C30*HC!$B$58/HC!$C$58 -> 121.50784 | J15: =W_h23!E21*W!$D$9/W_h23!$E$65 -> 150732.14 | K15: =F15*I15/Pop!G15 -> 86.192964 | L15: =LN(K15)-LN(K14) -> 0.0014196428 | M15: =J15/(I15*F15) -> 0.21752479 | N15: =LN(M15)-LN(M14) -> 0.013458372
A16: =EDATE(A15,1) -> 27791 | B16: =HC!F31 -> 5089 | C16: 5250.6667 | E16: =EDATE(E15,3) -> 30407 | F16: =AVERAGEIFS($C:$C,$A:$A,">="&$E16,$A:$A,"<"&$E17) -> 5726.4167 | H16: =EDATE(H15,3) -> 30407 | I16: =HC!C31*HC!$B$58/HC!$C$58 -> 121.71644 | J16: =W_h23!E22*W!$D$9/W_h23!$E$65 -> 151176.28 | K16: =F16*I16/Pop!G16 -> 86.477948 | L16: =LN(K16)-LN(K15) -> 0.0033008926 | M16: =J16/(I16*F16) -> 0.21689597 | N16: =LN(M16)-LN(M15) -> -0.0028950208
A17: =EDATE(A16,1) -> 27820 | B17: =HC!F32 -> 5198 | C17: 5255.0833 | E17: =EDATE(E16,3) -> 30498 | F17: =AVERAGEIFS($C:$C,$A:$A,">="&$E17,$A:$A,"<"&$E18) -> 5732.6806 | H17: =EDATE(H16,3) -> 30498 | I17: =HC!C32*HC!$B$58/HC!$C$58 -> 122.02933 | J17: =W_h23!E23*W!$D$9/W_h23!$E$65 -> 153582.22 | K17: =F17*I17/Pop!G17 -> 86.574149 | L17: =LN(K17)-LN(K16) -> 0.0011118185 | M17: =J17/(I17*F17) -> 0.21954268 | N17: =LN(M17)-LN(M16) -> 0.012128816
A18: =EDATE(A17,1) -> 27851 | B18: =HC!F33 -> 5273 | C18: 5259.4583 | E18: =EDATE(E17,3) -> 30590 | F18: =AVERAGEIFS($C:$C,$A:$A,">="&$E18,$A:$A,"<"&$E19) -> 5738.2778 | H18: =EDATE(H17,3) -> 30590 | I18: =HC!C33*HC!$B$58/HC!$C$58 -> 121.9598 | J18: =W_h23!E24*W!$D$9/W_h23!$E$65 -> 154625.37 | K18: =F18*I18/Pop!G18 -> 86.381094 | L18: =LN(K18)-LN(K17) -> -0.0022324316 | M18: =J18/(I18*F18) -> 0.22094413 | N18: =LN(M18)-LN(M17) -> 0.00636324
A19: =EDATE(A18,1) -> 27881 | B19: =HC!F34 -> 5331 | C19: 5263.6667 | E19: =EDATE(E18,3) -> 30682 | F19: =AVERAGEIFS($C:$C,$A:$A,">="&$E19,$A:$A,"<"&$E20) -> 5745.7639 | H19: =EDATE(H18,3) -> 30682 | I19: =HC!C34*HC!$B$58/HC!$C$58 -> 123.17662 | J19: =W_h23!E25*W!$D$9/W_h23!$E$65 -> 157391.69 | K19: =F19*I19/Pop!G19 -> 87.118988 | L19: =LN(K19)-LN(K18) -> 0.008506038 | M19: =J19/(I19*F19) -> 0.22238514 | N19: =LN(M19)-LN(M18) -> 0.0065008485
A20: =EDATE(A19,1) -> 27912 | B20: =HC!F35 -> 5347 | C20: 5268.1667 | E20: =EDATE(E19,3) -> 30773 | F20: =AVERAGEIFS($C:$C,$A:$A,">="&$E20,$A:$A,"<"&$E21) -> 5759.125 | H20: =EDATE(H19,3) -> 30773 | I20: =HC!C35*HC!$B$58/HC!$C$58 -> 122.82896 | J20: =W_h23!E26*W!$D$9/W_h23!$E$65 -> 160161.64 | K20: =F20*I20/Pop!G20 -> 86.842608 | L20: =LN(K20)-LN(K19) -> -0.0031774886 | M20: =J20/(I20*F20) -> 0.22641294 | N20: =LN(M20)-LN(M19) -> 0.017949779
... A42: =EDATE(A41,1) -> 28581 | B42: =HC!F57 -> 5413 | C42: 5394.3333 | E42: =EDATE(E41,3) -> 32782 | F42: =AVERAGEIFS($C:$C,$A:$A,">="&$E42,$A:$A,"<"&$E43) -> 6178.2361 | H42: =EDATE(H41,3) -> 32782 | I42: =HC!C57*HC!$B$58/HC!$C$58 -> 120.36056 | J42: =W_h23!E48*W!$D$9/W_h23!$E$65 -> 210932.51 | K42: =F42*I42/Pop!G42 -> 86.69926 | L42: =LN(K42)-LN(K41) -> 0.00091030994 | M42: =J42/(I42*F42) -> 0.28365786 | N42: =LN(M42)-LN(M41) -> 0.016301904
A43: =EDATE(A42,1) -> 28611 | B43: =HC!F58 -> 5532 | C43: 5400 | E43: =EDATE(E42,3) -> 32874 | F43: =AVERAGEIFS($C:$C,$A:$A,">="&$E43,$A:$A,"<"&$E44) -> 6204.625 | H43: =EDATE(H42,3) -> 32874 | I43: =HC!B58 -> 119.7 | J43: =W_h23!E49*W!$D$9/W_h23!$E$65 -> 214539.7 | K43: =F43*I43/Pop!G43 -> 86.449355 | L43: =LN(K43)-LN(K42) -> -0.0028866022 | M43: =J43/(I43*F43) -> 0.28886703 | N43: =LN(M43)-LN(M42) -> 0.018197693
A44: =EDATE(A43,1) -> 28642 | B44: =HC!F59 -> 5550 | C44: 5405.2083 | E44: =EDATE(E43,3) -> 32964 | F44: =AVERAGEIFS($C:$C,$A:$A,">="&$E44,$A:$A,"<"&$E45) -> 6235.1389 | H44: =EDATE(H43,3) -> 32964 | I44: =HC!B59 -> 119.3 | J44: =W_h23!E50*W!$D$9/W_h23!$E$65 -> 220339.67 | K44: =F44*I44/Pop!G44 -> 86.454076 | L44: =LN(K44)-LN(K43) -> 5.4607453e-05 | M44: =J44/(I44*F44) -> 0.29621437 | N44: =LN(M44)-LN(M43) -> 0.025116939
A45: =EDATE(A44,1) -> 28672 | B45: =HC!F60 -> 5494 | C45: 5412.0833 | E45: =EDATE(E44,3) -> 33055 | F45: =AVERAGEIFS($C:$C,$A:$A,">="&$E45,$A:$A,"<"&$E46) -> 6265.6944 | H45: =EDATE(H44,3) -> 33055 | I45: =HC!B60 -> 118.56667 | J45: =W_h23!E51*W!$D$9/W_h23!$E$65 -> 222856.01 | K45: =F45*I45/Pop!G45 -> 86.226515 | L45: =LN(K45)-LN(K44) -> -0.002635628 | M45: =J45/(I45*F45) -> 0.29998016 | N45: =LN(M45)-LN(M44) -> 0.012632906
A46: =EDATE(A45,1) -> 28703 | B46: =HC!F61 -> 5454 | C46: 5419.4167 | E46: =EDATE(E45,3) -> 33147 | F46: =AVERAGEIFS($C:$C,$A:$A,">="&$E46,$A:$A,"<"&$E47) -> 6294.9444 | H46: =EDATE(H45,3) -> 33147 | I46: =HC!B61 -> 118.2 | J46: =W_h23!E52*W!$D$9/W_h23!$E$65 -> 230343.01 | K46: =F46*I46/Pop!G46 -> 86.239223 | L46: =LN(K46)-LN(K45) -> 0.00014736657 | M46: =J46/(I46*F46) -> 0.30957484 | N46: =LN(M46)-LN(M45) -> 0.031483554
A47: =EDATE(A46,1) -> 28734 | B47: =HC!F62 -> 5460 | C47: 5424.75 | E47: =EDATE(E46,3) -> 33239 | F47: =AVERAGEIFS($C:$C,$A:$A,">="&$E47,$A:$A,"<"&$E48) -> 6325.6944 | H47: =EDATE(H46,3) -> 33239 | I47: =HC!B62 -> 117.03333 | J47: =W_h23!E53*W!$D$9/W_h23!$E$65 -> 233279.59 | K47: =F47*I47/Pop!G47 -> 85.689534 | L47: =LN(K47)-LN(K46) -> -0.0063944059 | M47: =J47/(I47*F47) -> 0.31510765 | N47: =LN(M47)-LN(M46) -> 0.017714452
A48: =EDATE(A47,1) -> 28764 | B48: =HC!F63 -> 5474 | C48: 5429.9583 | E48: =EDATE(E47,3) -> 33329 | F48: =AVERAGEIFS($C:$C,$A:$A,">="&$E48,$A:$A,"<"&$E49) -> 6353.8472 | H48: =EDATE(H47,3) -> 33329 | I48: =HC!B63 -> 116.43333 | J48: =W_h23!E54*W!$D$9/W_h23!$E$65 -> 238536.58 | K48: =F48*I48/Pop!G48 -> 85.525829 | L48: =LN(K48)-LN(K47) -> -0.0019122629 | M48: =J48/(I48*F48) -> 0.32243405 | N48: =LN(M48)-LN(M47) -> 0.022984268
A49: =EDATE(A48,1) -> 28795 | B49: =HC!F64 -> 5442 | C49: 5434.875 | E49: =EDATE(E48,3) -> 33420 | F49: =AVERAGEIFS($C:$C,$A:$A,">="&$E49,$A:$A,"<"&$E50) -> 6381.9722 | H49: =EDATE(H48,3) -> 33420 | I49: =HC!B64 -> 115.83333 | J49: =W_h23!E55*W!$D$9/W_h23!$E$65 -> 242172.48 | K49: =F49*I49/Pop!G49 -> 85.380979 | L49: =LN(K49)-LN(K48) -> -0.0016950832 | M49: =J49/(I49*F49) -> 0.32759429 | N49: =LN(M49)-LN(M48) -> 0.015877304
A50: =EDATE(A49,1) -> 28825 | B50: =HC!F65 -> 5375 | C50: 5438.9167 | E50: =EDATE(E49,3) -> 33512 | F50: =AVERAGEIFS($C:$C,$A:$A,">="&$E50,$A:$A,"<"&$E51) -> 6402.9167 | H50: =EDATE(H49,3) -> 33512 | I50: =HC!B65 -> 115.76667 | J50: =W_h23!E56*W!$D$9/W_h23!$E$65 -> 246179.83 | K50: =F50*I50/Pop!G50 -> 85.579209 | L50: =LN(K50)-LN(K49) -> 0.0023190245 | M50: =J50/(I50*F50) -> 0.33211698 | N50: =LN(M50)-LN(M49) -> 0.013711349
A51: =EDATE(A50,1) -> 28856 | B51: =HC!F66 -> 5294 | C51: 5444.5 | E51: =EDATE(E50,3) -> 33604 | F51: =AVERAGEIFS($C:$C,$A:$A,">="&$E51,$A:$A,"<"&$E52) -> 6414.5972 | H51: =EDATE(H50,3) -> 33604 | I51: =HC!B66 -> 114.86667 | J51: =W_h23!E57*W!$D$9/W_h23!$E$65 -> 245945.51 | K51: =F51*I51/Pop!G51 -> 85.035937 | L51: =LN(K51)-LN(K50) -> -0.0063684158 | M51: =J51/(I51*F51) -> 0.33379167 | N51: =LN(M51)-LN(M50) -> 0.0050297859
A52: =EDATE(A51,1) -> 28887 | B52: =HC!F67 -> 5284 | C52: 5452.25 | E52: =EDATE(E51,3) -> 33695 | F52: =AVERAGEIFS($C:$C,$A:$A,">="&$E52,$A:$A,"<"&$E53) -> 6428.8889 | H52: =EDATE(H51,3) -> 33695 | I52: =HC!B67 -> 114.23333 | J52: =W_h23!E58*W!$D$9/W_h23!$E$65 -> 246946.83 | K52: =F52*I52/Pop!G52 -> 84.722359 | L52: =LN(K52)-LN(K51) -> -0.0036944135 | M52: =J52/(I52*F52) -> 0.3362596 | N52: =LN(M52)-LN(M51) -> 0.0073664378
A53: =EDATE(A52,1) -> 28915 | B53: =HC!F68 -> 5353 | C53: 5459.4583 | E53: =EDATE(E52,3) -> 33786 | F53: =AVERAGEIFS($C:$C,$A:$A,">="&$E53,$A:$A,"<"&$E54) -> 6437.4167 | H53: =EDATE(H52,3) -> 33786 | I53: =HC!B68 -> 112.8 | J53: =W_h23!E59*W!$D$9/W_h23!$E$65 -> 249186.34 | K53: =F53*I53/Pop!G53 -> 83.729902 | L53: =LN(K53)-LN(K52) -> -0.011783371 | M53: =J53/(I53*F53) -> 0.34316542 | N53: =LN(M53)-LN(M52) -> 0.020329113
A54: =EDATE(A53,1) -> 28946 | B54: =HC!F69 -> 5482 | C54: 5465.75 | E54: =EDATE(E53,3) -> 33878 | F54: =AVERAGEIFS($C:$C,$A:$A,">="&$E54,$A:$A,"<"&$E55) -> 6440.2222 | H54: =EDATE(H53,3) -> 33878 | I54: =HC!B69 -> 112.8 | J54: =W_h23!E60*W!$D$9/W_h23!$E$65 -> 251141.77 | K54: =F54*I54/Pop!G54 -> 83.697764 | L54: =LN(K54)-LN(K53) -> -0.00038390766 | M54: =J54/(I54*F54) -> 0.34570766 | N54: =LN(M54)-LN(M53) -> 0.0073809078
... A58: =EDATE(A57,1) -> 29068 | B58: =HC!F73 -> 5554 | C58: 5484.875 | E58: =EDATE(E57,3) -> 34243 | F58: =AVERAGEIFS($C:$C,$A:$A,">="&$E58,$A:$A,"<"&$E59) -> 6457.4583 | H58: =EDATE(H57,3) -> 34243 | I58: =HC!B73 -> 110 | J58: =W_h23!E64*W!$D$9/W_h23!$E$65 -> 255808.18 | K58: =F58*I58/Pop!G58 -> 81.694019 | L58: =LN(K58)-LN(K57) -> -0.006060737 | M58: =J58/(I58*F58) -> 0.36013069 | N58: =LN(M58)-LN(M57) -> 0.0017239127
A59: =EDATE(A58,1) -> 29099 | B59: =HC!F74 -> 5533 | C59: 5490.1667 | E59: =EDATE(E58,3) -> 34335 | F59: =AVERAGEIFS($C:$C,$A:$A,">="&$E59,$A:$A,"<"&$E60) -> 6459.5139 | H59: =EDATE(H58,3) -> 34335 | I59: =HC!B74 -> 110.53333 | J59: =W!D9 -> 257725.8 | K59: =F59*I59/Pop!G59 -> 82.106799 | L59: =LN(K59)-LN(K58) -> 0.0050400374 | M59: =J59/(I59*F59) -> 0.36096475 | N59: =LN(M59)-LN(M58) -> 0.0023133176
A60: =EDATE(A59,1) -> 29129 | B60: =HC!F75 -> 5552 | C60: 5496.2917 | E60: =EDATE(E59,3) -> 34425 | F60: =AVERAGEIFS($C:$C,$A:$A,">="&$E60,$A:$A,"<"&$E61) -> 6455.8611 | H60: =EDATE(H59,3) -> 34425 | I60: =HC!B75 -> 109.43333 | J60: =W!D10 -> 263991.3 | K60: =F60*I60/Pop!G60 -> 81.237107 | L60: =LN(K60)-LN(K59) -> -0.0106487 | M60: =J60/(I60*F60) -> 0.37366791 | N60: =LN(M60)-LN(M59) -> 0.034587166
A61: =EDATE(A60,1) -> 29160 | B61: =HC!F76 -> 5509 | C61: 5500.625 | E61: =EDATE(E60,3) -> 34516 | F61: =AVERAGEIFS($C:$C,$A:$A,">="&$E61,$A:$A,"<"&$E62) -> 6453.625 | H61: =EDATE(H60,3) -> 34516 | I61: =HC!B76 -> 110.3 | J61: =W!D11 -> 259822.7 | K61: =F61*I61/Pop!G61 -> 81.844137 | L61: =LN(K61)-LN(K60) -> 0.007444546 | M61: =J61/(I61*F61) -> 0.36500419 | N61: =LN(M61)-LN(M60) -> -0.023458634
A62: =EDATE(A61,1) -> 29190 | B62: =HC!F77 -> 5432 | C62: 5504.3333 | E62: =EDATE(E61,3) -> 34608 | F62: =AVERAGEIFS($C:$C,$A:$A,">="&$E62,$A:$A,"<"&$E63) -> 6452.5972 | H62: =EDATE(H61,3) -> 34608 | I62: =HC!B77 -> 110.16667 | J62: =W!D12 -> 263912.3 | K62: =F62*I62/Pop!G62 -> 81.723701 | L62: =LN(K62)-LN(K61) -> -0.0014726169 | M62: =J62/(I62*F62) -> 0.37125718 | N62: =LN(M62)-LN(M61) -> 0.0169862
A63: =EDATE(A62,1) -> 29221 | B63: =HC!F78 -> 5333 | C63: 5509.375 | E63: =EDATE(E62,3) -> 34700 | F63: =AVERAGEIFS($C:$C,$A:$A,">="&$E63,$A:$A,"<"&$E64) -> 6454.0972 | H63: =EDATE(H62,3) -> 34700 | I63: =HC!B78 -> 110.33333 | J63: =W!D13 -> 263228.9 | K63: =F63*I63/Pop!G63 -> 81.864795 | L63: =LN(K63)-LN(K62) -> 0.0017249931 | M63: =J63/(I63*F63) -> 0.36965052 | N63: =LN(M63)-LN(M62) -> -0.0043370087
A64: =EDATE(A63,1) -> 29252 | B64: =HC!F79 -> 5339 | C64: 5514.2083 | E64: =EDATE(E63,3) -> 34790 | F64: =AVERAGEIFS($C:$C,$A:$A,">="&$E64,$A:$A,"<"&$E65) -> 6457.9167 | H64: =EDATE(H63,3) -> 34790 | I64: =HC!B79 -> 109.86667 | J64: =W!D14 -> 264515.6 | K64: =F64*I64/Pop!G64 -> 81.575768 | L64: =LN(K64)-LN(K63) -> -0.0035367882 | M64: =J64/(I64*F64) -> 0.37281459 | N64: =LN(M64)-LN(M63) -> 0.0085231993
A65: =EDATE(A64,1) -> 29281 | B65: =HC!F80 -> 5425 | C65: 5520.1667 | E65: =EDATE(E64,3) -> 34881 | F65: =AVERAGEIFS($C:$C,$A:$A,">="&$E65,$A:$A,"<"&$E66) -> 6455.9722 | H65: =EDATE(H64,3) -> 34881 | I65: =HC!B80 -> 110.26667 | J65: =W!D15 -> 266548.4 | K65: =F65*I65/Pop!G65 -> 81.863934 | L65: =LN(K65)-LN(K64) -> 0.0035262653 | M65: =J65/(I65*F65) -> 0.37442961 | N65: =LN(M65)-LN(M64) -> 0.0043225868
A66: =EDATE(A65,1) -> 29312 | B66: =HC!F81 -> 5557 | C66: 5525.9583 | E66: =EDATE(E65,3) -> 34973 | F66: =AVERAGEIFS($C:$C,$A:$A,">="&$E66,$A:$A,"<"&$E67) -> 6458.4722 | H66: =EDATE(H65,3) -> 34973 | I66: =HC!B81 -> 110.6 | J66: =W!D16 -> 269186.2 | K66: =F66*I66/Pop!G66 -> 82.170239 | L66: =LN(K66)-LN(K65) -> 0.0037346515 | M66: =J66/(I66*F66) -> 0.37684944 | N66: =LN(M66)-LN(M65) -> 0.0064419148
A67: =EDATE(A66,1) -> 29342 | B67: =HC!F82 -> 5610 | C67: 5529.9167 | E67: =EDATE(E66,3) -> 35065 | F67: =AVERAGEIFS($C:$C,$A:$A,">="&$E67,$A:$A,"<"&$E68) -> 6466.9028 | H67: =EDATE(H66,3) -> 35065 | I67: =HC!B82 -> 110.7 | J67: =W!D17 -> 267655.8 | K67: =F67*I67/Pop!G67 -> 82.380848 | L67: =LN(K67)-LN(K66) -> 0.002559805 | M67: =J67/(I67*F67) -> 0.37388041 | N67: =LN(M67)-LN(M66) -> -0.0079097544
A68: =EDATE(A67,1) -> 29373 | B68: =HC!F83 -> 5658 | C68: 5533.875 | E68: =EDATE(E67,3) -> 35156 | F68: =AVERAGEIFS($C:$C,$A:$A,">="&$E68,$A:$A,"<"&$E69) -> 6478.9306 | H68: =EDATE(H67,3) -> 35156 | I68: =HC!B83 -> 110.3 | J68: =W!D18 -> 269167.3 | K68: =F68*I68/Pop!G68 -> 82.25806 | L68: =LN(K68)-LN(K67) -> -0.0014915993 | M68: =J68/(I68*F68) -> 0.37665476 | N68: =LN(M68)-LN(M67) -> 0.0073930359
A69: =EDATE(A68,1) -> 29403 | B69: =HC!F84 -> 5641 | C69: 5539.125 | E69: =EDATE(E68,3) -> 35247 | F69: =AVERAGEIFS($C:$C,$A:$A,">="&$E69,$A:$A,"<"&$E70) -> 6498.9861 | H69: =EDATE(H68,3) -> 35247 | I69: =HC!B84 -> 109.9 | J69: =W!D19 -> 272168.5 | K69: =F69*I69/Pop!G69 -> 82.209518 | L69: =LN(K69)-LN(K68) -> -0.00059030191 | M69: =J69/(I69*F69) -> 0.38106105 | N69: =LN(M69)-LN(M68) -> 0.011630582
A70: =EDATE(A69,1) -> 29434 | B70: =HC!F85 -> 5609 | C70: 5544.7083 | E70: =EDATE(E69,3) -> 35339 | F70: =AVERAGEIFS($C:$C,$A:$A,">="&$E70,$A:$A,"<"&$E71) -> 6522.5694 | H70: =EDATE(H69,3) -> 35339 | I70: =HC!B85 -> 110.53333 | J70: =W!D20 -> 273459.6 | K70: =F70*I70/Pop!G70 -> 82.950693 | L70: =LN(K70)-LN(K69) -> 0.0089752921 | M70: =J70/(I70*F70) -> 0.37929856 | N70: =LN(M70)-LN(M69) -> -0.0046359399
... A166: =EDATE(A165,1) -> 32356 | B166: =HC!F181 -> 6073 | C166: 6021.75 | E166: =EDATE(E165,3) -> 44105 | F166: =AVERAGEIFS($C:$C,$A:$A,">="&$E166,$A:$A,"<"&$E167) -> 6667.1944 | H166: =EDATE(H165,3) -> 44105 | I166: =HC!B181 -> 94.4 | J166: =W!D116 -> 281736.8 | K166: =F166*I166/Pop!G166 -> 84.517043 | L166: =LN(K166)-LN(K165) -> 0.012399969 | M166: =J166/(I166*F166) -> 0.44763956 | N166: =LN(M166)-LN(M165) -> -0.0068111193
A167: =EDATE(A166,1) -> 32387 | B167: =HC!F182 -> 6064 | C167: 6031.125 | E167: =EDATE(E166,3) -> 44197 | H167: =EDATE(H166,3) -> 44197 | I167: =HC!B182 -> 94.166667 | J167: =W!D117 -> 289005.9 | K167: =F167*I167/Pop!G167 -> #DIV/0! | L167: =LN(K167)-LN(K166) -> #DIV/0! | M167: =J167/(I167*F167) -> #DIV/0! | N167: =LN(M167)-LN(M166) -> #DIV/0!
A168: =EDATE(A167,1) -> 32417 | B168: =HC!F183 -> 6065 | C168: 6039.75 | H168: =EDATE(H167,3) -> 44287 | I168: =HC!B183 -> 94.9 | J168: =W!D118 -> 284184.6 | K168: =F168*I168/Pop!G168 -> #DIV/0! | L168: =LN(K168)-LN(K167) -> #DIV/0! | M168: =J168/(I168*F168) -> #DIV/0! | N168: =LN(M168)-LN(M167) -> #DIV/0!
A169: =EDATE(A168,1) -> 32448 | B169: =HC!F184 -> 6049 | C169: 6048
A170: =EDATE(A169,1) -> 32478 | B170: =HC!F185 -> 6002 | C170: 6057.7917
A171: =EDATE(A170,1) -> 32509 | B171: =HC!F186 -> 5905 | C171: 6068.9583
A172: =EDATE(A171,1) -> 32540 | B172: =HC!F187 -> 5917 | C172: 6079.5833
A173: =EDATE(A172,1) -> 32568 | B173: =HC!F188 -> 5999 | C173: 6089.7083
A174: =EDATE(A173,1) -> 32599 | B174: =HC!F189 -> 6134 | C174: 6100.2083
A175: =EDATE(A174,1) -> 32629 | B175: =HC!F190 -> 6208 | C175: 6111
A176: =EDATE(A175,1) -> 32660 | B176: =HC!F191 -> 6239 | C176: 6122.2083
A177: =EDATE(A176,1) -> 32690 | B177: =HC!F192 -> 6240 | C177: 6133.4583
A178: =EDATE(A177,1) -> 32721 | B178: =HC!F193 -> 6193 | C178: 6144.5
A179: =EDATE(A178,1) -> 32752 | B179: =HC!F194 -> 6187 | C179: 6156.4583
A180: =EDATE(A179,1) -> 32782 | B180: =HC!F195 -> 6194 | C180: 6167.9583
... A555: =EDATE(A554,1) -> 44197 | B555: =HC!F570 -> 6637 | C555: 6671.9167
A556: =EDATE(A555,1) -> 44228 | B556: =HC!F571 -> 6646
A557: =EDATE(A556,1) -> 44256 | B557: =HC!F572 -> 6649
A558: =EDATE(A557,1) -> 44287 | B558: =HC!F573 -> 6657
A559: =EDATE(A558,1) -> 44317 | B559: =HC!F574 -> 6667
A560: =EDATE(A559,1) -> 44348 | B560: =HC!F575 -> 6692
A561: =EDATE(A560,1) -> 44378 | B561: =HC!F576 -> 6711

Sheet l_NSR
B1: O/N Mutan
B2: % p.a. | C2: % quarterly
A3: 29281 | B3: =NSR!B18*NSR!$C$40/NSR!$B$40 -> 9.3708924 | C3: =(1+B3/100)^(1/4)-1 -> 0.022646271 | E3: ＜算出方法＞
A4: =EDATE(A3,3) -> 29373 | B4: =NSR!B19*NSR!$C$40/NSR!$B$40 -> 12.737158 | C4: =(1+B4/100)^(1/4)-1 -> 0.030425911 | E4: ・O/N無担コール
A5: =EDATE(A4,3) -> 29465 | B5: =NSR!B20*NSR!$C$40/NSR!$B$40 -> 12.320643 | C5: =(1+B5/100)^(1/4)-1 -> 0.029472845
A6: =EDATE(A5,3) -> 29556 | B6: =NSR!B21*NSR!$C$40/NSR!$B$40 -> 10.221216 | C6: =(1+B6/100)^(1/4)-1 -> 0.024628189
A7: =EDATE(A6,3) -> 29646 | B7: =NSR!B22*NSR!$C$40/NSR!$B$40 -> 8.6965703 | C7: =(1+B7/100)^(1/4)-1 -> 0.021066341
A8: =EDATE(A7,3) -> 29738 | B8: =NSR!B23*NSR!$C$40/NSR!$B$40 -> 7.2716017 | C8: =(1+B8/100)^(1/4)-1 -> 0.01770332
A9: =EDATE(A8,3) -> 29830 | B9: =NSR!B24*NSR!$C$40/NSR!$B$40 -> 7.4052542 | C9: =(1+B9/100)^(1/4)-1 -> 0.018020168
A10: =EDATE(A9,3) -> 29921 | B10: =NSR!B25*NSR!$C$40/NSR!$B$40 -> 6.9960924 | C10: =(1+B10/100)^(1/4)-1 -> 0.017049239
A11: =EDATE(A10,3) -> 30011 | B11: =NSR!B26*NSR!$C$40/NSR!$B$40 -> 6.749928 | C11: =(1+B11/100)^(1/4)-1 -> 0.016463756
A12: =EDATE(A11,3) -> 30103 | B12: =NSR!B27*NSR!$C$40/NSR!$B$40 -> 7.3249129 | C12: =(1+B12/100)^(1/4)-1 -> 0.01782974
A13: =EDATE(A12,3) -> 30195 | B13: =NSR!B28*NSR!$C$40/NSR!$B$40 -> 7.2698315 | C13: =(1+B13/100)^(1/4)-1 -> 0.017699121
A14: =EDATE(A13,3) -> 30286 | B14: =NSR!B29*NSR!$C$40/NSR!$B$40 -> 6.9868667 | C14: =(1+B14/100)^(1/4)-1 -> 0.017027315
A15: =EDATE(A14,3) -> 30376 | B15: =NSR!B30*NSR!$C$40/NSR!$B$40 -> 6.7769241 | C15: =(1+B15/100)^(1/4)-1 -> 0.016528014
A16: =EDATE(A15,3) -> 30468 | B16: =NSR!B31*NSR!$C$40/NSR!$B$40 -> 6.3227234 | C16: =(1+B16/100)^(1/4)-1 -> 0.015445275
... A24: =EDATE(A23,3) -> 31199 | B24: =NSR!B39*NSR!$C$40/NSR!$B$40 -> 6.1977519 | C24: =(1+B24/100)^(1/4)-1 -> 0.015146755
A25: =EDATE(A24,3) -> 31291 | B25: =NSR!C40 -> 6.3871667 | C25: =(1+B25/100)^(1/4)-1 -> 0.015599108
A26: =EDATE(A25,3) -> 31382 | B26: =NSR!C41 -> 7.4403333 | C26: =(1+B26/100)^(1/4)-1 -> 0.01810328
A27: =EDATE(A26,3) -> 31472 | B27: =NSR!C42 -> 6.2754333 | C27: =(1+B27/100)^(1/4)-1 -> 0.015332344
A28: =EDATE(A27,3) -> 31564 | B28: =NSR!C43 -> 4.6293 | C28: =(1+B28/100)^(1/4)-1 -> 0.011377598
A29: =EDATE(A28,3) -> 31656 | B29: =NSR!C44 -> 4.6884667 | C29: =(1+B29/100)^(1/4)-1 -> 0.011520549
A30: =EDATE(A29,3) -> 31747 | B30: =NSR!C45 -> 4.2521 | C30: =(1+B30/100)^(1/4)-1 -> 0.010464832
A31: =EDATE(A30,3) -> 31837 | B31: =NSR!C46 -> 4.1998 | C31: =(1+B31/100)^(1/4)-1 -> 0.010338078
A32: =EDATE(A31,3) -> 31929 | B32: =NSR!C47 -> 3.4391667 | C32: =(1+B32/100)^(1/4)-1 -> 0.0084892037
A33: =EDATE(A32,3) -> 32021 | B33: =NSR!C48 -> 3.3747667 | C33: =(1+B33/100)^(1/4)-1 -> 0.0083321987
A34: =EDATE(A33,3) -> 32112 | B34: =NSR!C49 -> 3.6614333 | C34: =(1+B34/100)^(1/4)-1 -> 0.0090305198
A35: =EDATE(A34,3) -> 32203 | B35: =NSR!C50 -> 3.686 | C35: =(1+B35/100)^(1/4)-1 -> 0.0090902969
A36: =EDATE(A35,3) -> 32295 | B36: =NSR!C51 -> 3.5175667 | C36: =(1+B36/100)^(1/4)-1 -> 0.0086802413
... A168: =EDATE(A167,3) -> 44348 | B168: =NSR!C183 -> -0.019333333 | C168: =(1+B168/100)^(1/4)-1 -> -4.8336838e-05

Sheet l_NB,NEC
B1: FoF (100mn) | D1: TSE (mn) | K1: Equity (bn) | M1: Equity per capita | O1: Equity per capita (real) | Q1: QoQ
B2: Bank | C2: All | D2: Bank | E2: Sec. | F2: Ins. | G2: Others | H2: Bank (adj,) | I2: All | J2: All (excl. Finance) | K2: Bank | L2: All (excl. Finance) | M2: Bank | N2: All (excl. Finance) | O2: Bank | P2: All (excl. Bank) | Q2: Bank | R2: All (excl. Bank)
A3: 29221 | B3: =B4*FoF!J18/FoF!J19 -> 6829.3636 | C3: =C4*FoF!K18/FoF!K19 -> 163819.93 | D3: =AVERAGEIFS(TSE!BF:BF,TSE!$B:$B,">="&'l_NB,NEC'!$A3,TSE!$B:$B,"<"&'l_NB,NEC'!$A4) -> 13640606 | E3: =AVERAGEIFS(TSE!BH:BH,TSE!$B:$B,">="&'l_NB,NEC'!$A3,TSE!$B:$B,"<"&'l_NB,NEC'!$A4) -> #DIV/0! | F3: =AVERAGEIFS(TSE!BJ:BJ,TSE!$B:$B,">="&'l_NB,NEC'!$A3,TSE!$B:$B,"<"&'l_NB,NEC'!$A4) -> #DIV/0! | G3: =AVERAGEIFS(TSE!BL:BL,TSE!$B:$B,">="&'l_NB,NEC'!$A3,TSE!$B:$B,"<"&'l_NB,NEC'!$A4) -> #DIV/0! | H3: =D3*$D$57/SUM($D$57:$G$57) -> 11238364 | I3: =AVERAGEIFS(TSE!BR:BR,TSE!$B:$B,">="&'l_NB,NEC'!$A3,TSE!$B:$B,"<"&'l_NB,NEC'!$A4) -> 66680802 | J3: =I3-D3 -> 53040196 | K3: =H3*$K$67/$H$67 -> 4295.3667 | L3: =J3*$L$63/$J$63 -> 57987.696 | M3: =K3/Pop!$G3 -> 0.54761163 | N3: =L3/Pop!$G3 -> 7.3927882 | O3: =M3/l_pi_c!$G$3*100 -> 0.60321135 | P3: =N3/l_pi_c!$G$3*100 -> 8.1433876 | T3: ＜算出方法＞
A4: =EDATE(A3,3) -> 29312 | B4: =B5*FoF!J19/FoF!J20 -> 6841.6019 | C4: =C5*FoF!K19/FoF!K20 -> 165457.5 | D4: =AVERAGEIFS(TSE!BF:BF,TSE!$B:$B,">="&'l_NB,NEC'!$A4,TSE!$B:$B,"<"&'l_NB,NEC'!$A5) -> 13731339 | E4: =AVERAGEIFS(TSE!BH:BH,TSE!$B:$B,">="&'l_NB,NEC'!$A4,TSE!$B:$B,"<"&'l_NB,NEC'!$A5) -> #DIV/0! | F4: =AVERAGEIFS(TSE!BJ:BJ,TSE!$B:$B,">="&'l_NB,NEC'!$A4,TSE!$B:$B,"<"&'l_NB,NEC'!$A5) -> #DIV/0! | G4: =AVERAGEIFS(TSE!BL:BL,TSE!$B:$B,">="&'l_NB,NEC'!$A4,TSE!$B:$B,"<"&'l_NB,NEC'!$A5) -> #DIV/0! | H4: =D4*$D$57/SUM($D$57:$G$57) -> 11313119 | I4: =AVERAGEIFS(TSE!BR:BR,TSE!$B:$B,">="&'l_NB,NEC'!$A4,TSE!$B:$B,"<"&'l_NB,NEC'!$A5) -> 67887813 | J4: =I4-D4 -> 54156474 | K4: =H4*$K$67/$H$67 -> 4323.9383 | L4: =J4*$L$63/$J$63 -> 59208.099 | M4: =K4/Pop!$G4 -> 0.5499124 | N4: =L4/Pop!$G4 -> 7.5300028 | O4: =M4/l_pi_c!$G$3*100 -> 0.60574572 | P4: =N4/l_pi_c!$G$3*100 -> 8.2945338 | Q4: =LN(O4)-LN(O3) -> 0.0041926592 | R4: =LN(P4)-LN(P3) -> 0.018390464 | T4: ・基本はFoF（08SNAを、93SNA・68SNAを用いて接続）
A5: =EDATE(A4,3) -> 29403 | B5: =B6*FoF!J20/FoF!J21 -> 6920.0037 | C5: =C6*FoF!K20/FoF!K21 -> 167399.65 | D5: =AVERAGEIFS(TSE!BF:BF,TSE!$B:$B,">="&'l_NB,NEC'!$A5,TSE!$B:$B,"<"&'l_NB,NEC'!$A6) -> 13988228 | E5: =AVERAGEIFS(TSE!BH:BH,TSE!$B:$B,">="&'l_NB,NEC'!$A5,TSE!$B:$B,"<"&'l_NB,NEC'!$A6) -> #DIV/0! | F5: =AVERAGEIFS(TSE!BJ:BJ,TSE!$B:$B,">="&'l_NB,NEC'!$A5,TSE!$B:$B,"<"&'l_NB,NEC'!$A6) -> #DIV/0! | G5: =AVERAGEIFS(TSE!BL:BL,TSE!$B:$B,">="&'l_NB,NEC'!$A5,TSE!$B:$B,"<"&'l_NB,NEC'!$A6) -> #DIV/0! | H5: =D5*$D$57/SUM($D$57:$G$57) -> 11524767 | I5: =AVERAGEIFS(TSE!BR:BR,TSE!$B:$B,">="&'l_NB,NEC'!$A5,TSE!$B:$B,"<"&'l_NB,NEC'!$A6) -> 69860737 | J5: =I5-D5 -> 55872509 | K5: =H5*$K$67/$H$67 -> 4404.8314 | L5: =J5*$L$63/$J$63 -> 61084.203 | M5: =K5/Pop!$G5 -> 0.55887646 | N5: =L5/Pop!$G5 -> 7.7502451 | O5: =M5/l_pi_c!$G$3*100 -> 0.61561991 | P5: =N5/l_pi_c!$G$3*100 -> 8.5371376 | Q5: =LN(O5)-LN(O4) -> 0.016169455 | R5: =LN(P5)-LN(P4) -> 0.028829053 | T5: ・もっとも、FoFが1994年頃以前は簿価になっているため、TSEの業種別時価総額を使って接続
A6: =EDATE(A5,3) -> 29495 | B6: =B7*FoF!J21/FoF!J22 -> 7033.5905 | C6: =C7*FoF!K21/FoF!K22 -> 169698.42 | D6: =AVERAGEIFS(TSE!BF:BF,TSE!$B:$B,">="&'l_NB,NEC'!$A6,TSE!$B:$B,"<"&'l_NB,NEC'!$A7) -> 14219911 | E6: =AVERAGEIFS(TSE!BH:BH,TSE!$B:$B,">="&'l_NB,NEC'!$A6,TSE!$B:$B,"<"&'l_NB,NEC'!$A7) -> #DIV/0! | F6: =AVERAGEIFS(TSE!BJ:BJ,TSE!$B:$B,">="&'l_NB,NEC'!$A6,TSE!$B:$B,"<"&'l_NB,NEC'!$A7) -> #DIV/0! | G6: =AVERAGEIFS(TSE!BL:BL,TSE!$B:$B,">="&'l_NB,NEC'!$A6,TSE!$B:$B,"<"&'l_NB,NEC'!$A7) -> #DIV/0! | H6: =D6*$D$57/SUM($D$57:$G$57) -> 11715648 | I6: =AVERAGEIFS(TSE!BR:BR,TSE!$B:$B,">="&'l_NB,NEC'!$A6,TSE!$B:$B,"<"&'l_NB,NEC'!$A7) -> 72960977 | J6: =I6-D6 -> 58741067 | K6: =H6*$K$67/$H$67 -> 4477.7872 | L6: =J6*$L$63/$J$63 -> 64220.334 | M6: =K6/Pop!$G6 -> 0.56699492 | N6: =L6/Pop!$G6 -> 8.1318297 | O6: =M6/l_pi_c!$G$3*100 -> 0.62456265 | P6: =N6/l_pi_c!$G$3*100 -> 8.957465 | Q6: =LN(O6)-LN(O5) -> 0.014421895 | R6: =LN(P6)-LN(P5) -> 0.04806148 | T6: ・算出された自己資本を人口で除し、GDPデフレーターで実質化
A7: =EDATE(A6,3) -> 29587 | B7: =B8*FoF!J22/FoF!J23 -> 7098.6066 | C7: =C8*FoF!K22/FoF!K23 -> 171554.79 | D7: =AVERAGEIFS(TSE!BF:BF,TSE!$B:$B,">="&'l_NB,NEC'!$A7,TSE!$B:$B,"<"&'l_NB,NEC'!$A8) -> 15143537 | E7: =AVERAGEIFS(TSE!BH:BH,TSE!$B:$B,">="&'l_NB,NEC'!$A7,TSE!$B:$B,"<"&'l_NB,NEC'!$A8) -> #DIV/0! | F7: =AVERAGEIFS(TSE!BJ:BJ,TSE!$B:$B,">="&'l_NB,NEC'!$A7,TSE!$B:$B,"<"&'l_NB,NEC'!$A8) -> #DIV/0! | G7: =AVERAGEIFS(TSE!BL:BL,TSE!$B:$B,">="&'l_NB,NEC'!$A7,TSE!$B:$B,"<"&'l_NB,NEC'!$A8) -> #DIV/0! | H7: =D7*$D$57/SUM($D$57:$G$57) -> 12476615 | I7: =AVERAGEIFS(TSE!BR:BR,TSE!$B:$B,">="&'l_NB,NEC'!$A7,TSE!$B:$B,"<"&'l_NB,NEC'!$A8) -> 76830762 | J7: =I7-D7 -> 61687225 | K7: =H7*$K$67/$H$67 -> 4768.6331 | L7: =J7*$L$63/$J$63 -> 67441.305 | M7: =K7/Pop!$G7 -> 0.60286239 | N7: =L7/Pop!$G7 -> 8.5260966 | O7: =M7/l_pi_c!$G$3*100 -> 0.66407179 | P7: =N7/l_pi_c!$G$3*100 -> 9.3917623 | Q7: =LN(O7)-LN(O6) -> 0.061338615 | R7: =LN(P7)-LN(P6) -> 0.047345692
A8: =EDATE(A7,3) -> 29677 | B8: =B9*FoF!J23/FoF!J24 -> 7173.1839 | C8: =C9*FoF!K23/FoF!K24 -> 173610.67 | D8: =AVERAGEIFS(TSE!BF:BF,TSE!$B:$B,">="&'l_NB,NEC'!$A8,TSE!$B:$B,"<"&'l_NB,NEC'!$A9) -> 16344555 | E8: =AVERAGEIFS(TSE!BH:BH,TSE!$B:$B,">="&'l_NB,NEC'!$A8,TSE!$B:$B,"<"&'l_NB,NEC'!$A9) -> #DIV/0! | F8: =AVERAGEIFS(TSE!BJ:BJ,TSE!$B:$B,">="&'l_NB,NEC'!$A8,TSE!$B:$B,"<"&'l_NB,NEC'!$A9) -> #DIV/0! | G8: =AVERAGEIFS(TSE!BL:BL,TSE!$B:$B,">="&'l_NB,NEC'!$A8,TSE!$B:$B,"<"&'l_NB,NEC'!$A9) -> #DIV/0! | H8: =D8*$D$57/SUM($D$57:$G$57) -> 13466122 | I8: =AVERAGEIFS(TSE!BR:BR,TSE!$B:$B,">="&'l_NB,NEC'!$A8,TSE!$B:$B,"<"&'l_NB,NEC'!$A9) -> 85498029 | J8: =I8-D8 -> 69153474 | K8: =H8*$K$67/$H$67 -> 5146.8284 | L8: =J8*$L$63/$J$63 -> 75603.994 | M8: =K8/Pop!$G8 -> 0.64990563 | N8: =L8/Pop!$G8 -> 9.5467457 | O8: =M8/l_pi_c!$G$3*100 -> 0.7158914 | P8: =N8/l_pi_c!$G$3*100 -> 10.516039 | Q8: =LN(O8)-LN(O7) -> 0.075138219 | R8: =LN(P8)-LN(P7) -> 0.11306869
A9: =EDATE(A8,3) -> 29768 | B9: =B10*FoF!J24/FoF!J25 -> 7668.0708 | C9: =C10*FoF!K24/FoF!K25 -> 175425.59 | D9: =AVERAGEIFS(TSE!BF:BF,TSE!$B:$B,">="&'l_NB,NEC'!$A9,TSE!$B:$B,"<"&'l_NB,NEC'!$A10) -> 16916333 | E9: =AVERAGEIFS(TSE!BH:BH,TSE!$B:$B,">="&'l_NB,NEC'!$A9,TSE!$B:$B,"<"&'l_NB,NEC'!$A10) -> #DIV/0! | F9: =AVERAGEIFS(TSE!BJ:BJ,TSE!$B:$B,">="&'l_NB,NEC'!$A9,TSE!$B:$B,"<"&'l_NB,NEC'!$A10) -> #DIV/0! | G9: =AVERAGEIFS(TSE!BL:BL,TSE!$B:$B,">="&'l_NB,NEC'!$A9,TSE!$B:$B,"<"&'l_NB,NEC'!$A10) -> #DIV/0! | H9: =D9*$D$57/SUM($D$57:$G$57) -> 13937204 | I9: =AVERAGEIFS(TSE!BR:BR,TSE!$B:$B,">="&'l_NB,NEC'!$A9,TSE!$B:$B,"<"&'l_NB,NEC'!$A10) -> 87821782 | J9: =I9-D9 -> 70905449 | K9: =H9*$K$67/$H$67 -> 5326.8787 | L9: =J9*$L$63/$J$63 -> 77519.39 | M9: =K9/Pop!$G9 -> 0.6718917 | N9: =L9/Pop!$G9 -> 9.7777024 | O9: =M9/l_pi_c!$G$3*100 -> 0.74010974 | P9: =N9/l_pi_c!$G$3*100 -> 10.770445 | Q9: =LN(O9)-LN(O8) -> 0.03327 | R9: =LN(P9)-LN(P8) -> 0.0239042
A10: =EDATE(A9,3) -> 29860 | B10: =B11*FoF!J25/FoF!J26 -> 7840.5546 | C10: =C11*FoF!K25/FoF!K26 -> 180548.43 | D10: =AVERAGEIFS(TSE!BF:BF,TSE!$B:$B,">="&'l_NB,NEC'!$A10,TSE!$B:$B,"<"&'l_NB,NEC'!$A11) -> 17488371 | E10: =AVERAGEIFS(TSE!BH:BH,TSE!$B:$B,">="&'l_NB,NEC'!$A10,TSE!$B:$B,"<"&'l_NB,NEC'!$A11) -> #DIV/0! | F10: =AVERAGEIFS(TSE!BJ:BJ,TSE!$B:$B,">="&'l_NB,NEC'!$A10,TSE!$B:$B,"<"&'l_NB,NEC'!$A11) -> #DIV/0! | G10: =AVERAGEIFS(TSE!BL:BL,TSE!$B:$B,">="&'l_NB,NEC'!$A10,TSE!$B:$B,"<"&'l_NB,NEC'!$A11) -> #DIV/0! | H10: =D10*$D$57/SUM($D$57:$G$57) -> 14408501 | I10: =AVERAGEIFS(TSE!BR:BR,TSE!$B:$B,">="&'l_NB,NEC'!$A10,TSE!$B:$B,"<"&'l_NB,NEC'!$A11) -> 86028723 | J10: =I10-D10 -> 68540353 | K10: =H10*$K$67/$H$67 -> 5507.0109 | L10: =J10*$L$63/$J$63 -> 74933.681 | M10: =K10/Pop!$G10 -> 0.69351512 | N10: =L10/Pop!$G10 -> 9.436633 | O10: =M10/l_pi_c!$G$3*100 -> 0.76392861 | P10: =N10/l_pi_c!$G$3*100 -> 10.394747 | Q10: =LN(O10)-LN(O9) -> 0.031675862 | R10: =LN(P10)-LN(P9) -> -0.035505288
A11: =EDATE(A10,3) -> 29952 | B11: =B12*FoF!J26/FoF!J27 -> 7886.4483 | C11: =C12*FoF!K26/FoF!K27 -> 182755.63 | D11: =AVERAGEIFS(TSE!BF:BF,TSE!$B:$B,">="&'l_NB,NEC'!$A11,TSE!$B:$B,"<"&'l_NB,NEC'!$A12) -> 18455115 | E11: =AVERAGEIFS(TSE!BH:BH,TSE!$B:$B,">="&'l_NB,NEC'!$A11,TSE!$B:$B,"<"&'l_NB,NEC'!$A12) -> #DIV/0! | F11: =AVERAGEIFS(TSE!BJ:BJ,TSE!$B:$B,">="&'l_NB,NEC'!$A11,TSE!$B:$B,"<"&'l_NB,NEC'!$A12) -> #DIV/0! | G11: =AVERAGEIFS(TSE!BL:BL,TSE!$B:$B,">="&'l_NB,NEC'!$A11,TSE!$B:$B,"<"&'l_NB,NEC'!$A12) -> #DIV/0! | H11: =D11*$D$57/SUM($D$57:$G$57) -> 15204992 | I11: =AVERAGEIFS(TSE!BR:BR,TSE!$B:$B,">="&'l_NB,NEC'!$A11,TSE!$B:$B,"<"&'l_NB,NEC'!$A12) -> 86244726 | J11: =I11-D11 -> 67789611 | K11: =H11*$K$67/$H$67 -> 5811.4345 | L11: =J11*$L$63/$J$63 -> 74112.911 | M11: =K11/Pop!$G11 -> 0.73034477 | N11: =L11/Pop!$G11 -> 9.3140476 | O11: =M11/l_pi_c!$G$3*100 -> 0.80449763 | P11: =N11/l_pi_c!$G$3*100 -> 10.259715 | Q11: =LN(O11)-LN(O10) -> 0.051743682 | R11: =LN(P11)-LN(P10) -> -0.013075491
A12: =EDATE(A11,3) -> 30042 | B12: =B13*FoF!J27/FoF!J28 -> 7975.1761 | C12: =C13*FoF!K27/FoF!K28 -> 185227.89 | D12: =AVERAGEIFS(TSE!BF:BF,TSE!$B:$B,">="&'l_NB,NEC'!$A12,TSE!$B:$B,"<"&'l_NB,NEC'!$A13) -> 18463939 | E12: =AVERAGEIFS(TSE!BH:BH,TSE!$B:$B,">="&'l_NB,NEC'!$A12,TSE!$B:$B,"<"&'l_NB,NEC'!$A13) -> #DIV/0! | F12: =AVERAGEIFS(TSE!BJ:BJ,TSE!$B:$B,">="&'l_NB,NEC'!$A12,TSE!$B:$B,"<"&'l_NB,NEC'!$A13) -> #DIV/0! | G12: =AVERAGEIFS(TSE!BL:BL,TSE!$B:$B,">="&'l_NB,NEC'!$A12,TSE!$B:$B,"<"&'l_NB,NEC'!$A13) -> #DIV/0! | H12: =D12*$D$57/SUM($D$57:$G$57) -> 15212262 | I12: =AVERAGEIFS(TSE!BR:BR,TSE!$B:$B,">="&'l_NB,NEC'!$A12,TSE!$B:$B,"<"&'l_NB,NEC'!$A13) -> 84703523 | J12: =I12-D12 -> 66239584 | K12: =H12*$K$67/$H$67 -> 5814.2132 | L12: =J12*$L$63/$J$63 -> 72418.301 | M12: =K12/Pop!$G12 -> 0.72889246 | N12: =L12/Pop!$G12 -> 9.0786409 | O12: =M12/l_pi_c!$G$3*100 -> 0.80289786 | P12: =N12/l_pi_c!$G$3*100 -> 10.000407 | Q12: =LN(O12)-LN(O11) -> -0.0019905157 | R12: =LN(P12)-LN(P11) -> -0.025599253
A13: =EDATE(A12,3) -> 30133 | B13: =B14*FoF!J28/FoF!J29 -> 8004.2421 | C13: =C14*FoF!K28/FoF!K29 -> 187797.5 | D13: =AVERAGEIFS(TSE!BF:BF,TSE!$B:$B,">="&'l_NB,NEC'!$A13,TSE!$B:$B,"<"&'l_NB,NEC'!$A14) -> 18363039 | E13: =AVERAGEIFS(TSE!BH:BH,TSE!$B:$B,">="&'l_NB,NEC'!$A13,TSE!$B:$B,"<"&'l_NB,NEC'!$A14) -> #DIV/0! | F13: =AVERAGEIFS(TSE!BJ:BJ,TSE!$B:$B,">="&'l_NB,NEC'!$A13,TSE!$B:$B,"<"&'l_NB,NEC'!$A14) -> #DIV/0! | G13: =AVERAGEIFS(TSE!BL:BL,TSE!$B:$B,">="&'l_NB,NEC'!$A13,TSE!$B:$B,"<"&'l_NB,NEC'!$A14) -> #DIV/0! | H13: =D13*$D$57/SUM($D$57:$G$57) -> 15129132 | I13: =AVERAGEIFS(TSE!BR:BR,TSE!$B:$B,">="&'l_NB,NEC'!$A13,TSE!$B:$B,"<"&'l_NB,NEC'!$A14) -> 82672432 | J13: =I13-D13 -> 64309393 | K13: =H13*$K$67/$H$67 -> 5782.4402 | L13: =J13*$L$63/$J$63 -> 70308.065 | M13: =K13/Pop!$G13 -> 0.72294936 | N13: =L13/Pop!$G13 -> 8.7902631 | O13: =M13/l_pi_c!$G$3*100 -> 0.79635135 | P13: =N13/l_pi_c!$G$3*100 -> 9.68275 | Q13: =LN(O13)-LN(O12) -> -0.0081870184 | R13: =LN(P13)-LN(P12) -> -0.032279855
A14: =EDATE(A13,3) -> 30225 | B14: =B15*FoF!J29/FoF!J30 -> 8015.3331 | C14: =C15*FoF!K29/FoF!K30 -> 191599.87 | D14: =AVERAGEIFS(TSE!BF:BF,TSE!$B:$B,">="&'l_NB,NEC'!$A14,TSE!$B:$B,"<"&'l_NB,NEC'!$A15) -> 19033669 | E14: =AVERAGEIFS(TSE!BH:BH,TSE!$B:$B,">="&'l_NB,NEC'!$A14,TSE!$B:$B,"<"&'l_NB,NEC'!$A15) -> #DIV/0! | F14: =AVERAGEIFS(TSE!BJ:BJ,TSE!$B:$B,">="&'l_NB,NEC'!$A14,TSE!$B:$B,"<"&'l_NB,NEC'!$A15) -> #DIV/0! | G14: =AVERAGEIFS(TSE!BL:BL,TSE!$B:$B,">="&'l_NB,NEC'!$A14,TSE!$B:$B,"<"&'l_NB,NEC'!$A15) -> #DIV/0! | H14: =D14*$D$57/SUM($D$57:$G$57) -> 15681657 | I14: =AVERAGEIFS(TSE!BR:BR,TSE!$B:$B,">="&'l_NB,NEC'!$A14,TSE!$B:$B,"<"&'l_NB,NEC'!$A15) -> 89994933 | J14: =I14-D14 -> 70961265 | K14: =H14*$K$67/$H$67 -> 5993.6184 | L14: =J14*$L$63/$J$63 -> 77580.412 | M14: =K14/Pop!$G14 -> 0.7474194 | N14: =L14/Pop!$G14 -> 9.6744738 | O14: =M14/l_pi_c!$G$3*100 -> 0.82330586 | P14: =N14/l_pi_c!$G$3*100 -> 10.656736 | Q14: =LN(O14)-LN(O13) -> 0.033287285 | R14: =LN(P14)-LN(P13) -> 0.09584621
A15: =EDATE(A14,3) -> 30317 | B15: =B16*FoF!J30/FoF!J31 -> 8564.1451 | C15: =C16*FoF!K30/FoF!K31 -> 282524.2 | D15: =AVERAGEIFS(TSE!BF:BF,TSE!$B:$B,">="&'l_NB,NEC'!$A15,TSE!$B:$B,"<"&'l_NB,NEC'!$A16) -> 19598560 | E15: =AVERAGEIFS(TSE!BH:BH,TSE!$B:$B,">="&'l_NB,NEC'!$A15,TSE!$B:$B,"<"&'l_NB,NEC'!$A16) -> #DIV/0! | F15: =AVERAGEIFS(TSE!BJ:BJ,TSE!$B:$B,">="&'l_NB,NEC'!$A15,TSE!$B:$B,"<"&'l_NB,NEC'!$A16) -> #DIV/0! | G15: =AVERAGEIFS(TSE!BL:BL,TSE!$B:$B,">="&'l_NB,NEC'!$A15,TSE!$B:$B,"<"&'l_NB,NEC'!$A16) -> #DIV/0! | H15: =D15*$D$57/SUM($D$57:$G$57) -> 16147066 | I15: =AVERAGEIFS(TSE!BR:BR,TSE!$B:$B,">="&'l_NB,NEC'!$A15,TSE!$B:$B,"<"&'l_NB,NEC'!$A16) -> 94728175 | J15: =I15-D15 -> 75129614 | K15: =H15*$K$67/$H$67 -> 6171.5003 | L15: =J15*$L$63/$J$63 -> 82137.578 | M15: =K15/Pop!$G15 -> 0.76765391 | N15: =L15/Pop!$G15 -> 10.21684 | O15: =M15/l_pi_c!$G$3*100 -> 0.84559481 | P15: =N15/l_pi_c!$G$3*100 -> 11.254169 | Q15: =LN(O15)-LN(O14) -> 0.026712529 | R15: =LN(P15)-LN(P14) -> 0.054546516
A16: =EDATE(A15,3) -> 30407 | B16: =B17*FoF!J31/FoF!J32 -> 8576.001 | C16: =C17*FoF!K31/FoF!K32 -> 285623.93 | D16: =AVERAGEIFS(TSE!BF:BF,TSE!$B:$B,">="&'l_NB,NEC'!$A16,TSE!$B:$B,"<"&'l_NB,NEC'!$A17) -> 19946785 | E16: =AVERAGEIFS(TSE!BH:BH,TSE!$B:$B,">="&'l_NB,NEC'!$A16,TSE!$B:$B,"<"&'l_NB,NEC'!$A17) -> #DIV/0! | F16: =AVERAGEIFS(TSE!BJ:BJ,TSE!$B:$B,">="&'l_NB,NEC'!$A16,TSE!$B:$B,"<"&'l_NB,NEC'!$A17) -> #DIV/0! | G16: =AVERAGEIFS(TSE!BL:BL,TSE!$B:$B,">="&'l_NB,NEC'!$A16,TSE!$B:$B,"<"&'l_NB,NEC'!$A17) -> #DIV/0! | H16: =D16*$D$57/SUM($D$57:$G$57) -> 16433965 | I16: =AVERAGEIFS(TSE!BR:BR,TSE!$B:$B,">="&'l_NB,NEC'!$A16,TSE!$B:$B,"<"&'l_NB,NEC'!$A17) -> 1.0186826e+08 | J16: =I16-D16 -> 81921472 | K16: =H16*$K$67/$H$67 -> 6281.1547 | L16: =J16*$L$63/$J$63 -> 89562.968 | M16: =K16/Pop!$G16 -> 0.77931437 | N16: =L16/Pop!$G16 -> 11.112241 | O16: =M16/l_pi_c!$G$3*100 -> 0.85843917 | P16: =N16/l_pi_c!$G$3*100 -> 12.240482 | Q16: =LN(O16)-LN(O15) -> 0.015075519 | R16: =LN(P16)-LN(P15) -> 0.084009966
A17: =EDATE(A16,3) -> 30498 | B17: =B18*FoF!J32/FoF!J33 -> 8576.001 | C17: =C18*FoF!K32/FoF!K33 -> 289046.54 | D17: =AVERAGEIFS(TSE!BF:BF,TSE!$B:$B,">="&'l_NB,NEC'!$A17,TSE!$B:$B,"<"&'l_NB,NEC'!$A18) -> 20061807 | E17: =AVERAGEIFS(TSE!BH:BH,TSE!$B:$B,">="&'l_NB,NEC'!$A17,TSE!$B:$B,"<"&'l_NB,NEC'!$A18) -> #DIV/0! | F17: =AVERAGEIFS(TSE!BJ:BJ,TSE!$B:$B,">="&'l_NB,NEC'!$A17,TSE!$B:$B,"<"&'l_NB,NEC'!$A18) -> #DIV/0! | G17: =AVERAGEIFS(TSE!BL:BL,TSE!$B:$B,">="&'l_NB,NEC'!$A17,TSE!$B:$B,"<"&'l_NB,NEC'!$A18) -> #DIV/0! | H17: =D17*$D$57/SUM($D$57:$G$57) -> 16528730 | I17: =AVERAGEIFS(TSE!BR:BR,TSE!$B:$B,">="&'l_NB,NEC'!$A17,TSE!$B:$B,"<"&'l_NB,NEC'!$A18) -> 1.0916871e+08 | J17: =I17-D17 -> 89106903 | K17: =H17*$K$67/$H$67 -> 6317.3747 | L17: =J17*$L$63/$J$63 -> 97418.644 | M17: =K17/Pop!$G17 -> 0.78181298 | N17: =L17/Pop!$G17 -> 12.056141 | O17: =M17/l_pi_c!$G$3*100 -> 0.86119147 | P17: =N17/l_pi_c!$G$3*100 -> 13.280217 | Q17: =LN(O17)-LN(O16) -> 0.0032010432 | R17: =LN(P17)-LN(P16) -> 0.081526839
A18: =EDATE(A17,3) -> 30590 | B18: =B19*FoF!J33/FoF!J34 -> 8859.3945 | C18: =C19*FoF!K33/FoF!K34 -> 293789.62 | D18: =AVERAGEIFS(TSE!BF:BF,TSE!$B:$B,">="&'l_NB,NEC'!$A18,TSE!$B:$B,"<"&'l_NB,NEC'!$A19) -> 20210831 | E18: =AVERAGEIFS(TSE!BH:BH,TSE!$B:$B,">="&'l_NB,NEC'!$A18,TSE!$B:$B,"<"&'l_NB,NEC'!$A19) -> #DIV/0! | F18: =AVERAGEIFS(TSE!BJ:BJ,TSE!$B:$B,">="&'l_NB,NEC'!$A18,TSE!$B:$B,"<"&'l_NB,NEC'!$A19) -> #DIV/0! | G18: =AVERAGEIFS(TSE!BL:BL,TSE!$B:$B,">="&'l_NB,NEC'!$A18,TSE!$B:$B,"<"&'l_NB,NEC'!$A19) -> #DIV/0! | H18: =D18*$D$57/SUM($D$57:$G$57) -> 16651510 | I18: =AVERAGEIFS(TSE!BR:BR,TSE!$B:$B,">="&'l_NB,NEC'!$A18,TSE!$B:$B,"<"&'l_NB,NEC'!$A19) -> 114427300 | J18: =I18-D18 -> 94216469 | K18: =H18*$K$67/$H$67 -> 6364.3018 | L18: =J18*$L$63/$J$63 -> 103004.82 | M18: =K18/Pop!$G18 -> 0.7855452 | N18: =L18/Pop!$G18 -> 12.713876 | O18: =M18/l_pi_c!$G$3*100 -> 0.86530263 | P18: =N18/l_pi_c!$G$3*100 -> 14.004732 | Q18: =LN(O18)-LN(O17) -> 0.0047624439 | R18: =LN(P18)-LN(P17) -> 0.053119827
... A56: =EDATE(A55,3) -> 34060 | B56: =B57*FoF!J71/FoF!J72 -> 50686.522 | C56: =C57*FoF!K71/FoF!K72 -> 644377.67 | D56: =AVERAGEIFS(TSE!BF:BF,TSE!$B:$B,">="&'l_NB,NEC'!$A56,TSE!$B:$B,"<"&'l_NB,NEC'!$A57) -> 102707965 | E56: =AVERAGEIFS(TSE!BH:BH,TSE!$B:$B,">="&'l_NB,NEC'!$A56,TSE!$B:$B,"<"&'l_NB,NEC'!$A57) -> #DIV/0! | F56: =AVERAGEIFS(TSE!BJ:BJ,TSE!$B:$B,">="&'l_NB,NEC'!$A56,TSE!$B:$B,"<"&'l_NB,NEC'!$A57) -> #DIV/0! | G56: =AVERAGEIFS(TSE!BL:BL,TSE!$B:$B,">="&'l_NB,NEC'!$A56,TSE!$B:$B,"<"&'l_NB,NEC'!$A57) -> #DIV/0! | H56: =D56*$D$57/SUM($D$57:$G$57) -> 84620106 | I56: =AVERAGEIFS(TSE!BR:BR,TSE!$B:$B,">="&'l_NB,NEC'!$A56,TSE!$B:$B,"<"&'l_NB,NEC'!$A57) -> 347121505 | J56: =I56-D56 -> 244413540 | K56: =H56*$K$67/$H$67 -> 32342.286 | L56: =J56*$L$63/$J$63 -> 267212.02 | M56: =K56/Pop!$G56 -> 3.7218534 | N56: =L56/Pop!$G56 -> 30.749959 | O56: =M56/l_pi_c!$G$3*100 -> 4.099738 | P56: =N56/l_pi_c!$G$3*100 -> 33.872043 | Q56: =LN(O56)-LN(O55) -> 0.19837642 | R56: =LN(P56)-LN(P55) -> 0.182377
A57: =EDATE(A56,3) -> 34151 | B57: =B58*FoF!J72/FoF!J73 -> 50754.215 | C57: =C58*FoF!K72/FoF!K73 -> 646916.44 | D57: =AVERAGEIFS(TSE!BF:BF,TSE!$B:$B,">="&'l_NB,NEC'!$A57,TSE!$B:$B,"<"&'l_NB,NEC'!$A58) -> 91999328 | E57: =AVERAGEIFS(TSE!BH:BH,TSE!$B:$B,">="&'l_NB,NEC'!$A57,TSE!$B:$B,"<"&'l_NB,NEC'!$A58) -> 10954884 | F57: =AVERAGEIFS(TSE!BJ:BJ,TSE!$B:$B,">="&'l_NB,NEC'!$A57,TSE!$B:$B,"<"&'l_NB,NEC'!$A58) -> 6489364.7 | G57: =AVERAGEIFS(TSE!BL:BL,TSE!$B:$B,">="&'l_NB,NEC'!$A57,TSE!$B:$B,"<"&'l_NB,NEC'!$A58) -> 2220946 | H57: =D57 -> 91999328 | I57: =AVERAGEIFS(TSE!BR:BR,TSE!$B:$B,">="&'l_NB,NEC'!$A57,TSE!$B:$B,"<"&'l_NB,NEC'!$A58) -> 358007403 | J57: =I57-SUM(D57:G57) -> 246342880 | K57: =H57*$K$67/$H$67 -> 35162.666 | L57: =J57*$L$63/$J$63 -> 269321.33 | M57: =K57/Pop!$G57 -> 4.0447723 | N57: =L57/Pop!$G57 -> 30.980115 | O57: =M57/l_pi_c!$G$3*100 -> 4.4554433 | P57: =N57/l_pi_c!$G$3*100 -> 34.125567 | Q57: =LN(O57)-LN(O56) -> 0.083203492 | R57: =LN(P57)-LN(P56) -> 0.0074568761
A58: =EDATE(A57,3) -> 34243 | B58: =B59*FoF!J73/FoF!J74 -> 51185.616 | C58: =C59*FoF!K73/FoF!K74 -> 647105.35 | D58: =AVERAGEIFS(TSE!BF:BF,TSE!$B:$B,">="&'l_NB,NEC'!$A58,TSE!$B:$B,"<"&'l_NB,NEC'!$A59) -> 80909970 | E58: =AVERAGEIFS(TSE!BH:BH,TSE!$B:$B,">="&'l_NB,NEC'!$A58,TSE!$B:$B,"<"&'l_NB,NEC'!$A59) -> 9497957.7 | F58: =AVERAGEIFS(TSE!BJ:BJ,TSE!$B:$B,">="&'l_NB,NEC'!$A58,TSE!$B:$B,"<"&'l_NB,NEC'!$A59) -> 5852888.7 | G58: =AVERAGEIFS(TSE!BL:BL,TSE!$B:$B,">="&'l_NB,NEC'!$A58,TSE!$B:$B,"<"&'l_NB,NEC'!$A59) -> 1899059.7 | H58: =D58 -> 80909970 | I58: =AVERAGEIFS(TSE!BR:BR,TSE!$B:$B,">="&'l_NB,NEC'!$A58,TSE!$B:$B,"<"&'l_NB,NEC'!$A59) -> 3.2259047e+08 | J58: =I58-SUM(D58:G58) -> 2.2443059e+08 | K58: =H58*$K$67/$H$67 -> 30924.251 | L58: =J58*$L$63/$J$63 -> 245365.1 | M58: =K58/Pop!$G58 -> 3.556601 | N58: =L58/Pop!$G58 -> 28.219463 | O58: =M58/l_pi_c!$G$3*100 -> 3.9177073 | P58: =N58/l_pi_c!$G$3*100 -> 31.084622 | Q58: =LN(O58)-LN(O57) -> -0.12861995 | R58: =LN(P58)-LN(P57) -> -0.09333363
A59: =EDATE(A58,3) -> 34335 | B59: =B60*FoF!J74/FoF!J75 -> 51201.678 | C59: =C60*FoF!K74/FoF!K75 -> 649164.12 | D59: =AVERAGEIFS(TSE!BF:BF,TSE!$B:$B,">="&'l_NB,NEC'!$A59,TSE!$B:$B,"<"&'l_NB,NEC'!$A60) -> 82981512 | E59: =AVERAGEIFS(TSE!BH:BH,TSE!$B:$B,">="&'l_NB,NEC'!$A59,TSE!$B:$B,"<"&'l_NB,NEC'!$A60) -> 12339850 | F59: =AVERAGEIFS(TSE!BJ:BJ,TSE!$B:$B,">="&'l_NB,NEC'!$A59,TSE!$B:$B,"<"&'l_NB,NEC'!$A60) -> 6115760.7 | G59: =AVERAGEIFS(TSE!BL:BL,TSE!$B:$B,">="&'l_NB,NEC'!$A59,TSE!$B:$B,"<"&'l_NB,NEC'!$A60) -> 2055843.7 | H59: =D59 -> 82981512 | I59: =AVERAGEIFS(TSE!BR:BR,TSE!$B:$B,">="&'l_NB,NEC'!$A59,TSE!$B:$B,"<"&'l_NB,NEC'!$A60) -> 350386837 | J59: =I59-SUM(D59:G59) -> 2.4689387e+08 | K59: =H59*$K$67/$H$67 -> 31716.006 | L59: =J59*$L$63/$J$63 -> 269923.71 | M59: =K59/Pop!$G59 -> 3.6472414 | N59: =L59/Pop!$G59 -> 31.040382 | O59: =M59/l_pi_c!$G$3*100 -> 4.0175505 | P59: =N59/l_pi_c!$G$3*100 -> 34.191953 | Q59: =LN(O59)-LN(O58) -> 0.025165777 | R59: =LN(P59)-LN(P58) -> 0.095277084
A60: =EDATE(A59,3) -> 34425 | B60: =B61*FoF!J75/FoF!J76 -> 51656.791 | C60: =C61*FoF!K75/FoF!K76 -> 652222.41 | D60: =AVERAGEIFS(TSE!BF:BF,TSE!$B:$B,">="&'l_NB,NEC'!$A60,TSE!$B:$B,"<"&'l_NB,NEC'!$A61) -> 85109863 | E60: =AVERAGEIFS(TSE!BH:BH,TSE!$B:$B,">="&'l_NB,NEC'!$A60,TSE!$B:$B,"<"&'l_NB,NEC'!$A61) -> 12528234 | F60: =AVERAGEIFS(TSE!BJ:BJ,TSE!$B:$B,">="&'l_NB,NEC'!$A60,TSE!$B:$B,"<"&'l_NB,NEC'!$A61) -> 6344779 | G60: =AVERAGEIFS(TSE!BL:BL,TSE!$B:$B,">="&'l_NB,NEC'!$A60,TSE!$B:$B,"<"&'l_NB,NEC'!$A61) -> 2062852.3 | H60: =D60 -> 85109863 | I60: =AVERAGEIFS(TSE!BR:BR,TSE!$B:$B,">="&'l_NB,NEC'!$A60,TSE!$B:$B,"<"&'l_NB,NEC'!$A61) -> 3.6055228e+08 | J60: =I60-SUM(D60:G60) -> 2.5450655e+08 | K60: =H60*$K$67/$H$67 -> 32529.474 | L60: =J60*$L$63/$J$63 -> 278246.49 | M60: =K60/Pop!$G60 -> 3.740483 | N60: =L60/Pop!$G60 -> 31.994869 | O60: =M60/l_pi_c!$G$3*100 -> 4.1202591 | P60: =N60/l_pi_c!$G$3*100 -> 35.24335 | Q60: =LN(O60)-LN(O59) -> 0.025243643 | R60: =LN(P60)-LN(P59) -> 0.030286547
A61: =EDATE(A60,3) -> 34516 | B61: =B62*FoF!J76/FoF!J77 -> 51666.352 | C61: =C62*FoF!K76/FoF!K77 -> 655119.72 | D61: =AVERAGEIFS(TSE!BF:BF,TSE!$B:$B,">="&'l_NB,NEC'!$A61,TSE!$B:$B,"<"&'l_NB,NEC'!$A62) -> 81457753 | E61: =AVERAGEIFS(TSE!BH:BH,TSE!$B:$B,">="&'l_NB,NEC'!$A61,TSE!$B:$B,"<"&'l_NB,NEC'!$A62) -> 11465470 | F61: =AVERAGEIFS(TSE!BJ:BJ,TSE!$B:$B,">="&'l_NB,NEC'!$A61,TSE!$B:$B,"<"&'l_NB,NEC'!$A62) -> 6081381 | G61: =AVERAGEIFS(TSE!BL:BL,TSE!$B:$B,">="&'l_NB,NEC'!$A61,TSE!$B:$B,"<"&'l_NB,NEC'!$A62) -> 1988574 | H61: =D61 -> 81457753 | I61: =AVERAGEIFS(TSE!BR:BR,TSE!$B:$B,">="&'l_NB,NEC'!$A61,TSE!$B:$B,"<"&'l_NB,NEC'!$A62) -> 353200697 | J61: =I61-SUM(D61:G61) -> 252207519 | K61: =H61*$K$67/$H$67 -> 31133.616 | L61: =J61*$L$63/$J$63 -> 275733.01 | M61: =K61/Pop!$G61 -> 3.5796281 | N61: =L61/Pop!$G61 -> 31.702762 | O61: =M61/l_pi_c!$G$3*100 -> 3.9430724 | P61: =N61/l_pi_c!$G$3*100 -> 34.921585 | Q61: =LN(O61)-LN(O60) -> -0.043955829 | R61: =LN(P61)-LN(P60) -> -0.0091717483
A62: =EDATE(A61,3) -> 34608 | B62: =B63*FoF!J77/FoF!J78 -> 52516.533 | C62: =C63*FoF!K77/FoF!K78 -> 655576.59 | D62: =AVERAGEIFS(TSE!BF:BF,TSE!$B:$B,">="&'l_NB,NEC'!$A62,TSE!$B:$B,"<"&'l_NB,NEC'!$A63) -> 78228215 | E62: =AVERAGEIFS(TSE!BH:BH,TSE!$B:$B,">="&'l_NB,NEC'!$A62,TSE!$B:$B,"<"&'l_NB,NEC'!$A63) -> 10452908 | F62: =AVERAGEIFS(TSE!BJ:BJ,TSE!$B:$B,">="&'l_NB,NEC'!$A62,TSE!$B:$B,"<"&'l_NB,NEC'!$A63) -> 5702183.3 | G62: =AVERAGEIFS(TSE!BL:BL,TSE!$B:$B,">="&'l_NB,NEC'!$A62,TSE!$B:$B,"<"&'l_NB,NEC'!$A63) -> 1804974.7 | H62: =D62 -> 78228215 | I62: =AVERAGEIFS(TSE!BR:BR,TSE!$B:$B,">="&'l_NB,NEC'!$A62,TSE!$B:$B,"<"&'l_NB,NEC'!$A63) -> 3.4089912e+08 | J62: =I62-SUM(D62:G62) -> 2.4471084e+08 | K62: =H62*$K$67/$H$67 -> 29899.269 | L62: =J62*$L$63/$J$63 -> 267537.05 | M62: =K62/Pop!$G62 -> 3.4373506 | N62: =L62/Pop!$G62 -> 30.757228 | O62: =M62/l_pi_c!$G$3*100 -> 3.7863492 | P62: =N62/l_pi_c!$G$3*100 -> 33.88005 | Q62: =LN(O62)-LN(O61) -> -0.040557918 | R62: =LN(P62)-LN(P61) -> -0.030278774
A63: =EDATE(A62,3) -> 34700 | B63: =B64*FoF!J78/FoF!J79 -> 52789.6 | C63: =C64*FoF!K78/FoF!K79 -> 2341958.5 | D63: =AVERAGEIFS(TSE!BF:BF,TSE!$B:$B,">="&'l_NB,NEC'!$A63,TSE!$B:$B,"<"&'l_NB,NEC'!$A64) -> 71962683 | E63: =AVERAGEIFS(TSE!BH:BH,TSE!$B:$B,">="&'l_NB,NEC'!$A63,TSE!$B:$B,"<"&'l_NB,NEC'!$A64) -> 8828298 | F63: =AVERAGEIFS(TSE!BJ:BJ,TSE!$B:$B,">="&'l_NB,NEC'!$A63,TSE!$B:$B,"<"&'l_NB,NEC'!$A64) -> 4994123.3 | G63: =AVERAGEIFS(TSE!BL:BL,TSE!$B:$B,">="&'l_NB,NEC'!$A63,TSE!$B:$B,"<"&'l_NB,NEC'!$A64) -> 1572497.7 | H63: =D63 -> 71962683 | I63: =AVERAGEIFS(TSE!BR:BR,TSE!$B:$B,">="&'l_NB,NEC'!$A63,TSE!$B:$B,"<"&'l_NB,NEC'!$A64) -> 301571904 | J63: =I63-SUM(D63:G63) -> 2.142143e+08 | K63: =H63*$K$67/$H$67 -> 27504.547 | L63: =C63/10 -> 234195.85 | M63: =K63/Pop!$G63 -> 3.1619823 | N63: =L63/Pop!$G63 -> 26.923662 | O63: =M63/l_pi_c!$G$3*100 -> 3.4830225 | P63: =N63/l_pi_c!$G$3*100 -> 29.657257 | Q63: =LN(O63)-LN(O62) -> -0.083501855 | R63: =LN(P63)-LN(P62) -> -0.13311949
A64: =EDATE(A63,3) -> 34790 | B64: =B65*FoF!J79/FoF!J80 -> 52778.892 | C64: =C65*FoF!K79/FoF!K80 -> 2146632.4 | D64: =AVERAGEIFS(TSE!BF:BF,TSE!$B:$B,">="&'l_NB,NEC'!$A64,TSE!$B:$B,"<"&'l_NB,NEC'!$A65) -> 67343295 | E64: =AVERAGEIFS(TSE!BH:BH,TSE!$B:$B,">="&'l_NB,NEC'!$A64,TSE!$B:$B,"<"&'l_NB,NEC'!$A65) -> 7466655.3 | F64: =AVERAGEIFS(TSE!BJ:BJ,TSE!$B:$B,">="&'l_NB,NEC'!$A64,TSE!$B:$B,"<"&'l_NB,NEC'!$A65) -> 4618586.3 | G64: =AVERAGEIFS(TSE!BL:BL,TSE!$B:$B,">="&'l_NB,NEC'!$A64,TSE!$B:$B,"<"&'l_NB,NEC'!$A65) -> 1409174.7 | H64: =D64 -> 67343295 | I64: =AVERAGEIFS(TSE!BR:BR,TSE!$B:$B,">="&'l_NB,NEC'!$A64,TSE!$B:$B,"<"&'l_NB,NEC'!$A65) -> 277086180 | J64: =I64-SUM(D64:G64) -> 1.9624847e+08 | K64: =H64*$K$67/$H$67 -> 25738.99 | L64: =C64/10 -> 214663.24 | M64: =K64/Pop!$G64 -> 2.9593361 | N64: =L64/Pop!$G64 -> 24.68087 | O64: =M64/l_pi_c!$G$3*100 -> 3.2598014 | P64: =N64/l_pi_c!$G$3*100 -> 27.186751 | Q64: =LN(O64)-LN(O63) -> -0.066234171 | R64: =LN(P64)-LN(P63) -> -0.086977078
A65: =EDATE(A64,3) -> 34881 | B65: =B66*FoF!J80/FoF!J81 -> 53086.379 | C65: =C66*FoF!K80/FoF!K81 -> 2609305 | D65: =AVERAGEIFS(TSE!BF:BF,TSE!$B:$B,">="&'l_NB,NEC'!$A65,TSE!$B:$B,"<"&'l_NB,NEC'!$A66) -> 71994797 | E65: =AVERAGEIFS(TSE!BH:BH,TSE!$B:$B,">="&'l_NB,NEC'!$A65,TSE!$B:$B,"<"&'l_NB,NEC'!$A66) -> 8869230 | F65: =AVERAGEIFS(TSE!BJ:BJ,TSE!$B:$B,">="&'l_NB,NEC'!$A65,TSE!$B:$B,"<"&'l_NB,NEC'!$A66) -> 5027312.3 | G65: =AVERAGEIFS(TSE!BL:BL,TSE!$B:$B,">="&'l_NB,NEC'!$A65,TSE!$B:$B,"<"&'l_NB,NEC'!$A66) -> 1562305 | H65: =D65 -> 71994797 | I65: =AVERAGEIFS(TSE!BR:BR,TSE!$B:$B,">="&'l_NB,NEC'!$A65,TSE!$B:$B,"<"&'l_NB,NEC'!$A66) -> 308938858 | J65: =I65-SUM(D65:G65) -> 2.2148521e+08 | K65: =H65*$K$67/$H$67 -> 27516.821 | L65: =C65/10 -> 260930.5 | M65: =K65/Pop!$G65 -> 3.1643533 | N65: =L65/Pop!$G65 -> 30.006239 | O65: =M65/l_pi_c!$G$3*100 -> 3.4856342 | P65: =N65/l_pi_c!$G$3*100 -> 33.052812 | Q65: =LN(O65)-LN(O64) -> 0.066983744 | R65: =LN(P65)-LN(P64) -> 0.19537686
A66: =EDATE(A65,3) -> 34973 | B66: =B67*FoF!J81/FoF!J82 -> 53518.545 | C66: =C67*FoF!K81/FoF!K82 -> 2837973.4 | D66: =AVERAGEIFS(TSE!BF:BF,TSE!$B:$B,">="&'l_NB,NEC'!$A66,TSE!$B:$B,"<"&'l_NB,NEC'!$A67) -> 74995658 | E66: =AVERAGEIFS(TSE!BH:BH,TSE!$B:$B,">="&'l_NB,NEC'!$A66,TSE!$B:$B,"<"&'l_NB,NEC'!$A67) -> 10160673 | F66: =AVERAGEIFS(TSE!BJ:BJ,TSE!$B:$B,">="&'l_NB,NEC'!$A66,TSE!$B:$B,"<"&'l_NB,NEC'!$A67) -> 5384456 | G66: =AVERAGEIFS(TSE!BL:BL,TSE!$B:$B,">="&'l_NB,NEC'!$A66,TSE!$B:$B,"<"&'l_NB,NEC'!$A67) -> 1726398.7 | H66: =D66 -> 74995658 | I66: =AVERAGEIFS(TSE!BR:BR,TSE!$B:$B,">="&'l_NB,NEC'!$A66,TSE!$B:$B,"<"&'l_NB,NEC'!$A67) -> 330665422 | J66: =I66-SUM(D66:G66) -> 2.3839824e+08 | K66: =H66*$K$67/$H$67 -> 28663.767 | L66: =C66/10 -> 283797.34 | M66: =K66/Pop!$G66 -> 3.2973336 | N66: =L66/Pop!$G66 -> 32.6466 | O66: =M66/l_pi_c!$G$3*100 -> 3.6321162 | P66: =N66/l_pi_c!$G$3*100 -> 35.961251 | Q66: =LN(O66)-LN(O65) -> 0.041165439 | R66: =LN(P66)-LN(P65) -> 0.084335373
A67: =EDATE(A66,3) -> 35065 | B67: =B68*FoF!J82/FoF!J83 -> 296294.26 | C67: =C68*FoF!K82/FoF!K83 -> 2993455.1 | D67: =AVERAGEIFS(TSE!BF:BF,TSE!$B:$B,">="&'l_NB,NEC'!$A67,TSE!$B:$B,"<"&'l_NB,NEC'!$A68) -> 77522200 | E67: =AVERAGEIFS(TSE!BH:BH,TSE!$B:$B,">="&'l_NB,NEC'!$A67,TSE!$B:$B,"<"&'l_NB,NEC'!$A68) -> 11613333 | F67: =AVERAGEIFS(TSE!BJ:BJ,TSE!$B:$B,">="&'l_NB,NEC'!$A67,TSE!$B:$B,"<"&'l_NB,NEC'!$A68) -> 6027116 | G67: =AVERAGEIFS(TSE!BL:BL,TSE!$B:$B,">="&'l_NB,NEC'!$A67,TSE!$B:$B,"<"&'l_NB,NEC'!$A68) -> 1852961 | H67: =D67 -> 77522200 | I67: =AVERAGEIFS(TSE!BR:BR,TSE!$B:$B,">="&'l_NB,NEC'!$A67,TSE!$B:$B,"<"&'l_NB,NEC'!$A68) -> 3.5537863e+08 | J67: =I67-SUM(D67:G67) -> 2.5836302e+08 | K67: =B67/10 -> 29629.426 | L67: =C67/10 -> 299345.51 | M67: =K67/Pop!$G67 -> 3.4096165 | N67: =L67/Pop!$G67 -> 34.44729 | O67: =M67/l_pi_c!$G$3*100 -> 3.7557993 | P67: =N67/l_pi_c!$G$3*100 -> 37.944768 | Q67: =LN(O67)-LN(O66) -> 0.033485686 | R67: =LN(P67)-LN(P66) -> 0.053689625
A68: =EDATE(A67,3) -> 35156 | B68: =B69*FoF!J83/FoF!J84 -> 318320.55 | C68: =C69*FoF!K83/FoF!K84 -> 3193062.6 | D68: =AVERAGEIFS(TSE!BF:BF,TSE!$B:$B,">="&'l_NB,NEC'!$A68,TSE!$B:$B,"<"&'l_NB,NEC'!$A69) -> 83122914 | E68: =AVERAGEIFS(TSE!BH:BH,TSE!$B:$B,">="&'l_NB,NEC'!$A68,TSE!$B:$B,"<"&'l_NB,NEC'!$A69) -> 11272957 | F68: =AVERAGEIFS(TSE!BJ:BJ,TSE!$B:$B,">="&'l_NB,NEC'!$A68,TSE!$B:$B,"<"&'l_NB,NEC'!$A69) -> 6501518.7 | G68: =AVERAGEIFS(TSE!BL:BL,TSE!$B:$B,">="&'l_NB,NEC'!$A68,TSE!$B:$B,"<"&'l_NB,NEC'!$A69) -> 1978232.3 | H68: =D68 -> 83122914 | I68: =AVERAGEIFS(TSE!BR:BR,TSE!$B:$B,">="&'l_NB,NEC'!$A68,TSE!$B:$B,"<"&'l_NB,NEC'!$A69) -> 379391332 | J68: =I68-SUM(D68:G68) -> 2.7651571e+08 | K68: =B68/10 -> 31832.055 | L68: =C68/10 -> 319306.26 | M68: =K68/Pop!$G68 -> 3.6640746 | N68: =L68/Pop!$G68 -> 36.754208 | O68: =M68/l_pi_c!$G$3*100 -> 4.0360929 | P68: =N68/l_pi_c!$G$3*100 -> 40.48591 | Q68: =LN(O68)-LN(O67) -> 0.07197597 | R68: =LN(P68)-LN(P67) -> 0.06482239
A69: =EDATE(A68,3) -> 35247 | B69: =B70*FoF!J84/FoF!J85 -> 302830.67 | C69: =C70*FoF!K84/FoF!K85 -> 3054719.1 | D69: =AVERAGEIFS(TSE!BF:BF,TSE!$B:$B,">="&'l_NB,NEC'!$A69,TSE!$B:$B,"<"&'l_NB,NEC'!$A70) -> 76348238 | E69: =AVERAGEIFS(TSE!BH:BH,TSE!$B:$B,">="&'l_NB,NEC'!$A69,TSE!$B:$B,"<"&'l_NB,NEC'!$A70) -> 9862498.3 | F69: =AVERAGEIFS(TSE!BJ:BJ,TSE!$B:$B,">="&'l_NB,NEC'!$A69,TSE!$B:$B,"<"&'l_NB,NEC'!$A70) -> 5923947.7 | G69: =AVERAGEIFS(TSE!BL:BL,TSE!$B:$B,">="&'l_NB,NEC'!$A69,TSE!$B:$B,"<"&'l_NB,NEC'!$A70) -> 2505478.7 | H69: =D69 -> 76348238 | I69: =AVERAGEIFS(TSE!BR:BR,TSE!$B:$B,">="&'l_NB,NEC'!$A69,TSE!$B:$B,"<"&'l_NB,NEC'!$A70) -> 3.5594069e+08 | J69: =I69-SUM(D69:G69) -> 2.6130052e+08 | K69: =B69/10 -> 30283.067 | L69: =C69/10 -> 305471.91 | M69: =K69/Pop!$G69 -> 3.4856089 | N69: =L69/Pop!$G69 -> 35.160098 | O69: =M69/l_pi_c!$G$3*100 -> 3.8395073 | P69: =N69/l_pi_c!$G$3*100 -> 38.729948 | Q69: =LN(O69)-LN(O68) -> -0.049933067 | R69: =LN(P69)-LN(P68) -> -0.044340863
A70: =EDATE(A69,3) -> 35339 | B70: =B71*FoF!J85/FoF!J86 -> 256660.08 | C70: =C71*FoF!K85/FoF!K86 -> 2839842.3 | D70: =AVERAGEIFS(TSE!BF:BF,TSE!$B:$B,">="&'l_NB,NEC'!$A70,TSE!$B:$B,"<"&'l_NB,NEC'!$A71) -> 72460828 | E70: =AVERAGEIFS(TSE!BH:BH,TSE!$B:$B,">="&'l_NB,NEC'!$A70,TSE!$B:$B,"<"&'l_NB,NEC'!$A71) -> 9015637 | F70: =AVERAGEIFS(TSE!BJ:BJ,TSE!$B:$B,">="&'l_NB,NEC'!$A70,TSE!$B:$B,"<"&'l_NB,NEC'!$A71) -> 5385241.7 | G70: =AVERAGEIFS(TSE!BL:BL,TSE!$B:$B,">="&'l_NB,NEC'!$A70,TSE!$B:$B,"<"&'l_NB,NEC'!$A71) -> 3824959 | H70: =D70 -> 72460828 | I70: =AVERAGEIFS(TSE!BR:BR,TSE!$B:$B,">="&'l_NB,NEC'!$A70,TSE!$B:$B,"<"&'l_NB,NEC'!$A71) -> 348394391 | J70: =I70-SUM(D70:G70) -> 2.5770773e+08 | K70: =B70/10 -> 25666.008 | L70: =C70/10 -> 283984.23 | M70: =K70/Pop!$G70 -> 2.9530199 | N70: =L70/Pop!$G70 -> 32.673997 | O70: =M70/l_pi_c!$G$3*100 -> 3.2528438 | P70: =N70/l_pi_c!$G$3*100 -> 35.991431 | Q70: =LN(O70)-LN(O69) -> -0.1658144 | R70: =LN(P70)-LN(P69) -> -0.07333228
A71: =EDATE(A70,3) -> 35431 | B71: =B72*FoF!J86/FoF!J87 -> 214905.24 | C71: =C72*FoF!K86/FoF!K87 -> 2714427.8 | D71: =AVERAGEIFS(TSE!BF:BF,TSE!$B:$B,">="&'l_NB,NEC'!$A71,TSE!$B:$B,"<"&'l_NB,NEC'!$A72) -> 56429726 | E71: =AVERAGEIFS(TSE!BH:BH,TSE!$B:$B,">="&'l_NB,NEC'!$A71,TSE!$B:$B,"<"&'l_NB,NEC'!$A72) -> 7023702 | F71: =AVERAGEIFS(TSE!BJ:BJ,TSE!$B:$B,">="&'l_NB,NEC'!$A71,TSE!$B:$B,"<"&'l_NB,NEC'!$A72) -> 4943377.3 | G71: =AVERAGEIFS(TSE!BL:BL,TSE!$B:$B,">="&'l_NB,NEC'!$A71,TSE!$B:$B,"<"&'l_NB,NEC'!$A72) -> 3632764.7 | H71: =D71 -> 56429726 | I71: =AVERAGEIFS(TSE!BR:BR,TSE!$B:$B,">="&'l_NB,NEC'!$A71,TSE!$B:$B,"<"&'l_NB,NEC'!$A72) -> 315560279 | J71: =I71-SUM(D71:G71) -> 2.4353071e+08 | K71: =B71/10 -> 21490.524 | L71: =C71/10 -> 271442.78 | M71: =K71/Pop!$G71 -> 2.4716272 | N71: =L71/Pop!$G71 -> 31.21866 | O71: =M71/l_pi_c!$G$3*100 -> 2.7225747 | P71: =N71/l_pi_c!$G$3*100 -> 34.388331 | Q71: =LN(O71)-LN(O70) -> -0.17795162 | R71: =LN(P71)-LN(P70) -> -0.045563592
A72: =EDATE(A71,3) -> 35521 | B72: =B73*FoF!J87/FoF!J88 -> 256927.8 | C72: =C73*FoF!K87/FoF!K88 -> 3036126.5 | D72: =AVERAGEIFS(TSE!BF:BF,TSE!$B:$B,">="&'l_NB,NEC'!$A72,TSE!$B:$B,"<"&'l_NB,NEC'!$A73) -> 60878550 | E72: =AVERAGEIFS(TSE!BH:BH,TSE!$B:$B,">="&'l_NB,NEC'!$A72,TSE!$B:$B,"<"&'l_NB,NEC'!$A73) -> 6628854.7 | F72: =AVERAGEIFS(TSE!BJ:BJ,TSE!$B:$B,">="&'l_NB,NEC'!$A72,TSE!$B:$B,"<"&'l_NB,NEC'!$A73) -> 5729981.3 | G72: =AVERAGEIFS(TSE!BL:BL,TSE!$B:$B,">="&'l_NB,NEC'!$A72,TSE!$B:$B,"<"&'l_NB,NEC'!$A73) -> 4043970.7 | H72: =D72 -> 60878550 | I72: =AVERAGEIFS(TSE!BR:BR,TSE!$B:$B,">="&'l_NB,NEC'!$A72,TSE!$B:$B,"<"&'l_NB,NEC'!$A73) -> 342593534 | J72: =I72-SUM(D72:G72) -> 265312177 | K72: =B72/10 -> 25692.78 | L72: =C72/10 -> 303612.65 | M72: =K72/Pop!$G72 -> 2.9540561 | N72: =L72/Pop!$G72 -> 34.908204 | O72: =M72/l_pi_c!$G$3*100 -> 3.2539852 | P72: =N72/l_pi_c!$G$3*100 -> 38.452479 | Q72: =LN(O72)-LN(O71) -> 0.17830245 | R72: =LN(P72)-LN(P71) -> 0.11170589
A73: =EDATE(A72,3) -> 35612 | B73: =B74*FoF!J88/FoF!J89 -> 231252.19 | C73: =C74*FoF!K88/FoF!K89 -> 2694470.4 | D73: =AVERAGEIFS(TSE!BF:BF,TSE!$B:$B,">="&'l_NB,NEC'!$A73,TSE!$B:$B,"<"&'l_NB,NEC'!$A74) -> 62212410 | E73: =AVERAGEIFS(TSE!BH:BH,TSE!$B:$B,">="&'l_NB,NEC'!$A73,TSE!$B:$B,"<"&'l_NB,NEC'!$A74) -> 6241689.7 | F73: =AVERAGEIFS(TSE!BJ:BJ,TSE!$B:$B,">="&'l_NB,NEC'!$A73,TSE!$B:$B,"<"&'l_NB,NEC'!$A74) -> 5808881.7 | G73: =AVERAGEIFS(TSE!BL:BL,TSE!$B:$B,">="&'l_NB,NEC'!$A73,TSE!$B:$B,"<"&'l_NB,NEC'!$A74) -> 4497033.7 | H73: =D73 -> 62212410 | I73: =AVERAGEIFS(TSE!BR:BR,TSE!$B:$B,">="&'l_NB,NEC'!$A73,TSE!$B:$B,"<"&'l_NB,NEC'!$A74) -> 3.3553695e+08 | J73: =I73-SUM(D73:G73) -> 2.5677693e+08 | K73: =B73/10 -> 23125.219 | L73: =C73/10 -> 269447.04 | M73: =K73/Pop!$G73 -> 2.6590135 | N73: =L73/Pop!$G73 -> 30.981904 | O73: =M73/l_pi_c!$G$3*100 -> 2.9289866 | P73: =N73/l_pi_c!$G$3*100 -> 34.127537 | Q73: =LN(O73)-LN(O72) -> -0.10522398 | R73: =LN(P73)-LN(P72) -> -0.11931857
A74: =EDATE(A73,3) -> 35704 | B74: =B75*FoF!G89/FoF!G90 -> 166118.72 | C74: =C75*FoF!I89/FoF!I90 -> 2361113 | D74: =AVERAGEIFS(TSE!BF:BF,TSE!$B:$B,">="&'l_NB,NEC'!$A74,TSE!$B:$B,"<"&'l_NB,NEC'!$A75) -> 46486015 | E74: =AVERAGEIFS(TSE!BH:BH,TSE!$B:$B,">="&'l_NB,NEC'!$A74,TSE!$B:$B,"<"&'l_NB,NEC'!$A75) -> 5116337.3 | F74: =AVERAGEIFS(TSE!BJ:BJ,TSE!$B:$B,">="&'l_NB,NEC'!$A74,TSE!$B:$B,"<"&'l_NB,NEC'!$A75) -> 5028717.3 | G74: =AVERAGEIFS(TSE!BL:BL,TSE!$B:$B,">="&'l_NB,NEC'!$A74,TSE!$B:$B,"<"&'l_NB,NEC'!$A75) -> 4658245.7 | H74: =D74 -> 46486015 | I74: =AVERAGEIFS(TSE!BR:BR,TSE!$B:$B,">="&'l_NB,NEC'!$A74,TSE!$B:$B,"<"&'l_NB,NEC'!$A75) -> 287705460 | J74: =I74-SUM(D74:G74) -> 226416145 | K74: =B74/10 -> 16611.872 | L74: =C74/10 -> 236111.3 | M74: =K74/Pop!$G74 -> 1.910481 | N74: =L74/Pop!$G74 -> 27.154446 | O74: =M74/l_pi_c!$G$3*100 -> 2.1044547 | P74: =N74/l_pi_c!$G$3*100 -> 29.911472 | Q74: =LN(O74)-LN(O73) -> -0.33060012 | R74: =LN(P74)-LN(P73) -> -0.13186252
